Workbook

Sheet Apr2025-EXPENSE
B1: APR 2025 EXPENSES
A2: FLAT # | B2: 1 | C2: WATER USED IN LTRS | D2: COMMON AREA WATER EQUALLY DIVIDED (L) | E2: TOTAL FRESH WATER CONSUMED(L) | F2: %OF TOTAL WATER USED | G2: WATER EXPENSE SHARING BY % | H2: #METERS | I2: METER RENT (Rs) | J2: TOTAL VARIABLE = (COMMON AREA METER RENT + WATER EXPENSE+ FLAT METER RENT (Rs)) | K2: FIXED EXPENSE SHARE(Rs) | L2: PARKING FEE(Rs) | M2: CLUB HOUSE FEE (Rs) | N2: SHIFTING FEE (Rs) | O2: GYM USAGE FEE(Rs) | P2: COVID+ GARBAGE FEE (Rs) | Q2: ANNUAL MEMBERSHIP FEE - 2022-2023 (Rs) | R2: TOTAL EXPENSE TO BE PAID (Rs)
A3: CH | B3: MPFOWA | C3: 0 | D3: 0 | H3: 1 | I3: =T7 -> 112.21
A4: GYM | B4: MPFOWA | C4: 0 | D4: 0 | H4: 1 | I4: =T7 -> 112.21 | S4: TOTAL FIXED EXPENSE | T4: ='ANNUAL-EXPENSE-DETAILS'!BF3 -> 287528
A5: BSMT | B5: MPFOWA | C5: 0 | D5: 0 | H5: 1 | I5: =T7 -> 112.21 | S5: TOTAL WATER EXPENSE | T5: ='ANNUAL-EXPENSE-DETAILS'!BE3 -> 39800
A6: F1 | B6: Shailesh Srivastava / Azeem Nawaz | C6: 2141.5 | D6: =SUM($C$3:$C$5)/64 -> 0 | E6: =C6+D6 -> 2141.5 | F6: =IF($C$70=0, 0, E6/$C$70) -> 0.0055356014 | G6: =F6*$T$5 -> 220.31694 | H6: 3 | I6: =$T$7*H6 -> 336.63 | J6: =G6+$T$9+I6 -> 562.20678 | K6: =$T$4/64 -> 4492.625 | L6: 0 | M6: 0 | N6: 0 | O6: 0 | P6: 0 | Q6: 500 | R6: =(J6+K6+L6+M6+Q6+N6+O6+P6)*$B$2 -> 5554.8318
A7: F2 | B7: Shanthanu | C7: 13938 | D7: =SUM($C$3:$C$5)/64 -> 0 | E7: =C7+D7 -> 13938 | F7: =IF($C$70=0, 0, E7/$C$70) -> 0.036028584 | G7: =F7*$T$5 -> 1433.9376 | H7: 4 | I7: =$T$7*H7 -> 448.84 | J7: =G7+$T$9+I7 -> 1888.0375 | K7: =$T$4/64 -> 4492.625 | L7: 0 | M7: 0 | N7: 0 | O7: 0 | P7: 0 | Q7: 500 | R7: =(J7+K7+L7+M7+Q7+N7+O7+P7)*$B$2 -> 6880.6625 | S7: RENT PER METER (Rs) | T7: 112.21
A8: F3 | B8: Samrat Kar | C8: 12648.5 | D8: =SUM($C$3:$C$5)/64 -> 0 | E8: =C8+D8 -> 12648.5 | F8: =IF($C$70=0, 0, E8/$C$70) -> 0.032695333 | G8: =F8*$T$5 -> 1301.2742 | H8: 4 | I8: =$T$7*H8 -> 448.84 | J8: =G8+$T$9+I8 -> 1755.3741 | K8: =$T$4/64 -> 4492.625 | L8: 750 | M8: 0 | N8: 0 | O8: 0 | P8: 0 | Q8: 500 | R8: =(J8+K8+L8+M8+Q8+N8+O8+P8)*$B$2 -> 7497.9991 | S8: COMMON AREA METER RENT(Rs) | T8: =$T$7*3 -> 336.63
A9: F4 | B9: Renu R | C9: 2944 | D9: =SUM($C$3:$C$5)/64 -> 0 | E9: =C9+D9 -> 2944 | F9: =IF($C$70=0, 0, E9/$C$70) -> 0.0076099979 | G9: =F9*$T$5 -> 302.87792 | H9: 4 | I9: =$T$7*H9 -> 448.84 | J9: =G9+$T$9+I9 -> 756.97776 | K9: =$T$4/64 -> 4492.625 | L9: 0 | M9: 0 | N9: 0 | O9: 0 | P9: 0 | Q9: 500 | R9: =(J9+K9+L9+M9+Q9+N9+O9+P9)*$B$2 -> 5749.6028 | S9: COMMON AREA METER RENT/FLAT (Rs) | T9: =T8/64 -> 5.2598437
A10: F5 | B10: Vamsidhar Bethanabatla / Madhuri Anumula | C10: 645.5 | D10: =SUM($C$3:$C$5)/64 -> 0 | E10: =C10+D10 -> 645.5 | F10: =IF($C$70=0, 0, E10/$C$70) -> 0.0016685644 | G10: =F10*$T$5 -> 66.408864 | H10: 3 | I10: =$T$7*H10 -> 336.63 | J10: =G10+$T$9+I10 -> 408.29871 | K10: =$T$4/64 -> 4492.625 | L10: 0 | M10: 0 | N10: 0 | O10: 0 | P10: 0 | Q10: 500 | R10: =(J10+K10+L10+M10+Q10+N10+O10+P10)*$B$2 -> 5400.9237
A11: F6 | B11: Meghana Viral Shah and Vviral Shah (Owner) / Sangeet and Swagat (Tenent) | C11: 5452 | D11: =SUM($C$3:$C$5)/64 -> 0 | E11: =C11+D11 -> 5452 | F11: =IF($C$70=0, 0, E11/$C$70) -> 0.014092972 | G11: =F11*$T$5 -> 560.90028 | H11: 3 | I11: =$T$7*H11 -> 336.63 | J11: =G11+$T$9+I11 -> 902.79012 | K11: =$T$4/64 -> 4492.625 | L11: 0 | M11: 0 | N11: 0 | O11: 0 | P11: 0 | Q11: 500 | R11: =(J11+K11+L11+M11+Q11+N11+O11+P11)*$B$2 -> 5895.4151 | S11: BALANCE IN ACCOUNT ON 30-Apr-2023
A12: F7 | B12: Vimal NK | C12: 938 | D12: =SUM($C$3:$C$5)/64 -> 0 | E12: =C12+D12 -> 938 | F12: =IF($C$70=0, 0, E12/$C$70) -> 0.0024246529 | G12: =F12*$T$5 -> 96.501185 | H12: 3 | I12: =$T$7*H12 -> 336.63 | J12: =G12+$T$9+I12 -> 438.39103 | K12: =$T$4/64 -> 4492.625 | L12: 750 | M12: 0 | N12: 0 | O12: 0 | P12: 0 | Q12: 500 | R12: =(J12+K12+L12+M12+Q12+N12+O12+P12)*$B$2 -> 6181.016 | S12: TOTAL NON MAINTENANCE CORPUS COLLECTION
A13: F8 | B13: Sujeet Kumar (Tenant)/Sreejith Menon (Owner) | C13: 249 | D13: =SUM($C$3:$C$5)/64 -> 0 | E13: =C13+D13 -> 249 | F13: =IF($C$70=0, 0, E13/$C$70) -> 0.00064364453 | G13: =F13*$T$5 -> 25.617052 | H13: 3 | I13: =$T$7*H13 -> 336.63 | J13: =G13+$T$9+I13 -> 367.5069 | K13: =$T$4/64 -> 4492.625 | L13: 0 | M13: 0 | N13: 0 | O13: 0 | P13: 0 | Q13: 500 | R13: =(J13+K13+L13+M13+Q13+N13+O13+P13)*$B$2 -> 5360.1319 | S13: TOTAL FD DONE
A14: F9 | B14: Vijay Suswaram (Owner) / Divya Shikha (Tenant) | C14: 1109.5 | D14: =SUM($C$3:$C$5)/64 -> 0 | E14: =C14+D14 -> 1109.5 | F14: =IF($C$70=0, 0, E14/$C$70) -> 0.0028679663 | G14: =F14*$T$5 -> 114.14506 | H14: 4 | I14: =$T$7*H14 -> 448.84 | J14: =G14+$T$9+I14 -> 568.2449 | K14: =$T$4/64 -> 4492.625 | L14: 0 | M14: 0 | N14: 0 | O14: 0 | P14: 0 | Q14: 500 | R14: =(J14+K14+L14+M14+Q14+N14+O14+P14)*$B$2 -> 5560.8699 | S14: AMOUNT AVAILABLE FOR NON MAINTENANCE CORPUS IN CURRENT AC | T14: =T12-T13 -> 0
A15: F10 | B15: Aby Thomas | C15: 2961 | D15: =SUM($C$3:$C$5)/64 -> 0 | E15: =C15+D15 -> 2961 | F15: =IF($C$70=0, 0, E15/$C$70) -> 0.0076539415 | G15: =F15*$T$5 -> 304.62687 | H15: 3 | I15: =$T$7*H15 -> 336.63 | J15: =G15+$T$9+I15 -> 646.51672 | K15: =$T$4/64 -> 4492.625 | L15: 0 | M15: 0 | N15: 1000 | O15: 0 | P15: 0 | Q15: 500 | R15: =(J15+K15+L15+M15+Q15+N15+O15+P15)*$B$2 -> 6639.1417 | S15: Pending vendor payments
A16: F11 | B16: Niwin Anto | C16: 509 | D16: =SUM($C$3:$C$5)/64 -> 0 | E16: =C16+D16 -> 509 | F16: =IF($C$70=0, 0, E16/$C$70) -> 0.0013157232 | G16: =F16*$T$5 -> 52.365781 | H16: 3 | I16: =$T$7*H16 -> 336.63 | J16: =G16+$T$9+I16 -> 394.25563 | K16: =$T$4/64 -> 4492.625 | L16: 0 | M16: 0 | N16: 0 | O16: 0 | P16: 0 | Q16: 500 | R16: =(J16+K16+L16+M16+Q16+N16+O16+P16)*$B$2 -> 5386.8806 | S16: AMOUNT AVAILABLE FOR MAINTENANCE | T16: =T11-T14-T15 -> 0
A17: F12 | B17: Anirudh Singh | C17: 0 | D17: =SUM($C$3:$C$5)/64 -> 0 | E17: =C17+D17 -> 0 | F17: =IF($C$70=0, 0, E17/$C$70) -> 0 | G17: =F17*$T$5 -> 0 | H17: 3 | I17: =$T$7*H17 -> 336.63 | J17: =G17+$T$9+I17 -> 341.88984 | K17: =$T$4/64 -> 4492.625 | L17: 0 | M17: 0 | N17: 0 | O17: 0 | P17: 0 | Q17: 500 | R17: =(J17+K17+L17+M17+Q17+N17+O17+P17)*$B$2 -> 5334.5148 | S17: TOTAL EXPENSE FOR THE MONTH | T17: ='ANNUAL-EXPENSE-DETAILS'!BI9 -> 0
A18: F13 | B18: Sanchay Saxena | C18: 261.5 | D18: =SUM($C$3:$C$5)/64 -> 0 | E18: =C18+D18 -> 261.5 | F18: =IF($C$70=0, 0, E18/$C$70) -> 0.000675956 | G18: =F18*$T$5 -> 26.903049 | H18: 4 | I18: =$T$7*H18 -> 448.84 | J18: =G18+$T$9+I18 -> 481.00289 | K18: =$T$4/64 -> 4492.625 | L18: 0 | M18: 0 | N18: 0 | O18: 0 | P18: 0 | Q18: 500 | R18: =(J18+K18+L18+M18+Q18+N18+O18+P18)*$B$2 -> 5473.6279 | S18: Maintenance deficit | T18: =T16-T17 -> 0
A19: F14 | B19: Hemant Patel | C19: 1 | D19: =SUM($C$3:$C$5)/64 -> 0 | E19: =C19+D19 -> 1 | F19: =IF($C$70=0, 0, E19/$C$70) -> 2.5849178e-06 | G19: =F19*$T$5 -> 0.10287973 | H19: 4 | I19: =$T$7*H19 -> 448.84 | J19: =G19+$T$9+I19 -> 454.20272 | K19: =$T$4/64 -> 4492.625 | L19: 750 | M19: 0 | N19: 0 | O19: 0 | P19: 0 | Q19: 500 | R19: =(J19+K19+L19+M19+Q19+N19+O19+P19)*$B$2 -> 6196.8277
A20: F15 | B20: Senthil.Vijayaragavan | C20: 2992.5 | D20: =SUM($C$3:$C$5)/64 -> 0 | E20: =C20+D20 -> 2992.5 | F20: =IF($C$70=0, 0, E20/$C$70) -> 0.0077353665 | G20: =F20*$T$5 -> 307.86759 | H20: 4 | I20: =$T$7*H20 -> 448.84 | J20: =G20+$T$9+I20 -> 761.96743 | K20: =$T$4/64 -> 4492.625 | L20: 750 | M20: 0 | N20: 0 | O20: 0 | P20: 0 | Q20: 500 | R20: =(J20+K20+L20+M20+Q20+N20+O20+P20)*$B$2 -> 6504.5924
A21: F16 | B21: Sreeja Sudharma | C21: 11572 | D21: =SUM($C$3:$C$5)/64 -> 0 | E21: =C21+D21 -> 11572 | F21: =IF($C$70=0, 0, E21/$C$70) -> 0.029912669 | G21: =F21*$T$5 -> 1190.5242 | H21: 3 | I21: =$T$7*H21 -> 336.63 | J21: =G21+$T$9+I21 -> 1532.4141 | K21: =$T$4/64 -> 4492.625 | L21: 0 | M21: 0 | N21: 0 | O21: 0 | P21: 0 | Q21: 500 | R21: =(J21+K21+L21+M21+Q21+N21+O21+P21)*$B$2 -> 6525.0391
A22: G1 | B22: Venkataramanan C | C22: 9626.5 | D22: =SUM($C$3:$C$5)/64 -> 0 | E22: =C22+D22 -> 9626.5 | F22: =IF($C$70=0, 0, E22/$C$70) -> 0.024883711 | G22: =F22*$T$5 -> 990.3717 | H22: 3 | I22: =$T$7*H22 -> 336.63 | J22: =G22+$T$9+I22 -> 1332.2615 | K22: =$T$4/64 -> 4492.625 | L22: 0 | M22: 0 | N22: 0 | O22: 0 | P22: 0 | Q22: 500 | R22: =(J22+K22+L22+M22+Q22+N22+O22+P22)*$B$2 -> 6324.8865
A23: G2 | B23: Kaushik Kasibhatla | C23: 18123 | D23: =SUM($C$3:$C$5)/64 -> 0 | E23: =C23+D23 -> 18123 | F23: =IF($C$70=0, 0, E23/$C$70) -> 0.046846465 | G23: =F23*$T$5 -> 1864.4893 | H23: 4 | I23: =$T$7*H23 -> 448.84 | J23: =G23+$T$9+I23 -> 2318.5891 | K23: =$T$4/64 -> 4492.625 | L23: 0 | M23: 0 | N23: 0 | O23: 0 | P23: 0 | Q23: 500 | R23: =(J23+K23+L23+M23+Q23+N23+O23+P23)*$B$2 -> 7311.2141
A24: G3 | B24: Balakrishnan | C24: 10814 | D24: =SUM($C$3:$C$5)/64 -> 0 | E24: =C24+D24 -> 10814 | F24: =IF($C$70=0, 0, E24/$C$70) -> 0.027953301 | G24: =F24*$T$5 -> 1112.5414 | H24: 4 | I24: =$T$7*H24 -> 448.84 | J24: =G24+$T$9+I24 -> 1566.6412 | K24: =$T$4/64 -> 4492.625 | L24: 0 | M24: 0 | N24: 0 | O24: 0 | P24: 0 | Q24: 500 | R24: =(J24+K24+L24+M24+Q24+N24+O24+P24)*$B$2 -> 6559.2662
A25: G4 | B25: Ashwin Pandith | C25: 14242 | D25: =SUM($C$3:$C$5)/64 -> 0 | E25: =C25+D25 -> 14242 | F25: =IF($C$70=0, 0, E25/$C$70) -> 0.036814399 | G25: =F25*$T$5 -> 1465.2131 | H25: 4 | I25: =$T$7*H25 -> 448.84 | J25: =G25+$T$9+I25 -> 1919.3129 | K25: =$T$4/64 -> 4492.625 | L25: 0 | M25: 0 | N25: 0 | O25: 0 | P25: 0 | Q25: 500 | R25: =(J25+K25+L25+M25+Q25+N25+O25+P25)*$B$2 -> 6911.9379
A26: G5 | B26: Mayank Phophaliya | C26: 1868.5 | D26: =SUM($C$3:$C$5)/64 -> 0 | E26: =C26+D26 -> 1868.5 | F26: =IF($C$70=0, 0, E26/$C$70) -> 0.0048299189 | G26: =F26*$T$5 -> 192.23077 | H26: 3 | I26: =$T$7*H26 -> 336.63 | J26: =G26+$T$9+I26 -> 534.12061 | K26: =$T$4/64 -> 4492.625 | L26: 0 | M26: 0 | N26: 0 | O26: 0 | P26: 0 | Q26: 500 | R26: =(J26+K26+L26+M26+Q26+N26+O26+P26)*$B$2 -> 5526.7456
A27: G6 | B27: Mohit Daga | C27: 11222.5 | D27: =SUM($C$3:$C$5)/64 -> 0 | E27: =C27+D27 -> 11222.5 | F27: =IF($C$70=0, 0, E27/$C$70) -> 0.02900924 | G27: =F27*$T$5 -> 1154.5677 | H27: 3 | I27: =$T$7*H27 -> 336.63 | J27: =G27+$T$9+I27 -> 1496.4576 | K27: =$T$4/64 -> 4492.625 | L27: 0 | M27: 0 | N27: 0 | O27: 0 | P27: 0 | Q27: 500 | R27: =(J27+K27+L27+M27+Q27+N27+O27+P27)*$B$2 -> 6489.0826
A28: G7 | B28: Prince Richfield | C28: 4402.5 | D28: =SUM($C$3:$C$5)/64 -> 0 | E28: =C28+D28 -> 4402.5 | F28: =IF($C$70=0, 0, E28/$C$70) -> 0.011380101 | G28: =F28*$T$5 -> 452.928 | H28: 3 | I28: =$T$7*H28 -> 336.63 | J28: =G28+$T$9+I28 -> 794.81784 | K28: =$T$4/64 -> 4492.625 | L28: 0 | M28: 0 | N28: 0 | O28: 0 | P28: 0 | Q28: 500 | R28: =(J28+K28+L28+M28+Q28+N28+O28+P28)*$B$2 -> 5787.4428
A29: G8 | B29: Ranjithkumar R / Sameer (tenant) / Princy (tenant) | C29: 9830 | D29: =SUM($C$3:$C$5)/64 -> 0 | E29: =C29+D29 -> 9830 | F29: =IF($C$70=0, 0, E29/$C$70) -> 0.025409742 | G29: =F29*$T$5 -> 1011.3077 | H29: 3 | I29: =$T$7*H29 -> 336.63 | J29: =G29+$T$9+I29 -> 1353.1976 | K29: =$T$4/64 -> 4492.625 | L29: 0 | M29: 0 | N29: 0 | O29: 0 | P29: 0 | Q29: 500 | R29: =(J29+K29+L29+M29+Q29+N29+O29+P29)*$B$2 -> 6345.8226
A30: G9 | B30: Chandramouli | C30: 6673.5 | D30: =SUM($C$3:$C$5)/64 -> 0 | E30: =C30+D30 -> 6673.5 | F30: =IF($C$70=0, 0, E30/$C$70) -> 0.017250449 | G30: =F30*$T$5 -> 686.56786 | H30: 5 | I30: =$T$7*H30 -> 561.05 | J30: =G30+$T$9+I30 -> 1252.8777 | K30: =$T$4/64 -> 4492.625 | L30: 0 | M30: 0 | N30: 0 | O30: 0 | P30: 0 | Q30: 500 | R30: =(J30+K30+L30+M30+Q30+N30+O30+P30)*$B$2 -> 6245.5027
... A69: T16 | B69: Madhusoodanan P.R. | C69: 3201.5 | D69: =SUM($C$3:$C$5)/64 -> 0 | E69: =C69+D69 -> 3201.5 | F69: =IF($C$70=0, 0, E69/$C$70) -> 0.0082756143 | G69: =F69*$T$5 -> 329.36945 | H69: 3 | I69: =$T$7*H69 -> 336.63 | J69: =G69+$T$9+I69 -> 671.25929 | K69: =$T$4/64 -> 4492.625 | L69: 0 | M69: 0 | N69: 0 | O69: 0 | P69: 0 | Q69: 500 | R69: =(J69+K69+L69+M69+Q69+N69+O69+P69)*$B$2 -> 5663.8843
A70: TOTAL | B70: TOTAL | C70: =SUM(C3:C69) -> 386859.5 | D70: =SUM(D3:D69) -> 0 | E70: =SUM(E5:E69) -> 386859.5 | F70: =SUM(F6:F69) -> 1 | G70: =SUM(G6:G69) -> 39800 | H70: =SUM(H3:H69) -> 223 | I70: =SUM(I3:I69) -> 25022.83 | J70: =SUM(J6:J69) -> 64822.83 | K70: =SUM(K6:K69) -> 287528 | L70: =SUM(L6:L69) -> 3750 | M70: =SUM(M6:M69) -> 0 | N70: =SUM(N6:N69) -> 1000 | O70: =SUM(O6:O69) -> 0 | P70: =SUM(P6:P69) -> 0 | Q70: =SUM(Q6:Q69) -> 32000 | R70: =SUM(R6:R69) -> 389100.83

Sheet Apr2025-COLLECTION
A1: FLAT # | C1: Amount | D1: Date | E1: Amount | F1: Date | G1: Amount | H1: Date | I1: Amount | J1: Date | K1: Total
A2: F1 | B2: Shailesh Srivastava / Azeem Nawaz | C2: 4944 | D2: 45775 | K2: =SUM(C2,E2,G2,I2) -> 4944
A3: F2 | B3: Shanthanu | K3: =SUM(C3,E3,G3,I3) -> 0
A4: F3 | B4: Samrat Kar | C4: 6000 | D4: 45748 | E4: 6317 | F4: 45768 | K4: =SUM(C4,E4,G4,I4) -> 12317
A5: F4 | B5: Renu R | C5: 5000 | D5: 45761 | K5: =SUM(C5,E5,G5,I5) -> 5000
A6: F5 | B6: Vamsidhar Bethanabatla / Madhuri Anumula | C6: 9457 | D6: 45768 | K6: =SUM(C6,E6,G6,I6) -> 9457
A7: F6 | B7: Meghana Viral Shah and Vviral Shah (Owner) / Sangeet and Swagat (Tenent) | C7: 4155 | D7: 45756 | E7: 4871 | F7: 45775 | K7: =SUM(C7,E7,G7,I7) -> 9026
A8: F7 | B8: Vimal NK | K8: =SUM(C8,E8,G8,I8) -> 0
A9: F8 | B9: Sujeet Kumar (Tenant)/Sreejith Menon (Owner) | C9: 4603 | D9: 45762 | K9: =SUM(C9,E9,G9,I9) -> 4603
A10: F9 | B10: Vijay Suswaram (Owner) / Divya Shikha (Tenant) | C10: 4943 | D10: 45767 | K10: =SUM(C10,E10,G10,I10) -> 4943
A11: F10 | B11: Aby Thomas | C11: 5314 | D11: 45750 | K11: =SUM(C11,E11,G11,I11) -> 5314
A12: F11 | B12: N. Geetha | C12: 4632 | D12: 45762 | K12: =SUM(C12,E12,G12,I12) -> 4632
A13: F12 | B13: Anirudh Singh | C13: 4603 | D13: 45761 | K13: =SUM(C13,E13,G13,I13) -> 4603
A14: F13 | B14: Sanchay Saxena | C14: 4730 | D14: 45775 | K14: =SUM(C14,E14,G14,I14) -> 4730
A15: F14 | B15: Hemant Patel | C15: 5727 | D15: 45765 | K15: =SUM(C15,E15,G15,I15) -> 5727
A16: F15 | B16: Senthil.Vijayaragavan | C16: 5709 | D16: 45769 | K16: =SUM(C16,E16,G16,I16) -> 5709
A17: F16 | B17: Sreeja Sudharma | K17: =SUM(C17,E17,G17,I17) -> 0
A18: G1 | B18: Venkataramanan C | C18: 5139 | D18: 45770 | K18: =SUM(C18,E18,G18,I18) -> 5139
A19: G2 | B19: Kaushik Kasibhatla | C19: 5645 | D19: 45765 | K19: =SUM(C19,E19,G19,I19) -> 5645
A20: G3 | B20: Balakrishnan | C20: 5364 | D20: 45771 | K20: =SUM(C20,E20,G20,I20) -> 5364
A21: G4 | B21: Ashwin Pandith | C21: 5441 | D21: 45771 | K21: =SUM(C21,E21,G21,I21) -> 5441
A22: G5 | B22: Mayank Phophaliya | K22: =SUM(C22,E22,G22,I22) -> 0
A23: G6 | B23: Mohit Daga | K23: =SUM(C23,E23,G23,I23) -> 0
A24: G7 | B24: Prince Richfield | C24: 9614 | D24: 45762 | K24: =SUM(C24,E24,G24,I24) -> 9614
A25: G8 | B25: Ranjithkumar R / Sameer (tenant) / Princy (tenant) | C25: 15000 | D25: 45750 | K25: =SUM(C25,E25,G25,I25) -> 15000
A26: G9 | B26: Chandramouli | K26: =SUM(C26,E26,G26,I26) -> 0
A27: G10 | B27: Cijo Jacob / Thara Joy | C27: 4965 | D27: 45760 | K27: =SUM(C27,E27,G27,I27) -> 4965
A28: G11 | B28: Ketan Verlekar | K28: =SUM(C28,E28,G28,I28) -> 0
A29: G12 | B29: Shyam Nair | C29: 4112 | D29: 45749 | E29: 4868 | F29: 45762 | K29: =SUM(C29,E29,G29,I29) -> 8980
A30: G13 | B30: Ajai.B | K30: =SUM(C30,E30,G30,I30) -> 0
A31: G14 | B31: Surajit Borah | C31: 5081 | D31: 45762 | K31: =SUM(C31,E31,G31,I31) -> 5081
A32: G15 | B32: Suresh Nallusamy / Antriksh (tenant) | C32: 4403 | D32: 45749 | E32: 4935 | F32: 45765 | K32: =SUM(C32,E32,G32,I32) -> 9338
A33: G16 | B33: Praveen Ganesan | C33: 9047 | D33: 45767 | K33: =SUM(C33,E33,G33,I33) -> 9047
A34: S1 | B34: S.N.Behera | C34: 4592 | D34: 45766 | K34: =SUM(C34,E34,G34,I34) -> 4592
A35: S2 | B35: Sonal Singh | K35: =SUM(C35,E35,G35,I35) -> 0
A36: S3 | B36: Koteswararao | C36: 5088 | D36: 45770 | K36: =SUM(C36,E36,G36,I36) -> 5088
A37: S4 | B37: Swaminathan | C37: 4768 | D37: 45762 | K37: =SUM(C37,E37,G37,I37) -> 4768
A38: S5 | B38: Abhishek Gopalakrishnan | K38: =SUM(C38,E38,G38,I38) -> 0
A39: S6 | B39: Vivek Dhingra / Pratyush Das | K39: =SUM(C39,E39,G39,I39) -> 0
A40: S7 | B40: Harish B | C40: 4677 | D40: 45771 | K40: =SUM(C40,E40,G40,I40) -> 4677
A41: S8 | B41: Irudayaraj Alwin | C41: 5994 | D41: 45777 | K41: =SUM(C41,E41,G41,I41) -> 5994
A42: S9 | B42: Pawan GS | C42: 6000 | D42: 45767 | K42: =SUM(C42,E42,G42,I42) -> 6000
A43: S10 | B43: Lakshmikanth | K43: =SUM(C43,E43,G43,I43) -> 0
A44: S11 | B44: Gowrish Patnaik / Somananth GM | C44: 4685 | D44: 45765 | K44: =SUM(C44,E44,G44,I44) -> 4685
A45: S12 | B45: Saovik Mondal | C45: 5270 | D45: 45767 | K45: =SUM(C45,E45,G45,I45) -> 5270
A46: S13 | B46: Ramadevi S. | C46: 4808 | D46: 45775 | K46: =SUM(C46,E46,G46,I46) -> 4808
A47: S14 | B47: Nishant Upadhyay(Owner)/ Fabian (Tenant) | C47: 12494 | D47: 45769 | K47: =SUM(C47,E47,G47,I47) -> 12494
A48: S15 | B48: Manas Dasgupta | K48: =SUM(C48,E48,G48,I48) -> 0
A49: S16 | B49: Devendra Singh Rawat / Nancy | C49: 10455 | D49: 45767 | K49: =SUM(C49,E49,G49,I49) -> 10455
A50: T1 | B50: Prashant Sikdar | C50: 5820 | D50: 45772 | K50: =SUM(C50,E50,G50,I50) -> 5820
A51: T2 | B51: Kunal Mehta | C51: 5236 | D51: 45761 | K51: =SUM(C51,E51,G51,I51) -> 5236
A52: T3 | B52: Kapil Garg | C52: 4978 | D52: 45765 | K52: =SUM(C52,E52,G52,I52) -> 4978
A53: T4 | B53: Vijet Alva (Owner) - Masood (Tenant) | C53: 10099 | D53: 45771 | K53: =SUM(C53,E53,G53,I53) -> 10099
A54: T5 | B54: Ganesh Iyer and Latha Iyer( owner) Richa (Tenant) | C54: 4996 | D54: 45761 | K54: =SUM(C54,E54,G54,I54) -> 4996
A55: T6 | B55: Mythili Ramesh | C55: 4864 | D55: 45750 | E55: 5499 | F55: 45776 | K55: =SUM(C55,E55,G55,I55) -> 10363
A56: T7 | B56: Vinyas Ramachandra / Shwetha Marnamikatta / Katari Siva Rama Raju | K56: =SUM(C56,E56,G56,I56) -> 0
A57: T8 | B57: Lalit Kumar Sharma | C57: 10568 | D57: 45768 | K57: =SUM(C57,E57,G57,I57) -> 10568
A58: T9 | B58: Nishith Sahu and Priyanka Rani (Owner)/ Anmol Verma (Tenant) | C58: 5255 | D58: 45762 | K58: =SUM(C58,E58,G58,I58) -> 5255
A59: T10 | B59: Vamsidhar Bethanabatla / Madhuri Anumula | C59: 5754 | D59: 45768 | K59: =SUM(C59,E59,G59,I59) -> 5754
A60: T11 | B60: Arvind Balasubramanian | C60: 4809 | D60: 45777 | K60: =SUM(C60,E60,G60,I60) -> 4809
A61: T12 | B61: Prasenjit | C61: 4668 | D61: 45761 | K61: =SUM(C61,E61,G61,I61) -> 4668
A62: T13 | B62: Rahul Kumar | K62: =SUM(C62,E62,G62,I62) -> 0
A63: T14 | B63: Jeya / Kanda / Satya (tenant)/Vinuta (tenant) | C63: 6065 | D63: 45753 | K63: =SUM(C63,E63,G63,I63) -> 6065
A64: T15 | B64: Trevor | C64: 5359 | D64: 45766 | K64: =SUM(C64,E64,G64,I64) -> 5359
A65: T16 | B65: Madhusoodanan P.R. | C65: 9775 | D65: 45777 | K65: =SUM(C65,E65,G65,I65) -> 9775
A66: TOTAL | K66: =SUM(K2:K65) -> 327195

Sheet May2025-EXPENSE
A1: 1 | B1: MAY 2025 EXPENSES
A2: FLAT # | B2: 1 | C2: WATER USED IN LTRS | D2: COMMON AREA EQUALLY DEVIDED | E2: TOTAL FRESH WATER CONSUMED | F2: %OF TOTAL USED | G2: WATER EXPENSE SHARING BY % | H2: #METERS | I2: METER RENT | J2: VARIABLE EXPENSE = COMMON AREA METER RENT + WATER EXPENSE+ FLAT METER RENT | K2: FIXED EXPENSE SHARE | L2: PARKING FEE | M2: CLUB HOUSE BOOKING | N2: SHIFTING FEE | O2: GYM USAGE FEE | P2: POLYCARBONATE SHEET REPAIR | R2: TOTAL EXPENSE TO BE PAID
A3: CH | B3: MPFOWA | C3: 0 | D3: 0 | H3: 1 | I3: =T7 -> 117.81166
A4: GYM | B4: MPFOWA | C4: 0 | D4: 0 | H4: 1 | I4: =T7 -> 117.81166 | S4: TOTAL FIXED EXPENSE | T4: ='ANNUAL-EXPENSE-DETAILS'!BF4 -> 234938
A5: BSMT | B5: MPFOWA | C5: 0 | D5: 0 | H5: 1 | I5: =T7 -> 117.81166 | S5: TOTAL WATER EXPENSE | T5: ='ANNUAL-EXPENSE-DETAILS'!BE4 -> 38600
A6: F1 | B6: Shailesh Srivastava / Azeem Nawaz | C6: 3713 | D6: =SUM($C$3:$C$5)/64 -> 0 | E6: =C6+D6 -> 3713 | F6: =IF($C$70=0, 0, E6/$C$70) -> 0.0093496421 | G6: =F6*$T$5 -> 360.89619 | H6: 3 | I6: =$T$7*H6 -> 353.43498 | J6: =G6+$T$9+I6 -> 719.85358 | K6: =$T$4/64 -> 3670.9062 | L6: 0 | M6: 0 | N6: 0 | O6: 0 | R6: =(SUM(J6:P6)*$B$2) -> 4390.7598
A7: F2 | B7: Shanthanu | C7: 14642 | D7: =SUM($C$3:$C$5)/64 -> 0 | E7: =C7+D7 -> 14642 | F7: =IF($C$70=0, 0, E7/$C$70) -> 0.036869771 | G7: =F7*$T$5 -> 1423.1732 | H7: 4 | I7: =$T$7*H7 -> 471.24664 | J7: =G7+$T$9+I7 -> 1899.9422 | K7: =$T$4/64 -> 3670.9062 | L7: 0 | M7: 0 | N7: 0 | O7: 0 | R7: =(SUM(J7:P7)*$B$2) -> 5570.8485 | S7: RENT PER METER | T7: 117.81166
A8: F3 | B8: Samrat Kar | C8: 11039 | D8: =SUM($C$3:$C$5)/64 -> 0 | E8: =C8+D8 -> 11039 | F8: =IF($C$70=0, 0, E8/$C$70) -> 0.027797118 | G8: =F8*$T$5 -> 1072.9688 | H8: 4 | I8: =$T$7*H8 -> 471.24664 | J8: =G8+$T$9+I8 -> 1549.7378 | K8: =$T$4/64 -> 3670.9062 | L8: 750 | M8: 0 | N8: 0 | O8: 0 | R8: =(SUM(J8:P8)*$B$2) -> 5970.6441 | S8: COMMON AREA METER RENT | T8: =$T$7*3 -> 353.43498
A9: F4 | B9: Renu R | C9: 3180 | D9: =SUM($C$3:$C$5)/64 -> 0 | E9: =C9+D9 -> 3180 | F9: =IF($C$70=0, 0, E9/$C$70) -> 0.0080075039 | G9: =F9*$T$5 -> 309.08965 | H9: 4 | I9: =$T$7*H9 -> 471.24664 | J9: =G9+$T$9+I9 -> 785.85871 | K9: =$T$4/64 -> 3670.9062 | L9: 0 | M9: 0 | N9: 0 | O9: 0 | R9: =(SUM(J9:P9)*$B$2) -> 4456.765 | S9: COMMON AREA METER RENT/FLAT | T9: =T8/64 -> 5.5224215
A10: F5 | B10: Vamsidhar Bethanabatla / Madhuri Anumula | C10: 94.5 | D10: =SUM($C$3:$C$5)/64 -> 0 | E10: =C10+D10 -> 94.5 | F10: =IF($C$70=0, 0, E10/$C$70) -> 0.00023795884 | G10: =F10*$T$5 -> 9.1852113 | H10: 3 | I10: =$T$7*H10 -> 353.43498 | J10: =G10+$T$9+I10 -> 368.14261 | K10: =$T$4/64 -> 3670.9062 | L10: 0 | M10: 0 | N10: 0 | O10: 0 | R10: =(SUM(J10:P10)*$B$2) -> 4039.0489
A11: F6 | B11: Meghana Viral Shah and Vviral Shah (Owner) / Sangeet and Swagat (Tenent) | C11: 3278 | D11: =SUM($C$3:$C$5)/64 -> 0 | E11: =C11+D11 -> 3278 | F11: =IF($C$70=0, 0, E11/$C$70) -> 0.008254276 | G11: =F11*$T$5 -> 318.61505 | H11: 3 | I11: =$T$7*H11 -> 353.43498 | J11: =G11+$T$9+I11 -> 677.57245 | K11: =$T$4/64 -> 3670.9062 | L11: 0 | M11: 0 | N11: 0 | O11: 0 | R11: =(SUM(J11:P11)*$B$2) -> 4348.4787
A12: F7 | B12: Vimal NK | C12: 384.5 | D12: =SUM($C$3:$C$5)/64 -> 0 | E12: =C12+D12 -> 384.5 | F12: =IF($C$70=0, 0, E12/$C$70) -> 0.00096820291 | G12: =F12*$T$5 -> 37.372632 | H12: 3 | I12: =$T$7*H12 -> 353.43498 | J12: =G12+$T$9+I12 -> 396.33003 | K12: =$T$4/64 -> 3670.9062 | L12: 750 | M12: 0 | N12: 0 | O12: 0 | R12: =(SUM(J12:P12)*$B$2) -> 4817.2363 | S12: BALANCE IN ACCOUNT TILL 31MAY2023
A13: F8 | B13: Sujeet Kumar (Tenant)/Sreejith Menon (Owner) | C13: 323 | D13: =SUM($C$3:$C$5)/64 -> 0 | E13: =C13+D13 -> 323 | F13: =IF($C$70=0, 0, E13/$C$70) -> 0.0008133408 | G13: =F13*$T$5 -> 31.394955 | H13: 3 | I13: =$T$7*H13 -> 353.43498 | J13: =G13+$T$9+I13 -> 390.35235 | K13: =$T$4/64 -> 3670.9062 | L13: 0 | M13: 0 | N13: 0 | O13: 0 | R13: =(SUM(J13:P13)*$B$2) -> 4061.2586 | S13: TOTAL NON MAINTENANCE CORPUS COLLECTION
A14: F9 | B14: Vijay Suswaram (Owner) / Divya Shikha (Tenant) | C14: 1898.5 | D14: =SUM($C$3:$C$5)/64 -> 0 | E14: =C14+D14 -> 1898.5 | F14: =IF($C$70=0, 0, E14/$C$70) -> 0.0047805805 | G14: =F14*$T$5 -> 184.53041 | H14: 4 | I14: =$T$7*H14 -> 471.24664 | J14: =G14+$T$9+I14 -> 661.29947 | K14: =$T$4/64 -> 3670.9062 | L14: 0 | M14: 0 | N14: 0 | O14: 0 | R14: =(SUM(J14:P14)*$B$2) -> 4332.2057 | S14: TOTAL FD DONE
A15: F10 | B15: Aby Thomas | C15: 2399.5 | D15: =SUM($C$3:$C$5)/64 -> 0 | E15: =C15+D15 -> 2399.5 | F15: =IF($C$70=0, 0, E15/$C$70) -> 0.0060421401 | G15: =F15*$T$5 -> 233.22661 | H15: 3 | I15: =$T$7*H15 -> 353.43498 | J15: =G15+$T$9+I15 -> 592.18401 | K15: =$T$4/64 -> 3670.9062 | L15: 0 | M15: 0 | N15: 0 | O15: 0 | R15: =(SUM(J15:P15)*$B$2) -> 4263.0903 | S15: Pending vendor payments
A16: F11 | B16: Niwin Anto | C16: 2663.5 | D16: =SUM($C$3:$C$5)/64 -> 0 | E16: =C16+D16 -> 2663.5 | F16: =IF($C$70=0, 0, E16/$C$70) -> 0.006706914 | G16: =F16*$T$5 -> 258.88688 | H16: 3 | I16: =$T$7*H16 -> 353.43498 | J16: =G16+$T$9+I16 -> 617.84428 | K16: =$T$4/64 -> 3670.9062 | L16: 0 | M16: 0 | N16: 0 | O16: 0 | R16: =(SUM(J16:P16)*$B$2) -> 4288.7505 | S16: AMOUNT AVAILABLE FOR NON MAINTENANCE CORPUS | T16: =T13-T14 -> 0
A17: F12 | B17: Anirudh Singh | C17: 6.5 | D17: =SUM($C$3:$C$5)/64 -> 0 | E17: =C17+D17 -> 6.5 | F17: =IF($C$70=0, 0, E17/$C$70) -> 1.6367539e-05 | G17: =F17*$T$5 -> 0.63178702 | H17: 3 | I17: =$T$7*H17 -> 353.43498 | J17: =G17+$T$9+I17 -> 359.58919 | K17: =$T$4/64 -> 3670.9062 | L17: 0 | M17: 0 | N17: 0 | O17: 0 | R17: =(SUM(J17:P17)*$B$2) -> 4030.4954 | S17: AMOUNT AVAILABLE FOR MAINTENANCE | T17: =T12-T15-T16 -> 0
A18: F13 | B18: Sanchay Saxena | C18: 11835 | D18: =SUM($C$3:$C$5)/64 -> 0 | E18: =C18+D18 -> 11835 | F18: =IF($C$70=0, 0, E18/$C$70) -> 0.029801512 | G18: =F18*$T$5 -> 1150.3384 | H18: 4 | I18: =$T$7*H18 -> 471.24664 | J18: =G18+$T$9+I18 -> 1627.1074 | K18: =$T$4/64 -> 3670.9062 | L18: 0 | M18: 0 | N18: 1000 | O18: 0 | R18: =(SUM(J18:P18)*$B$2) -> 6298.0137 | S18: Maintenance Deficit | T18: =T17-(T4+T5+23830) -> -297368
A19: F14 | B19: Hemant Patel | C19: 169 | D19: =SUM($C$3:$C$5)/64 -> 0 | E19: =C19+D19 -> 169 | F19: =IF($C$70=0, 0, E19/$C$70) -> 0.00042555602 | G19: =F19*$T$5 -> 16.426463 | H19: 4 | I19: =$T$7*H19 -> 471.24664 | J19: =G19+$T$9+I19 -> 493.19552 | K19: =$T$4/64 -> 3670.9062 | L19: 750 | M19: 0 | N19: 0 | O19: 0 | R19: =(SUM(J19:P19)*$B$2) -> 4914.1018
A20: F15 | B20: Senthil.Vijayaragavan | C20: 6077 | D20: =SUM($C$3:$C$5)/64 -> 0 | E20: =C20+D20 -> 6077 | F20: =IF($C$70=0, 0, E20/$C$70) -> 0.01530239 | G20: =F20*$T$5 -> 590.67227 | H20: 4 | I20: =$T$7*H20 -> 471.24664 | J20: =G20+$T$9+I20 -> 1067.4413 | K20: =$T$4/64 -> 3670.9062 | L20: 750 | M20: 0 | N20: 0 | O20: 0 | R20: =(SUM(J20:P20)*$B$2) -> 5488.3476
A21: F16 | B21: Sreeja Sudharma | C21: 14053.5 | D21: =SUM($C$3:$C$5)/64 -> 0 | E21: =C21+D21 -> 14053.5 | F21: =IF($C$70=0, 0, E21/$C$70) -> 0.035387879 | G21: =F21*$T$5 -> 1365.9721 | H21: 3 | I21: =$T$7*H21 -> 353.43498 | J21: =G21+$T$9+I21 -> 1724.9295 | K21: =$T$4/64 -> 3670.9062 | L21: 0 | M21: 0 | N21: 0 | O21: 0 | R21: =(SUM(J21:P21)*$B$2) -> 5395.8358
A22: G1 | B22: Venkataramanan C | C22: 10047 | D22: =SUM($C$3:$C$5)/64 -> 0 | E22: =C22+D22 -> 10047 | F22: =IF($C$70=0, 0, E22/$C$70) -> 0.02529918 | G22: =F22*$T$5 -> 976.54834 | H22: 3 | I22: =$T$7*H22 -> 353.43498 | J22: =G22+$T$9+I22 -> 1335.5057 | K22: =$T$4/64 -> 3670.9062 | L22: 0 | M22: 0 | N22: 0 | O22: 0 | R22: =(SUM(J22:P22)*$B$2) -> 5006.412
A23: G2 | B23: Kaushik Kasibhatla | C23: 10642 | D23: =SUM($C$3:$C$5)/64 -> 0 | E23: =C23+D23 -> 10642 | F23: =IF($C$70=0, 0, E23/$C$70) -> 0.026797439 | G23: =F23*$T$5 -> 1034.3811 | H23: 4 | I23: =$T$7*H23 -> 471.24664 | J23: =G23+$T$9+I23 -> 1511.1502 | K23: =$T$4/64 -> 3670.9062 | L23: 0 | M23: 0 | N23: 0 | O23: 0 | R23: =(SUM(J23:P23)*$B$2) -> 5182.0565
A24: G3 | B24: Balakrishnan | C24: 10536.5 | D24: =SUM($C$3:$C$5)/64 -> 0 | E24: =C24+D24 -> 10536.5 | F24: =IF($C$70=0, 0, E24/$C$70) -> 0.026531781 | G24: =F24*$T$5 -> 1024.1268 | H24: 4 | I24: =$T$7*H24 -> 471.24664 | J24: =G24+$T$9+I24 -> 1500.8958 | K24: =$T$4/64 -> 3670.9062 | L24: 0 | M24: 0 | N24: 0 | O24: 0 | R24: =(SUM(J24:P24)*$B$2) -> 5171.8021
A25: G4 | B25: Ashwin Pandith | C25: 10096 | D25: =SUM($C$3:$C$5)/64 -> 0 | E25: =C25+D25 -> 10096 | F25: =IF($C$70=0, 0, E25/$C$70) -> 0.025422566 | G25: =F25*$T$5 -> 981.31104 | H25: 4 | I25: =$T$7*H25 -> 471.24664 | J25: =G25+$T$9+I25 -> 1458.0801 | K25: =$T$4/64 -> 3670.9062 | L25: 0 | M25: 0 | N25: 0 | O25: 0 | R25: =(SUM(J25:P25)*$B$2) -> 5128.9863
A26: G5 | B26: Mayank Phophaliya | C26: 3222 | D26: =SUM($C$3:$C$5)/64 -> 0 | E26: =C26+D26 -> 3222 | F26: =IF($C$70=0, 0, E26/$C$70) -> 0.0081132634 | G26: =F26*$T$5 -> 313.17197 | H26: 3 | I26: =$T$7*H26 -> 353.43498 | J26: =G26+$T$9+I26 -> 672.12936 | K26: =$T$4/64 -> 3670.9062 | L26: 0 | M26: 0 | N26: 0 | O26: 0 | R26: =(SUM(J26:P26)*$B$2) -> 4343.0356
A27: G6 | B27: Mohit Daga | C27: 4532.5 | D27: =SUM($C$3:$C$5)/64 -> 0 | E27: =C27+D27 -> 4532.5 | F27: =IF($C$70=0, 0, E27/$C$70) -> 0.011413211 | G27: =F27*$T$5 -> 440.54995 | H27: 3 | I27: =$T$7*H27 -> 353.43498 | J27: =G27+$T$9+I27 -> 799.50735 | K27: =$T$4/64 -> 3670.9062 | L27: 0 | M27: 0 | N27: 0 | O27: 0 | R27: =(SUM(J27:P27)*$B$2) -> 4470.4136
A28: G7 | B28: Prince Richfield | C28: 720 | D28: =SUM($C$3:$C$5)/64 -> 0 | E28: =C28+D28 -> 720 | F28: =IF($C$70=0, 0, E28/$C$70) -> 0.0018130197 | G28: =F28*$T$5 -> 69.982562 | H28: 3 | I28: =$T$7*H28 -> 353.43498 | J28: =G28+$T$9+I28 -> 428.93996 | K28: =$T$4/64 -> 3670.9062 | L28: 0 | M28: 0 | N28: 0 | O28: 0 | R28: =(SUM(J28:P28)*$B$2) -> 4099.8462
A29: G8 | B29: Ranjithkumar R / Sameer (tenant) / Princy (tenant) | C29: 7814.5 | D29: =SUM($C$3:$C$5)/64 -> 0 | E29: =C29+D29 -> 7814.5 | F29: =IF($C$70=0, 0, E29/$C$70) -> 0.019677559 | G29: =F29*$T$5 -> 759.5538 | H29: 3 | I29: =$T$7*H29 -> 353.43498 | J29: =G29+$T$9+I29 -> 1118.5112 | K29: =$T$4/64 -> 3670.9062 | L29: 0 | M29: 0 | N29: 0 | O29: 0 | R29: =(SUM(J29:P29)*$B$2) -> 4789.4174
A30: G9 | B30: Chandramouli | C30: 4775 | D30: =SUM($C$3:$C$5)/64 -> 0 | E30: =C30+D30 -> 4775 | F30: =IF($C$70=0, 0, E30/$C$70) -> 0.012023846 | G30: =F30*$T$5 -> 464.12047 | H30: 5 | I30: =$T$7*H30 -> 589.0583 | J30: =G30+$T$9+I30 -> 1058.7012 | K30: =$T$4/64 -> 3670.9062 | L30: 0 | M30: 0 | N30: 0 | O30: 0 | R30: =(SUM(J30:P30)*$B$2) -> 4729.6074
... A69: T16 | B69: Madhusoodanan P.R. | C69: 1094 | D69: =SUM($C$3:$C$5)/64 -> 0 | E69: =C69+D69 -> 1094 | F69: =IF($C$70=0, 0, E69/$C$70) -> 0.0027547828 | G69: =F69*$T$5 -> 106.33462 | H69: 3 | I69: =$T$7*H69 -> 353.43498 | J69: =G69+$T$9+I69 -> 465.29201 | K69: =$T$4/64 -> 3670.9062 | L69: 0 | M69: 0 | N69: 0 | O69: 0 | R69: =(SUM(J69:P69)*$B$2) -> 4136.1983
A70: TOTAL | B70: TOTAL | C70: =SUM(C3:C69) -> 397127.5 | D70: =SUM(D3:D69) -> 0 | E70: =SUM(E5:E69) -> 397127.5 | F70: =SUM(F6:F69) -> 1 | G70: =SUM(G6:G69) -> 38600 | H70: =SUM(H3:H69) -> 223 | I70: =SUM(I3:I69) -> 26272 | J70: =SUM(J6:J69) -> 64872 | K70: =SUM(K6:K69) -> 234938 | L70: =SUM(L3:L69) -> 3750 | M70: =SUM(M3:M69) -> 0 | N70: =SUM(N3:N69) -> 5000 | O70: =SUM(O3:O69) -> 0 | P70: =SUM(P3:P69) -> 0 | R70: =SUM(R3:R69) -> 308560

Sheet May2025-COLLECTION
A1: FLAT # | C1: Amount | D1: Date | E1: Amount | F1: Date | G1: Amount | H1: Date | I1: Amount | J1: Date | K1: Total
A2: F1 | B2: Shailesh Srivastava / Azeem Nawaz | C2: 5513 | D2: 45800 | K2: =SUM(C2,E2,G2,I2) -> 5513
A3: F2 | B3: Shanthanu | C3: 9182 | D3: 45798 | K3: =SUM(C3,E3,G3,I3) -> 9182
A4: F3 | B4: Samrat Kar | C4: 6000 | D4: 45778 | K4: =SUM(C4,E4,G4,I4) -> 6000
A5: F4 | B5: Renu R | C5: 5710 | D5: 45792 | K5: =SUM(C5,E5,G5,I5) -> 5710
A6: F5 | B6: Vamsidhar Bethanabatla / Madhuri Anumula | C6: 5354 | D6: 45792 | K6: =SUM(C6,E6,G6,I6) -> 5354
A7: F6 | B7: Meghana Viral Shah and Vviral Shah (Owner) / Sangeet and Swagat (Tenent) | C7: 5864 | D7: 45807 | K7: =SUM(C7,E7,G7,I7) -> 5864
A8: F7 | B8: Vimal NK | C8: 5466 | D8: 45781 | E8: 6136 | F8: 45798 | K8: =SUM(C8,E8,G8,I8) -> 11602
A9: F8 | B9: Sujeet Kumar (Tenant)/Sreejith Menon (Owner) | C9: 5312 | D9: 45792 | K9: =SUM(C9,E9,G9,I9) -> 5312
A10: F9 | B10: Vijay Suswaram (Owner) / Divya Shikha (Tenant) | C10: 5516 | D10: 45796 | K10: =SUM(C10,E10,G10,I10) -> 5516
A11: F10 | B11: Aby Thomas | C11: 5600 | D11: 45806 | K11: =SUM(C11,E11,G11,I11) -> 5600
A12: F11 | B12: Niwin Anto | C12: 5340 | D12: 45794 | K12: =SUM(C12,E12,G12,I12) -> 5340
A13: F12 | B13: Anirudh Singh | C13: 5286 | D13: 45796 | K13: =SUM(C13,E13,G13,I13) -> 5286
A14: F13 | B14: Sanchay Saxena | C14: 5426 | D14: 45806 | K14: =SUM(C14,E14,G14,I14) -> 5426
A15: F14 | B15: Hemant Patel | C15: 6148 | D15: 45793 | K15: =SUM(C15,E15,G15,I15) -> 6148
A16: F15 | B16: Senthil.Vijayaragavan | C16: 6465 | D16: 45797 | K16: =SUM(C16,E16,G16,I16) -> 6465
A17: F16 | B17: Sreeja Sudharma | K17: =SUM(C17,E17,G17,I17) -> 0
A18: G1 | B18: Venkataramanan C | K18: =SUM(C18,E18,G18,I18) -> 0
A19: G2 | B19: Kaushik Kasibhatla | K19: =SUM(C19,E19,G19,I19) -> 0
A20: G3 | B20: Balakrishnan | C20: 6545 | D20: 45796 | K20: =SUM(C20,E20,G20,I20) -> 6545
A21: G4 | B21: Ashwin Pandith | C21: 6908 | D21: 45793 | K21: =SUM(C21,E21,G21,I21) -> 6908
A22: G5 | B22: Mayank Phophaliya | C22: 6000 | D22: 45797 | K22: =SUM(C22,E22,G22,I22) -> 6000
A23: G6 | B23: Mohit Daga | K23: =SUM(C23,E23,G23,I23) -> 0
A24: G7 | B24: Prince Richfield | C24: 5752 | D24: 45798 | K24: =SUM(C24,E24,G24,I24) -> 5752
A25: G8 | B25: Ranjithkumar R / Sameer (tenant) / Princy (tenant) | C25: 6328 | D25: 45806 | K25: =SUM(C25,E25,G25,I25) -> 6328
A26: G9 | B26: Chandramouli | C26: 5203 | D26: 45781 | K26: =SUM(C26,E26,G26,I26) -> 5203
A27: G10 | B27: Cijo Jacob / Thara Joy | C27: 6240 | D27: 45799 | K27: =SUM(C27,E27,G27,I27) -> 6240
A28: G11 | B28: Ketan Verlekar | C28: 4689 | D28: 45780 | E28: 5599 | F28: 45792 | K28: =SUM(C28,E28,G28,I28) -> 10288
A29: G12 | B29: Shyam Nair | C29: 5803 | D29: 45806 | K29: =SUM(C29,E29,G29,I29) -> 5803
A30: G13 | B30: Ajai.B | C30: 6379 | D30: 45807 | K30: =SUM(C30,E30,G30,I30) -> 6379
A31: G14 | B31: Surajit Borah | C31: 5734 | D31: 45806 | K31: =SUM(C31,E31,G31,I31) -> 5734
A32: G15 | B32: Suresh Nallusamy / Antriksh (tenant) | K32: =SUM(C32,E32,G32,I32) -> 0
A33: G16 | B33: Praveen Ganesan | K33: =SUM(C33,E33,G33,I33) -> 0
A34: S1 | B34: S.N.Behera | C34: 5286 | D34: 45796 | K34: =SUM(C34,E34,G34,I34) -> 5286
A35: S2 | B35: Sonal Singh | C35: 12856 | D35: 45780 | E35: 8243 | F35: 45806 | K35: =SUM(C35,E35,G35,I35) -> 21099
A36: S3 | B36: Koteswararao | C36: 5553 | D36: 45798 | K36: =SUM(C36,E36,G36,I36) -> 5553
A37: S4 | B37: Swaminathan | C37: 6853 | D37: 45792 | K37: =SUM(C37,E37,G37,I37) -> 6853
A38: S5 | B38: Abhishek Gopalakrishnan | C38: 6314 | D38: 45797 | K38: =SUM(C38,E38,G38,I38) -> 6314
A39: S6 | B39: Vivek Dhingra / Pratyush Das | C39: 5320 | D39: 45795 | K39: =SUM(C39,E39,G39,I39) -> 5320
A40: S7 | B40: Harish B | C40: 5402 | D40: 45804 | K40: =SUM(C40,E40,G40,I40) -> 5402
A41: S8 | B41: Irudayaraj Alwin | C41: 5431 | D41: 45807 | K41: =SUM(C41,E41,G41,I41) -> 5431
A42: S9 | B42: Pawan GS | C42: 6410 | D42: 45798 | E42: 5302 | F42: 45808 | K42: =SUM(C42,E42,G42,I42) -> 11712
A43: S10 | B43: Lakshmikanth | K43: =SUM(C43,E43,G43,I43) -> 0
A44: S11 | B44: Gowrish Patnaik / Somananth GM | C44: 5330 | D44: 45792 | K44: =SUM(C44,E44,G44,I44) -> 5330
A45: S12 | B45: Saovik Mondal | K45: =SUM(C45,E45,G45,I45) -> 0
A46: S13 | B46: Ramadevi S. | C46: 5665 | D46: 45806 | K46: =SUM(C46,E46,G46,I46) -> 5665
A47: S14 | B47: Nishant Upadhyay(Owner)/ Fabian (Tenant) | K47: =SUM(C47,E47,G47,I47) -> 0
A48: S15 | B48: Manas Dasgupta | C48: 7056 | D48: 45806 | K48: =SUM(C48,E48,G48,I48) -> 7056
A49: S16 | B49: Devendra Singh Rawat / Nancy | C49: 5800 | D49: 45793 | K49: =SUM(C49,E49,G49,I49) -> 5800
A50: T1 | B50: Prashant Sikdar | C50: 6823 | D50: 45801 | K50: =SUM(C50,E50,G50,I50) -> 6823
A51: T2 | B51: Kunal Mehta | K51: =SUM(C51,E51,G51,I51) -> 0
A52: T3 | B52: Kapil Garg | C52: 6537 | D52: 45794 | E52: 5391 | F52: 45806 | K52: =SUM(C52,E52,G52,I52) -> 11928
A53: T4 | B53: Vijet Alva (Owner) - Masood (Tenant) | K53: =SUM(C53,E53,G53,I53) -> 0
A54: T5 | B54: Ganesh Iyer and Latha Iyer( owner) Richa (Tenant) | C54: 5941 | D54: 45797 | K54: =SUM(C54,E54,G54,I54) -> 5941
A55: T6 | B55: Mythili Ramesh | C55: 6739 | D55: 45806 | K55: =SUM(C55,E55,G55,I55) -> 6739
A56: T7 | B56: Vinyas Ramachandra / Shwetha Marnamikatta / Katari Siva Rama Raju | K56: =SUM(C56,E56,G56,I56) -> 0
A57: T8 | B57: Lalit Kumar Sharma | C57: 6007 | D57: 45806 | K57: =SUM(C57,E57,G57,I57) -> 6007
A58: T9 | B58: Nishith Sahu and Priyanka Rani (Owner)/ Anmol Verma (Tenant) | C58: 5977 | D58: 45792 | K58: =SUM(C58,E58,G58,I58) -> 5977
A59: T10 | B59: Vamsidhar Bethanabatla / Madhuri Anumula | C59: 6577 | D59: 45792 | K59: =SUM(C59,E59,G59,I59) -> 6577
A60: T11 | B60: Arvind Balasubramanian | K60: =SUM(C60,E60,G60,I60) -> 0
A61: T12 | B61: Prasenjit | C61: 5427 | D61: 45791 | E61: 676 | F61: 45797 | K61: =SUM(C61,E61,G61,I61) -> 6103
A62: T13 | B62: Rahul Kumar | C62: 12000 | D62: 45785 | K62: =SUM(C62,E62,G62,I62) -> 12000
A63: T14 | B63: Jeya / Kanda / Satya (tenant)/Vinuta (tenant) | C63: 6000 | D63: 45794 | E63: 5709 | F63: 45806 | K63: =SUM(C63,E63,G63,I63) -> 11709
A64: T15 | B64: Trevor | C64: 6247 | D64: 45798 | K64: =SUM(C64,E64,G64,I64) -> 6247
A65: T16 | B65: Madhusoodanan P.R. | C65: 5625 | D65: 45806 | K65: =SUM(C65,E65,G65,I65) -> 5625
A66: TOTAL | K66: =SUM(K2:K65) -> 353995

Sheet June2025-EXPENSE
B1: JUN 2025 EXPENSES
A2: FLAT # | B2: 1 | C2: WATER USED IN LTRS (L) | D2: COMMON AREA EQUALLY DEVIDED | E2: TOTAL FRESH WATER CONSUMED | F2: %OF TOTAL USED | G2: WATER EXPENSE SHARING BY % | H2: #METERS | I2: METER RENT | J2: VARIABLE EXPENSE = COMMON AREA METER RENT + WATER EXPENSE+ FLAT METER RENT | K2: FIXED EXPENSE SHARE | L2: PARKING FEE | M2: CLUB BOOKING FEE | N2: POLYCARBONATE PROJECT CANCELLATION CREDIT AMOUNT | O2: SHIFTING FEE | P2: GYM USAGE FEE | R2: TOTAL EXPENSE TO BE PAID
A3: CH | B3: MPFOWA | C3: 0 | D3: 0 | H3: 1 | I3: =H3*$T$7 -> 117.81166
A4: GYM | B4: MPFOWA | C4: 0 | D4: 0 | H4: 1 | I4: =H4*$T$7 -> 117.81166 | S4: TOTAL FIXED EXPENSE | T4: ='ANNUAL-EXPENSE-DETAILS'!BF5 -> 250490
A5: BSMT | B5: MPFOWA | C5: 0 | D5: 0 | H5: 1 | I5: =H5*$T$7 -> 117.81166 | S5: TOTAL WATER EXPENSE | T5: ='ANNUAL-EXPENSE-DETAILS'!BE5 -> 36000
A6: F1 | B6: Shailesh Srivastava / Azeem Nawaz | C6: 3271 | D6: =SUM($C$3:$C$5)/64 -> 0 | E6: =C6+D6 -> 3271 | F6: =IF($C$70=0, 0, E6/$C$70) -> 0.0075966859 | G6: =F6*$T$5 -> 273.48069 | H6: 3 | I6: =$T$7*H6 -> 353.43498 | J6: =G6+$T$9+I6 -> 632.43809 | K6: =$T$11/64 -> 3913.9062 | L6: 0 | M6: 0 | O6: 0 | P6: 0 | R6: =(SUM(J6:P6))*$B$2 -> 4546.3443
A7: F2 | B7: Shanthanu | C7: 14633 | D7: =SUM($C$3:$C$5)/64 -> 0 | E7: =C7+D7 -> 14633 | F7: =IF($C$70=0, 0, E7/$C$70) -> 0.033984196 | G7: =F7*$T$5 -> 1223.431 | H7: 4 | I7: =$T$7*H7 -> 471.24664 | J7: =G7+$T$9+I7 -> 1700.2001 | K7: =$T$11/64 -> 3913.9062 | L7: 0 | M7: 0 | O7: 0 | P7: 0 | R7: =(SUM(J7:P7))*$B$2 -> 5614.1064 | S7: RENT PER METER | T7: 117.81166
A8: F3 | B8: Samrat Kar | C8: 11395 | D8: =SUM($C$3:$C$5)/64 -> 0 | E8: =C8+D8 -> 11395 | F8: =IF($C$70=0, 0, E8/$C$70) -> 0.02646415 | G8: =F8*$T$5 -> 952.70941 | H8: 4 | I8: =$T$7*H8 -> 471.24664 | J8: =G8+$T$9+I8 -> 1429.4785 | K8: =$T$11/64 -> 3913.9062 | L8: 750 | M8: 0 | O8: 0 | P8: 0 | R8: =(SUM(J8:P8))*$B$2 -> 6093.3847 | S8: COMMON AREA METER RENT | T8: =$T$7*3 -> 353.43498
A9: F4 | B9: Renu R | C9: 3264.5 | D9: =SUM($C$3:$C$5)/64 -> 0 | E9: =C9+D9 -> 3264.5 | F9: =IF($C$70=0, 0, E9/$C$70) -> 0.0075815901 | G9: =F9*$T$5 -> 272.93724 | H9: 4 | I9: =$T$7*H9 -> 471.24664 | J9: =G9+$T$9+I9 -> 749.7063 | K9: =$T$11/64 -> 3913.9062 | L9: 0 | M9: 0 | O9: 0 | P9: 0 | R9: =(SUM(J9:P9))*$B$2 -> 4663.6125 | S9: COMMON AREA METER RENT/FLAT | T9: =T8/64 -> 5.5224215
A10: F5 | B10: Vamsidhar Bethanabatla / Madhuri Anumula | C10: 0 | D10: =SUM($C$3:$C$5)/64 -> 0 | E10: =C10+D10 -> 0 | F10: =IF($C$70=0, 0, E10/$C$70) -> 0 | G10: =F10*$T$5 -> 0 | H10: 3 | I10: =$T$7*H10 -> 353.43498 | J10: =G10+$T$9+I10 -> 358.9574 | K10: =$T$11/64 -> 3913.9062 | L10: 0 | M10: 0 | O10: 0 | P10: 0 | R10: =(SUM(J10:P10))*$B$2 -> 4272.8636
A11: F6 | B11: Meghana Viral Shah and Vviral Shah (Owner) / Sangeet and Swagat (Tenent) | C11: 4251 | D11: =SUM($C$3:$C$5)/64 -> 0 | E11: =C11+D11 -> 4251 | F11: =IF($C$70=0, 0, E11/$C$70) -> 0.0098726725 | G11: =F11*$T$5 -> 355.41621 | H11: 3 | I11: =$T$7*H11 -> 353.43498 | J11: =G11+$T$9+I11 -> 714.37361 | K11: =$T$11/64 -> 3913.9062 | L11: 0 | M11: 0 | O11: 0 | P11: 0 | R11: =(SUM(J11:P11))*$B$2 -> 4628.2799 | S11: TOTAL FIXED EXPENSE | T11: ='ANNUAL-EXPENSE-DETAILS'!BF5 -> 250490
A12: F7 | B12: Vimal NK | C12: 335.5 | D12: =SUM($C$3:$C$5)/64 -> 0 | E12: =C12+D12 -> 335.5 | F12: =IF($C$70=0, 0, E12/$C$70) -> 0.00077917705 | G12: =F12*$T$5 -> 28.050374 | H12: 3 | I12: =$T$7*H12 -> 353.43498 | J12: =G12+$T$9+I12 -> 387.00777 | K12: =$T$11/64 -> 3913.9062 | L12: 750 | M12: 0 | O12: 0 | P12: 0 | R12: =(SUM(J12:P12))*$B$2 -> 5050.914
A13: F8 | B13: Sujeet Kumar (Tenant)/Sreejith Menon (Owner) | C13: 220.5 | D13: =SUM($C$3:$C$5)/64 -> 0 | E13: =C13+D13 -> 220.5 | F13: =IF($C$70=0, 0, E13/$C$70) -> 0.00051209698 | G13: =F13*$T$5 -> 18.435491 | H13: 3 | I13: =$T$7*H13 -> 353.43498 | J13: =G13+$T$9+I13 -> 377.39289 | K13: =$T$11/64 -> 3913.9062 | L13: 0 | M13: 0 | O13: 0 | P13: 0 | R13: =(SUM(J13:P13))*$B$2 -> 4291.2991
A14: F9 | B14: Vijay Suswaram (Owner) / Divya Shikha (Tenant) | C14: 2107 | D14: =SUM($C$3:$C$5)/64 -> 0 | E14: =C14+D14 -> 2107 | F14: =IF($C$70=0, 0, E14/$C$70) -> 0.0048933712 | G14: =F14*$T$5 -> 176.16136 | H14: 4 | I14: =$T$7*H14 -> 471.24664 | J14: =G14+$T$9+I14 -> 652.93042 | K14: =$T$11/64 -> 3913.9062 | L14: 0 | M14: 0 | O14: 0 | P14: 0 | R14: =(SUM(J14:P14))*$B$2 -> 4566.8367 | S14: BALANCE IN ACCOUNT ON 30-JUN-2023
A15: F10 | B15: Aby Thomas | C15: 3152.5 | D15: =SUM($C$3:$C$5)/64 -> 0 | E15: =C15+D15 -> 3152.5 | F15: =IF($C$70=0, 0, E15/$C$70) -> 0.0073214773 | G15: =F15*$T$5 -> 263.57318 | H15: 3 | I15: =$T$7*H15 -> 353.43498 | J15: =G15+$T$9+I15 -> 622.53058 | K15: =$T$11/64 -> 3913.9062 | L15: 0 | M15: 0 | O15: 0 | P15: 0 | R15: =(SUM(J15:P15))*$B$2 -> 4536.4368 | S15: TOTAL NON MAINTENANCE CORPUS COLLECTION
A16: F11 | B16: Niwin Anto | C16: 3724.5 | D16: =SUM($C$3:$C$5)/64 -> 0 | E16: =C16+D16 -> 3724.5 | F16: =IF($C$70=0, 0, E16/$C$70) -> 0.0086499103 | G16: =F16*$T$5 -> 311.39677 | H16: 3 | I16: =$T$7*H16 -> 353.43498 | J16: =G16+$T$9+I16 -> 670.35417 | K16: =$T$11/64 -> 3913.9062 | L16: 0 | M16: 0 | O16: 0 | P16: 0 | R16: =(SUM(J16:P16))*$B$2 -> 4584.2604 | S16: TOTAL FD DONE
A17: F12 | B17: Anirudh Singh | C17: 0 | D17: =SUM($C$3:$C$5)/64 -> 0 | E17: =C17+D17 -> 0 | F17: =IF($C$70=0, 0, E17/$C$70) -> 0 | G17: =F17*$T$5 -> 0 | H17: 3 | I17: =$T$7*H17 -> 353.43498 | J17: =G17+$T$9+I17 -> 358.9574 | K17: =$T$11/64 -> 3913.9062 | L17: 0 | M17: 0 | O17: 0 | P17: 0 | R17: =(SUM(J17:P17))*$B$2 -> 4272.8636 | S17: AMOUNT AVAILABLE FOR NON MAINTENANCE CORPUS | T17: =T15-T16 -> 0
A18: F13 | B18: Sanchay Saxena | C18: 14443 | D18: =SUM($C$3:$C$5)/64 -> 0 | E18: =C18+D18 -> 14443 | F18: =IF($C$70=0, 0, E18/$C$70) -> 0.033542933 | G18: =F18*$T$5 -> 1207.5456 | H18: 4 | I18: =$T$7*H18 -> 471.24664 | J18: =G18+$T$9+I18 -> 1684.3146 | K18: =$T$11/64 -> 3913.9062 | L18: 0 | M18: 0 | O18: 0 | P18: 0 | R18: =(SUM(J18:P18))*$B$2 -> 5598.2209 | S18: AMOUNT AVAILABLE FOR MAINTENANCE | T18: =T14-T17 -> 0
A19: F14 | B19: Hemant Patel | C19: 2996.5 | D19: =SUM($C$3:$C$5)/64 -> 0 | E19: =C19+D19 -> 2996.5 | F19: =IF($C$70=0, 0, E19/$C$70) -> 0.0069591774 | G19: =F19*$T$5 -> 250.53039 | H19: 4 | I19: =$T$7*H19 -> 471.24664 | J19: =G19+$T$9+I19 -> 727.29944 | K19: =$T$11/64 -> 3913.9062 | L19: 750 | M19: 0 | O19: 0 | P19: 0 | R19: =(SUM(J19:P19))*$B$2 -> 5391.2057
A20: F15 | B20: Senthil.Vijayaragavan | C20: 6829.5 | D20: =SUM($C$3:$C$5)/64 -> 0 | E20: =C20+D20 -> 6829.5 | F20: =IF($C$70=0, 0, E20/$C$70) -> 0.015861072 | G20: =F20*$T$5 -> 570.99859 | H20: 4 | I20: =$T$7*H20 -> 471.24664 | J20: =G20+$T$9+I20 -> 1047.7676 | K20: =$T$11/64 -> 3913.9062 | L20: 750 | M20: 0 | O20: 0 | P20: 0 | R20: =(SUM(J20:P20))*$B$2 -> 5711.6739
A21: F16 | B21: Sreeja Sudharma | C21: 14374.5 | D21: =SUM($C$3:$C$5)/64 -> 0 | E21: =C21+D21 -> 14374.5 | F21: =IF($C$70=0, 0, E21/$C$70) -> 0.033383846 | G21: =F21*$T$5 -> 1201.8185 | H21: 3 | I21: =$T$7*H21 -> 353.43498 | J21: =G21+$T$9+I21 -> 1560.7759 | K21: =$T$11/64 -> 3913.9062 | L21: 0 | M21: 0 | O21: 0 | P21: 0 | R21: =(SUM(J21:P21))*$B$2 -> 5474.6821
A22: G1 | B22: Venkataramanan C | C22: 10757.5 | D22: =SUM($C$3:$C$5)/64 -> 0 | E22: =C22+D22 -> 10757.5 | F22: =IF($C$70=0, 0, E22/$C$70) -> 0.024983598 | G22: =F22*$T$5 -> 899.40952 | H22: 3 | I22: =$T$7*H22 -> 353.43498 | J22: =G22+$T$9+I22 -> 1258.3669 | K22: =$T$11/64 -> 3913.9062 | L22: 0 | M22: 0 | O22: 0 | P22: 0 | R22: =(SUM(J22:P22))*$B$2 -> 5172.2732
A23: G2 | B23: Kaushik Kasibhatla | C23: 20300.5 | D23: =SUM($C$3:$C$5)/64 -> 0 | E23: =C23+D23 -> 20300.5 | F23: =IF($C$70=0, 0, E23/$C$70) -> 0.047146598 | G23: =F23*$T$5 -> 1697.2775 | H23: 4 | I23: =$T$7*H23 -> 471.24664 | J23: =G23+$T$9+I23 -> 2174.0466 | K23: =$T$11/64 -> 3913.9062 | L23: 0 | M23: 0 | O23: 0 | P23: 0 | R23: =(SUM(J23:P23))*$B$2 -> 6087.9528
A24: G3 | B24: Balakrishnan | C24: 8713.5 | D24: =SUM($C$3:$C$5)/64 -> 0 | E24: =C24+D24 -> 8713.5 | F24: =IF($C$70=0, 0, E24/$C$70) -> 0.02023654 | G24: =F24*$T$5 -> 728.51544 | H24: 4 | I24: =$T$7*H24 -> 471.24664 | J24: =G24+$T$9+I24 -> 1205.2845 | K24: =$T$11/64 -> 3913.9062 | L24: 0 | M24: 0 | O24: 0 | P24: 0 | R24: =(SUM(J24:P24))*$B$2 -> 5119.1907
A25: G4 | B25: Ashwin Pandith | C25: 8961.5 | D25: =SUM($C$3:$C$5)/64 -> 0 | E25: =C25+D25 -> 8961.5 | F25: =IF($C$70=0, 0, E25/$C$70) -> 0.020812504 | G25: =F25*$T$5 -> 749.25014 | H25: 4 | I25: =$T$7*H25 -> 471.24664 | J25: =G25+$T$9+I25 -> 1226.0192 | K25: =$T$11/64 -> 3913.9062 | L25: 0 | M25: 0 | O25: 0 | P25: 0 | R25: =(SUM(J25:P25))*$B$2 -> 5139.9255
A26: G5 | B26: Mayank Phophaliya | C26: 3003 | D26: =SUM($C$3:$C$5)/64 -> 0 | E26: =C26+D26 -> 3003 | F26: =IF($C$70=0, 0, E26/$C$70) -> 0.0069742732 | G26: =F26*$T$5 -> 251.07384 | H26: 3 | I26: =$T$7*H26 -> 353.43498 | J26: =G26+$T$9+I26 -> 610.03123 | K26: =$T$11/64 -> 3913.9062 | L26: 0 | M26: 0 | O26: 0 | P26: 0 | R26: =(SUM(J26:P26))*$B$2 -> 4523.9375
A27: G6 | B27: Mohit Daga | C27: 10558.5 | D27: =SUM($C$3:$C$5)/64 -> 0 | E27: =C27+D27 -> 10558.5 | F27: =IF($C$70=0, 0, E27/$C$70) -> 0.024521433 | G27: =F27*$T$5 -> 882.77159 | H27: 3 | I27: =$T$7*H27 -> 353.43498 | J27: =G27+$T$9+I27 -> 1241.729 | K27: =$T$11/64 -> 3913.9062 | L27: 0 | M27: 0 | O27: 0 | P27: 0 | R27: =(SUM(J27:P27))*$B$2 -> 5155.6352
A28: G7 | B28: Prince Richfield | C28: 3958.5 | D28: =SUM($C$3:$C$5)/64 -> 0 | E28: =C28+D28 -> 3958.5 | F28: =IF($C$70=0, 0, E28/$C$70) -> 0.0091933602 | G28: =F28*$T$5 -> 330.96097 | H28: 3 | I28: =$T$7*H28 -> 353.43498 | J28: =G28+$T$9+I28 -> 689.91836 | K28: =$T$11/64 -> 3913.9062 | L28: 0 | M28: 0 | O28: 0 | P28: 0 | R28: =(SUM(J28:P28))*$B$2 -> 4603.8246
A29: G8 | B29: Ranjithkumar R / Sameer (tenant) / Princy (tenant) | C29: 5275.5 | D29: =SUM($C$3:$C$5)/64 -> 0 | E29: =C29+D29 -> 5275.5 | F29: =IF($C$70=0, 0, E29/$C$70) -> 0.012252007 | G29: =F29*$T$5 -> 441.07227 | H29: 3 | I29: =$T$7*H29 -> 353.43498 | J29: =G29+$T$9+I29 -> 800.02967 | K29: =$T$11/64 -> 3913.9062 | L29: 0 | M29: 0 | O29: 0 | P29: 0 | R29: =(SUM(J29:P29))*$B$2 -> 4713.9359
A30: G9 | B30: Chandramouli | C30: 8302 | D30: =SUM($C$3:$C$5)/64 -> 0 | E30: =C30+D30 -> 8302 | F30: =IF($C$70=0, 0, E30/$C$70) -> 0.019280858 | G30: =F30*$T$5 -> 694.11088 | H30: 5 | I30: =$T$7*H30 -> 589.0583 | J30: =G30+$T$9+I30 -> 1288.6916 | K30: =$T$11/64 -> 3913.9062 | L30: 0 | M30: 0 | O30: 0 | P30: 0 | R30: =(SUM(J30:P30))*$B$2 -> 5202.5979
... A69: T16 | B69: Madhusoodanan P.R. | C69: 8239.5 | D69: =SUM($C$3:$C$5)/64 -> 0 | E69: =C69+D69 -> 8239.5 | F69: =IF($C$70=0, 0, E69/$C$70) -> 0.019135706 | G69: =F69*$T$5 -> 688.88541 | H69: 3 | I69: =$T$7*H69 -> 353.43498 | J69: =G69+$T$9+I69 -> 1047.8428 | K69: =$T$11/64 -> 3913.9062 | L69: 0 | M69: 0 | O69: 0 | P69: 0 | R69: =(SUM(J69:P69))*$B$2 -> 4961.7491
B70: TOTAL | C70: =SUM(C3:C69) -> 430582.5 | D70: =SUM(D3:D69) -> 0 | E70: =SUM(E3:E69) -> 430582.5 | F70: =IF($C$70=0, 0, E70/$C$70) -> 1 | G70: =SUM(G3:G69) -> 36000 | H70: =SUM(H3:H69) -> 223 | I70: =SUM(I3:I69) -> 26272 | J70: =SUM(J3:J69) -> 62272 | K70: =SUM(K3:K69) -> 250490 | L70: =SUM(L3:L69) -> 3750 | M70: =SUM(M3:M69) -> 0 | N70: =SUM(N3:N69) -> 0 | ... P70: =SUM(P3:P69) -> 0 | R70: =SUM(R3:R69) -> 316512

Sheet June2025-COLLECTION
A1: FLAT # | C1: Amount | D1: Date | E1: Amount | F1: Date | G1: Amount | H1: Date | I1: Amount | J1: Date | K1: Total
A2: F1 | B2: Shailesh Srivastava / Azeem Nawaz | C2: 4374 | D2: 45831 | K2: =SUM(C2,E2,G2,I2) -> 4374
A3: F2 | B3: Shanthanu | C3: 33159 | D3: 45818 | E3: 8466 | F3: 45818 | K3: =SUM(C3,E3,G3,I3) -> 41625
A4: F3 | B4: Samrat Kar | C4: 6000 | D4: 45809 | K4: =SUM(C4,E4,G4,I4) -> 6000
A5: F4 | B5: Renu R | C5: 4434 | D5: 45819 | K5: =SUM(C5,E5,G5,I5) -> 4434
A6: F5 | B6: Vamsidhar Bethanabatla / Madhuri Anumula | C6: 4022 | D6: 45828 | E6: 4000 | F6: 45837 | K6: =SUM(C6,E6,G6,I6) -> 8022
A7: F6 | B7: Meghana Viral Shah and Vviral Shah (Owner) / Sangeet and Swagat (Tenent) | C7: 4331 | D7: 45821 | K7: =SUM(C7,E7,G7,I7) -> 4331
A8: F7 | B8: Vimal NK | C8: 4800.17 | D8: 45828 | K8: =SUM(C8,E8,G8,I8) -> 4800.17
A9: F8 | B9: Sujeet Kumar (Tenant)/Sreejith Menon (Owner) | C9: 4044 | D9: 45819 | K9: =SUM(C9,E9,G9,I9) -> 4044
A10: F9 | B10: Vijay Suswaram (Owner) / Divya Shikha (Tenant) | C10: 4310 | D10: 45821 | K10: =SUM(C10,E10,G10,I10) -> 4310
A11: F10 | B11: Aby Thomas | C11: 4246 | D11: 45832 | K11: =SUM(C11,E11,G11,I11) -> 4246
A12: F11 | B12: Niwin Anto | C12: 4272 | D12: 45819 | K12: =SUM(C12,E12,G12,I12) -> 4272
A13: F12 | B13: Anirudh Singh | C13: 4013 | D13: 45819 | K13: =SUM(C13,E13,G13,I13) -> 4013
A14: F13 | B14: Sanchay Saxena | C14: 6275 | D14: 45822 | K14: =SUM(C14,E14,G14,I14) -> 6275
A15: F14 | B15: Hemant Patel | C15: 4891 | D15: 45819 | K15: =SUM(C15,E15,G15,I15) -> 4891
A16: F15 | B16: Senthil.Vijayaragavan | C16: 5466 | D16: 45820 | K16: =SUM(C16,E16,G16,I16) -> 5466
A17: F16 | B17: Sreeja Sudharma | K17: =SUM(C17,E17,G17,I17) -> 0
A18: G1 | B18: Venkataramanan C | C18: 6306 | D18: 45809 | E18: 4989 | F18: 45821 | K18: =SUM(C18,E18,G18,I18) -> 11295
A19: G2 | B19: Kaushik Kasibhatla | C19: 5159 | D19: 45824 | E19: 7318 | F19: 45824 | K19: =SUM(C19,E19,G19,I19) -> 12477
A20: G3 | B20: Balakrishnan | C20: 5150 | D20: 45827 | K20: =SUM(C20,E20,G20,I20) -> 5150
A21: G4 | B21: Ashwin Pandith | C21: 5107 | D21: 45820 | K21: =SUM(C21,E21,G21,I21) -> 5107
A22: G5 | B22: Mayank Phophaliya | K22: =SUM(C22,E22,G22,I22) -> 0
A23: G6 | B23: Mohit Daga | C23: 85000 | D23: 45819 | K23: =SUM(C23,E23,G23,I23) -> 85000
A24: G7 | B24: Prince Richfield | K24: =SUM(C24,E24,G24,I24) -> 0
A25: G8 | B25: Ranjithkumar R / Sameer (tenant) / Princy (tenant) | C25: 4772 | D25: 45822 | K25: =SUM(C25,E25,G25,I25) -> 4772
A26: G9 | B26: Ankur Agarwal | C26: 6218 | D26: 45822 | E26: 4701 | F26: 45822 | K26: =SUM(C26,E26,G26,I26) -> 10919
A27: G10 | B27: Cijo Jacob / Thara Joy | C27: 4790 | D27: 45819 | K27: =SUM(C27,E27,G27,I27) -> 4790
A28: G11 | B28: Ketan Verlekar | C28: 4399 | D28: 45829 | K28: =SUM(C28,E28,G28,I28) -> 4399
A29: G12 | B29: Shyam Nair | C29: 9519 | D29: 45817 | E29: 5127 | F29: 45831 | K29: =SUM(C29,E29,G29,I29) -> 14646
A30: G13 | B30: Ajai.B | K30: =SUM(C30,E30,G30,I30) -> 0
A31: G14 | B31: Surajit Borah | C31: 5435 | D31: 45829 | K31: =SUM(C31,E31,G31,I31) -> 5435
A32: G15 | B32: Suresh Nallusamy / Antriksh (tenant) | C32: 4568 | D32: 45819 | K32: =SUM(C32,E32,G32,I32) -> 4568
A33: G16 | B33: Praveen Ganesan | C33: 5425 | D33: 45809 | E33: 4733 | F33: 45820 | K33: =SUM(C33,E33,G33,I33) -> 10158
A34: S1 | B34: S.N.Behera | C34: 4012 | D34: 45823 | K34: =SUM(C34,E34,G34,I34) -> 4012
A35: S2 | B35: Sonal Singh | C35: 50000 | D35: 45817 | E35: 20000 | F35: 45827 | G35: 7099 | H35: 45836 | K35: =SUM(C35,E35,G35,I35) -> 77099
A36: S3 | B36: Koteswararao | C36: 39966.54 | D36: 45827 | E36: 4272 | F36: 45829 | K36: =SUM(C36,E36,G36,I36) -> 44238.54
A37: S4 | B37: Swaminathan | C37: 4897 | D37: 45819 | K37: =SUM(C37,E37,G37,I37) -> 4897
A38: S5 | B38: Abhishek Gopalakrishnan | K38: =SUM(C38,E38,G38,I38) -> 0
A39: S6 | B39: Vivek Dhingra / Pratyush Das | K39: =SUM(C39,E39,G39,I39) -> 0
A40: S7 | B40: Harish B | C40: 4060 | D40: 45832 | K40: =SUM(C40,E40,G40,I40) -> 4060
A41: S8 | B41: Irudayaraj Alwin | C41: 4838 | D41: 45821 | K41: =SUM(C41,E41,G41,I41) -> 4838
A42: S9 | B42: Pawan GS | C42: 5025 | D42: 45826 | K42: =SUM(C42,E42,G42,I42) -> 5025
A43: S10 | B43: Lakshmikanth | K43: =SUM(C43,E43,G43,I43) -> 0
A44: S11 | B44: Gowrish Patnaik / Somananth GM | C44: 4348 | D44: 45828 | K44: =SUM(C44,E44,G44,I44) -> 4348
A45: S12 | B45: Saovik Mondal | C45: 6180 | D45: 45812 | E45: 4971 | F45: 45828 | K45: =SUM(C45,E45,G45,I45) -> 11151
A46: S13 | B46: Ramadevi S. | C46: 4439 | D46: 45822 | K46: =SUM(C46,E46,G46,I46) -> 4439
A47: S14 | B47: Nishant Upadhyay(Owner)/ Fabian (Tenant) | K47: =SUM(C47,E47,G47,I47) -> 0
A48: S15 | B48: Manas Dasgupta | K48: =SUM(C48,E48,G48,I48) -> 0
A49: S16 | B49: Devendra Singh Rawat / Nancy | C49: 4372 | D49: 45820 | K49: =SUM(C49,E49,G49,I49) -> 4372
A50: T1 | B50: Prashant Sikdar | C50: 5591 | D50: 45818 | K50: =SUM(C50,E50,G50,I50) -> 5591
A51: T2 | B51: Kunal Mehta | C51: 69469 | D51: 45811 | K51: =SUM(C51,E51,G51,I51) -> 69469
A52: T3 | B52: Kapil Garg | C52: 4905 | D52: 45822 | K52: =SUM(C52,E52,G52,I52) -> 4905
A53: T4 | B53: Vijet Alva (Owner) - Masood (Tenant) | C53: 5529 | D53: 45812 | K53: =SUM(C53,E53,G53,I53) -> 5529
A54: T5 | B54: Ganesh Iyer and Latha Iyer( owner) Richa (Tenant) | K54: =SUM(C54,E54,G54,I54) -> 0
A55: T6 | B55: Mythili Ramesh | K55: =SUM(C55,E55,G55,I55) -> 0
A56: T7 | B56: Vinyas Ramachandra / Shwetha Marnamikatta / Katari Siva Rama Raju | C56: 4076 | D56: 45826 | K56: =SUM(C56,E56,G56,I56) -> 4076
A57: T8 | B57: Lalit Kumar Sharma | C57: 4778 | D57: 45834 | K57: =SUM(C57,E57,G57,I57) -> 4778
A58: T9 | B58: Nishith Sahu and Priyanka Rani (Owner)/ Anmol Verma (Tenant) | C58: 5426 | D58: 45819 | K58: =SUM(C58,E58,G58,I58) -> 5426
A59: T10 | B59: Vamsidhar Bethanabatla / Madhuri Anumula | C59: 4959 | D59: 45828 | K59: =SUM(C59,E59,G59,I59) -> 4959
A60: T11 | B60: Arvind Balasubramanian | C60: 5669 | D60: 45813 | E60: 4859 | F60: 45819 | K60: =SUM(C60,E60,G60,I60) -> 10528
A61: T12 | B61: Prasenjit | C61: 4195 | D61: 45819 | K61: =SUM(C61,E61,G61,I61) -> 4195
A62: T13 | B62: Rahul Kumar | K62: =SUM(C62,E62,G62,I62) -> 0
A63: T14 | B63: Jeya / Kanda / Satya (tenant)/Vinuta (tenant) | C63: 5191 | D63: 45819 | E63: 71 | F63: 45823 | K63: =SUM(C63,E63,G63,I63) -> 5262
A64: T15 | B64: Trevor | K64: =SUM(C64,E64,G64,I64) -> 0
A65: T16 | B65: Madhusoodanan P.R. | C65: 4119 | D65: 45824 | K65: =SUM(C65,E65,G65,I65) -> 4119
A66: TOTAL | K66: =SUM(K2:K65) -> 587135.71

Sheet July2025-EXPENSE
B1: JUL 2025 EXPENSES
A2: FLAT # | B2: 1 | C2: WATER USED IN LTRS | D2: COMMON AREA EQUALLY DEVIDED | E2: TOTAL FRESH WATER CONSUMED | F2: %OF TOTAL USED | G2: WATER EXPENSE SHARING BY % | H2: #METERS | I2: METER RENT | J2: VARIABLE EXPENSE = COMMON AREA METER RENT + WATER EXPENSE+ FLAT METER RENT | K2: FIXED EXPENSE SHARE | L2: PARKING FEE | M2: CLUB BOOKING FEE | N2: SHIFTING FEE | O2: GYM USAGE FEE | R2: TOTAL EXPENSE TO BE PAID
A3: CH | B3: MPFOWA | C3: 570.5 | D3: 0 | H3: 1 | I3: =T7 -> 117.81166
A4: GYM | B4: MPFOWA | C4: 0 | D4: 0 | H4: 1 | I4: =T7 -> 117.81166 | S4: TOTAL FIXED EXPENSE | T4: ='ANNUAL-EXPENSE-DETAILS'!BF6 -> 303879
A5: BSMT | B5: MPFOWA | C5: 0 | D5: 0 | H5: 1 | I5: =T7 -> 117.81166 | S5: TOTAL WATER EXPENSE | T5: ='ANNUAL-EXPENSE-DETAILS'!BE6 -> 39800
A6: F1 | B6: Shailesh Srivastava / Azeem Nawaz | C6: 4312 | D6: =SUM($C$3:$C$5)/64 -> 8.9140625 | E6: =C6+D6 -> 4320.9141 | F6: =IF($C$70=0, 0, E6/$C$70) -> 0.0097901545 | G6: =F6*$T$5 -> 389.64815 | H6: 3 | I6: =$T$7*H6 -> 353.43498 | J6: =G6+$T$9+I6 -> 748.60555 | K6: =$T$11/64 -> 4748.1094 | L6: 0 | M6: 0 | N6: 0 | O6: 0 | R6: =(J6+K6+L6+M6+N6+O6)*$B$2 -> 5496.7149
A7: F2 | B7: Shanthanu | C7: 17011.5 | D7: =SUM($C$3:$C$5)/64 -> 8.9140625 | E7: =C7+D7 -> 17020.414 | F7: =IF($C$70=0, 0, E7/$C$70) -> 0.038564174 | G7: =F7*$T$5 -> 1534.8541 | H7: 4 | I7: =$T$7*H7 -> 471.24664 | J7: =G7+$T$9+I7 -> 2011.6232 | K7: =$T$11/64 -> 4748.1094 | L7: 0 | M7: 0 | N7: 0 | O7: 0 | R7: =(J7+K7+L7+M7+N7+O7)*$B$2 -> 6759.7326 | S7: RENT PER METER | T7: 117.81166
A8: F3 | B8: Samrat Kar | C8: 17231.5 | D8: =SUM($C$3:$C$5)/64 -> 8.9140625 | E8: =C8+D8 -> 17240.414 | F8: =IF($C$70=0, 0, E8/$C$70) -> 0.039062642 | G8: =F8*$T$5 -> 1554.6931 | H8: 4 | I8: =$T$7*H8 -> 471.24664 | J8: =G8+$T$9+I8 -> 2031.4622 | K8: =$T$11/64 -> 4748.1094 | L8: 750 | M8: 0 | N8: 0 | O8: 0 | R8: =(J8+K8+L8+M8+N8+O8)*$B$2 -> 7529.5716 | S8: COMMON AREA METER RENT | T8: =$T$7*3 -> 353.43498
A9: F4 | B9: Renu R | C9: 3636 | D9: =SUM($C$3:$C$5)/64 -> 8.9140625 | E9: =C9+D9 -> 3644.9141 | F9: =IF($C$70=0, 0, E9/$C$70) -> 0.0082585007 | G9: =F9*$T$5 -> 328.68833 | H9: 4 | I9: =$T$7*H9 -> 471.24664 | J9: =G9+$T$9+I9 -> 805.45739 | K9: =$T$11/64 -> 4748.1094 | L9: 0 | M9: 0 | N9: 0 | O9: 0 | R9: =(J9+K9+L9+M9+N9+O9)*$B$2 -> 5553.5668 | S9: COMMON AREA METER RENT/FLAT | T9: =T8/64 -> 5.5224215
A10: F5 | B10: Vamsidhar Bethanabatla / Madhuri Anumula | C10: 715.5 | D10: =SUM($C$3:$C$5)/64 -> 8.9140625 | E10: =C10+D10 -> 724.41406 | F10: =IF($C$70=0, 0, E10/$C$70) -> 0.0016413485 | G10: =F10*$T$5 -> 65.325668 | H10: 3 | I10: =$T$7*H10 -> 353.43498 | J10: =G10+$T$9+I10 -> 424.28307 | K10: =$T$11/64 -> 4748.1094 | L10: 0 | M10: 0 | N10: 0 | O10: 0 | R10: =(J10+K10+L10+M10+N10+O10)*$B$2 -> 5172.3924
A11: F6 | B11: Meghana Viral Shah and Vviral Shah (Owner) / Sangeet and Swagat (Tenent) | C11: 3962.5 | D11: =SUM($C$3:$C$5)/64 -> 8.9140625 | E11: =C11+D11 -> 3971.4141 | F11: =IF($C$70=0, 0, E11/$C$70) -> 0.0089982714 | G11: =F11*$T$5 -> 358.1312 | H11: 3 | I11: =$T$7*H11 -> 353.43498 | J11: =G11+$T$9+I11 -> 717.0886 | K11: =$T$11/64 -> 4748.1094 | L11: 0 | M11: 0 | N11: 0 | O11: 0 | R11: =(J11+K11+L11+M11+N11+O11)*$B$2 -> 5465.198 | S11: TOTAL FIXED EXPENSE | T11: ='ANNUAL-EXPENSE-DETAILS'!BF6 -> 303879
A12: F7 | B12: Vimal NK | C12: 895.5 | D12: =SUM($C$3:$C$5)/64 -> 8.9140625 | E12: =C12+D12 -> 904.41406 | F12: =IF($C$70=0, 0, E12/$C$70) -> 0.0020491853 | G12: =F12*$T$5 -> 81.557573 | H12: 3 | I12: =$T$7*H12 -> 353.43498 | J12: =G12+$T$9+I12 -> 440.51497 | K12: =$T$11/64 -> 4748.1094 | L12: 750 | M12: 0 | N12: 0 | O12: 0 | R12: =(J12+K12+L12+M12+N12+O12)*$B$2 -> 5938.6243
A13: F8 | B13: Sujeet Kumar (Tenant)/Sreejith Menon (Owner) | C13: 148.5 | D13: =SUM($C$3:$C$5)/64 -> 8.9140625 | E13: =C13+D13 -> 157.41406 | F13: =IF($C$70=0, 0, E13/$C$70) -> 0.0003566625 | G13: =F13*$T$5 -> 14.195167 | H13: 3 | I13: =$T$7*H13 -> 353.43498 | J13: =G13+$T$9+I13 -> 373.15257 | K13: =$T$11/64 -> 4748.1094 | L13: 0 | M13: 0 | N13: 0 | O13: 0 | R13: =(J13+K13+L13+M13+N13+O13)*$B$2 -> 5121.2619
A14: F9 | B14: Vijay Suswaram (Owner) / Divya Shikha (Tenant) | C14: 2308 | D14: =SUM($C$3:$C$5)/64 -> 8.9140625 | E14: =C14+D14 -> 2316.9141 | F14: =IF($C$70=0, 0, E14/$C$70) -> 0.0052495713 | G14: =F14*$T$5 -> 208.93294 | H14: 4 | I14: =$T$7*H14 -> 471.24664 | J14: =G14+$T$9+I14 -> 685.702 | K14: =$T$11/64 -> 4748.1094 | L14: 0 | M14: 0 | N14: 0 | O14: 0 | R14: =(J14+K14+L14+M14+N14+O14)*$B$2 -> 5433.8114 | S14: BALANCE IN ACCOUNT ON 31-JULY-2023
A15: F10 | B15: Aby Thomas | C15: 3221 | D15: =SUM($C$3:$C$5)/64 -> 8.9140625 | E15: =C15+D15 -> 3229.9141 | F15: =IF($C$70=0, 0, E15/$C$70) -> 0.0073182103 | G15: =F15*$T$5 -> 291.26477 | H15: 3 | I15: =$T$7*H15 -> 353.43498 | J15: =G15+$T$9+I15 -> 650.22217 | K15: =$T$11/64 -> 4748.1094 | L15: 0 | M15: 0 | N15: 0 | O15: 0 | R15: =(J15+K15+L15+M15+N15+O15)*$B$2 -> 5398.3315 | S15: TOTAL NON MAINTENANCE CORPUS COLLECTION
A16: F11 | B16: Niwin Anto | C16: 1220.5 | D16: =SUM($C$3:$C$5)/64 -> 8.9140625 | E16: =C16+D16 -> 1229.4141 | F16: =IF($C$70=0, 0, E16/$C$70) -> 0.0027855573 | G16: =F16*$T$5 -> 110.86518 | H16: 3 | I16: =$T$7*H16 -> 353.43498 | J16: =G16+$T$9+I16 -> 469.82258 | K16: =$T$11/64 -> 4748.1094 | L16: 0 | M16: 0 | N16: 0 | O16: 0 | R16: =(J16+K16+L16+M16+N16+O16)*$B$2 -> 5217.932 | S16: TOTAL FD DONE
A17: F12 | B17: Anirudh Singh | C17: 1.5 | D17: =SUM($C$3:$C$5)/64 -> 8.9140625 | E17: =C17+D17 -> 10.414062 | F17: =IF($C$70=0, 0, E17/$C$70) -> 2.3595767e-05 | G17: =F17*$T$5 -> 0.93911152 | H17: 3 | I17: =$T$7*H17 -> 353.43498 | J17: =G17+$T$9+I17 -> 359.89651 | K17: =$T$11/64 -> 4748.1094 | L17: 0 | M17: 0 | N17: 0 | O17: 0 | R17: =(J17+K17+L17+M17+N17+O17)*$B$2 -> 5108.0059 | S17: AMOUNT AVAILABLE FOR NON MAINTENANCE CORPUS | T17: =T15-T16 -> 0
A18: F13 | B18: Sanchay Saxena | C18: 11200.5 | D18: =SUM($C$3:$C$5)/64 -> 8.9140625 | E18: =C18+D18 -> 11209.414 | F18: =IF($C$70=0, 0, E18/$C$70) -> 0.025397843 | G18: =F18*$T$5 -> 1010.8341 | H18: 4 | I18: =$T$7*H18 -> 471.24664 | J18: =G18+$T$9+I18 -> 1487.6032 | K18: =$T$11/64 -> 4748.1094 | L18: 0 | M18: 0 | N18: 0 | O18: 0 | R18: =(J18+K18+L18+M18+N18+O18)*$B$2 -> 6235.7126 | S18: AMOUNT AVAILABLE FOR MAINTENANCE | T18: =T14-T17 -> 0
A19: F14 | B19: Hemant Patel | C19: 2363.5 | D19: =SUM($C$3:$C$5)/64 -> 8.9140625 | E19: =C19+D19 -> 2372.4141 | F19: =IF($C$70=0, 0, E19/$C$70) -> 0.005375321 | G19: =F19*$T$5 -> 213.93778 | H19: 4 | I19: =$T$7*H19 -> 471.24664 | J19: =G19+$T$9+I19 -> 690.70683 | K19: =$T$11/64 -> 4748.1094 | L19: 0 | M19: 0 | N19: 0 | O19: 0 | R19: =(J19+K19+L19+M19+N19+O19)*$B$2 -> 5438.8162
A20: F15 | B20: Senthil.Vijayaragavan | C20: 5665 | D20: =SUM($C$3:$C$5)/64 -> 8.9140625 | E20: =C20+D20 -> 5673.9141 | F20: =IF($C$70=0, 0, E20/$C$70) -> 0.012855728 | G20: =F20*$T$5 -> 511.65797 | H20: 4 | I20: =$T$7*H20 -> 471.24664 | J20: =G20+$T$9+I20 -> 988.42703 | K20: =$T$11/64 -> 4748.1094 | L20: 750 | M20: 0 | N20: 0 | O20: 0 | R20: =(J20+K20+L20+M20+N20+O20)*$B$2 -> 6486.5364
A21: F16 | B21: Sreeja Sudharma | C21: 12832.5 | D21: =SUM($C$3:$C$5)/64 -> 8.9140625 | E21: =C21+D21 -> 12841.414 | F21: =IF($C$70=0, 0, E21/$C$70) -> 0.029095563 | G21: =F21*$T$5 -> 1158.0034 | H21: 3 | I21: =$T$7*H21 -> 353.43498 | J21: =G21+$T$9+I21 -> 1516.9608 | K21: =$T$11/64 -> 4748.1094 | L21: 0 | M21: 0 | N21: 0 | O21: 0 | R21: =(J21+K21+L21+M21+N21+O21)*$B$2 -> 6265.0702
A22: G1 | B22: Venkataramanan C | C22: 10356 | D22: =SUM($C$3:$C$5)/64 -> 8.9140625 | E22: =C22+D22 -> 10364.914 | F22: =IF($C$70=0, 0, E22/$C$70) -> 0.023484408 | G22: =F22*$T$5 -> 934.67945 | H22: 3 | I22: =$T$7*H22 -> 353.43498 | J22: =G22+$T$9+I22 -> 1293.6368 | K22: =$T$11/64 -> 4748.1094 | L22: 0 | M22: 0 | N22: 0 | O22: 0 | R22: =(J22+K22+L22+M22+N22+O22)*$B$2 -> 6041.7462
A23: G2 | B23: Kaushik Kasibhatla | C23: 13897 | D23: =SUM($C$3:$C$5)/64 -> 8.9140625 | E23: =C23+D23 -> 13905.914 | F23: =IF($C$70=0, 0, E23/$C$70) -> 0.031507465 | G23: =F23*$T$5 -> 1253.9971 | H23: 4 | I23: =$T$7*H23 -> 471.24664 | J23: =G23+$T$9+I23 -> 1730.7662 | K23: =$T$11/64 -> 4748.1094 | L23: 0 | M23: 0 | N23: 0 | O23: 0 | R23: =(J23+K23+L23+M23+N23+O23)*$B$2 -> 6478.8755
A24: G3 | B24: Balakrishnan | C24: 14771 | D24: =SUM($C$3:$C$5)/64 -> 8.9140625 | E24: =C24+D24 -> 14779.914 | F24: =IF($C$70=0, 0, E24/$C$70) -> 0.033487739 | G24: =F24*$T$5 -> 1332.812 | H24: 4 | I24: =$T$7*H24 -> 471.24664 | J24: =G24+$T$9+I24 -> 1809.5811 | K24: =$T$11/64 -> 4748.1094 | L24: 0 | M24: 0 | N24: 0 | O24: 0 | R24: =(J24+K24+L24+M24+N24+O24)*$B$2 -> 6557.6904
A25: G4 | B25: Ashwin Pandith | C25: 20576 | D25: =SUM($C$3:$C$5)/64 -> 8.9140625 | E25: =C25+D25 -> 20584.914 | F25: =IF($C$70=0, 0, E25/$C$70) -> 0.046640476 | G25: =F25*$T$5 -> 1856.291 | H25: 4 | I25: =$T$7*H25 -> 471.24664 | J25: =G25+$T$9+I25 -> 2333.06 | K25: =$T$11/64 -> 4748.1094 | L25: 0 | M25: 0 | N25: 0 | O25: 0 | R25: =(J25+K25+L25+M25+N25+O25)*$B$2 -> 7081.1694
A26: G5 | B26: Mayank Phophaliya | C26: 4303.5 | D26: =SUM($C$3:$C$5)/64 -> 8.9140625 | E26: =C26+D26 -> 4312.4141 | F26: =IF($C$70=0, 0, E26/$C$70) -> 0.0097708955 | G26: =F26*$T$5 -> 388.88164 | H26: 3 | I26: =$T$7*H26 -> 353.43498 | J26: =G26+$T$9+I26 -> 747.83904 | K26: =$T$11/64 -> 4748.1094 | L26: 0 | M26: 0 | N26: 0 | O26: 0 | R26: =(J26+K26+L26+M26+N26+O26)*$B$2 -> 5495.9484
A27: G6 | B27: Mohit Daga | C27: 7473.5 | D27: =SUM($C$3:$C$5)/64 -> 8.9140625 | E27: =C27+D27 -> 7482.4141 | F27: =IF($C$70=0, 0, E27/$C$70) -> 0.016953355 | G27: =F27*$T$5 -> 674.74353 | H27: 3 | I27: =$T$7*H27 -> 353.43498 | J27: =G27+$T$9+I27 -> 1033.7009 | K27: =$T$11/64 -> 4748.1094 | L27: 0 | M27: 0 | N27: 0 | O27: 0 | R27: =(J27+K27+L27+M27+N27+O27)*$B$2 -> 5781.8103
A28: G7 | B28: Prince Richfield | C28: 5843 | D28: =SUM($C$3:$C$5)/64 -> 8.9140625 | E28: =C28+D28 -> 5851.9141 | F28: =IF($C$70=0, 0, E28/$C$70) -> 0.013259033 | G28: =F28*$T$5 -> 527.70952 | H28: 3 | I28: =$T$7*H28 -> 353.43498 | J28: =G28+$T$9+I28 -> 886.66692 | K28: =$T$11/64 -> 4748.1094 | L28: 0 | M28: 0 | N28: 0 | O28: 0 | R28: =(J28+K28+L28+M28+N28+O28)*$B$2 -> 5634.7763
A29: G8 | B29: Ranjithkumar R / Sameer (tenant) / Princy (tenant) | C29: 9415.5 | D29: =SUM($C$3:$C$5)/64 -> 8.9140625 | E29: =C29+D29 -> 9424.4141 | F29: =IF($C$70=0, 0, E29/$C$70) -> 0.021353461 | G29: =F29*$T$5 -> 849.86775 | H29: 3 | I29: =$T$7*H29 -> 353.43498 | J29: =G29+$T$9+I29 -> 1208.8251 | K29: =$T$11/64 -> 4748.1094 | L29: 0 | M29: 0 | N29: 0 | O29: 0 | R29: =(J29+K29+L29+M29+N29+O29)*$B$2 -> 5956.9345
A30: G9 | B30: Chandramouli | C30: 5828.5 | D30: =SUM($C$3:$C$5)/64 -> 8.9140625 | E30: =C30+D30 -> 5837.4141 | F30: =IF($C$70=0, 0, E30/$C$70) -> 0.01322618 | G30: =F30*$T$5 -> 526.40195 | H30: 5 | I30: =$T$7*H30 -> 589.0583 | J30: =G30+$T$9+I30 -> 1120.9827 | K30: =$T$11/64 -> 4748.1094 | L30: 0 | M30: 0 | N30: 0 | O30: 0 | R30: =(J30+K30+L30+M30+N30+O30)*$B$2 -> 5869.092
... A69: T16 | B69: Madhusoodanan P.R. | C69: 8509.5 | D69: =SUM($C$3:$C$5)/64 -> 8.9140625 | E69: =C69+D69 -> 8518.4141 | F69: =IF($C$70=0, 0, E69/$C$70) -> 0.019300682 | G69: =F69*$T$5 -> 768.16716 | H69: 3 | I69: =$T$7*H69 -> 353.43498 | J69: =G69+$T$9+I69 -> 1127.1246 | K69: =$T$11/64 -> 4748.1094 | L69: 0 | M69: 0 | N69: 0 | O69: 0 | R69: =(J69+K69+L69+M69+N69+O69)*$B$2 -> 5875.2339
B70: TOTAL | C70: =SUM(C3:C69) -> 441353 | D70: =SUM(D3:D69) -> 570.5 | E70: =SUM(E3:E69) -> 441353 | F70: =SUM(F3:F69) -> 1 | G70: =SUM(G3:G69) -> 39800 | H70: =SUM(H3:H69) -> 223 | I70: =SUM(I3:I69) -> 26272 | J70: =SUM(J3:J69) -> 66072 | ... O70: =SUM(O3:O69) -> 0 | R70: =SUM(R3:R69) -> 372951

Sheet July2025-EXPENSE-Flatwise
A1: Expense Head | C1: {=TRANSPOSE('INCOME-EXPENSE-CYCLES'!A3:A66)} -> F1 | D1: F2 | E1: F3 | F1: F4 | G1: F5 | H1: F6 | I1: F7 | J1: F8 | K1: F9 | L1: F10 | M1: F11 | N1: F12 | O1: F13 | P1: F14 | Q1: F15 | R1: F16 | S1: G1 | T1: G2 | U1: G3 | V1: G4 | W1: G5 | X1: G6 | Y1: G7 | Z1: G8 | AA1: G9 | AB1: G10 | AC1: G11 | AD1: G12 | AE1: G13 | AF1: G14 | AG1: G15 | AH1: G16 | AI1: S1 | AJ1: S2 | AK1: S3 | AL1: S4 | AM1: S5 | AN1: S6 | AO1: S7 | AP1: S8 | AQ1: S9 | AR1: S10 | AS1: S11 | AT1: S12 | AU1: S13 | AV1: S14 | AW1: S15 | AX1: S16 | AY1: T1 | AZ1: T2 | BA1: T3 | BB1: T4 | BC1: T5 | BD1: T6 | BE1: T7 | BF1: T8 | BG1: T9 | BH1: T10 | BI1: T11 | BJ1: T12 | BK1: T13 | BL1: T14 | BM1: T15 | BN1: T16
A2: Water consumption (Litres) | C2: {=TRANSPOSE('July2025-EXPENSE'!E6:E69)} -> 4320.9141 | D2: 17020.414 | E2: 17240.414 | F2: 3644.9141 | G2: 724.41406 | H2: 3971.4141 | I2: 904.41406 | J2: 157.41406 | K2: 2316.9141 | L2: 3229.9141 | M2: 1229.4141 | N2: 10.414062 | O2: 11209.414 | P2: 2372.4141 | Q2: 5673.9141 | R2: 12841.414 | S2: 10364.914 | T2: 13905.914 | U2: 14779.914 | V2: 20584.914 | W2: 4312.4141 | X2: 7482.4141 | Y2: 5851.9141 | Z2: 9424.4141 | AA2: 5837.4141 | AB2: 9988.4141 | AC2: 2990.9141 | AD2: 11232.914 | AE2: 7763.9141 | AF2: 6269.4141 | AG2: 8.9140625 | AH2: 2110.4141 | AI2: 784.41406 | AJ2: 34111.914 | AK2: 2577.9141 | AL2: 2026.9141 | AM2: 8225.9141 | AN2: 308.91406 | AO2: 674.91406 | AP2: 19106.414 | AQ2: 2420.4141 | AR2: 548.41406 | AS2: 8929.4141 | AT2: 8847.9141 | AU2: 3298.4141 | AV2: 5220.4141 | AW2: 14166.414 | AX2: 4644.9141 | AY2: 14535.414 | AZ2: 15236.914 | BA2: 9869.4141 | BB2: 11494.414 | BC2: 2155.9141 | BD2: 13178.914 | BE2: 1564.4141 | BF2: 1035.9141 | BG2: 6817.9141 | BH2: 310.41406 | BI2: 2707.9141 | BJ2: 1237.9141 | BK2: 3438.4141 | BL2: 3199.4141 | BM2: 10380.414 | BN2: 8518.4141
A3: Water consumption (%age of total) | C3: {=TRANSPOSE('July2025-EXPENSE'!F6:F69)} -> 0.0097901545 | D3: 0.038564174 | E3: 0.039062642 | F3: 0.0082585007 | G3: 0.0016413485 | H3: 0.0089982714 | I3: 0.0020491853 | J3: 0.0003566625 | K3: 0.0052495713 | L3: 0.0073182103 | M3: 0.0027855573 | N3: 2.3595767e-05 | O3: 0.025397843 | P3: 0.005375321 | Q3: 0.012855728 | R3: 0.029095563 | S3: 0.023484408 | T3: 0.031507465 | U3: 0.033487739 | V3: 0.046640476 | W3: 0.0097708955 | X3: 0.016953355 | Y3: 0.013259033 | Z3: 0.021353461 | AA3: 0.01322618 | AB3: 0.02263135 | AC3: 0.0067766936 | AD3: 0.025451088 | AE3: 0.017591166 | AF3: 0.014204988 | AG3: 2.0197127e-05 | AH3: 0.0047816919 | AI3: 0.0017772941 | AJ3: 0.077289412 | AK3: 0.0058409347 | AL3: 0.0045925009 | AM3: 0.018637948 | AN3: 0.00069992514 | AO3: 0.0015291933 | AP3: 0.04329055 | AQ3: 0.0054840775 | AR3: 0.0012425747 | AS3: 0.02023191 | AT3: 0.02004725 | AU3: 0.0074734148 | AV3: 0.011828206 | AW3: 0.032097695 | AX3: 0.010524261 | AY3: 0.032933761 | AZ3: 0.034523191 | BA3: 0.022361724 | BB3: 0.026043584 | BC3: 0.004884784 | BD3: 0.029860257 | BE3: 0.0035445869 | BF3: 0.0023471327 | BG3: 0.015447757 | BH3: 0.00070332379 | BI3: 0.0061354835 | BJ3: 0.0028048162 | BK3: 0.0077906213 | BL3: 0.0072491046 | BM3: 0.023519528 | BN3: 0.019300682
A4: Water meter rent | C4: {=TRANSPOSE('July2025-EXPENSE'!I6:I69)} -> 353.43498 | D4: 471.24664 | E4: 471.24664 | F4: 471.24664 | G4: 353.43498 | H4: 353.43498 | I4: 353.43498 | J4: 353.43498 | K4: 471.24664 | L4: 353.43498 | M4: 353.43498 | N4: 353.43498 | O4: 471.24664 | P4: 471.24664 | Q4: 471.24664 | R4: 353.43498 | S4: 353.43498 | T4: 471.24664 | U4: 471.24664 | V4: 471.24664 | W4: 353.43498 | X4: 353.43498 | Y4: 353.43498 | Z4: 353.43498 | AA4: 589.0583 | AB4: 353.43498 | AC4: 353.43498 | AD4: 353.43498 | AE4: 471.24664 | AF4: 471.24664 | AG4: 471.24664 | AH4: 353.43498 | AI4: 353.43498 | AJ4: 471.24664 | AK4: 471.24664 | AL4: 353.43498 | AM4: 353.43498 | AN4: 353.43498 | AO4: 353.43498 | AP4: 353.43498 | AQ4: 471.24664 | AR4: 353.43498 | AS4: 353.43498 | AT4: 353.43498 | AU4: 471.24664 | AV4: 471.24664 | AW4: 471.24664 | AX4: 353.43498 | AY4: 353.43498 | AZ4: 471.24664 | BA4: 471.24664 | BB4: 471.24664 | BC4: 353.43498 | BD4: 353.43498 | BE4: 353.43498 | BF4: 353.43498 | BG4: 471.24664 | BH4: 353.43498 | BI4: 353.43498 | BJ4: 353.43498 | BK4: 471.24664 | BL4: 471.24664 | BM4: 471.24664 | BN4: 353.43498
A5: Common meter rent (eq. distributed) | C5: ='July2025-EXPENSE'!$T$9 -> 5.5224215 | D5: ='July2025-EXPENSE'!$T$9 -> 5.5224215 | E5: ='July2025-EXPENSE'!$T$9 -> 5.5224215 | F5: ='July2025-EXPENSE'!$T$9 -> 5.5224215 | G5: ='July2025-EXPENSE'!$T$9 -> 5.5224215 | H5: ='July2025-EXPENSE'!$T$9 -> 5.5224215 | I5: ='July2025-EXPENSE'!$T$9 -> 5.5224215 | J5: ='July2025-EXPENSE'!$T$9 -> 5.5224215 | ... BN5: ='July2025-EXPENSE'!$T$9 -> 5.5224215
A6: Total water related expense | C6: {=TRANSPOSE('July2025-EXPENSE'!J6:J69)} -> 748.60555 | D6: 2011.6232 | E6: 2031.4622 | F6: 805.45739 | G6: 424.28307 | H6: 717.0886 | I6: 440.51497 | J6: 373.15257 | K6: 685.702 | L6: 650.22217 | M6: 469.82258 | N6: 359.89651 | O6: 1487.6032 | P6: 690.70683 | Q6: 988.42703 | R6: 1516.9608 | S6: 1293.6368 | T6: 1730.7662 | U6: 1809.5811 | V6: 2333.06 | W6: 747.83904 | X6: 1033.7009 | Y6: 886.66692 | Z6: 1208.8251 | AA6: 1120.9827 | AB6: 1259.6851 | AC6: 628.6698 | AD6: 1371.9107 | AE6: 1176.8975 | AF6: 1042.1276 | AG6: 477.5729 | AH6: 549.26874 | AI6: 429.6937 | AJ6: 3552.8877 | AK6: 709.23826 | AL6: 541.73894 | AM6: 1100.7477 | AN6: 386.81442 | AO6: 419.81929 | AP6: 2081.9213 | AQ6: 695.03534 | AR6: 408.41187 | AS6: 1164.1874 | AT6: 1156.838 | AU6: 774.21097 | AV6: 947.53164 | AW6: 1754.2573 | AX6: 777.82298 | AY6: 1669.7211 | AZ6: 1850.7921 | BA6: 1366.7657 | BB6: 1513.3037 | BC6: 553.3718 | BD6: 1547.3956 | BE6: 500.03196 | BF6: 452.37328 | BG6: 1091.5898 | BH6: 386.94969 | BI6: 603.14964 | BJ6: 470.58908 | BK6: 786.83578 | BL6: 765.28342 | BM6: 1412.8463 | BN6: 1127.1246
A7: Society Parking Rent | C7: {=TRANSPOSE('July2025-EXPENSE'!L6:L69)} -> 0 | D7: 0 | E7: 750 | F7: 0 | G7: 0 | H7: 0 | I7: 750 | J7: 0 | K7: 0 | L7: 0 | M7: 0 | N7: 0 | O7: 0 | P7: 0 | Q7: 750 | R7: 0 | S7: 0 | T7: 0 | U7: 0 | V7: 0 | W7: 0 | X7: 0 | Y7: 0 | Z7: 0 | AA7: 0 | AB7: 0 | AC7: 0 | AD7: 0 | AE7: 0 | AF7: 0 | AG7: 0 | AH7: 0 | AI7: 0 | AJ7: 0 | AK7: 0 | AL7: 0 | AM7: 0 | AN7: 0 | AO7: 0 | AP7: 0 | AQ7: 0 | AR7: 0 | AS7: 0 | AT7: 0 | AU7: 0 | AV7: 0 | AW7: 0 | AX7: 0 | AY7: 0 | AZ7: 0 | BA7: 0 | BB7: 0 | BC7: 0 | BD7: 0 | BE7: 0 | BF7: 0 | BG7: 0 | BH7: 750 | BI7: 0 | BJ7: 0 | BK7: 0 | BL7: 0 | BM7: 0 | BN7: 0
A8: Clubhouse booking fee | C8: {=TRANSPOSE('July2025-EXPENSE'!M6:M69)} -> 0 | D8: 0 | E8: 0 | F8: 0 | G8: 0 | H8: 0 | I8: 0 | J8: 0 | K8: 0 | L8: 0 | M8: 0 | N8: 0 | O8: 0 | P8: 0 | Q8: 0 | R8: 0 | S8: 0 | T8: 0 | U8: 0 | V8: 0 | W8: 0 | X8: 0 | Y8: 0 | Z8: 0 | AA8: 0 | AB8: 0 | AC8: 0 | AD8: 0 | AE8: 0 | AF8: 0 | AG8: 0 | AH8: 0 | AI8: 0 | AJ8: 0 | AK8: 0 | AL8: 0 | AM8: 0 | AN8: 0 | AO8: 0 | AP8: 0 | AQ8: 0 | AR8: 0 | AS8: 0 | AT8: 0 | AU8: 0 | AV8: 0 | AW8: 0 | AX8: 0 | AY8: 0 | AZ8: 0 | BA8: 0 | BB8: 0 | BC8: 0 | BD8: 0 | BE8: 0 | BF8: 0 | BG8: 0 | BH8: 0 | BI8: 0 | BJ8: 0 | BK8: 0 | BL8: 0 | BM8: 0 | BN8: 0
A9: Moving in/out charges | C9: {=TRANSPOSE('July2025-EXPENSE'!N6:N69)} -> 0 | D9: 0 | E9: 0 | F9: 0 | G9: 0 | H9: 0 | I9: 0 | J9: 0 | K9: 0 | L9: 0 | M9: 0 | N9: 0 | O9: 0 | P9: 0 | Q9: 0 | R9: 0 | S9: 0 | T9: 0 | U9: 0 | V9: 0 | W9: 0 | X9: 0 | Y9: 0 | Z9: 0 | AA9: 0 | AB9: 0 | AC9: 0 | AD9: 0 | AE9: 0 | AF9: 0 | AG9: 0 | AH9: 0 | AI9: 0 | AJ9: 0 | AK9: 0 | AL9: 0 | AM9: 0 | AN9: 0 | AO9: 0 | AP9: 0 | AQ9: 0 | AR9: 0 | AS9: 0 | AT9: 0 | AU9: 0 | AV9: 0 | AW9: 0 | AX9: 0 | AY9: 0 | AZ9: 0 | BA9: 0 | BB9: 0 | BC9: 0 | BD9: 0 | BE9: 0 | BF9: 0 | BG9: 0 | BH9: 0 | BI9: 0 | BJ9: 0 | BK9: 0 | BL9: 0 | BM9: 0 | BN9: 0
A10: Gym usage fee | C10: {=TRANSPOSE('July2025-EXPENSE'!O6:O69)} -> 0 | D10: 0 | E10: 0 | F10: 0 | G10: 0 | H10: 0 | I10: 0 | J10: 0 | K10: 0 | L10: 0 | M10: 0 | N10: 0 | O10: 0 | P10: 0 | Q10: 0 | R10: 0 | S10: 0 | T10: 0 | U10: 0 | V10: 0 | W10: 0 | X10: 0 | Y10: 0 | Z10: 0 | AA10: 0 | AB10: 0 | AC10: 0 | AD10: 0 | AE10: 0 | AF10: 0 | AG10: 0 | AH10: 0 | AI10: 0 | AJ10: 0 | AK10: 0 | AL10: 0 | AM10: 0 | AN10: 0 | AO10: 0 | AP10: 0 | AQ10: 0 | AR10: 0 | AS10: 0 | AT10: 0 | AU10: 0 | AV10: 0 | AW10: 0 | AX10: 0 | AY10: 0 | AZ10: 0 | BA10: 0 | BB10: 0 | BC10: 0 | BD10: 0 | BE10: 0 | BF10: 0 | BG10: 0 | BH10: 0 | BI10: 0 | BJ10: 0 | BK10: 0 | BL10: 0 | BM10: 0 | BN10: 0
A11: {=TRANSPOSE('ANNUAL-EXPENSE-DETAILS'!B2:BC2)} -> DRINKING WATER SLN WATER SUP | B11: {=TRANSPOSE('ANNUAL-EXPENSE-DETAILS'!B6:BC6)} -> 16800
A12: STP SLUDGE CLEANING BALAJI | B12: 23000
A13: STP MAINTENANCE | B13: 30000 | C13: =$B13/64 -> 468.75 | D13: =$B13/64 -> 468.75 | E13: =$B13/64 -> 468.75 | F13: =$B13/64 -> 468.75 | G13: =$B13/64 -> 468.75 | H13: =$B13/64 -> 468.75 | I13: =$B13/64 -> 468.75 | J13: =$B13/64 -> 468.75 | ... BN13: =$B13/64 -> 468.75
A14: STP MATERIALS | B14: 1600 | C14: =$B14/64 -> 25 | D14: =$B14/64 -> 25 | E14: =$B14/64 -> 25 | F14: =$B14/64 -> 25 | G14: =$B14/64 -> 25 | H14: =$B14/64 -> 25 | I14: =$B14/64 -> 25 | J14: =$B14/64 -> 25 | ... BN14: =$B14/64 -> 25
A15: STP REPAIR | B15: 0 | C15: =$B15/64 -> 0 | D15: =$B15/64 -> 0 | E15: =$B15/64 -> 0 | F15: =$B15/64 -> 0 | G15: =$B15/64 -> 0 | H15: =$B15/64 -> 0 | I15: =$B15/64 -> 0 | J15: =$B15/64 -> 0 | ... BN15: =$B15/64 -> 0
A16: COMMON ELECTRICITY BILL | B16: 29359 | C16: =$B16/64 -> 458.73438 | D16: =$B16/64 -> 458.73438 | E16: =$B16/64 -> 458.73438 | F16: =$B16/64 -> 458.73438 | G16: =$B16/64 -> 458.73438 | H16: =$B16/64 -> 458.73438 | I16: =$B16/64 -> 458.73438 | J16: =$B16/64 -> 458.73438 | ... BN16: =$B16/64 -> 458.73438
A17: BECOM Service tax | B17: 0 | C17: =$B17/64 -> 0 | D17: =$B17/64 -> 0 | E17: =$B17/64 -> 0 | F17: =$B17/64 -> 0 | G17: =$B17/64 -> 0 | H17: =$B17/64 -> 0 | I17: =$B17/64 -> 0 | J17: =$B17/64 -> 0 | ... BN17: =$B17/64 -> 0
A18: SECURITY SERVICES | B18: 151040 | C18: =$B18/64 -> 2360 | D18: =$B18/64 -> 2360 | E18: =$B18/64 -> 2360 | F18: =$B18/64 -> 2360 | G18: =$B18/64 -> 2360 | H18: =$B18/64 -> 2360 | I18: =$B18/64 -> 2360 | J18: =$B18/64 -> 2360 | ... BN18: =$B18/64 -> 2360
A19: GARBAGE REMOVAL | B19: 6600 | C19: =$B19/64 -> 103.125 | D19: =$B19/64 -> 103.125 | E19: =$B19/64 -> 103.125 | F19: =$B19/64 -> 103.125 | G19: =$B19/64 -> 103.125 | H19: =$B19/64 -> 103.125 | I19: =$B19/64 -> 103.125 | J19: =$B19/64 -> 103.125 | ... BN19: =$B19/64 -> 103.125
A20: PETTY CASH | B20: 10000 | C20: =$B20/64 -> 156.25 | D20: =$B20/64 -> 156.25 | E20: =$B20/64 -> 156.25 | F20: =$B20/64 -> 156.25 | G20: =$B20/64 -> 156.25 | H20: =$B20/64 -> 156.25 | I20: =$B20/64 -> 156.25 | J20: =$B20/64 -> 156.25 | ... BN20: =$B20/64 -> 156.25
A21: ELEVATOR MAINTENANCE | B21: 28980 | C21: =$B21/64 -> 452.8125 | D21: =$B21/64 -> 452.8125 | E21: =$B21/64 -> 452.8125 | F21: =$B21/64 -> 452.8125 | G21: =$B21/64 -> 452.8125 | H21: =$B21/64 -> 452.8125 | I21: =$B21/64 -> 452.8125 | J21: =$B21/64 -> 452.8125 | ... BN21: =$B21/64 -> 452.8125
A22: MOTOR REPAIR | B22: 0 | C22: =$B22/64 -> 0 | D22: =$B22/64 -> 0 | E22: =$B22/64 -> 0 | F22: =$B22/64 -> 0 | G22: =$B22/64 -> 0 | H22: =$B22/64 -> 0 | I22: =$B22/64 -> 0 | J22: =$B22/64 -> 0 | ... BN22: =$B22/64 -> 0
A23: PLUMBING MATERIAL | B23: 0 | C23: =$B23/64 -> 0 | D23: =$B23/64 -> 0 | E23: =$B23/64 -> 0 | F23: =$B23/64 -> 0 | G23: =$B23/64 -> 0 | H23: =$B23/64 -> 0 | I23: =$B23/64 -> 0 | J23: =$B23/64 -> 0 | ... BN23: =$B23/64 -> 0
A24: ELECTRICITY MATERIAL | B24: 0 | C24: =$B24/64 -> 0 | D24: =$B24/64 -> 0 | E24: =$B24/64 -> 0 | F24: =$B24/64 -> 0 | G24: =$B24/64 -> 0 | H24: =$B24/64 -> 0 | I24: =$B24/64 -> 0 | J24: =$B24/64 -> 0 | ... BN24: =$B24/64 -> 0
... A60: Speed Breaker near the gate | B60: 6000 | C60: =$B60/64 -> 93.75 | D60: =$B60/64 -> 93.75 | E60: =$B60/64 -> 93.75 | F60: =$B60/64 -> 93.75 | G60: =$B60/64 -> 93.75 | H60: =$B60/64 -> 93.75 | I60: =$B60/64 -> 93.75 | J60: =$B60/64 -> 93.75 | ... BN60: =$B60/64 -> 93.75
A61: Gym Equipment Repairs | B61: 0 | C61: =SUM(C6,C13:C60) -> 5496.7149 | D61: =SUM(D6,D13:D60) -> 6759.7326 | E61: =SUM(E6,E13:E60) -> 6779.5716 | F61: =SUM(F6,F13:F60) -> 5553.5668 | G61: =SUM(G6,G13:G60) -> 5172.3924 | H61: =SUM(H6,H13:H60) -> 5465.198 | I61: =SUM(I6,I13:I60) -> 5188.6243 | J61: =SUM(J6,J13:J60) -> 5121.2619 | ... BN61: =SUM(BN6,BN13:BN60) -> 5875.2339
A62: Additional Waste Disposal | B62: 0
A63: Swimming Pool Cleaning | B63: 0
A64: HOUSE KEEPING MATERIALS | B64: 0

Sheet July2025-EXPENSE-Flatwise-Trans
A1: {=TRANSPOSE('July2025-EXPENSE-Flatwise'!A1:BN61)} -> Expense Head | B1: Water consumption (Litres) | C1: Water consumption (%age of total) | D1: Water meter rent | E1: Common meter rent (eq. distributed) | F1: Total water related expense | G1: Society Parking Rent | H1: Clubhouse booking fee | I1: Moving in/out charges | J1: Gym usage fee | K1: DRINKING WATER SLN WATER SUP | L1: STP SLUDGE CLEANING BALAJI | M1: STP MAINTENANCE | N1: STP MATERIALS | O1: STP REPAIR | P1: COMMON ELECTRICITY BILL | Q1: BECOM Service tax | R1: SECURITY SERVICES | S1: GARBAGE REMOVAL | T1: PETTY CASH | U1: ELEVATOR MAINTENANCE | V1: MOTOR REPAIR | W1: PLUMBING MATERIAL | X1: ELECTRICITY MATERIAL | Y1: ELECTRICITY MATERIAL | Z1: TRANSFORMER REPAIR | AA1: GENERATOR MAINTENANCE EPITOME | AB1: GARDENING | AC1: PLUMBER WAGE | AD1: ELECTRICIAN WAGE | AE1: MANAGER WAGE | AF1: TANK AND SUMP CLEANING | AG1: SECURITY WATER EXPENSES GREENMART | AH1: SWIMMING POOL MOTOR REPAIR | AI1: CCTV REPAIR | AJ1: CCTV monitor | AK1: WATER PIPE | AL1: RAILING FOR STAIRCASE | AM1: Play area sand | AN1: BARBED WIRE REPAIR | AO1: DRIED LEAVES REMOVAL | AP1: DRAIN CLEANING | AQ1: Security room & Play area painting | AR1: Play area sand removal & cracks filling | AS1: Front garden cleaning and red soil filling | AT1: Landscaping work for STP water disposal | AU1: ACCOUNTING | AV1: Lift Painting | AW1: Lift wiring sepration | AX1: Earthing repair | AY1: Pest Control | AZ1: Freshwater pipe repair | BA1: NBH device replacement | BB1: NBH VMS | BC1: REPAIRS | BD1: Cricket Net | BE1: LOOK AHEAD EXPENSE | BF1: Rear bondary cleaning | BG1: 9,7,8,11 series terrace pipe repairs | BH1: Speed Breaker near the gate | BI1: Gym Equipment Repairs
A2: 0 | B2: 0 | C2: 0 | D2: 0 | E2: 0 | F2: 0 | G2: 0 | H2: 0 | I2: 0 | J2: 0 | K2: 16800 | L2: 23000 | M2: 30000 | N2: 1600 | O2: 0 | P2: 29359 | Q2: 0 | R2: 151040 | S2: 6600 | T2: 10000 | U2: 28980 | V2: 0 | W2: 0 | X2: 0 | Y2: 0 | Z2: 0 | AA2: 0 | AB2: 3000 | AC2: 7000 | AD2: 6000 | AE2: 9000 | AF2: 0 | AG2: 0 | AH2: 0 | AI2: 0 | AJ2: 0 | AK2: 0 | AL2: 0 | AM2: 0 | AN2: 0 | AO2: 3300 | AP2: 0 | AQ2: 0 | AR2: 0 | AS2: 0 | AT2: 0 | AU2: 5000 | AV2: 0 | AW2: 0 | AX2: 0 | AY2: 7000 | AZ2: 0 | BA2: 0 | BB2: 0 | BC2: 0 | BD2: 0 | BE2: 0 | BF2: 0 | BG2: 0 | BH2: 6000 | BI2: 0
A3: F1 | B3: 4320.9141 | C3: 0.0097901545 | D3: 353.43498 | E3: 5.5224215 | F3: 748.60555 | G3: 0 | H3: 0 | I3: 0 | J3: 0 | K3: 0 | L3: 0 | M3: 468.75 | N3: 25 | O3: 0 | P3: 458.73438 | Q3: 0 | R3: 2360 | S3: 103.125 | T3: 156.25 | U3: 452.8125 | V3: 0 | W3: 0 | X3: 0 | Y3: 0 | Z3: 0 | AA3: 0 | AB3: 46.875 | AC3: 109.375 | AD3: 93.75 | AE3: 140.625 | AF3: 0 | AG3: 0 | AH3: 0 | AI3: 0 | AJ3: 0 | AK3: 0 | AL3: 0 | AM3: 0 | AN3: 0 | AO3: 51.5625 | AP3: 0 | AQ3: 0 | AR3: 0 | AS3: 0 | AT3: 0 | AU3: 78.125 | AV3: 0 | AW3: 0 | AX3: 0 | AY3: 109.375 | AZ3: 0 | BA3: 0 | BB3: 0 | BC3: 0 | BD3: 0 | BE3: 0 | BF3: 0 | BG3: 0 | BH3: 93.75 | BI3: 5496.7149
A4: F2 | B4: 17020.414 | C4: 0.038564174 | D4: 471.24664 | E4: 5.5224215 | F4: 2011.6232 | G4: 0 | H4: 0 | I4: 0 | J4: 0 | K4: 0 | L4: 0 | M4: 468.75 | N4: 25 | O4: 0 | P4: 458.73438 | Q4: 0 | R4: 2360 | S4: 103.125 | T4: 156.25 | U4: 452.8125 | V4: 0 | W4: 0 | X4: 0 | Y4: 0 | Z4: 0 | AA4: 0 | AB4: 46.875 | AC4: 109.375 | AD4: 93.75 | AE4: 140.625 | AF4: 0 | AG4: 0 | AH4: 0 | AI4: 0 | AJ4: 0 | AK4: 0 | AL4: 0 | AM4: 0 | AN4: 0 | AO4: 51.5625 | AP4: 0 | AQ4: 0 | AR4: 0 | AS4: 0 | AT4: 0 | AU4: 78.125 | AV4: 0 | AW4: 0 | AX4: 0 | AY4: 109.375 | AZ4: 0 | BA4: 0 | BB4: 0 | BC4: 0 | BD4: 0 | BE4: 0 | BF4: 0 | BG4: 0 | BH4: 93.75 | BI4: 6759.7326
A5: F3 | B5: 17240.414 | C5: 0.039062642 | D5: 471.24664 | E5: 5.5224215 | F5: 2031.4622 | G5: 750 | H5: 0 | I5: 0 | J5: 0 | K5: 0 | L5: 0 | M5: 468.75 | N5: 25 | O5: 0 | P5: 458.73438 | Q5: 0 | R5: 2360 | S5: 103.125 | T5: 156.25 | U5: 452.8125 | V5: 0 | W5: 0 | X5: 0 | Y5: 0 | Z5: 0 | AA5: 0 | AB5: 46.875 | AC5: 109.375 | AD5: 93.75 | AE5: 140.625 | AF5: 0 | AG5: 0 | AH5: 0 | AI5: 0 | AJ5: 0 | AK5: 0 | AL5: 0 | AM5: 0 | AN5: 0 | AO5: 51.5625 | AP5: 0 | AQ5: 0 | AR5: 0 | AS5: 0 | AT5: 0 | AU5: 78.125 | AV5: 0 | AW5: 0 | AX5: 0 | AY5: 109.375 | AZ5: 0 | BA5: 0 | BB5: 0 | BC5: 0 | BD5: 0 | BE5: 0 | BF5: 0 | BG5: 0 | BH5: 93.75 | BI5: 6779.5716
A6: F4 | B6: 3644.9141 | C6: 0.0082585007 | D6: 471.24664 | E6: 5.5224215 | F6: 805.45739 | G6: 0 | H6: 0 | I6: 0 | J6: 0 | K6: 0 | L6: 0 | M6: 468.75 | N6: 25 | O6: 0 | P6: 458.73438 | Q6: 0 | R6: 2360 | S6: 103.125 | T6: 156.25 | U6: 452.8125 | V6: 0 | W6: 0 | X6: 0 | Y6: 0 | Z6: 0 | AA6: 0 | AB6: 46.875 | AC6: 109.375 | AD6: 93.75 | AE6: 140.625 | AF6: 0 | AG6: 0 | AH6: 0 | AI6: 0 | AJ6: 0 | AK6: 0 | AL6: 0 | AM6: 0 | AN6: 0 | AO6: 51.5625 | AP6: 0 | AQ6: 0 | AR6: 0 | AS6: 0 | AT6: 0 | AU6: 78.125 | AV6: 0 | AW6: 0 | AX6: 0 | AY6: 109.375 | AZ6: 0 | BA6: 0 | BB6: 0 | BC6: 0 | BD6: 0 | BE6: 0 | BF6: 0 | BG6: 0 | BH6: 93.75 | BI6: 5553.5668
A7: F5 | B7: 724.41406 | C7: 0.0016413485 | D7: 353.43498 | E7: 5.5224215 | F7: 424.28307 | G7: 0 | H7: 0 | I7: 0 | J7: 0 | K7: 0 | L7: 0 | M7: 468.75 | N7: 25 | O7: 0 | P7: 458.73438 | Q7: 0 | R7: 2360 | S7: 103.125 | T7: 156.25 | U7: 452.8125 | V7: 0 | W7: 0 | X7: 0 | Y7: 0 | Z7: 0 | AA7: 0 | AB7: 46.875 | AC7: 109.375 | AD7: 93.75 | AE7: 140.625 | AF7: 0 | AG7: 0 | AH7: 0 | AI7: 0 | AJ7: 0 | AK7: 0 | AL7: 0 | AM7: 0 | AN7: 0 | AO7: 51.5625 | AP7: 0 | AQ7: 0 | AR7: 0 | AS7: 0 | AT7: 0 | AU7: 78.125 | AV7: 0 | AW7: 0 | AX7: 0 | AY7: 109.375 | AZ7: 0 | BA7: 0 | BB7: 0 | BC7: 0 | BD7: 0 | BE7: 0 | BF7: 0 | BG7: 0 | BH7: 93.75 | BI7: 5172.3924
A8: F6 | B8: 3971.4141 | C8: 0.0089982714 | D8: 353.43498 | E8: 5.5224215 | F8: 717.0886 | G8: 0 | H8: 0 | I8: 0 | J8: 0 | K8: 0 | L8: 0 | M8: 468.75 | N8: 25 | O8: 0 | P8: 458.73438 | Q8: 0 | R8: 2360 | S8: 103.125 | T8: 156.25 | U8: 452.8125 | V8: 0 | W8: 0 | X8: 0 | Y8: 0 | Z8: 0 | AA8: 0 | AB8: 46.875 | AC8: 109.375 | AD8: 93.75 | AE8: 140.625 | AF8: 0 | AG8: 0 | AH8: 0 | AI8: 0 | AJ8: 0 | AK8: 0 | AL8: 0 | AM8: 0 | AN8: 0 | AO8: 51.5625 | AP8: 0 | AQ8: 0 | AR8: 0 | AS8: 0 | AT8: 0 | AU8: 78.125 | AV8: 0 | AW8: 0 | AX8: 0 | AY8: 109.375 | AZ8: 0 | BA8: 0 | BB8: 0 | BC8: 0 | BD8: 0 | BE8: 0 | BF8: 0 | BG8: 0 | BH8: 93.75 | BI8: 5465.198
A9: F7 | B9: 904.41406 | C9: 0.0020491853 | D9: 353.43498 | E9: 5.5224215 | F9: 440.51497 | G9: 750 | H9: 0 | I9: 0 | J9: 0 | K9: 0 | L9: 0 | M9: 468.75 | N9: 25 | O9: 0 | P9: 458.73438 | Q9: 0 | R9: 2360 | S9: 103.125 | T9: 156.25 | U9: 452.8125 | V9: 0 | W9: 0 | X9: 0 | Y9: 0 | Z9: 0 | AA9: 0 | AB9: 46.875 | AC9: 109.375 | AD9: 93.75 | AE9: 140.625 | AF9: 0 | AG9: 0 | AH9: 0 | AI9: 0 | AJ9: 0 | AK9: 0 | AL9: 0 | AM9: 0 | AN9: 0 | AO9: 51.5625 | AP9: 0 | AQ9: 0 | AR9: 0 | AS9: 0 | AT9: 0 | AU9: 78.125 | AV9: 0 | AW9: 0 | AX9: 0 | AY9: 109.375 | AZ9: 0 | BA9: 0 | BB9: 0 | BC9: 0 | BD9: 0 | BE9: 0 | BF9: 0 | BG9: 0 | BH9: 93.75 | BI9: 5188.6243
A10: F8 | B10: 157.41406 | C10: 0.0003566625 | D10: 353.43498 | E10: 5.5224215 | F10: 373.15257 | G10: 0 | H10: 0 | I10: 0 | J10: 0 | K10: 0 | L10: 0 | M10: 468.75 | N10: 25 | O10: 0 | P10: 458.73438 | Q10: 0 | R10: 2360 | S10: 103.125 | T10: 156.25 | U10: 452.8125 | V10: 0 | W10: 0 | X10: 0 | Y10: 0 | Z10: 0 | AA10: 0 | AB10: 46.875 | AC10: 109.375 | AD10: 93.75 | AE10: 140.625 | AF10: 0 | AG10: 0 | AH10: 0 | AI10: 0 | AJ10: 0 | AK10: 0 | AL10: 0 | AM10: 0 | AN10: 0 | AO10: 51.5625 | AP10: 0 | AQ10: 0 | AR10: 0 | AS10: 0 | AT10: 0 | AU10: 78.125 | AV10: 0 | AW10: 0 | AX10: 0 | AY10: 109.375 | AZ10: 0 | BA10: 0 | BB10: 0 | BC10: 0 | BD10: 0 | BE10: 0 | BF10: 0 | BG10: 0 | BH10: 93.75 | BI10: 5121.2619
A11: F9 | B11: 2316.9141 | C11: 0.0052495713 | D11: 471.24664 | E11: 5.5224215 | F11: 685.702 | G11: 0 | H11: 0 | I11: 0 | J11: 0 | K11: 0 | L11: 0 | M11: 468.75 | N11: 25 | O11: 0 | P11: 458.73438 | Q11: 0 | R11: 2360 | S11: 103.125 | T11: 156.25 | U11: 452.8125 | V11: 0 | W11: 0 | X11: 0 | Y11: 0 | Z11: 0 | AA11: 0 | AB11: 46.875 | AC11: 109.375 | AD11: 93.75 | AE11: 140.625 | AF11: 0 | AG11: 0 | AH11: 0 | AI11: 0 | AJ11: 0 | AK11: 0 | AL11: 0 | AM11: 0 | AN11: 0 | AO11: 51.5625 | AP11: 0 | AQ11: 0 | AR11: 0 | AS11: 0 | AT11: 0 | AU11: 78.125 | AV11: 0 | AW11: 0 | AX11: 0 | AY11: 109.375 | AZ11: 0 | BA11: 0 | BB11: 0 | BC11: 0 | BD11: 0 | BE11: 0 | BF11: 0 | BG11: 0 | BH11: 93.75 | BI11: 5433.8114
A12: F10 | B12: 3229.9141 | C12: 0.0073182103 | D12: 353.43498 | E12: 5.5224215 | F12: 650.22217 | G12: 0 | H12: 0 | I12: 0 | J12: 0 | K12: 0 | L12: 0 | M12: 468.75 | N12: 25 | O12: 0 | P12: 458.73438 | Q12: 0 | R12: 2360 | S12: 103.125 | T12: 156.25 | U12: 452.8125 | V12: 0 | W12: 0 | X12: 0 | Y12: 0 | Z12: 0 | AA12: 0 | AB12: 46.875 | AC12: 109.375 | AD12: 93.75 | AE12: 140.625 | AF12: 0 | AG12: 0 | AH12: 0 | AI12: 0 | AJ12: 0 | AK12: 0 | AL12: 0 | AM12: 0 | AN12: 0 | AO12: 51.5625 | AP12: 0 | AQ12: 0 | AR12: 0 | AS12: 0 | AT12: 0 | AU12: 78.125 | AV12: 0 | AW12: 0 | AX12: 0 | AY12: 109.375 | AZ12: 0 | BA12: 0 | BB12: 0 | BC12: 0 | BD12: 0 | BE12: 0 | BF12: 0 | BG12: 0 | BH12: 93.75 | BI12: 5398.3315
A13: F11 | B13: 1229.4141 | C13: 0.0027855573 | D13: 353.43498 | E13: 5.5224215 | F13: 469.82258 | G13: 0 | H13: 0 | I13: 0 | J13: 0 | K13: 0 | L13: 0 | M13: 468.75 | N13: 25 | O13: 0 | P13: 458.73438 | Q13: 0 | R13: 2360 | S13: 103.125 | T13: 156.25 | U13: 452.8125 | V13: 0 | W13: 0 | X13: 0 | Y13: 0 | Z13: 0 | AA13: 0 | AB13: 46.875 | AC13: 109.375 | AD13: 93.75 | AE13: 140.625 | AF13: 0 | AG13: 0 | AH13: 0 | AI13: 0 | AJ13: 0 | AK13: 0 | AL13: 0 | AM13: 0 | AN13: 0 | AO13: 51.5625 | AP13: 0 | AQ13: 0 | AR13: 0 | AS13: 0 | AT13: 0 | AU13: 78.125 | AV13: 0 | AW13: 0 | AX13: 0 | AY13: 109.375 | AZ13: 0 | BA13: 0 | BB13: 0 | BC13: 0 | BD13: 0 | BE13: 0 | BF13: 0 | BG13: 0 | BH13: 93.75 | BI13: 5217.932
A14: F12 | B14: 10.414062 | C14: 2.3595767e-05 | D14: 353.43498 | E14: 5.5224215 | F14: 359.89651 | G14: 0 | H14: 0 | I14: 0 | J14: 0 | K14: 0 | L14: 0 | M14: 468.75 | N14: 25 | O14: 0 | P14: 458.73438 | Q14: 0 | R14: 2360 | S14: 103.125 | T14: 156.25 | U14: 452.8125 | V14: 0 | W14: 0 | X14: 0 | Y14: 0 | Z14: 0 | AA14: 0 | AB14: 46.875 | AC14: 109.375 | AD14: 93.75 | AE14: 140.625 | AF14: 0 | AG14: 0 | AH14: 0 | AI14: 0 | AJ14: 0 | AK14: 0 | AL14: 0 | AM14: 0 | AN14: 0 | AO14: 51.5625 | AP14: 0 | AQ14: 0 | AR14: 0 | AS14: 0 | AT14: 0 | AU14: 78.125 | AV14: 0 | AW14: 0 | AX14: 0 | AY14: 109.375 | AZ14: 0 | BA14: 0 | BB14: 0 | BC14: 0 | BD14: 0 | BE14: 0 | BF14: 0 | BG14: 0 | BH14: 93.75 | BI14: 5108.0059
... A66: T16 | B66: 8518.4141 | C66: 0.019300682 | D66: 353.43498 | E66: 5.5224215 | F66: 1127.1246 | G66: 0 | H66: 0 | I66: 0 | J66: 0 | K66: 0 | L66: 0 | M66: 468.75 | N66: 25 | O66: 0 | P66: 458.73438 | Q66: 0 | R66: 2360 | S66: 103.125 | T66: 156.25 | U66: 452.8125 | V66: 0 | W66: 0 | X66: 0 | Y66: 0 | Z66: 0 | AA66: 0 | AB66: 46.875 | AC66: 109.375 | AD66: 93.75 | AE66: 140.625 | AF66: 0 | AG66: 0 | AH66: 0 | AI66: 0 | AJ66: 0 | AK66: 0 | AL66: 0 | AM66: 0 | AN66: 0 | AO66: 51.5625 | AP66: 0 | AQ66: 0 | AR66: 0 | AS66: 0 | AT66: 0 | AU66: 78.125 | AV66: 0 | AW66: 0 | AX66: 0 | AY66: 109.375 | AZ66: 0 | BA66: 0 | BB66: 0 | BC66: 0 | BD66: 0 | BE66: 0 | BF66: 0 | BG66: 0 | BH66: 93.75 | BI66: 5875.2339

Sheet July2025-COLLECTION
A1: FLAT # | C1: Amount | D1: Date | E1: Amount | F1: Date | G1: Amount | H1: Date | I1: Amount | J1: Date | K1: Total
A2: F1 | B2: Shailesh Srivastava / Azeem Nawaz | K2: =SUM(C2,E2,G2,I2) -> 0
A3: F2 | B3: Shanthanu | K3: =SUM(C3,E3,G3,I3) -> 0
A4: F3 | B4: Samrat Kar | C4: 6000 | D4: 45839 | K4: =SUM(C4,E4,G4,I4) -> 6000
A5: F4 | B5: Renu R | K5: =SUM(C5,E5,G5,I5) -> 0
A6: F5 | B6: Vamsidhar Bethanabatla / Madhuri Anumula | C6: 323 | D6: 45863 | K6: =SUM(C6,E6,G6,I6) -> 323
A7: F6 | B7: Meghana Viral Shah and Vviral Shah (Owner) / Sangeet and Swagat (Tenent) | C7: 1288 | D7: 45864 | K7: =SUM(C7,E7,G7,I7) -> 1288
A8: F7 | B8: Vimal NK | C8: 5050.91 | D8: 45859 | K8: =SUM(C8,E8,G8,I8) -> 5050.91
A9: F8 | B9: Sujeet Kumar (Tenant)/Sreejith Menon (Owner) | C9: 4291 | D9: 45854 | K9: =SUM(C9,E9,G9,I9) -> 4291
A10: F9 | B10: Vijay Suswaram (Owner) / Divya Shikha (Tenant) | C10: 4567 | D10: 45861 | K10: =SUM(C10,E10,G10,I10) -> 4567
A11: F10 | B11: Aby Thomas | C11: 4536 | D11: 45863 | K11: =SUM(C11,E11,G11,I11) -> 4536
A12: F11 | B12: N. Geetha | C12: 4584 | D12: 45855 | K12: =SUM(C12,E12,G12,I12) -> 4584
A13: F12 | B13: Anirudh Singh | C13: 4273 | D13: 45854 | K13: =SUM(C13,E13,G13,I13) -> 4273
A14: F13 | B14: Sanchay Saxena | C14: 5598.22 | D14: 45864 | K14: =SUM(C14,E14,G14,I14) -> 5598.22
A15: F14 | B15: Hemant Patel | C15: 5391 | D15: 45860 | K15: =SUM(C15,E15,G15,I15) -> 5391
A16: F15 | B16: Senthil.Vijayaragavan | C16: 5712 | D16: 45855 | K16: =SUM(C16,E16,G16,I16) -> 5712
A17: F16 | B17: Sreeja Sudharma | K17: =SUM(C17,E17,G17,I17) -> 0
A18: G1 | B18: Venkataramanan C | C18: 4700 | D18: 45857 | K18: =SUM(C18,E18,G18,I18) -> 4700
A19: G2 | B19: Kaushik Kasibhatla | C19: 6087.95 | D19: 45860 | K19: =SUM(C19,E19,G19,I19) -> 6087.95
A20: G3 | B20: Balakrishnan | C20: 5120 | D20: 45861 | K20: =SUM(C20,E20,G20,I20) -> 5120
A21: G4 | B21: Ashwin Pandith | C21: 5140 | D21: 45854 | K21: =SUM(C21,E21,G21,I21) -> 5140
A22: G5 | B22: Mayank Phophaliya | K22: =SUM(C22,E22,G22,I22) -> 0
A23: G6 | B23: Mohit Daga | C23: 20000 | D23: 45855 | K23: =SUM(C23,E23,G23,I23) -> 20000
A24: G7 | B24: Prince Richfield | C24: 4083 | D24: 45841 | K24: =SUM(C24,E24,G24,I24) -> 4083
A25: G8 | B25: Ranjithkumar R / Sameer (tenant) / Princy (tenant) | K25: =SUM(C25,E25,G25,I25) -> 0
A26: G9 | B26: Chandramouli | C26: 5203 | D26: 45856 | K26: =SUM(C26,E26,G26,I26) -> 5203
A27: G10 | B27: Cijo Jacob / Thara Joy | C27: 5062 | D27: 45855 | K27: =SUM(C27,E27,G27,I27) -> 5062
A28: G11 | B28: Ketan Verlekar | C28: 4541 | D28: 45854 | K28: =SUM(C28,E28,G28,I28) -> 4541
A29: G12 | B29: Shyam Nair | C29: 5083 | D29: 45863 | K29: =SUM(C29,E29,G29,I29) -> 5083
A30: G13 | B30: Ajai.B | C30: 13339 | D30: 45863 | K30: =SUM(C30,E30,G30,I30) -> 13339
A31: G14 | B31: Surajit Borah | C31: 4969 | D31: 45856 | K31: =SUM(C31,E31,G31,I31) -> 4969
A32: G15 | B32: Suresh Nallusamy / Antriksh (tenant) | K32: =SUM(C32,E32,G32,I32) -> 0
A33: G16 | B33: Praveen Ganesan | C33: 4519.05 | D33: 45857 | K33: =SUM(C33,E33,G33,I33) -> 4519.05
A34: S1 | B34: S.N.Behera | C34: 4365.17 | D34: 45857 | K34: =SUM(C34,E34,G34,I34) -> 4365.17
A35: S2 | B35: Sonal Singh | K35: =SUM(C35,E35,G35,I35) -> 0
A36: S3 | B36: Koteswararao | C36: 4573 | D36: 45857 | K36: =SUM(C36,E36,G36,I36) -> 4573
A37: S4 | B37: Swaminathan | C37: 4516 | D37: 45860 | K37: =SUM(C37,E37,G37,I37) -> 4516
A38: S5 | B38: Abhishek Gopalakrishnan | K38: =SUM(C38,E38,G38,I38) -> 0
A39: S6 | B39: Vivek Dhingra / Pratyush Das | K39: =SUM(C39,E39,G39,I39) -> 0
A40: S7 | B40: Harish B | C40: 4378 | D40: 45862 | K40: =SUM(C40,E40,G40,I40) -> 4378
A41: S8 | B41: Irudayaraj Alwin | C41: 5922.86 | D41: 45865 | K41: =SUM(C41,E41,G41,I41) -> 5922.86
A42: S9 | B42: Pawan GS | C42: 5000 | D42: 45856 | K42: =SUM(C42,E42,G42,I42) -> 5000
A43: S10 | B43: Lakshmikanth | K43: =SUM(C43,E43,G43,I43) -> 0
A44: S11 | B44: Gowrish Patnaik / Somananth GM | C44: 5000 | D44: 45860 | K44: =SUM(C44,E44,G44,I44) -> 5000
A45: S12 | B45: Saovik Mondal | C45: 5119 | D45: 45859 | K45: =SUM(C45,E45,G45,I45) -> 5119
A46: S13 | B46: Ramadevi S. | C46: 4778.53 | D46: 45864 | K46: =SUM(C46,E46,G46,I46) -> 4778.53
A47: S14 | B47: Nishant Upadhyay(Owner)/ Fabian (Tenant) | K47: =SUM(C47,E47,G47,I47) -> 0
A48: S15 | B48: Manas Dasgupta | C48: 5440 | D48: 45841 | E48: 4479 | F48: 45857 | K48: =SUM(C48,E48,G48,I48) -> 9919
A49: S16 | B49: Devendra Singh Rawat / Nancy | C49: 4475 | D49: 45857 | K49: =SUM(C49,E49,G49,I49) -> 4475
A50: T1 | B50: Prashant Sikdar | C50: 5410 | D50: 45857 | K50: =SUM(C50,E50,G50,I50) -> 5410
A51: T2 | B51: Kunal Mehta | K51: =SUM(C51,E51,G51,I51) -> 0
A52: T3 | B52: Kapil Garg | C52: 4860 | D52: 45860 | K52: =SUM(C52,E52,G52,I52) -> 4860
A53: T4 | B53: Vijet Alva (Owner) - Masood (Tenant) | K53: =SUM(C53,E53,G53,I53) -> 0
A54: T5 | B54: Ganesh Iyer and Latha Iyer( owner) Richa (Tenant) | K54: =SUM(C54,E54,G54,I54) -> 0
A55: T6 | B55: Mythili Ramesh | K55: =SUM(C55,E55,G55,I55) -> 0
A56: T7 | B56: Vinyas Ramachandra / Shwetha Marnamikatta / Katari Siva Rama Raju | C56: 4403.5 | D56: 45859 | K56: =SUM(C56,E56,G56,I56) -> 4403.5
A57: T8 | B57: Lalit Kumar Sharma | C57: 4529 | D57: 45865 | K57: =SUM(C57,E57,G57,I57) -> 4529
A58: T9 | B58: Nishith Sahu and Priyanka Rani (Owner)/ Anmol Verma (Tenant) | C58: 5329 | D58: 45854 | K58: =SUM(C58,E58,G58,I58) -> 5329
A59: T10 | B59: Vamsidhar Bethanabatla / Madhuri Anumula | C59: 5281 | D59: 45863 | K59: =SUM(C59,E59,G59,I59) -> 5281
A60: T11 | B60: Arvind Balasubramanian | C60: 4585 | D60: 45855 | K60: =SUM(C60,E60,G60,I60) -> 4585
A61: T12 | B61: Prasenjit | C61: 4410.4 | D61: 45859 | K61: =SUM(C61,E61,G61,I61) -> 4410.4
A62: T13 | B62: Rahul Kumar | C62: 12000 | D62: 45863 | K62: =SUM(C62,E62,G62,I62) -> 12000
A63: T14 | B63: Jeya / Kanda / Satya (tenant)/Vinuta (tenant) | C63: 4875 | D63: 45859 | K63: =SUM(C63,E63,G63,I63) -> 4875
A64: T15 | B64: Trevor | C64: 5152 | D64: 45863 | K64: =SUM(C64,E64,G64,I64) -> 5152
A65: T16 | B65: Madhusoodanan P.R. | C65: 4962 | D65: 45857 | K65: =SUM(C65,E65,G65,I65) -> 4962
A66: TOTAL | K66: =SUM(K2:K65) -> 263304.59

Sheet Aug2025-EXPENSE
B1: AUG 2025 EXPENSES
A2: FLAT # | B2: 1 | C2: WATER USED IN LTRS | D2: COMMON AREA EQUALLY DEVIDED | E2: TOTAL FRESH WATER CONSUMED | F2: %OF TOTAL USED | G2: WATER EXPENSE SHARING BY % | H2: #METERS | I2: METER RENT | J2: COMMON AREA METER RENT + WATER EXPENSE+ FLAT METER RENT | K2: FIXED EXPENSE SHARE | L2: PARKING FEE | M2: CLUB HOUSE BOOKING | N2: SHIFTING FEE | O2: GYM USAGE FEE | R2: TOTAL EXPENSE TO BE PAID
A3: CH | B3: MPFOWA | D3: 0 | H3: 1 | I3: =T7 -> 117.81166
A4: GYM | B4: MPFOWA | D4: 0 | H4: 1 | I4: =T7 -> 117.81166 | S4: TOTAL FIXED EXPENSE | T4: ='ANNUAL-EXPENSE-DETAILS'!BF7 -> 334269
A5: BSMT | B5: MPFOWA | D5: 0 | H5: 1 | I5: =T7 -> 117.81166 | S5: TOTAL WATER EXPENSE | T5: ='ANNUAL-EXPENSE-DETAILS'!BE7 -> 38700
A6: F1 | B6: Shailesh Srivastava / Azeem Nawaz | C6: 3717.5 | D6: =SUM($C$3:$C$5)/64 -> 0 | E6: =C6+D6 -> 3717.5 | F6: =IF($C$70=0, 0, E6/$C$70) -> 0.0085438754 | G6: =F6*$T$5 -> 330.64798 | H6: 3 | I6: =$T$7*H6 -> 353.43498 | J6: =G6+$T$9+I6 -> 689.60538 | K6: =$T$11/64 -> 5222.9531 | L6: 0 | M6: 0 | N6: 0 | O6: 0 | R6: =(J6+K6+L6+M6+N6+O6)*$B$2 -> 5912.5585
A7: F2 | B7: Shanthanu | C7: 16837 | D7: =SUM($C$3:$C$5)/64 -> 0 | E7: =C7+D7 -> 16837 | F7: =IF($C$70=0, 0, E7/$C$70) -> 0.038696229 | G7: =F7*$T$5 -> 1497.5441 | H7: 4 | I7: =$T$7*H7 -> 471.24664 | J7: =G7+$T$9+I7 -> 1974.3131 | K7: =$T$11/64 -> 5222.9531 | L7: 0 | M7: 0 | N7: 0 | O7: 0 | R7: =(J7+K7+L7+M7+N7+O7)*$B$2 -> 7197.2662 | S7: RENT PER METER | T7: 117.81166
A8: F3 | B8: Samrat Kar | C8: 14312.5 | D8: =SUM($C$3:$C$5)/64 -> 0 | E8: =C8+D8 -> 14312.5 | F8: =IF($C$70=0, 0, E8/$C$70) -> 0.032894208 | G8: =F8*$T$5 -> 1273.0058 | H8: 4 | I8: =$T$7*H8 -> 471.24664 | J8: =G8+$T$9+I8 -> 1749.7749 | K8: =$T$11/64 -> 5222.9531 | L8: 750 | M8: 0 | N8: 0 | O8: 0 | R8: =(J8+K8+L8+M8+N8+O8)*$B$2 -> 7722.728 | S8: COMMON AREA METER RENT | T8: =$T$7*3 -> 353.43498
A9: F4 | B9: Renu R | C9: 3938 | D9: =SUM($C$3:$C$5)/64 -> 0 | E9: =C9+D9 -> 3938 | F9: =IF($C$70=0, 0, E9/$C$70) -> 0.0090506473 | G9: =F9*$T$5 -> 350.26005 | H9: 4 | I9: =$T$7*H9 -> 471.24664 | J9: =G9+$T$9+I9 -> 827.02911 | K9: =$T$11/64 -> 5222.9531 | L9: 0 | M9: 0 | N9: 0 | O9: 0 | R9: =(J9+K9+L9+M9+N9+O9)*$B$2 -> 6049.9822 | S9: COMMON AREA METER RENT/FLAT | T9: =T8/64 -> 5.5224215
A10: F5 | B10: Vamsidhar Bethanabatla / Madhuri Anumula | C10: 5258 | D10: =SUM($C$3:$C$5)/64 -> 0 | E10: =C10+D10 -> 5258 | F10: =IF($C$70=0, 0, E10/$C$70) -> 0.012084384 | G10: =F10*$T$5 -> 467.66565 | H10: 3 | I10: =$T$7*H10 -> 353.43498 | J10: =G10+$T$9+I10 -> 826.62305 | K10: =$T$11/64 -> 5222.9531 | L10: 0 | M10: 0 | N10: 1000 | O10: 0 | R10: =(J10+K10+L10+M10+N10+O10)*$B$2 -> 7049.5762
A11: F6 | B11: Meghana Viral Shah and Vviral Shah (Owner) / Sangeet and Swagat (Tenent) | C11: 5707.5 | D11: =SUM($C$3:$C$5)/64 -> 0 | E11: =C11+D11 -> 5707.5 | F11: =IF($C$70=0, 0, E11/$C$70) -> 0.013117463 | G11: =F11*$T$5 -> 507.64582 | H11: 3 | I11: =$T$7*H11 -> 353.43498 | J11: =G11+$T$9+I11 -> 866.60322 | K11: =$T$11/64 -> 5222.9531 | L11: 0 | M11: 0 | N11: 0 | O11: 0 | R11: =(J11+K11+L11+M11+N11+O11)*$B$2 -> 6089.5563 | S11: TOTAL FIXED EXPENSE | T11: ='ANNUAL-EXPENSE-DETAILS'!BF7 -> 334269
A12: F7 | B12: Vimal NK | C12: 0 | D12: =SUM($C$3:$C$5)/64 -> 0 | E12: =C12+D12 -> 0 | F12: =IF($C$70=0, 0, E12/$C$70) -> 0 | G12: =F12*$T$5 -> 0 | H12: 3 | I12: =$T$7*H12 -> 353.43498 | J12: =G12+$T$9+I12 -> 358.9574 | K12: =$T$11/64 -> 5222.9531 | L12: 750 | M12: 0 | N12: 0 | O12: 0 | R12: =(J12+K12+L12+M12+N12+O12)*$B$2 -> 6331.9105
A13: F8 | B13: Sujeet Kumar (Tenant)/Sreejith Menon (Owner) | C13: 297.5 | D13: =SUM($C$3:$C$5)/64 -> 0 | E13: =C13+D13 -> 297.5 | F13: =IF($C$70=0, 0, E13/$C$70) -> 0.00068373986 | G13: =F13*$T$5 -> 26.460733 | H13: 3 | I13: =$T$7*H13 -> 353.43498 | J13: =G13+$T$9+I13 -> 385.41813 | K13: =$T$11/64 -> 5222.9531 | L13: 0 | M13: 0 | N13: 0 | O13: 0 | R13: =(J13+K13+L13+M13+N13+O13)*$B$2 -> 5608.3713 | S13: BALANCE IN ACCOUNT ON 31-AUG-2022
A14: F9 | B14: Vijay Suswaram (Owner) / Divya Shikha (Tenant) | C14: 2745.5 | D14: =SUM($C$3:$C$5)/64 -> 0 | E14: =C14+D14 -> 2745.5 | F14: =IF($C$70=0, 0, E14/$C$70) -> 0.0063099422 | G14: =F14*$T$5 -> 244.19476 | H14: 4 | I14: =$T$7*H14 -> 471.24664 | J14: =G14+$T$9+I14 -> 720.96382 | K14: =$T$11/64 -> 5222.9531 | L14: 0 | M14: 0 | N14: 0 | O14: 0 | R14: =(J14+K14+L14+M14+N14+O14)*$B$2 -> 5943.9169 | S14: TOTAL NON MAINTENANCE CORPUS COLLECTION
A15: F10 | B15: Aby Thomas | C15: 2382.5 | D15: =SUM($C$3:$C$5)/64 -> 0 | E15: =C15+D15 -> 2382.5 | F15: =IF($C$70=0, 0, E15/$C$70) -> 0.0054756646 | G15: =F15*$T$5 -> 211.90822 | H15: 3 | I15: =$T$7*H15 -> 353.43498 | J15: =G15+$T$9+I15 -> 570.86562 | K15: =$T$11/64 -> 5222.9531 | L15: 0 | M15: 0 | N15: 0 | O15: 0 | R15: =(J15+K15+L15+M15+N15+O15)*$B$2 -> 5793.8187 | S15: TOTAL FD DONE
A16: F11 | B16: Niwin Anto | C16: 1398.5 | D16: =SUM($C$3:$C$5)/64 -> 0 | E16: =C16+D16 -> 1398.5 | F16: =IF($C$70=0, 0, E16/$C$70) -> 0.0032141519 | G16: =F16*$T$5 -> 124.38768 | H16: 3 | I16: =$T$7*H16 -> 353.43498 | J16: =G16+$T$9+I16 -> 483.34508 | K16: =$T$11/64 -> 5222.9531 | L16: 0 | M16: 0 | N16: 0 | O16: 0 | R16: =(J16+K16+L16+M16+N16+O16)*$B$2 -> 5706.2982 | S16: AMOUNT AVAILABLE FOR NON MAINTENANCE CORPUS IN CURRENT AC | T16: =T14-T15 -> 0
A17: F12 | B17: Anirudh Singh | C17: 68.5 | D17: =SUM($C$3:$C$5)/64 -> 0 | E17: =C17+D17 -> 68.5 | F17: =IF($C$70=0, 0, E17/$C$70) -> 0.00015743254 | G17: =F17*$T$5 -> 6.0926393 | H17: 3 | I17: =$T$7*H17 -> 353.43498 | J17: =G17+$T$9+I17 -> 365.05004 | K17: =$T$11/64 -> 5222.9531 | L17: 0 | M17: 0 | N17: 0 | O17: 0 | R17: =(J17+K17+L17+M17+N17+O17)*$B$2 -> 5588.0032 | S17: AMOUNT AVAILABLE FOR MAINTENANCE | T17: =T13-T16 -> 0
A18: F13 | B18: Sanchay Saxena | C18: 6218 | D18: =SUM($C$3:$C$5)/64 -> 0 | E18: =C18+D18 -> 6218 | F18: =IF($C$70=0, 0, E18/$C$70) -> 0.014290738 | G18: =F18*$T$5 -> 553.05155 | H18: 4 | I18: =$T$7*H18 -> 471.24664 | J18: =G18+$T$9+I18 -> 1029.8206 | K18: =$T$11/64 -> 5222.9531 | L18: 0 | M18: 0 | N18: 0 | O18: 0 | R18: =(J18+K18+L18+M18+N18+O18)*$B$2 -> 6252.7737
A19: F14 | B19: Hemant Patel | C19: 2055.5 | D19: =SUM($C$3:$C$5)/64 -> 0 | E19: =C19+D19 -> 2055.5 | F19: =IF($C$70=0, 0, E19/$C$70) -> 0.0047241253 | G19: =F19*$T$5 -> 182.82365 | H19: 4 | I19: =$T$7*H19 -> 471.24664 | J19: =G19+$T$9+I19 -> 659.59271 | K19: =$T$11/64 -> 5222.9531 | L19: 0 | M19: 0 | N19: 0 | O19: 0 | R19: =(J19+K19+L19+M19+N19+O19)*$B$2 -> 5882.5458
A20: F15 | B20: Senthil.Vijayaragavan | C20: 4765 | D20: =SUM($C$3:$C$5)/64 -> 0 | E20: =C20+D20 -> 4765 | F20: =IF($C$70=0, 0, E20/$C$70) -> 0.010951329 | G20: =F20*$T$5 -> 423.81644 | H20: 4 | I20: =$T$7*H20 -> 471.24664 | J20: =G20+$T$9+I20 -> 900.5855 | K20: =$T$11/64 -> 5222.9531 | L20: 750 | M20: 0 | N20: 0 | O20: 0 | R20: =(J20+K20+L20+M20+N20+O20)*$B$2 -> 6873.5386 | S20: TOTAL WATER METER RENT (INR) | T20: =I70 -> 26272
A21: F16 | B21: Sreeja Sudharma | C21: 17561 | D21: =SUM($C$3:$C$5)/64 -> 0 | E21: =C21+D21 -> 17561 | F21: =IF($C$70=0, 0, E21/$C$70) -> 0.040360187 | G21: =F21*$T$5 -> 1561.9392 | H21: 3 | I21: =$T$7*H21 -> 353.43498 | J21: =G21+$T$9+I21 -> 1920.8966 | K21: =$T$11/64 -> 5222.9531 | L21: 0 | M21: 0 | N21: 0 | O21: 0 | R21: =(J21+K21+L21+M21+N21+O21)*$B$2 -> 7143.8498
A22: G1 | B22: Venkataramanan C | C22: 10698.5 | D22: =SUM($C$3:$C$5)/64 -> 0 | E22: =C22+D22 -> 10698.5 | F22: =IF($C$70=0, 0, E22/$C$70) -> 0.024588205 | G22: =F22*$T$5 -> 951.56352 | H22: 3 | I22: =$T$7*H22 -> 353.43498 | J22: =G22+$T$9+I22 -> 1310.5209 | K22: =$T$11/64 -> 5222.9531 | L22: 0 | M22: 0 | N22: 0 | O22: 0 | R22: =(J22+K22+L22+M22+N22+O22)*$B$2 -> 6533.474
A23: G2 | B23: Kaushik Kasibhatla | C23: 12066 | D23: =SUM($C$3:$C$5)/64 -> 0 | E23: =C23+D23 -> 12066 | F23: =IF($C$70=0, 0, E23/$C$70) -> 0.02773111 | G23: =F23*$T$5 -> 1073.1939 | H23: 4 | I23: =$T$7*H23 -> 471.24664 | J23: =G23+$T$9+I23 -> 1549.963 | K23: =$T$11/64 -> 5222.9531 | L23: 0 | M23: 0 | N23: 0 | O23: 0 | R23: =(J23+K23+L23+M23+N23+O23)*$B$2 -> 6772.9161
A24: G3 | B24: Balakrishnan | C24: 12020.5 | D24: =SUM($C$3:$C$5)/64 -> 0 | E24: =C24+D24 -> 12020.5 | F24: =IF($C$70=0, 0, E24/$C$70) -> 0.027626538 | G24: =F24*$T$5 -> 1069.147 | H24: 4 | I24: =$T$7*H24 -> 471.24664 | J24: =G24+$T$9+I24 -> 1545.9161 | K24: =$T$11/64 -> 5222.9531 | L24: 0 | M24: 0 | N24: 0 | O24: 0 | R24: =(J24+K24+L24+M24+N24+O24)*$B$2 -> 6768.8692
A25: G4 | B25: Ashwin Pandith | C25: 19087 | D25: =SUM($C$3:$C$5)/64 -> 0 | E25: =C25+D25 -> 19087 | F25: =IF($C$70=0, 0, E25/$C$70) -> 0.043867371 | G25: =F25*$T$5 -> 1697.6672 | H25: 4 | I25: =$T$7*H25 -> 471.24664 | J25: =G25+$T$9+I25 -> 2174.4363 | K25: =$T$11/64 -> 5222.9531 | L25: 0 | M25: 0 | N25: 0 | O25: 0 | R25: =(J25+K25+L25+M25+N25+O25)*$B$2 -> 7397.3894
A26: G5 | B26: Mayank Phophaliya | C26: 3277.5 | D26: =SUM($C$3:$C$5)/64 -> 0 | E26: =C26+D26 -> 3277.5 | F26: =IF($C$70=0, 0, E26/$C$70) -> 0.0075326299 | G26: =F26*$T$5 -> 291.51278 | H26: 3 | I26: =$T$7*H26 -> 353.43498 | J26: =G26+$T$9+I26 -> 650.47018 | K26: =$T$11/64 -> 5222.9531 | L26: 0 | M26: 0 | N26: 0 | O26: 0 | R26: =(J26+K26+L26+M26+N26+O26)*$B$2 -> 5873.4233
A27: G6 | B27: Mohit Daga | C27: 5923 | D27: =SUM($C$3:$C$5)/64 -> 0 | E27: =C27+D27 -> 5923 | F27: =IF($C$70=0, 0, E27/$C$70) -> 0.013612744 | G27: =F27*$T$5 -> 526.81317 | H27: 3 | I27: =$T$7*H27 -> 353.43498 | J27: =G27+$T$9+I27 -> 885.77057 | K27: =$T$11/64 -> 5222.9531 | L27: 0 | M27: 0 | N27: 0 | O27: 0 | R27: =(J27+K27+L27+M27+N27+O27)*$B$2 -> 6108.7237
A28: G7 | B28: Prince Richfield | C28: 5862.5 | D28: =SUM($C$3:$C$5)/64 -> 0 | E28: =C28+D28 -> 5862.5 | F28: =IF($C$70=0, 0, E28/$C$70) -> 0.013473697 | G28: =F28*$T$5 -> 521.43208 | H28: 3 | I28: =$T$7*H28 -> 353.43498 | J28: =G28+$T$9+I28 -> 880.38948 | K28: =$T$11/64 -> 5222.9531 | L28: 0 | M28: 0 | N28: 0 | O28: 0 | R28: =(J28+K28+L28+M28+N28+O28)*$B$2 -> 6103.3426
A29: G8 | B29: Ranjithkumar R / Sameer (tenant) / Princy (tenant) | C29: 10571 | D29: =SUM($C$3:$C$5)/64 -> 0 | E29: =C29+D29 -> 10571 | F29: =IF($C$70=0, 0, E29/$C$70) -> 0.024295173 | G29: =F29*$T$5 -> 940.22321 | H29: 3 | I29: =$T$7*H29 -> 353.43498 | J29: =G29+$T$9+I29 -> 1299.1806 | K29: =$T$11/64 -> 5222.9531 | L29: 0 | M29: 0 | N29: 0 | O29: 0 | R29: =(J29+K29+L29+M29+N29+O29)*$B$2 -> 6522.1337
A30: G9 | B30: Chandramouli | C30: 5252 | D30: =SUM($C$3:$C$5)/64 -> 0 | E30: =C30+D30 -> 5252 | F30: =IF($C$70=0, 0, E30/$C$70) -> 0.012070594 | G30: =F30*$T$5 -> 467.13199 | H30: 5 | I30: =$T$7*H30 -> 589.0583 | J30: =G30+$T$9+I30 -> 1061.7127 | K30: =$T$11/64 -> 5222.9531 | L30: 0 | M30: 0 | N30: 0 | O30: 0 | R30: =(J30+K30+L30+M30+N30+O30)*$B$2 -> 6284.6658
A31: G10 | B31: Cijo Jacob / Thara Joy | C31: 8899 | D31: =SUM($C$3:$C$5)/64 -> 0 | E31: =C31+D31 -> 8899 | F31: =IF($C$70=0, 0, E31/$C$70) -> 0.02045244 | G31: =F31*$T$5 -> 791.50944 | H31: 3 | I31: =$T$7*H31 -> 353.43498 | J31: =G31+$T$9+I31 -> 1150.4668 | K31: =$T$11/64 -> 5222.9531 | L31: 0 | M31: 0 | N31: 0 | O31: 0 | R31: =(J31+K31+L31+M31+N31+O31)*$B$2 -> 6373.42
A32: G11 | B32: Ketan Verlekar | C32: 1973 | D32: =SUM($C$3:$C$5)/64 -> 0 | E32: =C32+D32 -> 1973 | F32: =IF($C$70=0, 0, E32/$C$70) -> 0.0045345168 | G32: =F32*$T$5 -> 175.4858 | H32: 3 | I32: =$T$7*H32 -> 353.43498 | J32: =G32+$T$9+I32 -> 534.4432 | K32: =$T$11/64 -> 5222.9531 | L32: 0 | M32: 0 | N32: 0 | O32: 0 | R32: =(J32+K32+L32+M32+N32+O32)*$B$2 -> 5757.3963
... A69: T16 | B69: Madhusoodanan P.R. | C69: 7140.5 | D69: =SUM($C$3:$C$5)/64 -> 0 | E69: =C69+D69 -> 7140.5 | F69: =IF($C$70=0, 0, E69/$C$70) -> 0.016410906 | G69: =F69*$T$5 -> 635.10206 | H69: 3 | I69: =$T$7*H69 -> 353.43498 | J69: =G69+$T$9+I69 -> 994.05945 | K69: =$T$11/64 -> 5222.9531 | L69: 0 | M69: 0 | N69: 0 | O69: 0 | R69: =(J69+K69+L69+M69+N69+O69)*$B$2 -> 6217.0126
B70: TOTAL | C70: =SUM(C3:C69) -> 435107 | D70: =SUM(D3:D69) -> 0 | E70: =SUM(E3:E69) -> 435107 | F70: =IF($C$70=0, 0, E70/$C$70) -> 1 | G70: =SUM(G3:G69) -> 38700 | H70: =SUM(H3:H69) -> 223 | I70: =SUM(I3:I69) -> 26272 | J70: =SUM(J3:J69) -> 64972 | K70: =SUM(K3:K69) -> 334269 | L70: =SUM(L3:L69) -> 3000 | M70: =SUM(M3:M69) -> 1000 | N70: =SUM(N3:N69) -> 1000 | O70: =SUM(O3:O69) -> 0 | R70: =SUM(R3:R69) -> 404241

Sheet Aug2025-COLLECTION
A1: FLAT # | C1: Amount | D1: Date | E1: Amount | F1: Date | G1: Amount | H1: Date | I1: Amount | J1: Date | K1: Total
A2: F1 | B2: Shailesh Srivastava / Azeem Nawaz | C2: 5497 | D2: 45893 | K2: =SUM(C2,E2,G2,I2) -> 5497
A3: F2 | B3: Shanthanu | K3: =SUM(C3,E3,G3,I3) -> 0
A4: F3 | B4: Samrat Kar | C4: 6000 | D4: 45870 | K4: =SUM(C4,E4,G4,I4) -> 6000
A5: F4 | B5: Renu R | C5: 5554 | D5: 45879 | K5: =SUM(C5,E5,G5,I5) -> 5554
A6: F5 | B6: Vamsidhar Bethanabatla / Madhuri Anumula | C6: 5172 | D6: 45894 | K6: =SUM(C6,E6,G6,I6) -> 5172
A7: F6 | B7: Meghana Viral Shah and Vviral Shah (Owner) / Sangeet and Swagat (Tenent) | C7: 5465 | D7: 45893 | K7: =SUM(C7,E7,G7,I7) -> 5465
A8: F7 | B8: Vimal NK | C8: 5938.62 | D8: 45894 | K8: =SUM(C8,E8,G8,I8) -> 5938.62
A9: F8 | B9: Sujeet Kumar (Tenant)/Sreejith Menon (Owner) | C9: 5121 | D9: 45876 | K9: =SUM(C9,E9,G9,I9) -> 5121
A10: F9 | B10: Vijay Suswaram (Owner) / Divya Shikha (Tenant) | C10: 5434 | D10: 45892 | K10: =SUM(C10,E10,G10,I10) -> 5434
A11: F10 | B11: Aby Thomas | C11: 1057 | D11: 45884 | K11: =SUM(C11,E11,G11,I11) -> 1057
A12: F11 | B12: N. Geetha | C12: 5218 | D12: 45880 | K12: =SUM(C12,E12,G12,I12) -> 5218
A13: F12 | B13: Debashis Ghoshal / Manisha Ghoshal | C13: 5108 | D13: 45877 | K13: =SUM(C13,E13,G13,I13) -> 5108
A14: F13 | B14: Sanchay Saxena | K14: =SUM(C14,E14,G14,I14) -> 0
A15: F14 | B15: Hemant Patel | C15: 5439 | D15: 45879 | K15: =SUM(C15,E15,G15,I15) -> 5439
A16: F15 | B16: Senthil.Vijayaragavan | C16: 6487 | D16: 45889 | K16: =SUM(C16,E16,G16,I16) -> 6487
A17: F16 | B17: Sreeja Sudharma | K17: =SUM(C17,E17,G17,I17) -> 0
A18: G1 | B18: Venkataramanan C | C18: 6042 | D18: 45879 | K18: =SUM(C18,E18,G18,I18) -> 6042
A19: G2 | B19: Kaushik Kasibhatla | C19: 6478 | D19: 45884 | K19: =SUM(C19,E19,G19,I19) -> 6478
A20: G3 | B20: Balakrishnan | C20: 6558 | D20: 45894 | K20: =SUM(C20,E20,G20,I20) -> 6558
A21: G4 | B21: Ashwin Pandith | C21: 7082 | D21: 45883 | K21: =SUM(C21,E21,G21,I21) -> 7082
A22: G5 | B22: Mayank Phophaliya | K22: =SUM(C22,E22,G22,I22) -> 0
A23: G6 | B23: Mohit Daga | K23: =SUM(C23,E23,G23,I23) -> 0
A24: G7 | B24: Prince Richfield | K24: =SUM(C24,E24,G24,I24) -> 0
A25: G8 | B25: Ranjithkumar R / Sameer (tenant) / Princy (tenant) | K25: =SUM(C25,E25,G25,I25) -> 0
A26: G9 | B26: Ankur Agarwal | C26: 5869 | D26: 45876 | K26: =SUM(C26,E26,G26,I26) -> 5869
A27: G10 | B27: Cijo Jacob / Thara Joy | C27: 6008 | D27: 45884 | K27: =SUM(C27,E27,G27,I27) -> 6008
A28: G11 | B28: Ketan Verlekar | C28: 5377 | D28: 45884 | K28: =SUM(C28,E28,G28,I28) -> 5377
A29: G12 | B29: Shyam Nair | C29: 6120 | D29: 45894 | K29: =SUM(C29,E29,G29,I29) -> 6120
A30: G13 | B30: Ajai.B | K30: =SUM(C30,E30,G30,I30) -> 0
A31: G14 | B31: Surajit Borah | C31: 5790 | D31: 45891 | K31: =SUM(C31,E31,G31,I31) -> 5790
A32: G15 | B32: Suresh Nallusamy / Antriksh (tenant) | C32: 5226 | D32: 45877 | K32: =SUM(C32,E32,G32,I32) -> 5226
A33: G16 | B33: Praveen Ganesan | C33: 5297.38 | D33: 45878 | K33: =SUM(C33,E33,G33,I33) -> 5297.38
A34: S1 | B34: S.N.Behera | C34: 5177 | D34: 45878 | K34: =SUM(C34,E34,G34,I34) -> 5177
A35: S2 | B35: Sonal Singh | C35: 15859 | D35: 45885 | K35: =SUM(C35,E35,G35,I35) -> 15859
A36: S3 | B36: Koteswararao | C36: 5457 | D36: 45884 | K36: =SUM(C36,E36,G36,I36) -> 5457
A37: S4 | B37: Swaminathan | C37: 5290 | D37: 45891 | K37: =SUM(C37,E37,G37,I37) -> 5290
A38: S5 | B38: Abhishek Gopalakrishnan | C38: 5000 | D38: 45870 | K38: =SUM(C38,E38,G38,I38) -> 5000
A39: S6 | B39: Vivek Dhingra / Pratyush Das | K39: =SUM(C39,E39,G39,I39) -> 0
A40: S7 | B40: Harish B | C40: 5168 | D40: 45894 | K40: =SUM(C40,E40,G40,I40) -> 5168
A41: S8 | B41: Irudayaraj Alwin | C41: 6830.03 | D41: 45895 | K41: =SUM(C41,E41,G41,I41) -> 6830.03
A42: S9 | B42: Pawan GS | C42: 5500 | D42: 45884 | K42: =SUM(C42,E42,G42,I42) -> 5500
A43: S10 | B43: Lakshmikanth | K43: =SUM(C43,E43,G43,I43) -> 0
A44: S11 | B44: Gowrish Patnaik / Somananth GM | C44: 5000 | D44: 45895 | K44: =SUM(C44,E44,G44,I44) -> 5000
A45: S12 | B45: Saovik Mondal | C45: 5905 | D45: 45892 | K45: =SUM(C45,E45,G45,I45) -> 5905
A46: S13 | B46: Ramadevi S. | K46: =SUM(C46,E46,G46,I46) -> 0
A47: S14 | B47: Nishant Upadhyay(Owner)/ Fabian (Tenant) | C47: 10000 | D47: 45878 | K47: =SUM(C47,E47,G47,I47) -> 10000
A48: S15 | B48: Manas Dasgupta | C48: 6502 | D48: 45897 | K48: =SUM(C48,E48,G48,I48) -> 6502
A49: S16 | B49: Devendra Singh Rawat / Nancy | C49: 5525 | D49: 45884 | K49: =SUM(C49,E49,G49,I49) -> 5525
A50: T1 | B50: Prashant Sikdar | C50: 6420 | D50: 45889 | K50: =SUM(C50,E50,G50,I50) -> 6420
A51: T2 | B51: Kunal Mehta | C51: 18827 | D51: 45885 | K51: =SUM(C51,E51,G51,I51) -> 18827
A52: T3 | B52: Kapil Garg | C52: 6114.88 | D52: 45879 | K52: =SUM(C52,E52,G52,I52) -> 6114.88
A53: T4 | B53: Vijet Alva (Owner) - Masood (Tenant) | C53: 4926 | D53: 45872 | E53: 6261 | F53: 45899 | K53: =SUM(C53,E53,G53,I53) -> 11187
A54: T5 | B54: Ganesh Iyer and Latha Iyer( owner) Richa (Tenant) | C54: 4459 | D54: 45872 | K54: =SUM(C54,E54,G54,I54) -> 4459
A55: T6 | B55: Mythili Ramesh | C55: 5522 | D55: 45872 | E55: 6296 | F55: 45882 | K55: =SUM(C55,E55,G55,I55) -> 11818
A56: T7 | B56: Vinyas Ramachandra / Shwetha Marnamikatta / Katari Siva Rama Raju | C56: 1794 | D56: 45879 | K56: =SUM(C56,E56,G56,I56) -> 1794
A57: T8 | B57: Lalit Kumar Sharma | C57: 5200 | D57: 45896 | K57: =SUM(C57,E57,G57,I57) -> 5200
A58: T9 | B58: Nishith Sahu and Priyanka Rani (Owner)/ Anmol Verma (Tenant) | C58: 5840 | D58: 45876 | K58: =SUM(C58,E58,G58,I58) -> 5840
A59: T10 | B59: Vamsidhar Bethanabatla / Madhuri Anumula | C59: 5886 | D59: 45894 | K59: =SUM(C59,E59,G59,I59) -> 5886
A60: T11 | B60: Arvind Balasubramanian | C60: 5351 | D60: 45876 | K60: =SUM(C60,E60,G60,I60) -> 5351
A61: T12 | B61: Prasenjit | C61: 5218.7 | D61: 45889 | K61: =SUM(C61,E61,G61,I61) -> 5218.7
A62: T13 | B62: Rahul Kumar | K62: =SUM(C62,E62,G62,I62) -> 0
A63: T14 | B63: Jeya / Kanda / Satya (tenant)/Vinuta (tenant) | C63: 5514 | D63: 45897 | K63: =SUM(C63,E63,G63,I63) -> 5514
A64: T15 | B64: Trevor | C64: 6161 | D64: 45894 | K64: =SUM(C64,E64,G64,I64) -> 6161
A65: T16 | B65: Madhusoodanan P.R. | C65: 5875 | D65: 45892 | K65: =SUM(C65,E65,G65,I65) -> 5875
A66: TOTAL | K66: =SUM(K2:K65) -> 326216.61

Sheet Sep2025-EXPENSE
B1: SEPTEMBER 2025 EXPENSES
A2: FLAT # | B2: 1 | C2: WATER USED IN LTRS | D2: COMMON AREA EQUALLY DEVIDED | E2: TOTAL FRESH WATER CONSUMED | F2: %OF TOTAL USED | G2: WATER EXPENSE SHARING BY % | H2: #METERS | I2: METER RENT (INR) | J2: COMMON AREA METER RENT + WATER EXPENSE+ FLAT METER RENT | K2: FIXED EXPENSE SHARE | L2: PARKING FEE | M2: CLUB HOUSE BOOKING | N2: SHIFTING FEE | O2: GYM USAGE FEE | R2: TOTAL EXPENSE TO BE PAID
A3: CH | B3: MPFOWA | C3: 0 | D3: 0 | H3: 1 | I3: =T7 -> 117.81166
A4: GYM | B4: MPFOWA | C4: 0 | D4: 0 | H4: 1 | I4: =T7 -> 117.81166 | S4: TOTAL FIXED EXPENSE | T4: ='ANNUAL-EXPENSE-DETAILS'!BF8 -> 280426
A5: BSMT | B5: MPFOWA | C5: 0 | D5: 0 | H5: 1 | I5: =T7 -> 117.81166 | S5: TOTAL WATER EXPENSE | T5: ='ANNUAL-EXPENSE-DETAILS'!BE8 -> 30200
A6: F1 | B6: Shailesh Srivastava / Azeem Nawaz | C6: 2529.5 | D6: =SUM($C$3:$C$5)/64 -> 0 | E6: =C6+D6 -> 2529.5 | F6: =IF($C$70=0, 0, E6/$C$70) -> 0.0066001563 | G6: =F6*$T$5 -> 199.32472 | H6: 3 | I6: =$T$7*H6 -> 353.43498 | J6: =G6+$T$9+I6 -> 558.28212 | K6: =$T$11/64 -> 4381.6562 | L6: 0 | M6: 0 | N6: 0 | O6: 0 | R6: =(J6+K6+L6+M6+N6+O6)*$B$2 -> 4939.9384
A7: F2 | B7: Shanthanu | C7: 13404.5 | D7: =SUM($C$3:$C$5)/64 -> 0 | E7: =C7+D7 -> 13404.5 | F7: =IF($C$70=0, 0, E7/$C$70) -> 0.034976001 | G7: =F7*$T$5 -> 1056.2752 | H7: 4 | I7: =$T$7*H7 -> 471.24664 | J7: =G7+$T$9+I7 -> 1533.0443 | K7: =$T$11/64 -> 4381.6562 | L7: 0 | M7: 0 | N7: 0 | O7: 0 | R7: =(J7+K7+L7+M7+N7+O7)*$B$2 -> 5914.7005 | S7: RENT PER METER | T7: 117.81166
A8: F3 | B8: Samrat Kar | C8: 12579.5 | D8: =SUM($C$3:$C$5)/64 -> 0 | E8: =C8+D8 -> 12579.5 | F8: =IF($C$70=0, 0, E8/$C$70) -> 0.032823351 | G8: =F8*$T$5 -> 991.2652 | H8: 4 | I8: =$T$7*H8 -> 471.24664 | J8: =G8+$T$9+I8 -> 1468.0343 | K8: =$T$11/64 -> 4381.6562 | L8: 750 | M8: 0 | N8: 0 | O8: 0 | R8: =(J8+K8+L8+M8+N8+O8)*$B$2 -> 6599.6905 | S8: COMMON AREA METER RENT (INR) | T8: =$T$7*3 -> 353.43498
A9: F4 | B9: Renu R | C9: 3669.5 | D9: =SUM($C$3:$C$5)/64 -> 0 | E9: =C9+D9 -> 3669.5 | F9: =IF($C$70=0, 0, E9/$C$70) -> 0.0095747276 | G9: =F9*$T$5 -> 289.15677 | H9: 4 | I9: =$T$7*H9 -> 471.24664 | J9: =G9+$T$9+I9 -> 765.92583 | K9: =$T$11/64 -> 4381.6562 | L9: 0 | M9: 0 | N9: 0 | O9: 0 | R9: =(J9+K9+L9+M9+N9+O9)*$B$2 -> 5147.5821 | S9: COMMON AREA METER RENT/FLAT | T9: =T8/64 -> 5.5224215
A10: F5 | B10: Vamsidhar Bethanabatla / Madhuri Anumula | C10: 5956.5 | D10: =SUM($C$3:$C$5)/64 -> 0 | E10: =C10+D10 -> 5956.5 | F10: =IF($C$70=0, 0, E10/$C$70) -> 0.015542135 | G10: =F10*$T$5 -> 469.37248 | H10: 3 | I10: =$T$7*H10 -> 353.43498 | J10: =G10+$T$9+I10 -> 828.32988 | K10: =$T$11/64 -> 4381.6562 | L10: 0 | M10: 0 | N10: 0 | O10: 0 | R10: =(J10+K10+L10+M10+N10+O10)*$B$2 -> 5209.9861
A11: F6 | B11: Meghana Viral Shah and Vviral Shah (Owner) / Sangeet and Swagat (Tenent) | C11: 5003 | D11: =SUM($C$3:$C$5)/64 -> 0 | E11: =C11+D11 -> 5003 | F11: =IF($C$70=0, 0, E11/$C$70) -> 0.013054193 | G11: =F11*$T$5 -> 394.23664 | H11: 3 | I11: =$T$7*H11 -> 353.43498 | J11: =G11+$T$9+I11 -> 753.19404 | K11: =$T$11/64 -> 4381.6562 | L11: 0 | M11: 0 | N11: 0 | O11: 0 | R11: =(J11+K11+L11+M11+N11+O11)*$B$2 -> 5134.8503 | S11: TOTAL FIXED EXPENSE | T11: ='ANNUAL-EXPENSE-DETAILS'!BF8 -> 280426
A12: F7 | B12: Vimal NK | C12: 180.5 | D12: =SUM($C$3:$C$5)/64 -> 0 | E12: =C12+D12 -> 180.5 | F12: =IF($C$70=0, 0, E12/$C$70) -> 0.00047097379 | G12: =F12*$T$5 -> 14.223409 | H12: 3 | I12: =$T$7*H12 -> 353.43498 | J12: =G12+$T$9+I12 -> 373.18081 | K12: =$T$11/64 -> 4381.6562 | L12: 750 | M12: 0 | N12: 0 | O12: 0 | R12: =(J12+K12+L12+M12+N12+O12)*$B$2 -> 5504.8371
A13: F8 | B13: Sujeet Kumar (Tenant)/Sreejith Menon (Owner) | C13: 361.5 | D13: =SUM($C$3:$C$5)/64 -> 0 | E13: =C13+D13 -> 361.5 | F13: =IF($C$70=0, 0, E13/$C$70) -> 0.00094325222 | G13: =F13*$T$5 -> 28.486217 | H13: 3 | I13: =$T$7*H13 -> 353.43498 | J13: =G13+$T$9+I13 -> 387.44362 | K13: =$T$11/64 -> 4381.6562 | L13: 0 | M13: 0 | N13: 0 | O13: 0 | R13: =(J13+K13+L13+M13+N13+O13)*$B$2 -> 4769.0999
A14: F9 | B14: Vijay Suswaram (Owner) / Divya Shikha (Tenant) | C14: 2191 | D14: =SUM($C$3:$C$5)/64 -> 0 | E14: =C14+D14 -> 2191 | F14: =IF($C$70=0, 0, E14/$C$70) -> 0.0057169174 | G14: =F14*$T$5 -> 172.6509 | H14: 4 | I14: =$T$7*H14 -> 471.24664 | J14: =G14+$T$9+I14 -> 649.41996 | K14: =$T$11/64 -> 4381.6562 | L14: 0 | M14: 0 | N14: 0 | O14: 0 | R14: =(J14+K14+L14+M14+N14+O14)*$B$2 -> 5031.0762
A15: F10 | B15: Aby Thomas | C15: 3976.5 | D15: =SUM($C$3:$C$5)/64 -> 0 | E15: =C15+D15 -> 3976.5 | F15: =IF($C$70=0, 0, E15/$C$70) -> 0.010375774 | G15: =F15*$T$5 -> 313.34839 | H15: 3 | I15: =$T$7*H15 -> 353.43498 | J15: =G15+$T$9+I15 -> 672.30579 | K15: =$T$11/64 -> 4381.6562 | L15: 0 | M15: 0 | N15: 0 | O15: 0 | R15: =(J15+K15+L15+M15+N15+O15)*$B$2 -> 5053.962 | S15: BALANCE IN ACCOUNT ON 30-SEP-2022
A16: F11 | B16: Niwin Anto | C16: 700 | D16: =SUM($C$3:$C$5)/64 -> 0 | E16: =C16+D16 -> 700 | F16: =IF($C$70=0, 0, E16/$C$70) -> 0.0018264912 | G16: =F16*$T$5 -> 55.160033 | H16: 3 | I16: =$T$7*H16 -> 353.43498 | J16: =G16+$T$9+I16 -> 414.11743 | K16: =$T$11/64 -> 4381.6562 | L16: 0 | M16: 0 | N16: 0 | O16: 0 | R16: =(J16+K16+L16+M16+N16+O16)*$B$2 -> 4795.7737 | S16: TOTAL NON MAINTENANCE CORPUS COLLECTION
A17: F12 | B17: Anirudh Singh | C17: 0.5 | D17: =SUM($C$3:$C$5)/64 -> 0 | E17: =C17+D17 -> 0.5 | F17: =IF($C$70=0, 0, E17/$C$70) -> 1.3046365e-06 | G17: =F17*$T$5 -> 0.039400024 | H17: 3 | I17: =$T$7*H17 -> 353.43498 | J17: =G17+$T$9+I17 -> 358.9968 | K17: =$T$11/64 -> 4381.6562 | L17: 0 | M17: 0 | N17: 0 | O17: 0 | R17: =(J17+K17+L17+M17+N17+O17)*$B$2 -> 4740.653 | S17: TOTAL FD DONE
A18: F13 | B18: Sanchay Saxena | C18: 4662 | D18: =SUM($C$3:$C$5)/64 -> 0 | E18: =C18+D18 -> 4662 | F18: =IF($C$70=0, 0, E18/$C$70) -> 0.012164431 | G18: =F18*$T$5 -> 367.36582 | H18: 4 | I18: =$T$7*H18 -> 471.24664 | J18: =G18+$T$9+I18 -> 844.13488 | K18: =$T$11/64 -> 4381.6562 | L18: 0 | M18: 0 | N18: 0 | O18: 0 | R18: =(J18+K18+L18+M18+N18+O18)*$B$2 -> 5225.7911 | S18: AMOUNT AVAILABLE FOR NON MAINTENANCE CORPUS IN CURRENT AC | T18: =T16-T17 -> 0
A19: F14 | B19: Hemant Patel | C19: 1477.5 | D19: =SUM($C$3:$C$5)/64 -> 0 | E19: =C19+D19 -> 1477.5 | F19: =IF($C$70=0, 0, E19/$C$70) -> 0.003855201 | G19: =F19*$T$5 -> 116.42707 | H19: 4 | I19: =$T$7*H19 -> 471.24664 | J19: =G19+$T$9+I19 -> 593.19613 | K19: =$T$11/64 -> 4381.6562 | L19: 0 | M19: 0 | N19: 0 | O19: 0 | R19: =(J19+K19+L19+M19+N19+O19)*$B$2 -> 4974.8524 | S19: AMOUNT AVAILABLE FOR MAINTENANCE | T19: =T15-T18 -> 0
A20: F15 | B20: Senthil.Vijayaragavan | C20: 3834.5 | D20: =SUM($C$3:$C$5)/64 -> 0 | E20: =C20+D20 -> 3834.5 | F20: =IF($C$70=0, 0, E20/$C$70) -> 0.010005258 | G20: =F20*$T$5 -> 302.15878 | H20: 4 | I20: =$T$7*H20 -> 471.24664 | J20: =G20+$T$9+I20 -> 778.92784 | K20: =$T$11/64 -> 4381.6562 | L20: 750 | M20: 0 | N20: 0 | O20: 0 | R20: =(J20+K20+L20+M20+N20+O20)*$B$2 -> 5910.5841 | S20: TOTAL EXPENSE FOR THE MONTH | T20: ='ANNUAL-EXPENSE-DETAILS'!BH8 -> 336898
A21: F16 | B21: Sreeja Sudharma | C21: 15025 | D21: =SUM($C$3:$C$5)/64 -> 0 | E21: =C21+D21 -> 15025 | F21: =IF($C$70=0, 0, E21/$C$70) -> 0.039204328 | G21: =F21*$T$5 -> 1183.9707 | H21: 3 | I21: =$T$7*H21 -> 353.43498 | J21: =G21+$T$9+I21 -> 1542.9281 | K21: =$T$11/64 -> 4381.6562 | L21: 0 | M21: 0 | N21: 0 | O21: 0 | R21: =(J21+K21+L21+M21+N21+O21)*$B$2 -> 5924.5844
A22: G1 | B22: Venkataramanan C | C22: 10949.5 | D22: =SUM($C$3:$C$5)/64 -> 0 | E22: =C22+D22 -> 10949.5 | F22: =IF($C$70=0, 0, E22/$C$70) -> 0.028570236 | G22: =F22*$T$5 -> 862.82112 | H22: 3 | I22: =$T$7*H22 -> 353.43498 | J22: =G22+$T$9+I22 -> 1221.7785 | K22: =$T$11/64 -> 4381.6562 | L22: 0 | M22: 0 | N22: 0 | O22: 0 | R22: =(J22+K22+L22+M22+N22+O22)*$B$2 -> 5603.4348
A23: G2 | B23: Kaushik Kasibhatla | C23: 10594 | D23: =SUM($C$3:$C$5)/64 -> 0 | E23: =C23+D23 -> 10594 | F23: =IF($C$70=0, 0, E23/$C$70) -> 0.027642639 | G23: =F23*$T$5 -> 834.8077 | H23: 4 | I23: =$T$7*H23 -> 471.24664 | J23: =G23+$T$9+I23 -> 1311.5768 | K23: =$T$11/64 -> 4381.6562 | L23: 0 | M23: 0 | N23: 0 | O23: 0 | R23: =(J23+K23+L23+M23+N23+O23)*$B$2 -> 5693.233
A24: G3 | B24: Balakrishnan | C24: 11201 | D24: =SUM($C$3:$C$5)/64 -> 0 | E24: =C24+D24 -> 11201 | F24: =IF($C$70=0, 0, E24/$C$70) -> 0.029226468 | G24: =F24*$T$5 -> 882.63933 | H24: 4 | I24: =$T$7*H24 -> 471.24664 | J24: =G24+$T$9+I24 -> 1359.4084 | K24: =$T$11/64 -> 4381.6562 | L24: 0 | M24: 0 | N24: 0 | O24: 0 | R24: =(J24+K24+L24+M24+N24+O24)*$B$2 -> 5741.0646
A25: G4 | B25: Ashwin Pandith | C25: 18127 | D25: =SUM($C$3:$C$5)/64 -> 0 | E25: =C25+D25 -> 18127 | F25: =IF($C$70=0, 0, E25/$C$70) -> 0.047298293 | G25: =F25*$T$5 -> 1428.4085 | H25: 4 | I25: =$T$7*H25 -> 471.24664 | J25: =G25+$T$9+I25 -> 1905.1775 | K25: =$T$11/64 -> 4381.6562 | L25: 0 | M25: 0 | N25: 0 | O25: 0 | R25: =(J25+K25+L25+M25+N25+O25)*$B$2 -> 6286.8338
A26: G5 | B26: Mayank Phophaliya | C26: 4288.5 | D26: =SUM($C$3:$C$5)/64 -> 0 | E26: =C26+D26 -> 4288.5 | F26: =IF($C$70=0, 0, E26/$C$70) -> 0.011189868 | G26: =F26*$T$5 -> 337.934 | H26: 3 | I26: =$T$7*H26 -> 353.43498 | J26: =G26+$T$9+I26 -> 696.8914 | K26: =$T$11/64 -> 4381.6562 | L26: 0 | M26: 0 | N26: 0 | O26: 0 | R26: =(J26+K26+L26+M26+N26+O26)*$B$2 -> 5078.5477
A27: G6 | B27: Mohit Daga | C27: 5998 | D27: =SUM($C$3:$C$5)/64 -> 0 | E27: =C27+D27 -> 5998 | F27: =IF($C$70=0, 0, E27/$C$70) -> 0.01565042 | G27: =F27*$T$5 -> 472.64268 | H27: 3 | I27: =$T$7*H27 -> 353.43498 | J27: =G27+$T$9+I27 -> 831.60008 | K27: =$T$11/64 -> 4381.6562 | L27: 0 | M27: 0 | N27: 0 | O27: 0 | R27: =(J27+K27+L27+M27+N27+O27)*$B$2 -> 5213.2563
A28: G7 | B28: Prince Richfield | C28: 6639.5 | D28: =SUM($C$3:$C$5)/64 -> 0 | E28: =C28+D28 -> 6639.5 | F28: =IF($C$70=0, 0, E28/$C$70) -> 0.017324269 | G28: =F28*$T$5 -> 523.19292 | H28: 3 | I28: =$T$7*H28 -> 353.43498 | J28: =G28+$T$9+I28 -> 882.15031 | K28: =$T$11/64 -> 4381.6562 | L28: 0 | M28: 0 | N28: 0 | O28: 0 | R28: =(J28+K28+L28+M28+N28+O28)*$B$2 -> 5263.8066
A29: G8 | B29: Ranjithkumar R / Sameer (tenant) / Princy (tenant) | C29: 11752 | D29: =SUM($C$3:$C$5)/64 -> 0 | E29: =C29+D29 -> 11752 | F29: =IF($C$70=0, 0, E29/$C$70) -> 0.030664177 | G29: =F29*$T$5 -> 926.05816 | H29: 3 | I29: =$T$7*H29 -> 353.43498 | J29: =G29+$T$9+I29 -> 1285.0156 | K29: =$T$11/64 -> 4381.6562 | L29: 0 | M29: 0 | N29: 0 | O29: 0 | R29: =(J29+K29+L29+M29+N29+O29)*$B$2 -> 5666.6718
A30: G9 | B30: Chandramouli | C30: 5146.5 | D30: =SUM($C$3:$C$5)/64 -> 0 | E30: =C30+D30 -> 5146.5 | F30: =IF($C$70=0, 0, E30/$C$70) -> 0.013428624 | G30: =F30*$T$5 -> 405.54444 | H30: 5 | I30: =$T$7*H30 -> 589.0583 | J30: =G30+$T$9+I30 -> 1000.1252 | K30: =$T$11/64 -> 4381.6562 | L30: 0 | M30: 0 | N30: 0 | O30: 0 | R30: =(J30+K30+L30+M30+N30+O30)*$B$2 -> 5381.7814
A31: G10 | B31: Cijo Jacob / Thara Joy | C31: 6444 | D31: =SUM($C$3:$C$5)/64 -> 0 | E31: =C31+D31 -> 6444 | F31: =IF($C$70=0, 0, E31/$C$70) -> 0.016814156 | G31: =F31*$T$5 -> 507.78751 | H31: 3 | I31: =$T$7*H31 -> 353.43498 | J31: =G31+$T$9+I31 -> 866.7449 | K31: =$T$11/64 -> 4381.6562 | L31: 0 | M31: 0 | N31: 0 | O31: 0 | R31: =(J31+K31+L31+M31+N31+O31)*$B$2 -> 5248.4012
A32: G11 | B32: Ketan Verlekar | C32: 2462 | D32: =SUM($C$3:$C$5)/64 -> 0 | E32: =C32+D32 -> 2462 | F32: =IF($C$70=0, 0, E32/$C$70) -> 0.0064240304 | G32: =F32*$T$5 -> 194.00572 | H32: 3 | I32: =$T$7*H32 -> 353.43498 | J32: =G32+$T$9+I32 -> 552.96312 | K32: =$T$11/64 -> 4381.6562 | L32: 0 | M32: 0 | N32: 0 | O32: 0 | R32: =(J32+K32+L32+M32+N32+O32)*$B$2 -> 4934.6194
... A69: T16 | B69: Madhusoodanan P.R. | C69: 5245.5 | D69: =SUM($C$3:$C$5)/64 -> 0 | E69: =C69+D69 -> 5245.5 | F69: =IF($C$70=0, 0, E69/$C$70) -> 0.013686942 | G69: =F69*$T$5 -> 413.34565 | H69: 3 | I69: =$T$7*H69 -> 353.43498 | J69: =G69+$T$9+I69 -> 772.30305 | K69: =$T$11/64 -> 4381.6562 | L69: 0 | M69: 0 | N69: 0 | O69: 0 | R69: =(J69+K69+L69+M69+N69+O69)*$B$2 -> 5153.9593
B70: TOTAL | C70: =SUM(C3:C69) -> 383248.5 | D70: =SUM(D3:D69) -> 0 | E70: =SUM(E3:E69) -> 383248.5 | F70: =IF($C$70=0, 0, E70/$C$70) -> 1 | G70: =SUM(G3:G69) -> 30200 | H70: =SUM(H3:H69) -> 223 | I70: =SUM(I3:I69) -> 26272 | J70: =SUM(J3:J69) -> 56472 | K70: =SUM(K3:K69) -> 280426 | L70: =SUM(L3:L69) -> 3000 | M70: =SUM(M3:M69) -> 0 | N70: =SUM(N3:N69) -> 0 | O70: =SUM(O3:O69) -> 0 | R70: =SUM(R3:R69) -> 339898

Sheet Sep2025-COLLECTION
A1: FLAT # | C1: Amount | D1: Date | E1: Amount | F1: Date | G1: Amount | H1: Date | I1: Amount | J1: Date | K1: Total
A2: F1 | B2: Shailesh Srivastava / Azeem Nawaz | C2: 5497 | D2: 45923 | K2: =SUM(C2,E2,G2,I2) -> 5497
A3: F2 | B3: Shanthanu | C3: 26147 | D3: 45906 | K3: =SUM(C3,E3,G3,I3) -> 26147
A4: F3 | B4: Samrat Kar | C4: 6000 | D4: 45901 | K4: =SUM(C4,E4,G4,I4) -> 6000
A5: F4 | B5: Renu R | C5: 5554 | D5: 45922 | K5: =SUM(C5,E5,G5,I5) -> 5554
A6: F5 | B6: Vamsidhar Bethanabatla / Madhuri Anumula | C6: 7050 | D6: 45907 | K6: =SUM(C6,E6,G6,I6) -> 7050
A7: F6 | B7: Meghana Viral Shah and Vviral Shah (Owner) / Sangeet and Swagat (Tenent) | K7: =SUM(C7,E7,G7,I7) -> 0
A8: F7 | B8: Vimal NK | C8: 5939 | D8: 45922 | K8: =SUM(C8,E8,G8,I8) -> 5939
A9: F8 | B9: Sujeet Kumar (Tenant)/Sreejith Menon (Owner) | C9: 5121 | D9: 45907 | K9: =SUM(C9,E9,G9,I9) -> 5121
A10: F9 | B10: Vijay Suswaram (Owner) / Divya Shikha (Tenant) | C10: 5434 | D10: 45923 | K10: =SUM(C10,E10,G10,I10) -> 5434
A11: F10 | B11: Aby Thomas | K11: =SUM(C11,E11,G11,I11) -> 0
A12: F11 | B12: N. Geetha | C12: 5218 | D12: 45923 | K12: =SUM(C12,E12,G12,I12) -> 5218
A13: F12 | B13: Anirudh Singh | C13: 5108 | D13: 45907 | K13: =SUM(C13,E13,G13,I13) -> 5108
A14: F13 | B14: Sanchay Saxena | C14: 6253.71 | D14: 45906 | E14: 6252.77 | F14: 45906 | K14: =SUM(C14,E14,G14,I14) -> 12506.48
A15: F14 | B15: Hemant Patel | C15: 5439 | D15: 45923 | K15: =SUM(C15,E15,G15,I15) -> 5439
A16: F15 | B16: Senthil.Vijayaragavan | C16: 6487 | D16: 45925 | K16: =SUM(C16,E16,G16,I16) -> 6487
A17: F16 | B17: Sreeja Sudharma | K17: =SUM(C17,E17,G17,I17) -> 0
A18: G1 | B18: Venkataramanan C | C18: 6533 | D18: 45925 | K18: =SUM(C18,E18,G18,I18) -> 6533
A19: G2 | B19: Kaushik Kasibhatla | C19: 6772.92 | D19: 45916 | K19: =SUM(C19,E19,G19,I19) -> 6772.92
A20: G3 | B20: Balakrishnan | C20: 6558 | D20: 45930 | K20: =SUM(C20,E20,G20,I20) -> 6558
A21: G4 | B21: Ashwin Pandith | K21: =SUM(C21,E21,G21,I21) -> 0
A22: G5 | B22: Mayank Phophaliya | C22: 11102.41 | D22: 45910 | K22: =SUM(C22,E22,G22,I22) -> 11102.41
A23: G6 | B23: Mohit Daga | C23: 5212 | D23: 45907 | K23: =SUM(C23,E23,G23,I23) -> 5212
A24: G7 | B24: Prince Richfield | C24: 5635 | D24: 45925 | K24: =SUM(C24,E24,G24,I24) -> 5635
A25: G8 | B25: Ranjithkumar R / Sameer (tenant) / Princy (tenant) | C25: 6108 | D25: 45907 | K25: =SUM(C25,E25,G25,I25) -> 6108
A26: G9 | B26: Ankur Agarwal | C26: 5869 | D26: 45907 | K26: =SUM(C26,E26,G26,I26) -> 5869
A27: G10 | B27: Cijo Jacob / Thara Joy | C27: 6008 | D27: 45907 | E27: 6000 | F27: 45926 | K27: =SUM(C27,E27,G27,I27) -> 12008
A28: G11 | B28: Ketan Verlekar | C28: 5377 | D28: 9-Sep-0205 | K28: =SUM(C28,E28,G28,I28) -> 5377
A29: G12 | B29: Shyam Nair | C29: 6119 | D29: 45926 | K29: =SUM(C29,E29,G29,I29) -> 6119
A30: G13 | B30: Ajai.B | C30: 12208 | D30: 45907 | K30: =SUM(C30,E30,G30,I30) -> 12208
A31: G14 | B31: Surajit Borah | C31: 5790 | D31: 45922 | K31: =SUM(C31,E31,G31,I31) -> 5790
A32: G15 | B32: Suresh Nallusamy / Antriksh (tenant) | C32: 5226 | D32: 45929 | K32: =SUM(C32,E32,G32,I32) -> 5226
A33: G16 | B33: Praveen Ganesan | C33: 7235 | D33: 45924 | K33: =SUM(C33,E33,G33,I33) -> 7235
A34: S1 | B34: S.N.Behera | C34: 5581.91 | D34: 45906 | K34: =SUM(C34,E34,G34,I34) -> 5581.91
A35: S2 | B35: Sonal Singh | K35: =SUM(C35,E35,G35,I35) -> 0
A36: S3 | B36: Koteswararao | C36: 5457 | D36: 45913 | K36: =SUM(C36,E36,G36,I36) -> 5457
A37: S4 | B37: Swaminathan | C37: 5290 | D37: 45908 | K37: =SUM(C37,E37,G37,I37) -> 5290
A38: S5 | B38: Abhishek Gopalakrishnan | K38: =SUM(C38,E38,G38,I38) -> 0
A39: S6 | B39: Vivek Dhingra / Pratyush Das | C39: 15000 | D39: 45909 | K39: =SUM(C39,E39,G39,I39) -> 15000
A40: S7 | B40: Harish B | C40: 5168 | D40: 45924 | K40: =SUM(C40,E40,G40,I40) -> 5168
A41: S8 | B41: Irudayaraj Alwin | C41: 6981.26 | D41: 45909 | K41: =SUM(C41,E41,G41,I41) -> 6981.26
A42: S9 | B42: Pawan GS | C42: 6000 | D42: 45909 | K42: =SUM(C42,E42,G42,I42) -> 6000
A43: S10 | B43: Lakshmikanth | K43: =SUM(C43,E43,G43,I43) -> 0
A44: S11 | B44: Gowrish Patnaik / Somananth GM | C44: 31153 | D44: 45906 | E44: 6393 | F44: 45923 | K44: =SUM(C44,E44,G44,I44) -> 37546
A45: S12 | B45: Saovik Mondal | C45: 5905 | D45: 45922 | K45: =SUM(C45,E45,G45,I45) -> 5905
A46: S13 | B46: Ramadevi S. | C46: 5522.32 | D46: 45906 | E46: 6028.01 | F46: 45906 | K46: =SUM(C46,E46,G46,I46) -> 11550.33
A47: S14 | B47: Nishant Upadhyay(Owner)/ Fabian (Tenant) | K47: =SUM(C47,E47,G47,I47) -> 0
A48: S15 | B48: Manas Dasgupta | C48: 6788 | D48: 45924 | K48: =SUM(C48,E48,G48,I48) -> 6788
A49: S16 | B49: Devendra Singh Rawat / Nancy | C49: 5931 | D49: 45911 | K49: =SUM(C49,E49,G49,I49) -> 5931
A50: T1 | B50: Prashant Sikdar | C50: 6417 | D50: 45923 | K50: =SUM(C50,E50,G50,I50) -> 6417
A51: T2 | B51: Kunal Mehta | K51: =SUM(C51,E51,G51,I51) -> 0
A52: T3 | B52: Kapil Garg | C52: 6343 | D52: 45907 | K52: =SUM(C52,E52,G52,I52) -> 6343
A53: T4 | B53: Vijet Alva (Owner) - Masood (Tenant) | K53: =SUM(C53,E53,G53,I53) -> 0
A54: T5 | B54: Ganesh Iyer and Latha Iyer( owner) Richa (Tenant) | K54: =SUM(C54,E54,G54,I54) -> 0
A55: T6 | B55: Mythili Ramesh | K55: =SUM(C55,E55,G55,I55) -> 0
A56: T7 | B56: Vinyas Ramachandra / Shwetha Marnamikatta / Katari Siva Rama Raju | C56: 5777.61 | D56: 45907 | K56: =SUM(C56,E56,G56,I56) -> 5777.61
A57: T8 | B57: Lalit Kumar Sharma | K57: =SUM(C57,E57,G57,I57) -> 0
A58: T9 | B58: Nishith Sahu and Priyanka Rani (Owner)/ Anmol Verma (Tenant) | C58: 5840 | D58: 45907 | K58: =SUM(C58,E58,G58,I58) -> 5840
A59: T10 | B59: Vamsidhar Bethanabatla / Madhuri Anumula | C59: 7000 | D59: 45926 | E59: 2000 | F59: 45926 | K59: =SUM(C59,E59,G59,I59) -> 9000
A60: T11 | B60: Arvind Balasubramanian | K60: =SUM(C60,E60,G60,I60) -> 0
A61: T12 | B61: Prasenjit | C61: 5695.22 | D61: 45908 | K61: =SUM(C61,E61,G61,I61) -> 5695.22
A62: T13 | B62: Rahul Kumar | C62: 12000 | D62: 45908 | K62: =SUM(C62,E62,G62,I62) -> 12000
A63: T14 | B63: Jeya / Kanda / Satya (tenant)/Vinuta (tenant) | K63: =SUM(C63,E63,G63,I63) -> 0
A64: T15 | B64: Trevor | K64: =SUM(C64,E64,G64,I64) -> 0
A65: T16 | B65: Madhusoodanan P.R. | K65: =SUM(C65,E65,G65,I65) -> 0
A66: TOTAL | K66: =SUM(K2:K65) -> 377525.14

Sheet Oct2025-EXPENSE
B1: OCTOBER 2025 EXPENSES
A2: FLAT # | B2: 1 | C2: WATER USED IN LTRS | D2: COMMON AREA EQUALLY DEVIDED | E2: TOTAL FRESH WATER CONSUMED | F2: %OF TOTAL USED | G2: WATER EXPENSE SHARING BY % | H2: #METERS | I2: METER RENT | J2: COMMON AREA METER RENT + WATER EXPENSE+ FLAT METER RENT | K2: FIXED EXPENSE SHARE | L2: PARKING FEE | M2: CLUB HOUSE BOOKING FEE | N2: SHIFTING FEE | O2: GYM USAGE FEE | R2: TOTAL EXPENSE TO BE PAID
A3: CH | B3: MPFOWA | C3: 38.5 | D3: 0 | H3: 1 | I3: =T7 -> 117.81166 | J3: =I3 -> 117.81166
A4: GYM | B4: MPFOWA | C4: 0 | D4: 0 | H4: 1 | I4: =T7 -> 117.81166 | J4: =I4 -> 117.81166 | S4: TOTAL FIXED EXPENSE | T4: ='ANNUAL-EXPENSE-DETAILS'!BF9 -> 368295
A5: BSMT | B5: MPFOWA | C5: 0 | D5: 0 | H5: 1 | I5: =T7 -> 117.81166 | J5: =I5 -> 117.81166 | S5: TOTAL WATER EXPENSE | T5: ='ANNUAL-EXPENSE-DETAILS'!BE9 -> 35000
A6: F1 | B6: Shailesh Srivastava / Azeem Nawaz | C6: 2655.5 | D6: =SUM($C$3:$C$4)/64 -> 0.6015625 | E6: =C6+D6 -> 2656.1016 | F6: =IF($C$70=0, 0, E6/$C$70) -> 0.0080638696 | G6: =F6*$T$5 -> 282.23544 | H6: 3 | I6: =$T$7*H6 -> 353.43498 | J6: =G6+$T$9+I6 -> 641.19283 | K6: =$T$11/64 -> 5754.6094 | L6: 0 | M6: 0 | N6: 0 | O6: 0 | R6: =(J6+K6+L6+M6+N6+O6)*$B$2 -> 6395.8022
A7: F2 | B7: Shanthanu | C7: 7701 | D7: =SUM($C$3:$C$4)/64 -> 0.6015625 | E7: =C7+D7 -> 7701.6016 | F7: =IF($C$70=0, 0, E7/$C$70) -> 0.023381904 | G7: =F7*$T$5 -> 818.36663 | H7: 4 | I7: =$T$7*H7 -> 471.24664 | J7: =G7+$T$9+I7 -> 1295.1357 | K7: =$T$11/64 -> 5754.6094 | L7: 0 | M7: 0 | N7: 0 | O7: 0 | R7: =(J7+K7+L7+M7+N7+O7)*$B$2 -> 7049.7451 | S7: RENT PER METER | T7: 117.81166
A8: F3 | B8: Samrat Kar | C8: 11632.5 | D8: =SUM($C$3:$C$4)/64 -> 0.6015625 | E8: =C8+D8 -> 11633.102 | F8: =IF($C$70=0, 0, E8/$C$70) -> 0.035317857 | G8: =F8*$T$5 -> 1236.125 | H8: 4 | I8: =$T$7*H8 -> 471.24664 | J8: =G8+$T$9+I8 -> 1712.894 | K8: =$T$11/64 -> 5754.6094 | L8: 750 | M8: 0 | N8: 0 | O8: 0 | R8: =(J8+K8+L8+M8+N8+O8)*$B$2 -> 8217.5034 | S8: COMMON AREA METER RENT | T8: =$T$7*3 -> 353.43498
A9: F4 | B9: Renu R | C9: 4341 | D9: =SUM($C$3:$C$4)/64 -> 0.6015625 | E9: =C9+D9 -> 4341.6016 | F9: =IF($C$70=0, 0, E9/$C$70) -> 0.013181013 | G9: =F9*$T$5 -> 461.33545 | H9: 4 | I9: =$T$7*H9 -> 471.24664 | J9: =G9+$T$9+I9 -> 938.10451 | K9: =$T$11/64 -> 5754.6094 | L9: 0 | M9: 0 | N9: 0 | O9: 0 | R9: =(J9+K9+L9+M9+N9+O9)*$B$2 -> 6692.7139 | S9: COMMON AREA METER RENT/FLAT | T9: =T8/64 -> 5.5224215
A10: F5 | B10: Vamsidhar Bethanabatla / Madhuri Anumula | C10: 3922.5 | D10: =SUM($C$3:$C$4)/64 -> 0.6015625 | E10: =C10+D10 -> 3923.1016 | F10: =IF($C$70=0, 0, E10/$C$70) -> 0.011910455 | G10: =F10*$T$5 -> 416.86594 | H10: 3 | I10: =$T$7*H10 -> 353.43498 | J10: =G10+$T$9+I10 -> 775.82334 | K10: =$T$11/64 -> 5754.6094 | L10: 0 | M10: 0 | N10: 0 | O10: 0 | R10: =(J10+K10+L10+M10+N10+O10)*$B$2 -> 6530.4327
A11: F6 | B11: Meghana Viral Shah and Vviral Shah (Owner) / Sangeet and Swagat (Tenent) | C11: 4642 | D11: =SUM($C$3:$C$4)/64 -> 0.6015625 | E11: =C11+D11 -> 4642.6016 | F11: =IF($C$70=0, 0, E11/$C$70) -> 0.014094843 | G11: =F11*$T$5 -> 493.31949 | H11: 3 | I11: =$T$7*H11 -> 353.43498 | J11: =G11+$T$9+I11 -> 852.27689 | K11: =$T$11/64 -> 5754.6094 | L11: 0 | M11: 0 | N11: 0 | O11: 0 | R11: =(J11+K11+L11+M11+N11+O11)*$B$2 -> 6606.8863 | S11: TOTAL FIXED EXPENSE | T11: ='ANNUAL-EXPENSE-DETAILS'!BF9 -> 368295
A12: F7 | B12: Vimal NK | C12: 184 | D12: =SUM($C$3:$C$4)/64 -> 0.6015625 | E12: =C12+D12 -> 184.60156 | F12: =IF($C$70=0, 0, E12/$C$70) -> 0.00056044654 | G12: =F12*$T$5 -> 19.615629 | H12: 3 | I12: =$T$7*H12 -> 353.43498 | J12: =G12+$T$9+I12 -> 378.57303 | K12: =$T$11/64 -> 5754.6094 | L12: 750 | M12: 0 | N12: 0 | O12: 0 | R12: =(J12+K12+L12+M12+N12+O12)*$B$2 -> 6883.1824
A13: F8 | B13: Sujeet Kumar (Tenant)/Sreejith Menon (Owner) | C13: 254 | D13: =SUM($C$3:$C$4)/64 -> 0.6015625 | E13: =C13+D13 -> 254.60156 | F13: =IF($C$70=0, 0, E13/$C$70) -> 0.0007729651 | G13: =F13*$T$5 -> 27.053778 | H13: 3 | I13: =$T$7*H13 -> 353.43498 | J13: =G13+$T$9+I13 -> 386.01118 | K13: =$T$11/64 -> 5754.6094 | L13: 0 | M13: 0 | N13: 0 | O13: 0 | R13: =(J13+K13+L13+M13+N13+O13)*$B$2 -> 6140.6206 | S13: BALANCE IN ACCOUNT ON 31-OCT-2023
A14: F9 | B14: Vijay Suswaram (Owner) / Divya Shikha (Tenant) | C14: 2126 | D14: =SUM($C$3:$C$4)/64 -> 0.6015625 | E14: =C14+D14 -> 2126.6016 | F14: =IF($C$70=0, 0, E14/$C$70) -> 0.0064563185 | G14: =F14*$T$5 -> 225.97115 | H14: 4 | I14: =$T$7*H14 -> 471.24664 | J14: =G14+$T$9+I14 -> 702.74021 | K14: =$T$11/64 -> 5754.6094 | L14: 0 | M14: 0 | N14: 0 | O14: 0 | R14: =(J14+K14+L14+M14+N14+O14)*$B$2 -> 6457.3496 | S14: TOTAL NON MAINTENANCE CORPUS COLLECTION
A15: F10 | B15: Aby Thomas | C15: 2020.5 | D15: =SUM($C$3:$C$4)/64 -> 0.6015625 | E15: =C15+D15 -> 2021.1016 | F15: =IF($C$70=0, 0, E15/$C$70) -> 0.0061360227 | G15: =F15*$T$5 -> 214.76079 | H15: 3 | I15: =$T$7*H15 -> 353.43498 | J15: =G15+$T$9+I15 -> 573.71819 | K15: =$T$11/64 -> 5754.6094 | L15: 0 | M15: 0 | N15: 0 | O15: 0 | R15: =(J15+K15+L15+M15+N15+O15)*$B$2 -> 6328.3276 | S15: TOTAL FD DONE
A16: F11 | B16: Niwin Anto | C16: 0.5 | D16: =SUM($C$3:$C$4)/64 -> 0.6015625 | E16: =C16+D16 -> 1.1015625 | F16: =IF($C$70=0, 0, E16/$C$70) -> 3.344321e-06 | G16: =F16*$T$5 -> 0.11705124 | H16: 3 | I16: =$T$7*H16 -> 353.43498 | J16: =G16+$T$9+I16 -> 359.07445 | K16: =$T$11/64 -> 5754.6094 | L16: 0 | M16: 0 | N16: 0 | O16: 0 | R16: =(J16+K16+L16+M16+N16+O16)*$B$2 -> 6113.6838 | S16: AMOUNT AVAILABLE FOR NON MAINTENANCE CORPUS IN CURRENT AC | T16: =T14-T15 -> 0
A17: F12 | B17: Anirudh Singh | C17: 0.5 | D17: =SUM($C$3:$C$4)/64 -> 0.6015625 | E17: =C17+D17 -> 1.1015625 | F17: =IF($C$70=0, 0, E17/$C$70) -> 3.344321e-06 | G17: =F17*$T$5 -> 0.11705124 | H17: 3 | I17: =$T$7*H17 -> 353.43498 | J17: =G17+$T$9+I17 -> 359.07445 | K17: =$T$11/64 -> 5754.6094 | L17: 0 | M17: 0 | N17: 0 | O17: 0 | R17: =(J17+K17+L17+M17+N17+O17)*$B$2 -> 6113.6838 | S17: AMOUNT AVAILABLE FOR MAINTENANCE | T17: =T13-T16 -> 0
A18: F13 | B18: Sanchay Saxena | C18: 1614 | D18: =SUM($C$3:$C$4)/64 -> 0.6015625 | E18: =C18+D18 -> 1614.6016 | F18: =IF($C$70=0, 0, E18/$C$70) -> 0.0049018971 | G18: =F18*$T$5 -> 171.5664 | H18: 4 | I18: =$T$7*H18 -> 471.24664 | J18: =G18+$T$9+I18 -> 648.33545 | K18: =$T$11/64 -> 5754.6094 | L18: 0 | M18: 0 | N18: 0 | O18: 0 | R18: =(J18+K18+L18+M18+N18+O18)*$B$2 -> 6402.9448 | S18: TOTAL EXPENSE FOR THE MONTH | T18: ='ANNUAL-EXPENSE-DETAILS'!BH9 -> 429567
A19: F14 | B19: Hemant Patel | C19: 1987.5 | D19: =SUM($C$3:$C$4)/64 -> 0.6015625 | E19: =C19+D19 -> 1988.1016 | F19: =IF($C$70=0, 0, E19/$C$70) -> 0.0060358354 | G19: =F19*$T$5 -> 211.25424 | H19: 4 | I19: =$T$7*H19 -> 471.24664 | J19: =G19+$T$9+I19 -> 688.0233 | K19: =$T$11/64 -> 5754.6094 | L19: 0 | M19: 0 | N19: 0 | O19: 0 | R19: =(J19+K19+L19+M19+N19+O19)*$B$2 -> 6442.6327
A20: F15 | B20: Senthil.Vijayaragavan | C20: 9 | D20: =SUM($C$3:$C$4)/64 -> 0.6015625 | E20: =C20+D20 -> 9.6015625 | F20: =IF($C$70=0, 0, E20/$C$70) -> 2.9150146e-05 | G20: =F20*$T$5 -> 1.0202551 | H20: 4 | I20: =$T$7*H20 -> 471.24664 | J20: =G20+$T$9+I20 -> 477.78931 | K20: =$T$11/64 -> 5754.6094 | L20: 750 | M20: 0 | N20: 0 | O20: 0 | R20: =(J20+K20+L20+M20+N20+O20)*$B$2 -> 6982.3987
A21: F16 | B21: Sreeja Sudharma | C21: 12892.5 | D21: =SUM($C$3:$C$4)/64 -> 0.6015625 | E21: =C21+D21 -> 12893.102 | F21: =IF($C$70=0, 0, E21/$C$70) -> 0.039143191 | G21: =F21*$T$5 -> 1370.0117 | H21: 3 | I21: =$T$7*H21 -> 353.43498 | J21: =G21+$T$9+I21 -> 1728.9691 | K21: =$T$11/64 -> 5754.6094 | L21: 0 | M21: 0 | N21: 0 | O21: 0 | R21: =(J21+K21+L21+M21+N21+O21)*$B$2 -> 7483.5784
A22: G1 | B22: Venkataramanan C | C22: 10272 | D22: =SUM($C$3:$C$4)/64 -> 0.6015625 | E22: =C22+D22 -> 10272.602 | F22: =IF($C$70=0, 0, E22/$C$70) -> 0.031187407 | G22: =F22*$T$5 -> 1091.5592 | H22: 3 | I22: =$T$7*H22 -> 353.43498 | J22: =G22+$T$9+I22 -> 1450.5166 | K22: =$T$11/64 -> 5754.6094 | L22: 0 | M22: 0 | N22: 0 | O22: 0 | R22: =(J22+K22+L22+M22+N22+O22)*$B$2 -> 7205.126
A23: G2 | B23: Kaushik Kasibhatla | C23: 11467.5 | D23: =SUM($C$3:$C$4)/64 -> 0.6015625 | E23: =C23+D23 -> 11468.102 | F23: =IF($C$70=0, 0, E23/$C$70) -> 0.03481692 | G23: =F23*$T$5 -> 1218.5922 | H23: 4 | I23: =$T$7*H23 -> 471.24664 | J23: =G23+$T$9+I23 -> 1695.3613 | K23: =$T$11/64 -> 5754.6094 | L23: 0 | M23: 0 | N23: 0 | O23: 0 | R23: =(J23+K23+L23+M23+N23+O23)*$B$2 -> 7449.9706
A24: G3 | B24: Balakrishnan | C24: 11716.5 | D24: =SUM($C$3:$C$4)/64 -> 0.6015625 | E24: =C24+D24 -> 11717.102 | F24: =IF($C$70=0, 0, E24/$C$70) -> 0.035572879 | G24: =F24*$T$5 -> 1245.0508 | H24: 4 | I24: =$T$7*H24 -> 471.24664 | J24: =G24+$T$9+I24 -> 1721.8198 | K24: =$T$11/64 -> 5754.6094 | L24: 0 | M24: 500 | N24: 0 | O24: 0 | R24: =(J24+K24+L24+M24+N24+O24)*$B$2 -> 7976.4292
A25: G4 | B25: Ashwin Pandith | C25: 18874.5 | D25: =SUM($C$3:$C$4)/64 -> 0.6015625 | E25: =C25+D25 -> 18875.102 | F25: =IF($C$70=0, 0, E25/$C$70) -> 0.057304419 | G25: =F25*$T$5 -> 2005.6547 | H25: 4 | I25: =$T$7*H25 -> 471.24664 | J25: =G25+$T$9+I25 -> 2482.4237 | K25: =$T$11/64 -> 5754.6094 | L25: 0 | M25: 0 | N25: 0 | O25: 0 | R25: =(J25+K25+L25+M25+N25+O25)*$B$2 -> 8237.0331
A26: G5 | B26: Mayank Phophaliya | C26: 2859 | D26: =SUM($C$3:$C$4)/64 -> 0.6015625 | E26: =C26+D26 -> 2859.6016 | F26: =IF($C$70=0, 0, E26/$C$70) -> 0.0086816914 | G26: =F26*$T$5 -> 303.8592 | H26: 3 | I26: =$T$7*H26 -> 353.43498 | J26: =G26+$T$9+I26 -> 662.8166 | K26: =$T$11/64 -> 5754.6094 | L26: 0 | M26: 0 | N26: 0 | O26: 0 | R26: =(J26+K26+L26+M26+N26+O26)*$B$2 -> 6417.426
A27: G6 | B27: Mohit Daga | C27: 4719.5 | D27: =SUM($C$3:$C$4)/64 -> 0.6015625 | E27: =C27+D27 -> 4720.1016 | F27: =IF($C$70=0, 0, E27/$C$70) -> 0.014330131 | G27: =F27*$T$5 -> 501.55459 | H27: 3 | I27: =$T$7*H27 -> 353.43498 | J27: =G27+$T$9+I27 -> 860.51199 | K27: =$T$11/64 -> 5754.6094 | L27: 0 | M27: 0 | N27: 0 | O27: 0 | R27: =(J27+K27+L27+M27+N27+O27)*$B$2 -> 6615.1214
A28: G7 | B28: Prince Richfield | C28: 4907 | D28: =SUM($C$3:$C$4)/64 -> 0.6015625 | E28: =C28+D28 -> 4907.6016 | F28: =IF($C$70=0, 0, E28/$C$70) -> 0.014899377 | G28: =F28*$T$5 -> 521.4782 | H28: 3 | I28: =$T$7*H28 -> 353.43498 | J28: =G28+$T$9+I28 -> 880.4356 | K28: =$T$11/64 -> 5754.6094 | L28: 0 | M28: 0 | N28: 0 | O28: 0 | R28: =(J28+K28+L28+M28+N28+O28)*$B$2 -> 6635.045
A29: G8 | B29: Ranjithkumar R / Sameer (tenant) / Princy (tenant) | C29: 8556.5 | D29: =SUM($C$3:$C$4)/64 -> 0.6015625 | E29: =C29+D29 -> 8557.1016 | F29: =IF($C$70=0, 0, E29/$C$70) -> 0.025979184 | G29: =F29*$T$5 -> 909.27144 | H29: 3 | I29: =$T$7*H29 -> 353.43498 | J29: =G29+$T$9+I29 -> 1268.2288 | K29: =$T$11/64 -> 5754.6094 | L29: 0 | M29: 0 | N29: 0 | O29: 0 | R29: =(J29+K29+L29+M29+N29+O29)*$B$2 -> 7022.8382
A30: G9 | B30: Chandramouli | C30: 5255.5 | D30: =SUM($C$3:$C$4)/64 -> 0.6015625 | E30: =C30+D30 -> 5256.1016 | F30: =IF($C$70=0, 0, E30/$C$70) -> 0.015957416 | G30: =F30*$T$5 -> 558.50956 | H30: 5 | I30: =$T$7*H30 -> 589.0583 | J30: =G30+$T$9+I30 -> 1153.0903 | K30: =$T$11/64 -> 5754.6094 | L30: 0 | M30: 0 | N30: 0 | O30: 0 | R30: =(J30+K30+L30+M30+N30+O30)*$B$2 -> 6907.6997
... A69: T16 | B69: Madhusoodanan P.R. | C69: 4513 | D69: =SUM($C$3:$C$4)/64 -> 0.6015625 | E69: =C69+D69 -> 4513.6016 | F69: =IF($C$70=0, 0, E69/$C$70) -> 0.013703201 | G69: =F69*$T$5 -> 479.61205 | H69: 3 | I69: =$T$7*H69 -> 353.43498 | J69: =G69+$T$9+I69 -> 838.56944 | K69: =$T$11/64 -> 5754.6094 | L69: 0 | M69: 0 | N69: 0 | O69: 0 | R69: =(J69+K69+L69+M69+N69+O69)*$B$2 -> 6593.1788
B70: TOTAL | C70: =SUM(C3:C69) -> 329383 | D70: =SUM(D3:D69) -> 38.5 | E70: =SUM(E3:E69) -> 329383 | F70: =IF($C$70=0, 0, E70/$C$70) -> 1 | G70: =SUM(G3:G69) -> 35000 | H70: =SUM(H3:H69) -> 223 | I70: =SUM(I3:I69) -> 26272 | J70: =SUM(J3:J69) -> 61625.435 | K70: =SUM(K3:K69) -> 368295 | L70: =SUM(L3:L69) -> 3000 | M70: =SUM(M3:M69) -> 500 | N70: =SUM(N3:N69) -> 0 | O70: =SUM(O3:O69) -> 0 | R70: =SUM(R3:R69) -> 433067

Sheet Oct2025-COLLECTION
A1: FLAT # | C1: Amount | D1: Date | E1: Amount | F1: Date | G1: Amount | H1: Date | I1: Amount | J1: Date | K1: Total
A2: F1 | B2: Shailesh Srivastava / Azeem Nawaz | K2: =SUM(C2,E2,G2,I2) -> 0
A3: F2 | B3: Shanthanu | K3: =SUM(C3,E3,G3,I3) -> 0
A4: F3 | B4: Samrat Kar | C4: 6000 | D4: 45931 | K4: =SUM(C4,E4,G4,I4) -> 6000
A5: F4 | B5: Renu R | C5: 5148 | D5: 45945 | K5: =SUM(C5,E5,G5,I5) -> 5148
A6: F5 | B6: Vamsidhar Bethanabatla / Madhuri Anumula / Pulkit Gupta | C6: 5209.99 | D6: 45942 | K6: =SUM(C6,E6,G6,I6) -> 5209.99
A7: F6 | B7: Meghana Viral Shah and Vviral Shah (Owner) / Sangeet and Swagat (Tenent) | C7: 5135 | D7: 45959 | K7: =SUM(C7,E7,G7,I7) -> 5135
A8: F7 | B8: Vimal NK | K8: =SUM(C8,E8,G8,I8) -> 0
A9: F8 | B9: Sujeet Kumar (Tenant)/Sreejith Menon (Owner) | C9: 4769 | D9: 45948 | K9: =SUM(C9,E9,G9,I9) -> 4769
A10: F9 | B10: Vijay Suswaram (Owner) / Divya Shikha (Tenant) | C10: 5031 | D10: 45954 | K10: =SUM(C10,E10,G10,I10) -> 5031
A11: F10 | B11: Aby Thomas | C11: 5794 | D11: 45943 | K11: =SUM(C11,E11,G11,I11) -> 5794
A12: F11 | B12: N. Geetha | C12: 4780 | D12: 45948 | K12: =SUM(C12,E12,G12,I12) -> 4780
A13: F12 | B13: Anirudh Singh | C13: 4741 | D13: 45943 | K13: =SUM(C13,E13,G13,I13) -> 4741
A14: F13 | B14: Sanchay Saxena | C14: 5226 | D14: 45946 | K14: =SUM(C14,E14,G14,I14) -> 5226
A15: F14 | B15: Hemant Patel | C15: 4975 | D15: 45946 | K15: =SUM(C15,E15,G15,I15) -> 4975
A16: F15 | B16: Senthil.Vijayaragavan | C16: 5911 | D16: 45946 | K16: =SUM(C16,E16,G16,I16) -> 5911
A17: F16 | B17: Sreeja Sudharma | K17: =SUM(C17,E17,G17,I17) -> 0
A18: G1 | B18: Venkataramanan C | C18: 5603 | D18: 45947 | K18: =SUM(C18,E18,G18,I18) -> 5603
A19: G2 | B19: Kaushik Kasibhatla | C19: 7311.21 | D19: 45952 | K19: =SUM(C19,E19,G19,I19) -> 7311.21
A20: G3 | B20: Balakrishnan | C20: 5742 | D20: 45953 | K20: =SUM(C20,E20,G20,I20) -> 5742
A21: G4 | B21: Ashwin Pandith | C21: 6287 | D21: 45946 | K21: =SUM(C21,E21,G21,I21) -> 6287
A22: G5 | B22: Mayank Phophaliya | C22: 6000 | D22: 45953 | K22: =SUM(C22,E22,G22,I22) -> 6000
A23: G6 | B23: Mohit Daga | K23: =SUM(C23,E23,G23,I23) -> 0
A24: G7 | B24: Prince Richfield | C24: 5264 | D24: 45951 | K24: =SUM(C24,E24,G24,I24) -> 5264
A25: G8 | B25: Ranjithkumar R / Sameer (tenant) / Princy (tenant) | K25: =SUM(C25,E25,G25,I25) -> 0
A26: G9 | B26: Ankur Agarwal | C26: 5500 | D26: 45941 | K26: =SUM(C26,E26,G26,I26) -> 5500
A27: G10 | B27: Cijo Jacob / Thara Joy | K27: =SUM(C27,E27,G27,I27) -> 0
A28: G11 | B28: Ketan Verlekar | C28: 4935 | D28: 45945 | K28: =SUM(C28,E28,G28,I28) -> 4935
A29: G12 | B29: Shyam Nair | C29: 4978 | D29: 45956 | K29: =SUM(C29,E29,G29,I29) -> 4978
A30: G13 | B30: Ajai.B | K30: =SUM(C30,E30,G30,I30) -> 0
A31: G14 | B31: Surajit Borah | C31: 5304 | D31: 45945 | K31: =SUM(C31,E31,G31,I31) -> 5304
A32: G15 | B32: Suresh Nallusamy / Antriksh (tenant) | K32: =SUM(C32,E32,G32,I32) -> 0
A33: G16 | B33: Praveen Ganesan | C33: 4944 | D33: 45953 | K33: =SUM(C33,E33,G33,I33) -> 4944
A34: S1 | B34: S.N.Behera | C34: 4841.04 | D34: 45943 | K34: =SUM(C34,E34,G34,I34) -> 4841.04
A35: S2 | B35: Sonal Singh | K35: =SUM(C35,E35,G35,I35) -> 0
A36: S3 | B36: Koteswararao | C36: 4997 | D36: 45952 | K36: =SUM(C36,E36,G36,I36) -> 4997
A37: S4 | B37: Swaminathan | K37: =SUM(C37,E37,G37,I37) -> 0
A38: S5 | B38: Abhishek Gopalakrishnan | C38: 4935 | D38: 45950 | K38: =SUM(C38,E38,G38,I38) -> 4935
A39: S6 | B39: Vivek Dhingra / Pratyush Das | K39: =SUM(C39,E39,G39,I39) -> 0
A40: S7 | B40: Harish B | C40: 4741 | D40: 45955 | K40: =SUM(C40,E40,G40,I40) -> 4741
A41: S8 | B41: Irudayaraj Alwin | C41: 5862.45 | D41: 45956 | K41: =SUM(C41,E41,G41,I41) -> 5862.45
A42: S9 | B42: Pawan GS | C42: 5205 | D42: 45947 | K42: =SUM(C42,E42,G42,I42) -> 5205
A43: S10 | B43: Lakshmikanth | K43: =SUM(C43,E43,G43,I43) -> 0
A44: S11 | B44: Gowrish Patnaik / Somananth GM | C44: 5151 | D44: 45945 | K44: =SUM(C44,E44,G44,I44) -> 5151
A45: S12 | B45: Saovik Mondal | K45: =SUM(C45,E45,G45,I45) -> 0
A46: S13 | B46: Ramadevi S. | C46: 5067 | D46: 45946 | K46: =SUM(C46,E46,G46,I46) -> 5067
A47: S14 | B47: Nishant Upadhyay(Owner)/ Fabian (Tenant) | C47: 17240 | D47: 45933 | K47: =SUM(C47,E47,G47,I47) -> 17240
A48: S15 | B48: Manas Dasgupta | C48: 6032 | D48: 45944 | K48: =SUM(C48,E48,G48,I48) -> 6032
A49: S16 | B49: Devendra Singh Rawat / Nancy | C49: 5084 | D49: 45943 | K49: =SUM(C49,E49,G49,I49) -> 5084
A50: T1 | B50: Prashant Sikdar | C50: 6026 | D50: 45943 | K50: =SUM(C50,E50,G50,I50) -> 6026
A51: T2 | B51: Kunal Mehta | C51: 5775 | D51: 45953 | K51: =SUM(C51,E51,G51,I51) -> 5775
A52: T3 | B52: Kapil Garg | C52: 5605 | D52: 45944 | K52: =SUM(C52,E52,G52,I52) -> 5605
A53: T4 | B53: Vijet Alva (Owner) - Masood (Tenant) | K53: =SUM(C53,E53,G53,I53) -> 0
A54: T5 | B54: Ganesh Iyer and Latha Iyer( owner) Richa (Tenant) | C54: 4776 | D54: 45955 | K54: =SUM(C54,E54,G54,I54) -> 4776
A55: T6 | B55: Mythili Ramesh | C55: 6296 | D55: 45943 | K55: =SUM(C55,E55,G55,I55) -> 6296
A56: T7 | B56: Vinyas Ramachandra / Shwetha Marnamikatta / Katari Siva Rama Raju | K56: =SUM(C56,E56,G56,I56) -> 0
A57: T8 | B57: Lalit Kumar Sharma | C57: 4881 | D57: 45955 | K57: =SUM(C57,E57,G57,I57) -> 4881
A58: T9 | B58: Nishith Sahu and Priyanka Rani (Owner)/ Anmol Verma (Tenant) | C58: 5245 | D58: 45944 | K58: =SUM(C58,E58,G58,I58) -> 5245
A59: T10 | B59: Vamsidhar Bethanabatla / Madhuri Anumula | C59: 5796 | D59: 45944 | K59: =SUM(C59,E59,G59,I59) -> 5796
A60: T11 | B60: Arvind Balasubramanian | C60: 5176 | D60: 45943 | K60: =SUM(C60,E60,G60,I60) -> 5176
A61: T12 | B61: Prasenjit | C61: 4826.82 | D61: 45943 | K61: =SUM(C61,E61,G61,I61) -> 4826.82
A62: T13 | B62: Rahul Kumar | C62: 12000 | D62: 45931 | K62: =SUM(C62,E62,G62,I62) -> 12000
A63: T14 | B63: Jeya / Kanda / Satya (tenant)/Vinuta (tenant) | C63: 5237 | D63: 45959 | K63: =SUM(C63,E63,G63,I63) -> 5237
A64: T15 | B64: Trevor | C64: 5511 | D64: 45960 | K64: =SUM(C64,E64,G64,I64) -> 5511
A65: T16 | B65: Madhusoodanan P.R. | C65: 5154 | D65: 45957 | K65: =SUM(C65,E65,G65,I65) -> 5154
A66: TOTAL | K66: =SUM(K2:K65) -> 276048.51

Sheet Nov2025-EXPENSE
B1: NOVEMBER 2025 EXPENSES
A2: FLAT # | B2: 1 | C2: WATER USED IN LTRS | D2: COMMON AREA EQUALLY DEVIDED | E2: TOTAL FRESH WATER CONSUMED | F2: %OF TOTAL USED | G2: WATER EXPENSE SHARING BY % | H2: #METERS | I2: METER RENT | J2: COMMON AREA METER RENT + WATER EXPENSE+ FLAT METER RENT | K2: FIXED EXPENSE SHARE | L2: PARKING FEE | M2: CLUB BOOKING FEE | N2: SHIFTING FEE | O2: GYM USAGE FEE | P2: OWNERSHIP TRANSFER FEE | R2: TOTAL EXPENSE TO BE PAID
A3: CH | B3: MPFOWA | C3: 17.5 | D3: 0 | H3: 1 | I3: =T7 -> 117.81166
A4: GYM | B4: MPFOWA | C4: 7930 | D4: 0 | H4: 1 | I4: =T7 -> 117.81166 | S4: TOTAL FIXED EXPENSE | T4: ='ANNUAL-EXPENSE-DETAILS'!BF10 -> 389962
A5: BSMT | B5: MPFOWA | D5: 0 | H5: 1 | I5: =T7 -> 117.81166 | S5: TOTAL WATER EXPENSE | T5: ='ANNUAL-EXPENSE-DETAILS'!BE10 -> 39800
A6: F1 | B6: Shailesh Srivastava / Azeem Nawaz | C6: 1643.5 | D6: =SUM($C$3:$C$5)/64 -> 124.17969 | E6: =C6+D6 -> 1767.6797 | F6: =IF($C$70=0, 0, E6/$C$70) -> 0.0043010128 | G6: =F6*$T$5 -> 171.18031 | H6: 3 | I6: =$T$7*H6 -> 353.43498 | J6: =G6+$T$9+I6 -> 530.13771 | K6: =$T$11/64 -> 6093.1562 | L6: 0 | M6: 0 | N6: 0 | O6: 0 | R6: =(J6+K6+L6+M6+N6+O6)*$B$2 -> 6623.294
A7: F2 | B7: Shanthanu | C7: 6154 | D7: =SUM($C$3:$C$5)/64 -> 124.17969 | E7: =C7+D7 -> 6278.1797 | F7: =IF($C$70=0, 0, E7/$C$70) -> 0.015275692 | G7: =F7*$T$5 -> 607.97255 | H7: 4 | I7: =$T$7*H7 -> 471.24664 | J7: =G7+$T$9+I7 -> 1084.7416 | K7: =$T$11/64 -> 6093.1562 | L7: 0 | M7: 0 | N7: 0 | O7: 0 | R7: =(J7+K7+L7+M7+N7+O7)*$B$2 -> 7177.8979 | S7: RENT PER METER | T7: 117.81166
A8: F3 | B8: Samrat Kar | C8: 12942 | D8: =SUM($C$3:$C$5)/64 -> 124.17969 | E8: =C8+D8 -> 13066.18 | F8: =IF($C$70=0, 0, E8/$C$70) -> 0.031791849 | G8: =F8*$T$5 -> 1265.3156 | H8: 4 | I8: =$T$7*H8 -> 471.24664 | J8: =G8+$T$9+I8 -> 1742.0846 | K8: =$T$11/64 -> 6093.1562 | L8: 750 | M8: 0 | N8: 0 | O8: 0 | R8: =(J8+K8+L8+M8+N8+O8)*$B$2 -> 8585.2409 | S8: COMMON AREA METER RENT | T8: =$T$7*3 -> 353.43498
A9: F4 | B9: Renu R | C9: 4134 | D9: =SUM($C$3:$C$5)/64 -> 124.17969 | E9: =C9+D9 -> 4258.1797 | F9: =IF($C$70=0, 0, E9/$C$70) -> 0.010360749 | G9: =F9*$T$5 -> 412.3578 | H9: 4 | I9: =$T$7*H9 -> 471.24664 | J9: =G9+$T$9+I9 -> 889.12686 | K9: =$T$11/64 -> 6093.1562 | L9: 0 | M9: 0 | N9: 0 | O9: 0 | R9: =(J9+K9+L9+M9+N9+O9)*$B$2 -> 6982.2831 | S9: COMMON AREA METER RENT/FLAT | T9: =T8/64 -> 5.5224215
A10: F5 | B10: Vamsidhar Bethanabatla / Madhuri Anumula | C10: 5409.5 | D10: =SUM($C$3:$C$5)/64 -> 124.17969 | E10: =C10+D10 -> 5533.6797 | F10: =IF($C$70=0, 0, E10/$C$70) -> 0.013464219 | G10: =F10*$T$5 -> 535.87593 | H10: 3 | I10: =$T$7*H10 -> 353.43498 | J10: =G10+$T$9+I10 -> 894.83333 | K10: =$T$11/64 -> 6093.1562 | L10: 0 | M10: 0 | N10: 0 | O10: 0 | R10: =(J10+K10+L10+M10+N10+O10)*$B$2 -> 6987.9896
A11: F6 | B11: Meghana Viral Shah and Vviral Shah (Owner) / Sangeet and Swagat (Tenent) | C11: 5463.5 | D11: =SUM($C$3:$C$5)/64 -> 124.17969 | E11: =C11+D11 -> 5587.6797 | F11: =IF($C$70=0, 0, E11/$C$70) -> 0.013595609 | G11: =F11*$T$5 -> 541.10523 | H11: 3 | I11: =$T$7*H11 -> 353.43498 | J11: =G11+$T$9+I11 -> 900.06263 | K11: =$T$11/64 -> 6093.1562 | L11: 0 | M11: 0 | N11: 0 | O11: 0 | R11: =(J11+K11+L11+M11+N11+O11)*$B$2 -> 6993.2189 | S11: TOTAL FIXED EXPENSE | T11: ='ANNUAL-EXPENSE-DETAILS'!BF10 -> 389962
A12: F7 | B12: Vimal NK | C12: 67.5 | D12: =SUM($C$3:$C$5)/64 -> 124.17969 | E12: =C12+D12 -> 191.67969 | F12: =IF($C$70=0, 0, E12/$C$70) -> 0.00046638358 | G12: =F12*$T$5 -> 18.562067 | H12: 3 | I12: =$T$7*H12 -> 353.43498 | J12: =G12+$T$9+I12 -> 377.51947 | K12: =$T$11/64 -> 6093.1562 | L12: 750 | M12: 0 | N12: 0 | O12: 0 | R12: =(J12+K12+L12+M12+N12+O12)*$B$2 -> 7220.6757
A13: F8 | B13: Sujeet Kumar (Tenant)/Sreejith Menon (Owner) | C13: 10153.5 | D13: =SUM($C$3:$C$5)/64 -> 124.17969 | E13: =C13+D13 -> 10277.68 | F13: =IF($C$70=0, 0, E13/$C$70) -> 0.025007037 | G13: =F13*$T$5 -> 995.28008 | H13: 3 | I13: =$T$7*H13 -> 353.43498 | J13: =G13+$T$9+I13 -> 1354.2375 | K13: =$T$11/64 -> 6093.1562 | L13: 0 | M13: 0 | N13: 0 | O13: 0 | R13: =(J13+K13+L13+M13+N13+O13)*$B$2 -> 7447.3937
A14: F9 | B14: Vijay Suswaram (Owner) / Divya Shikha (Tenant) | C14: 1753.5 | D14: =SUM($C$3:$C$5)/64 -> 124.17969 | E14: =C14+D14 -> 1877.6797 | F14: =IF($C$70=0, 0, E14/$C$70) -> 0.0045686582 | G14: =F14*$T$5 -> 181.8326 | H14: 4 | I14: =$T$7*H14 -> 471.24664 | J14: =G14+$T$9+I14 -> 658.60165 | K14: =$T$11/64 -> 6093.1562 | L14: 0 | M14: 0 | N14: 0 | O14: 0 | R14: =(J14+K14+L14+M14+N14+O14)*$B$2 -> 6751.7579 | S14: TOTAL WATER METER RENT | T14: =CEILING( I70,1) -> 26272
A15: F10 | B15: Aby Thomas | C15: 2803 | D15: =SUM($C$3:$C$5)/64 -> 124.17969 | E15: =C15+D15 -> 2927.1797 | F15: =IF($C$70=0, 0, E15/$C$70) -> 0.007122239 | G15: =F15*$T$5 -> 283.46511 | H15: 3 | I15: =$T$7*H15 -> 353.43498 | J15: =G15+$T$9+I15 -> 642.42251 | K15: =$T$11/64 -> 6093.1562 | L15: 0 | M15: 0 | N15: 0 | O15: 0 | R15: =(J15+K15+L15+M15+N15+O15)*$B$2 -> 6735.5788
A16: F11 | B16: Niwin Anto | C16: 596 | D16: =SUM($C$3:$C$5)/64 -> 124.17969 | E16: =C16+D16 -> 720.17969 | F16: =IF($C$70=0, 0, E16/$C$70) -> 0.0017522983 | G16: =F16*$T$5 -> 69.74147 | H16: 3 | I16: =$T$7*H16 -> 353.43498 | J16: =G16+$T$9+I16 -> 428.69887 | K16: =$T$11/64 -> 6093.1562 | L16: 0 | M16: 0 | N16: 0 | O16: 0 | R16: =(J16+K16+L16+M16+N16+O16)*$B$2 -> 6521.8551 | S16: BALANCE IN ACCOUNT ON 30-NOV-2023
A17: F12 | B17: Anirudh Singh | C17: 7938 | D17: =SUM($C$3:$C$5)/64 -> 124.17969 | E17: =C17+D17 -> 8062.1797 | F17: =IF($C$70=0, 0, E17/$C$70) -> 0.019616415 | G17: =F17*$T$5 -> 780.7333 | H17: 3 | I17: =$T$7*H17 -> 353.43498 | J17: =G17+$T$9+I17 -> 1139.6907 | K17: =$T$11/64 -> 6093.1562 | L17: 0 | M17: 0 | N17: 0 | O17: 0 | R17: =(J17+K17+L17+M17+N17+O17)*$B$2 -> 7232.847 | S17: TOTAL NON MAINTENANCE CORPUS COLLECTION
A18: F13 | B18: Sanchay Saxena | C18: 5060 | D18: =SUM($C$3:$C$5)/64 -> 124.17969 | E18: =C18+D18 -> 5184.1797 | F18: =IF($C$70=0, 0, E18/$C$70) -> 0.012613837 | G18: =F18*$T$5 -> 502.0307 | H18: 4 | I18: =$T$7*H18 -> 471.24664 | J18: =G18+$T$9+I18 -> 978.79976 | K18: =$T$11/64 -> 6093.1562 | L18: 0 | M18: 0 | N18: 0 | O18: 0 | R18: =(J18+K18+L18+M18+N18+O18)*$B$2 -> 7071.956 | S18: TOTAL FD DONE
A19: F14 | B19: Hemant Patel | C19: 5375 | D19: =SUM($C$3:$C$5)/64 -> 124.17969 | E19: =C19+D19 -> 5499.1797 | F19: =IF($C$70=0, 0, E19/$C$70) -> 0.013380276 | G19: =F19*$T$5 -> 532.53498 | H19: 4 | I19: =$T$7*H19 -> 471.24664 | J19: =G19+$T$9+I19 -> 1009.304 | K19: =$T$11/64 -> 6093.1562 | L19: 0 | M19: 0 | N19: 0 | O19: 0 | R19: =(J19+K19+L19+M19+N19+O19)*$B$2 -> 7102.4603 | S19: AMOUNT AVAILABLE FOR NON MAINTENANCE CORPUS IN CURRENT AC | T19: =T17-T18 -> 0
A20: F15 | B20: Senthil.Vijayaragavan | C20: 2321 | D20: =SUM($C$3:$C$5)/64 -> 124.17969 | E20: =C20+D20 -> 2445.1797 | F20: =IF($C$70=0, 0, E20/$C$70) -> 0.0059494653 | G20: =F20*$T$5 -> 236.78872 | H20: 4 | I20: =$T$7*H20 -> 471.24664 | J20: =G20+$T$9+I20 -> 713.55778 | K20: =$T$11/64 -> 6093.1562 | L20: 750 | M20: 0 | N20: 0 | O20: 0 | R20: =(J20+K20+L20+M20+N20+O20)*$B$2 -> 7556.714 | S20: AMOUNT AVAILABLE FOR MAINTENANCE | T20: =T16-T19 -> 0
A21: F16 | B21: Sreeja Sudharma | C21: 13770 | D21: =SUM($C$3:$C$5)/64 -> 124.17969 | E21: =C21+D21 -> 13894.18 | F21: =IF($C$70=0, 0, E21/$C$70) -> 0.033806489 | G21: =F21*$T$5 -> 1345.4983 | H21: 3 | I21: =$T$7*H21 -> 353.43498 | J21: =G21+$T$9+I21 -> 1704.4557 | K21: =$T$11/64 -> 6093.1562 | L21: 0 | M21: 0 | N21: 0 | O21: 0 | R21: =(J21+K21+L21+M21+N21+O21)*$B$2 -> 7797.6119 | S21: TOTAL EXPENSE FOR THE MONTH | T21: ='ANNUAL-EXPENSE-DETAILS'!BH10 -> 456034
A22: G1 | B22: Venkataramanan C | C22: 7123 | D22: =SUM($C$3:$C$5)/64 -> 124.17969 | E22: =C22+D22 -> 7247.1797 | F22: =IF($C$70=0, 0, E22/$C$70) -> 0.017633405 | G22: =F22*$T$5 -> 701.80953 | H22: 3 | I22: =$T$7*H22 -> 353.43498 | J22: =G22+$T$9+I22 -> 1060.7669 | K22: =$T$11/64 -> 6093.1562 | L22: 0 | M22: 0 | N22: 0 | O22: 0 | R22: =(J22+K22+L22+M22+N22+O22)*$B$2 -> 7153.9232
A23: G2 | B23: Kaushik Kasibhatla | C23: 16075.5 | D23: =SUM($C$3:$C$5)/64 -> 124.17969 | E23: =C23+D23 -> 16199.68 | F23: =IF($C$70=0, 0, E23/$C$70) -> 0.039416094 | G23: =F23*$T$5 -> 1568.7605 | H23: 4 | I23: =$T$7*H23 -> 471.24664 | J23: =G23+$T$9+I23 -> 2045.5296 | K23: =$T$11/64 -> 6093.1562 | L23: 0 | M23: 0 | N23: 0 | O23: 0 | R23: =(J23+K23+L23+M23+N23+O23)*$B$2 -> 8138.6859
A24: G3 | B24: Balakrishnan | C24: 7276.5 | D24: =SUM($C$3:$C$5)/64 -> 124.17969 | E24: =C24+D24 -> 7400.6797 | F24: =IF($C$70=0, 0, E24/$C$70) -> 0.018006892 | G24: =F24*$T$5 -> 716.67431 | H24: 4 | I24: =$T$7*H24 -> 471.24664 | J24: =G24+$T$9+I24 -> 1193.4434 | K24: =$T$11/64 -> 6093.1562 | L24: 0 | M24: 0 | N24: 0 | O24: 0 | R24: =(J24+K24+L24+M24+N24+O24)*$B$2 -> 7286.5996
A25: G4 | B25: Ashwin Pandith | C25: 14066 | D25: =SUM($C$3:$C$5)/64 -> 124.17969 | E25: =C25+D25 -> 14190.18 | F25: =IF($C$70=0, 0, E25/$C$70) -> 0.034526699 | G25: =F25*$T$5 -> 1374.1626 | H25: 4 | I25: =$T$7*H25 -> 471.24664 | J25: =G25+$T$9+I25 -> 1850.9317 | K25: =$T$11/64 -> 6093.1562 | L25: 0 | M25: 0 | N25: 0 | O25: 0 | R25: =(J25+K25+L25+M25+N25+O25)*$B$2 -> 7944.0879
A26: G5 | B26: Mayank Phophaliya | C26: 4783 | D26: =SUM($C$3:$C$5)/64 -> 124.17969 | E26: =C26+D26 -> 4907.1797 | F26: =IF($C$70=0, 0, E26/$C$70) -> 0.011939857 | G26: =F26*$T$5 -> 475.2063 | H26: 3 | I26: =$T$7*H26 -> 353.43498 | J26: =G26+$T$9+I26 -> 834.1637 | K26: =$T$11/64 -> 6093.1562 | L26: 0 | M26: 0 | N26: 0 | O26: 0 | R26: =(J26+K26+L26+M26+N26+O26)*$B$2 -> 6927.32
A27: G6 | B27: Mohit Daga | C27: 3536.5 | D27: =SUM($C$3:$C$5)/64 -> 124.17969 | E27: =C27+D27 -> 3660.6797 | F27: =IF($C$70=0, 0, E27/$C$70) -> 0.0089069474 | G27: =F27*$T$5 -> 354.49651 | H27: 3 | I27: =$T$7*H27 -> 353.43498 | J27: =G27+$T$9+I27 -> 713.45391 | K27: =$T$11/64 -> 6093.1562 | L27: 0 | M27: 0 | N27: 0 | O27: 0 | R27: =(J27+K27+L27+M27+N27+O27)*$B$2 -> 6806.6102
A28: G7 | B28: Prince Richfield | C28: 3014.5 | D28: =SUM($C$3:$C$5)/64 -> 124.17969 | E28: =C28+D28 -> 3138.6797 | F28: =IF($C$70=0, 0, E28/$C$70) -> 0.0076368482 | G28: =F28*$T$5 -> 303.94656 | H28: 3 | I28: =$T$7*H28 -> 353.43498 | J28: =G28+$T$9+I28 -> 662.90396 | K28: =$T$11/64 -> 6093.1562 | L28: 0 | M28: 0 | N28: 0 | O28: 0 | R28: =(J28+K28+L28+M28+N28+O28)*$B$2 -> 6756.0602
A29: G8 | B29: Ranjithkumar R / Sameer (tenant) / Princy (tenant) | C29: 9028 | D29: =SUM($C$3:$C$5)/64 -> 124.17969 | E29: =C29+D29 -> 9152.1797 | F29: =IF($C$70=0, 0, E29/$C$70) -> 0.022268538 | G29: =F29*$T$5 -> 886.2878 | H29: 3 | I29: =$T$7*H29 -> 353.43498 | J29: =G29+$T$9+I29 -> 1245.2452 | K29: =$T$11/64 -> 6093.1562 | L29: 0 | M29: 0 | N29: 0 | O29: 0 | R29: =(J29+K29+L29+M29+N29+O29)*$B$2 -> 7338.4014
A30: G9 | B30: Chandramouli | C30: 3402.5 | D30: =SUM($C$3:$C$5)/64 -> 124.17969 | E30: =C30+D30 -> 3526.6797 | F30: =IF($C$70=0, 0, E30/$C$70) -> 0.0085809066 | G30: =F30*$T$5 -> 341.52008 | H30: 5 | I30: =$T$7*H30 -> 589.0583 | J30: =G30+$T$9+I30 -> 936.1008 | K30: =$T$11/64 -> 6093.1562 | L30: 0 | M30: 0 | N30: 0 | O30: 0 | R30: =(J30+K30+L30+M30+N30+O30)*$B$2 -> 7029.2571
A31: G10 | B31: Richa Singh | C31: 2481.5 | D31: =SUM($C$3:$C$5)/64 -> 124.17969 | E31: =C31+D31 -> 2605.6797 | F31: =IF($C$70=0, 0, E31/$C$70) -> 0.0063399844 | G31: =F31*$T$5 -> 252.33138 | H31: 3 | I31: =$T$7*H31 -> 353.43498 | J31: =G31+$T$9+I31 -> 611.28878 | K31: =$T$11/64 -> 6093.1562 | L31: 0 | M31: 0 | N31: 0 | O31: 0 | P31: 1134 | R31: =(J31+K31+L31+M31+N31+O31+P31)*$B$2 -> 7838.445
A32: G11 | B32: Ketan Verlekar | C32: 1688.5 | D32: =SUM($C$3:$C$5)/64 -> 124.17969 | E32: =C32+D32 -> 1812.6797 | F32: =IF($C$70=0, 0, E32/$C$70) -> 0.0044105041 | G32: =F32*$T$5 -> 175.53806 | H32: 3 | I32: =$T$7*H32 -> 353.43498 | J32: =G32+$T$9+I32 -> 534.49546 | K32: =$T$11/64 -> 6093.1562 | L32: 0 | M32: 0 | N32: 0 | O32: 0 | R32: =(J32+K32+L32+M32+N32+O32)*$B$2 -> 6627.6517
A33: G12 | B33: Shyam Nair | C33: 14346.5 | D33: =SUM($C$3:$C$5)/64 -> 124.17969 | E33: =C33+D33 -> 14470.68 | F33: =IF($C$70=0, 0, E33/$C$70) -> 0.035209195 | G33: =F33*$T$5 -> 1401.3259 | H33: 3 | I33: =$T$7*H33 -> 353.43498 | J33: =G33+$T$9+I33 -> 1760.2833 | K33: =$T$11/64 -> 6093.1562 | L33: 0 | M33: 0 | N33: 0 | O33: 0 | R33: =(J33+K33+L33+M33+N33+O33)*$B$2 -> 7853.4396
A34: G13 | B34: Ajai.B | C34: 12069 | D34: =SUM($C$3:$C$5)/64 -> 124.17969 | E34: =C34+D34 -> 12193.18 | F34: =IF($C$70=0, 0, E34/$C$70) -> 0.029667717 | G34: =F34*$T$5 -> 1180.7752 | H34: 4 | I34: =$T$7*H34 -> 471.24664 | J34: =G34+$T$9+I34 -> 1657.5442 | K34: =$T$11/64 -> 6093.1562 | L34: 0 | M34: 0 | N34: 0 | O34: 0 | R34: =(J34+K34+L34+M34+N34+O34)*$B$2 -> 7750.7005
A35: G14 | B35: Surajit Borah | C35: 7255 | D35: =SUM($C$3:$C$5)/64 -> 124.17969 | E35: =C35+D35 -> 7379.1797 | F35: =IF($C$70=0, 0, E35/$C$70) -> 0.01795458 | G35: =F35*$T$5 -> 714.59228 | H35: 4 | I35: =$T$7*H35 -> 471.24664 | J35: =G35+$T$9+I35 -> 1191.3613 | K35: =$T$11/64 -> 6093.1562 | L35: 0 | M35: 0 | N35: 0 | O35: 0 | R35: =(J35+K35+L35+M35+N35+O35)*$B$2 -> 7284.5176
A36: G15 | B36: Suresh Nallusamy / Antriksh (tenant) | C36: 10256 | D36: =SUM($C$3:$C$5)/64 -> 124.17969 | E36: =C36+D36 -> 10380.18 | F36: =IF($C$70=0, 0, E36/$C$70) -> 0.025256434 | G36: =F36*$T$5 -> 1005.2061 | H36: 4 | I36: =$T$7*H36 -> 471.24664 | J36: =G36+$T$9+I36 -> 1481.9751 | K36: =$T$11/64 -> 6093.1562 | L36: 0 | M36: 0 | N36: 0 | O36: 0 | R36: =(J36+K36+L36+M36+N36+O36)*$B$2 -> 7575.1314
A37: G16 | B37: Praveen Ganesan | C37: 3014 | D37: =SUM($C$3:$C$5)/64 -> 124.17969 | E37: =C37+D37 -> 3138.1797 | F37: =IF($C$70=0, 0, E37/$C$70) -> 0.0076356316 | G37: =F37*$T$5 -> 303.89814 | H37: 3 | I37: =$T$7*H37 -> 353.43498 | J37: =G37+$T$9+I37 -> 662.85554 | K37: =$T$11/64 -> 6093.1562 | L37: 0 | M37: 0 | N37: 0 | O37: 0 | R37: =(J37+K37+L37+M37+N37+O37)*$B$2 -> 6756.0118
A38: S1 | B38: S.N.Behera | C38: 7224.5 | D38: =SUM($C$3:$C$5)/64 -> 124.17969 | E38: =C38+D38 -> 7348.6797 | F38: =IF($C$70=0, 0, E38/$C$70) -> 0.017880369 | G38: =F38*$T$5 -> 711.63869 | H38: 3 | I38: =$T$7*H38 -> 353.43498 | J38: =G38+$T$9+I38 -> 1070.5961 | K38: =$T$11/64 -> 6093.1562 | L38: 0 | M38: 0 | N38: 0 | O38: 0 | R38: =(J38+K38+L38+M38+N38+O38)*$B$2 -> 7163.7523
A39: S2 | B39: Sonal Singh | C39: 24430 | D39: =SUM($C$3:$C$5)/64 -> 124.17969 | E39: =C39+D39 -> 24554.18 | F39: =IF($C$70=0, 0, E39/$C$70) -> 0.059743765 | G39: =F39*$T$5 -> 2377.8019 | H39: 4 | I39: =$T$7*H39 -> 471.24664 | J39: =G39+$T$9+I39 -> 2854.5709 | K39: =$T$11/64 -> 6093.1562 | L39: 0 | M39: 0 | N39: 0 | O39: 0 | R39: =(J39+K39+L39+M39+N39+O39)*$B$2 -> 8947.7272
A40: S3 | B40: Koteswararao | C40: 1871.5 | D40: =SUM($C$3:$C$5)/64 -> 124.17969 | E40: =C40+D40 -> 1995.6797 | F40: =IF($C$70=0, 0, E40/$C$70) -> 0.0048557688 | G40: =F40*$T$5 -> 193.2596 | H40: 4 | I40: =$T$7*H40 -> 471.24664 | J40: =G40+$T$9+I40 -> 670.02865 | K40: =$T$11/64 -> 6093.1562 | L40: 0 | M40: 0 | N40: 0 | O40: 0 | R40: =(J40+K40+L40+M40+N40+O40)*$B$2 -> 6763.1849
A41: S4 | B41: Swaminathan | C41: 12639.5 | D41: =SUM($C$3:$C$5)/64 -> 124.17969 | E41: =C41+D41 -> 12763.68 | F41: =IF($C$70=0, 0, E41/$C$70) -> 0.031055824 | G41: =F41*$T$5 -> 1236.0218 | H41: 3 | I41: =$T$7*H41 -> 353.43498 | J41: =G41+$T$9+I41 -> 1594.9792 | K41: =$T$11/64 -> 6093.1562 | L41: 0 | M41: 0 | N41: 0 | O41: 0 | R41: =(J41+K41+L41+M41+N41+O41)*$B$2 -> 7688.1354
A42: S5 | B42: Abhishek Gopalakrishnan | C42: 850 | D42: =SUM($C$3:$C$5)/64 -> 124.17969 | E42: =C42+D42 -> 974.17969 | F42: =IF($C$70=0, 0, E42/$C$70) -> 0.0023703159 | G42: =F42*$T$5 -> 94.338573 | H42: 3 | I42: =$T$7*H42 -> 353.43498 | J42: =G42+$T$9+I42 -> 453.29597 | K42: =$T$11/64 -> 6093.1562 | L42: 0 | M42: 0 | N42: 0 | O42: 0 | R42: =(J42+K42+L42+M42+N42+O42)*$B$2 -> 6546.4522
A43: S6 | B43: Vivek Dhingra / Pratyush Das | C43: 1.5 | D43: =SUM($C$3:$C$5)/64 -> 124.17969 | E43: =C43+D43 -> 125.67969 | F43: =IF($C$70=0, 0, E43/$C$70) -> 0.00030579632 | G43: =F43*$T$5 -> 12.170693 | H43: 3 | I43: =$T$7*H43 -> 353.43498 | J43: =G43+$T$9+I43 -> 371.12809 | K43: =$T$11/64 -> 6093.1562 | L43: 0 | M43: 0 | N43: 0 | O43: 0 | R43: =(J43+K43+L43+M43+N43+O43)*$B$2 -> 6464.2843
... A69: T16 | B69: Madhusoodanan P.R. | C69: 7010 | D69: =SUM($C$3:$C$5)/64 -> 124.17969 | E69: =C69+D69 -> 7134.1797 | F69: =IF($C$70=0, 0, E69/$C$70) -> 0.01735846 | G69: =F69*$T$5 -> 690.86672 | H69: 3 | I69: =$T$7*H69 -> 353.43498 | J69: =G69+$T$9+I69 -> 1049.8241 | K69: =$T$11/64 -> 6093.1562 | L69: 0 | M69: 0 | N69: 0 | O69: 0 | R69: =(J69+K69+L69+M69+N69+O69)*$B$2 -> 7142.9804
B70: TOTAL | C70: =SUM(C3:C69) -> 410991.5 | D70: =SUM(D3:D69) -> 7947.5 | E70: =SUM(E3:E69) -> 410991.5 | F70: =IF($C$70=0, 0, E70/$C$70) -> 1 | G70: =SUM(G3:G69) -> 39800 | H70: =SUM(H3:H69) -> 223 | I70: =SUM(I3:I69) -> 26272 | J70: =SUM(J3:J69) -> 66072 | K70: =SUM(K3:K69) -> 389962 | L70: =SUM(L3:L69) -> 3000 | M70: =SUM(M3:M69) -> 0 | N70: =SUM(N3:N69) -> 0 | O70: =SUM(O3:O69) -> 0 | R70: =SUM(R3:R69) -> 460168

Sheet Nov2025-COLLECTION
A1: FLAT # | C1: Amount | D1: Date | E1: Amount | F1: Date | G1: Amount | H1: Date | I1: Amount | J1: Date | K1: Total
A2: F1 | B2: Shailesh Srivastava / Azeem Nawaz | K2: =SUM(C2,E2,G2,I2) -> 0
A3: F2 | B3: Shanthanu | K3: =SUM(C3,E3,G3,I3) -> 0
A4: F3 | B4: Samrat Kar | C4: 6000 | D4: 45962 | K4: =SUM(C4,E4,G4,I4) -> 6000
A5: F4 | B5: Renu R | C5: 6231 | D5: 45977 | K5: =SUM(C5,E5,G5,I5) -> 6231
A6: F5 | B6: Vamsidhar Bethanabatla / Madhuri Anumula / Pulkit Gupta | C6: 6114 | D6: 45977 | K6: =SUM(C6,E6,G6,I6) -> 6114
A7: F6 | B7: Meghana Viral Shah and Vviral Shah (Owner) / Sangeet and Swagat (Tenent) | K7: =SUM(C7,E7,G7,I7) -> 0
A8: F7 | B8: Vimal NK | C8: 5505 | D8: 45966 | K8: =SUM(C8,E8,G8,I8) -> 5505
A9: F8 | B9: Sreejith Menon (Owner) | C9: 6114 | D9: 45978 | K9: =SUM(C9,E9,G9,I9) -> 6114
A10: F9 | B10: Vijay Suswaram (Owner) / Divya Shikha (Tenant) | C10: 6231 | D10: 45985 | K10: =SUM(C10,E10,G10,I10) -> 6231
A11: F10 | B11: Aby Thomas | K11: =SUM(C11,E11,G11,I11) -> 0
A12: F11 | B12: Geetha. N | C12: 6114 | D12: 45979 | K12: =SUM(C12,E12,G12,I12) -> 6114
A13: F12 | B13: Anirudh Singh | C13: 6114 | D13: 45978 | K13: =SUM(C13,E13,G13,I13) -> 6114
A14: F13 | B14: Sanchay Saxena | K14: =SUM(C14,E14,G14,I14) -> 0
A15: F14 | B15: Hemant Patel | C15: 6231 | D15: 45985 | K15: =SUM(C15,E15,G15,I15) -> 6231
A16: F15 | B16: Senthil.Vijayaragavan | C16: 6981 | D16: 45985 | K16: =SUM(C16,E16,G16,I16) -> 6981
A17: F16 | B17: Sreeja Sudharma | K17: =SUM(C17,E17,G17,I17) -> 0
A18: G1 | B18: Venkataramanan C | K18: =SUM(C18,E18,G18,I18) -> 0
A19: G2 | B19: Kaushik Kasibhatla | C19: 6231.38 | D19: 45987 | K19: =SUM(C19,E19,G19,I19) -> 6231.38
A20: G3 | B20: Balakrishnan | C20: 6731 | D20: 45989 | K20: =SUM(C20,E20,G20,I20) -> 6731
A21: G4 | B21: Ashwin Pandith | K21: =SUM(C21,E21,G21,I21) -> 0
A22: G5 | B22: Mayank Phophaliya | C22: 6114 | D22: 45984 | K22: =SUM(C22,E22,G22,I22) -> 6114
A23: G6 | B23: Mohit Daga | K23: =SUM(C23,E23,G23,I23) -> 0
A24: G7 | B24: Prince Richfield | C24: 6114 | D24: 45987 | K24: =SUM(C24,E24,G24,I24) -> 6114
A25: G8 | B25: Ranjithkumar R / Sameer (tenant) / Princy (tenant) | K25: =SUM(C25,E25,G25,I25) -> 0
A26: G9 | B26: Chandramouli | C26: 6354 | D26: 45990 | K26: =SUM(C26,E26,G26,I26) -> 6354
A27: G10 | B27: Cijo Jacob / Thara Joy | C27: 6114 | D27: 45989 | K27: =SUM(C27,E27,G27,I27) -> 6114
A28: G11 | B28: Ketan Verlekar | C28: 6114 | D28: 45979 | K28: =SUM(C28,E28,G28,I28) -> 6114
A29: G12 | B29: Shyam Nair | C29: 6114 | D29: 45988 | K29: =SUM(C29,E29,G29,I29) -> 6114
A30: G13 | B30: Ajai.B | K30: =SUM(C30,E30,G30,I30) -> 0
A31: G14 | B31: Surajit Borah | C31: 6231 | D31: 45980 | K31: =SUM(C31,E31,G31,I31) -> 6231
A32: G15 | B32: Suresh Nallusamy / Antriksh (tenant) | C32: 5011 | D32: 45965 | E32: 6231 | F32: 45987 | K32: =SUM(C32,E32,G32,I32) -> 11242
A33: G16 | B33: Praveen Ganesan | C33: 6114 | D33: 45988 | K33: =SUM(C33,E33,G33,I33) -> 6114
A34: S1 | B34: S.N.Behera | C34: 6114 | D34: 45978 | K34: =SUM(C34,E34,G34,I34) -> 6114
A35: S2 | B35: Sonal Singh | K35: =SUM(C35,E35,G35,I35) -> 0
A36: S3 | B36: Koteswararao | C36: 6231 | D36: 45986 | K36: =SUM(C36,E36,G36,I36) -> 6231
A37: S4 | B37: Swaminathan | C37: 5637 | D37: 45975 | E37: 6114 | F37: 45990 | K37: =SUM(C37,E37,G37,I37) -> 11751
A38: S5 | B38: Abhishek Gopalakrishnan | K38: =SUM(C38,E38,G38,I38) -> 0
A39: S6 | B39: Vivek Dhingra / Pratyush Das | K39: =SUM(C39,E39,G39,I39) -> 0
A40: S7 | B40: Harish B | C40: 6114 | D40: 45986 | K40: =SUM(C40,E40,G40,I40) -> 6114
A41: S8 | B41: Irudayaraj Alwin | C41: 6114 | D41: 45984 | K41: =SUM(C41,E41,G41,I41) -> 6114
A42: S9 | B42: Pawan GS | C42: 6240 | D42: 45978 | K42: =SUM(C42,E42,G42,I42) -> 6240
A43: S10 | B43: Lakshmikanth | K43: =SUM(C43,E43,G43,I43) -> 0
A44: S11 | B44: Gowrish Patnaik / Somananth GM | C44: 6114 | D44: 45988 | K44: =SUM(C44,E44,G44,I44) -> 6114
A45: S12 | B45: Saovik Mondal | C45: 5235 | D45: 45963 | E45: 6114 | F45: 45982 | K45: =SUM(C45,E45,G45,I45) -> 11349
A46: S13 | B46: Ramadevi S. | K46: =SUM(C46,E46,G46,I46) -> 0
A47: S14 | B47: Nishant Upadhyay(Owner)/ Fabian (Tenant) | K47: =SUM(C47,E47,G47,I47) -> 0
A48: S15 | B48: Manas Dasgupta | K48: =SUM(C48,E48,G48,I48) -> 0
A49: S16 | B49: Devendra Singh Rawat / Nancy | C49: 6114 | D49: 45977 | K49: =SUM(C49,E49,G49,I49) -> 6114
A50: T1 | B50: Prashant Sikdar | C50: 6114 | D50: 45982 | K50: =SUM(C50,E50,G50,I50) -> 6114
A51: T2 | B51: Kunal Mehta | K51: =SUM(C51,E51,G51,I51) -> 0
A52: T3 | B52: Kapil Garg | C52: 6231 | D52: 45981 | K52: =SUM(C52,E52,G52,I52) -> 6231
A53: T4 | B53: Vijet Alva (Owner) - Masood (Tenant) | K53: =SUM(C53,E53,G53,I53) -> 0
A54: T5 | B54: Ganesh Iyer and Latha Iyer( owner) Richa (Tenant) | K54: =SUM(C54,E54,G54,I54) -> 0
A55: T6 | B55: Mythili Ramesh | C55: 5634 | D55: 45965 | K55: =SUM(C55,E55,G55,I55) -> 5634
A56: T7 | B56: Vinyas Ramachandra / Shwetha Marnamikatta / Katari Siva Rama Raju | C56: 6114 | D56: 45983 | K56: =SUM(C56,E56,G56,I56) -> 6114
A57: T8 | B57: Lalit Kumar Sharma | C57: 6114 | D57: 45984 | K57: =SUM(C57,E57,G57,I57) -> 6114
A58: T9 | B58: Nishith Sahu and Priyanka Rani (Owner)/ Anmol Verma (Tenant) | C58: 6231 | D58: 45977 | K58: =SUM(C58,E58,G58,I58) -> 6231
A59: T10 | B59: Vamsidhar Bethanabatla / Madhuri Anumula | C59: 6864 | D59: 45977 | K59: =SUM(C59,E59,G59,I59) -> 6864
A60: T11 | B60: Arvind Balasubramanian | C60: 4834 | D60: 45973 | K60: =SUM(C60,E60,G60,I60) -> 4834
A61: T12 | B61: Prasenjit | C61: 6114 | D61: 45978 | K61: =SUM(C61,E61,G61,I61) -> 6114
A62: T13 | B62: Shonali Deokule / Reshma | C62: 12000 | D62: 45965 | K62: =SUM(C62,E62,G62,I62) -> 12000
A63: T14 | B63: Jeya / Kanda / Satya (tenant)/Vinuta (tenant) | C63: 6231 | D63: 45987 | K63: =SUM(C63,E63,G63,I63) -> 6231
A64: T15 | B64: Trevor | K64: =SUM(C64,E64,G64,I64) -> 0
A65: T16 | B65: Madhusoodanan P.R. | K65: =SUM(C65,E65,G65,I65) -> 0
A66: TOTAL | K66: =SUM(K2:K65) -> 273730.38

Sheet Dec2025-EXPENSE
B1: DECEMBER 2025 EXPENSES
A2: FLAT # | B2: 1 | C2: WATER USED IN LTRS | D2: COMMON AREA EQUALLY DEVIDED | E2: TOTAL FRESH WATER CONSUMED | F2: %OF TOTAL USED | G2: WATER EXPENSE SHARING BY % | H2: #METERS | I2: METER RENT | J2: COMMON AREA METER RENT + WATER EXPENSE+ FLAT METER RENT | K2: FIXED EXPENSE SHARE | L2: PARKING FEE | M2: CLUB BOOKING FEE | N2: SHIFTING FEE | O2: GYM USAGE FEE | R2: TOTAL EXPENSE TO BE PAID
A3: CH | B3: MPFOWA | C3: 5.5 | D3: 0 | H3: 1 | I3: =T7 -> 117.81166
A4: GYM | B4: MPFOWA | C4: 32 | D4: 0 | H4: 1 | I4: =T7 -> 117.81166 | S4: TOTAL FIXED EXPENSE | T4: ='ANNUAL-EXPENSE-DETAILS'!BF11 -> 285324
A5: BSMT | B5: MPFOWA | C5: 0 | D5: 0 | H5: 1 | I5: =T7 -> 117.81166 | S5: TOTAL WATER EXPENSE | T5: ='ANNUAL-EXPENSE-DETAILS'!BE11 -> 39800
A6: F1 | B6: Shailesh Srivastava / Azeem Nawaz | C6: 3110 | D6: =SUM($C$3:$C$5)/64 -> 0.5859375 | E6: =C6+D6 -> 3110.5859 | F6: =IF($C$70=0, 0, E6/$C$70) -> 0.0073717817 | G6: =F6*$T$5 -> 293.39691 | H6: 3 | I6: =$T$7*H6 -> 353.43498 | J6: =G6+$T$9+I6 -> 652.35431 | K6: =$T$11/64 -> 4458.1875 | L6: 0 | M6: 0 | N6: 0 | O6: 0 | R6: =(J6+K6+L6+M6+N6+O6)*$B$2 -> 5110.5418
A7: F2 | B7: Shanthanu | C7: 10075.5 | D7: =SUM($C$3:$C$5)/64 -> 0.5859375 | E7: =C7+D7 -> 10076.086 | F7: =IF($C$70=0, 0, E7/$C$70) -> 0.023879329 | G7: =F7*$T$5 -> 950.3973 | H7: 4 | I7: =$T$7*H7 -> 471.24664 | J7: =G7+$T$9+I7 -> 1427.1664 | K7: =$T$11/64 -> 4458.1875 | L7: 0 | M7: 0 | N7: 0 | O7: 0 | R7: =(J7+K7+L7+M7+N7+O7)*$B$2 -> 5885.3539 | S7: RENT PER METER | T7: 117.81166
A8: F3 | B8: Samrat Kar | C8: 13055.5 | D8: =SUM($C$3:$C$5)/64 -> 0.5859375 | E8: =C8+D8 -> 13056.086 | F8: =IF($C$70=0, 0, E8/$C$70) -> 0.030941635 | G8: =F8*$T$5 -> 1231.4771 | H8: 4 | I8: =$T$7*H8 -> 471.24664 | J8: =G8+$T$9+I8 -> 1708.2461 | K8: =$T$11/64 -> 4458.1875 | L8: 750 | M8: 0 | N8: 0 | O8: 0 | R8: =(J8+K8+L8+M8+N8+O8)*$B$2 -> 6916.4336 | S8: COMMON AREA METER RENT | T8: =$T$7*3 -> 353.43498
A9: F4 | B9: Renu R | C9: 3730.5 | D9: =SUM($C$3:$C$5)/64 -> 0.5859375 | E9: =C9+D9 -> 3731.0859 | F9: =IF($C$70=0, 0, E9/$C$70) -> 0.0088423054 | G9: =F9*$T$5 -> 351.92376 | H9: 4 | I9: =$T$7*H9 -> 471.24664 | J9: =G9+$T$9+I9 -> 828.69281 | K9: =$T$11/64 -> 4458.1875 | L9: 0 | M9: 0 | N9: 0 | O9: 0 | R9: =(J9+K9+L9+M9+N9+O9)*$B$2 -> 5286.8803 | S9: COMMON AREA METER RENT/FLAT | T9: =T8/64 -> 5.5224215
A10: F5 | B10: Vamsidhar Bethanabatla / Madhuri Anumula | C10: 5728 | D10: =SUM($C$3:$C$5)/64 -> 0.5859375 | E10: =C10+D10 -> 5728.5859 | F10: =IF($C$70=0, 0, E10/$C$70) -> 0.013576183 | G10: =F10*$T$5 -> 540.3321 | H10: 3 | I10: =$T$7*H10 -> 353.43498 | J10: =G10+$T$9+I10 -> 899.28949 | K10: =$T$11/64 -> 4458.1875 | L10: 0 | M10: 0 | N10: 0 | O10: 0 | R10: =(J10+K10+L10+M10+N10+O10)*$B$2 -> 5357.477
A11: F6 | B11: Meghana Viral Shah and Vviral Shah (Owner) / Sangeet and Swagat (Tenent) | C11: 3612.5 | D11: =SUM($C$3:$C$5)/64 -> 0.5859375 | E11: =C11+D11 -> 3613.0859 | F11: =IF($C$70=0, 0, E11/$C$70) -> 0.0085626571 | G11: =F11*$T$5 -> 340.79375 | H11: 3 | I11: =$T$7*H11 -> 353.43498 | J11: =G11+$T$9+I11 -> 699.75115 | K11: =$T$11/64 -> 4458.1875 | L11: 0 | M11: 0 | N11: 0 | O11: 0 | R11: =(J11+K11+L11+M11+N11+O11)*$B$2 -> 5157.9387 | S11: TOTAL FIXED EXPENSE | T11: ='ANNUAL-EXPENSE-DETAILS'!BF11 -> 285324
A12: F7 | B12: Vimal NK | C12: 19 | D12: =SUM($C$3:$C$5)/64 -> 0.5859375 | E12: =C12+D12 -> 19.585938 | F12: =IF($C$70=0, 0, E12/$C$70) -> 4.6416739e-05 | G12: =F12*$T$5 -> 1.8473862 | H12: 3 | I12: =$T$7*H12 -> 353.43498 | J12: =G12+$T$9+I12 -> 360.80478 | K12: =$T$11/64 -> 4458.1875 | L12: 750 | M12: 0 | N12: 0 | O12: 0 | R12: =(J12+K12+L12+M12+N12+O12)*$B$2 -> 5568.9923
A13: F8 | B13: Sujeet Kumar (Tenant)/Sreejith Menon (Owner) | C13: 22651 | D13: =SUM($C$3:$C$5)/64 -> 0.5859375 | E13: =C13+D13 -> 22651.586 | F13: =IF($C$70=0, 0, E13/$C$70) -> 0.053682023 | G13: =F13*$T$5 -> 2136.5445 | H13: 3 | I13: =$T$7*H13 -> 353.43498 | J13: =G13+$T$9+I13 -> 2495.5019 | K13: =$T$11/64 -> 4458.1875 | L13: 0 | M13: 0 | N13: 0 | O13: 0 | R13: =(J13+K13+L13+M13+N13+O13)*$B$2 -> 6953.6894 | S13: TOTAL WATER METER RENT | T13: =I70 -> 26272
A14: F9 | B14: Vijay Suswaram (Owner) / Divya Shikha (Tenant) | C14: 1887.5 | D14: =SUM($C$3:$C$5)/64 -> 0.5859375 | E14: =C14+D14 -> 1888.0859 | F14: =IF($C$70=0, 0, E14/$C$70) -> 0.0044745773 | G14: =F14*$T$5 -> 178.08818 | H14: 4 | I14: =$T$7*H14 -> 471.24664 | J14: =G14+$T$9+I14 -> 654.85724 | K14: =$T$11/64 -> 4458.1875 | L14: 0 | M14: 0 | N14: 0 | O14: 0 | R14: =(J14+K14+L14+M14+N14+O14)*$B$2 -> 5113.0447
A15: F10 | B15: Aby Thomas | C15: 2453 | D15: =SUM($C$3:$C$5)/64 -> 0.5859375 | E15: =C15+D15 -> 2453.5859 | F15: =IF($C$70=0, 0, E15/$C$70) -> 0.0058147565 | G15: =F15*$T$5 -> 231.42731 | H15: 3 | I15: =$T$7*H15 -> 353.43498 | J15: =G15+$T$9+I15 -> 590.38471 | K15: =$T$11/64 -> 4458.1875 | L15: 0 | M15: 0 | N15: 0 | O15: 0 | R15: =(J15+K15+L15+M15+N15+O15)*$B$2 -> 5048.5722 | S15: BALANCE IN ACCOUNT ON 31-DEC-2023
A16: F11 | B16: Niwin Anto | C16: 993 | D16: =SUM($C$3:$C$5)/64 -> 0.5859375 | E16: =C16+D16 -> 993.58594 | F16: =IF($C$70=0, 0, E16/$C$70) -> 0.0023547006 | G16: =F16*$T$5 -> 93.717084 | H16: 3 | I16: =$T$7*H16 -> 353.43498 | J16: =G16+$T$9+I16 -> 452.67448 | K16: =$T$11/64 -> 4458.1875 | L16: 0 | M16: 0 | N16: 0 | O16: 0 | R16: =(J16+K16+L16+M16+N16+O16)*$B$2 -> 4910.862 | S16: TOTAL NON MAINTENANCE CORPUS COLLECTION
A17: F12 | B17: Anirudh Singh | C17: 538.5 | D17: =SUM($C$3:$C$5)/64 -> 0.5859375 | E17: =C17+D17 -> 539.08594 | F17: =IF($C$70=0, 0, E17/$C$70) -> 0.0012775805 | G17: =F17*$T$5 -> 50.847703 | H17: 3 | I17: =$T$7*H17 -> 353.43498 | J17: =G17+$T$9+I17 -> 409.8051 | K17: =$T$11/64 -> 4458.1875 | L17: 0 | M17: 0 | N17: 0 | O17: 0 | R17: =(J17+K17+L17+M17+N17+O17)*$B$2 -> 4867.9926 | S17: TOTAL FD DONE
A18: F13 | B18: Sanchay Saxena | C18: 2235.5 | D18: =SUM($C$3:$C$5)/64 -> 0.5859375 | E18: =C18+D18 -> 2236.0859 | F18: =IF($C$70=0, 0, E18/$C$70) -> 0.005299303 | G18: =F18*$T$5 -> 210.91226 | H18: 4 | I18: =$T$7*H18 -> 471.24664 | J18: =G18+$T$9+I18 -> 687.68132 | K18: =$T$11/64 -> 4458.1875 | L18: 0 | M18: 0 | N18: 0 | O18: 0 | R18: =(J18+K18+L18+M18+N18+O18)*$B$2 -> 5145.8688 | S18: AMOUNT AVAILABLE FOR NON MAINTENANCE CORPUS IN CURRENT AC | T18: =T16-T17 -> 0
A19: F14 | B19: Hemant Patel | C19: 7655.5 | D19: =SUM($C$3:$C$5)/64 -> 0.5859375 | E19: =C19+D19 -> 7656.0859 | F19: =IF($C$70=0, 0, E19/$C$70) -> 0.018144168 | G19: =F19*$T$5 -> 722.13789 | H19: 4 | I19: =$T$7*H19 -> 471.24664 | J19: =G19+$T$9+I19 -> 1198.9069 | K19: =$T$11/64 -> 4458.1875 | L19: 0 | M19: 0 | N19: 0 | O19: 0 | R19: =(J19+K19+L19+M19+N19+O19)*$B$2 -> 5657.0944 | S19: AMOUNT AVAILABLE FOR MAINTENANCE | T19: =T15-T18 -> 0
A20: F15 | B20: Senthil.Vijayaragavan | C20: 3799 | D20: =SUM($C$3:$C$5)/64 -> 0.5859375 | E20: =C20+D20 -> 3799.5859 | F20: =IF($C$70=0, 0, E20/$C$70) -> 0.0090046437 | G20: =F20*$T$5 -> 358.38482 | H20: 4 | I20: =$T$7*H20 -> 471.24664 | J20: =G20+$T$9+I20 -> 835.15388 | K20: =$T$11/64 -> 4458.1875 | L20: 750 | M20: 0 | N20: 0 | O20: 0 | R20: =(J20+K20+L20+M20+N20+O20)*$B$2 -> 6043.3414 | S20: TOTAL EXPENSE FOR THE MONTH | T20: ='ANNUAL-EXPENSE-DETAILS'!BH11 -> 351396
A21: F16 | B21: Sreeja Sudharma | C21: 19344 | D21: =SUM($C$3:$C$5)/64 -> 0.5859375 | E21: =C21+D21 -> 19344.586 | F21: =IF($C$70=0, 0, E21/$C$70) -> 0.045844759 | G21: =F21*$T$5 -> 1824.6214 | H21: 3 | I21: =$T$7*H21 -> 353.43498 | J21: =G21+$T$9+I21 -> 2183.5788 | K21: =$T$11/64 -> 4458.1875 | L21: 0 | M21: 0 | N21: 0 | O21: 0 | R21: =(J21+K21+L21+M21+N21+O21)*$B$2 -> 6641.7663
A22: G1 | B22: Venkataramanan C | C22: 7851 | D22: =SUM($C$3:$C$5)/64 -> 0.5859375 | E22: =C22+D22 -> 7851.5859 | F22: =IF($C$70=0, 0, E22/$C$70) -> 0.018607484 | G22: =F22*$T$5 -> 740.57785 | H22: 3 | I22: =$T$7*H22 -> 353.43498 | J22: =G22+$T$9+I22 -> 1099.5353 | K22: =$T$11/64 -> 4458.1875 | L22: 0 | M22: 0 | N22: 0 | O22: 0 | R22: =(J22+K22+L22+M22+N22+O22)*$B$2 -> 5557.7228
A23: G2 | B23: Kaushik Kasibhatla | C23: 7584 | D23: =SUM($C$3:$C$5)/64 -> 0.5859375 | E23: =C23+D23 -> 7584.5859 | F23: =IF($C$70=0, 0, E23/$C$70) -> 0.01797472 | G23: =F23*$T$5 -> 715.39386 | H23: 4 | I23: =$T$7*H23 -> 471.24664 | J23: =G23+$T$9+I23 -> 1192.1629 | K23: =$T$11/64 -> 4458.1875 | L23: 0 | M23: 0 | N23: 0 | O23: 0 | R23: =(J23+K23+L23+M23+N23+O23)*$B$2 -> 5650.3504
A24: G3 | B24: Balakrishnan | C24: 9390.5 | D24: =SUM($C$3:$C$5)/64 -> 0.5859375 | E24: =C24+D24 -> 9391.0859 | F24: =IF($C$70=0, 0, E24/$C$70) -> 0.022255947 | G24: =F24*$T$5 -> 885.78668 | H24: 4 | I24: =$T$7*H24 -> 471.24664 | J24: =G24+$T$9+I24 -> 1362.5557 | K24: =$T$11/64 -> 4458.1875 | L24: 0 | M24: 0 | N24: 0 | O24: 0 | R24: =(J24+K24+L24+M24+N24+O24)*$B$2 -> 5820.7432
A25: G4 | B25: Ashwin Pandith | C25: 16823 | D25: =SUM($C$3:$C$5)/64 -> 0.5859375 | E25: =C25+D25 -> 16823.586 | F25: =IF($C$70=0, 0, E25/$C$70) -> 0.039870238 | G25: =F25*$T$5 -> 1586.8355 | H25: 4 | I25: =$T$7*H25 -> 471.24664 | J25: =G25+$T$9+I25 -> 2063.6045 | K25: =$T$11/64 -> 4458.1875 | L25: 0 | M25: 0 | N25: 0 | O25: 0 | R25: =(J25+K25+L25+M25+N25+O25)*$B$2 -> 6521.792
A26: G5 | B26: Mayank Phophaliya | C26: 13109 | D26: =SUM($C$3:$C$5)/64 -> 0.5859375 | E26: =C26+D26 -> 13109.586 | F26: =IF($C$70=0, 0, E26/$C$70) -> 0.031068425 | G26: =F26*$T$5 -> 1236.5233 | H26: 3 | I26: =$T$7*H26 -> 353.43498 | J26: =G26+$T$9+I26 -> 1595.4807 | K26: =$T$11/64 -> 4458.1875 | L26: 0 | M26: 0 | N26: 0 | O26: 0 | R26: =(J26+K26+L26+M26+N26+O26)*$B$2 -> 6053.6682
A27: G6 | B27: Mohit Daga | C27: 10438 | D27: =SUM($C$3:$C$5)/64 -> 0.5859375 | E27: =C27+D27 -> 10438.586 | F27: =IF($C$70=0, 0, E27/$C$70) -> 0.024738418 | G27: =F27*$T$5 -> 984.58905 | H27: 3 | I27: =$T$7*H27 -> 353.43498 | J27: =G27+$T$9+I27 -> 1343.5465 | K27: =$T$11/64 -> 4458.1875 | L27: 0 | M27: 0 | N27: 0 | O27: 0 | R27: =(J27+K27+L27+M27+N27+O27)*$B$2 -> 5801.734
A28: G7 | B28: Prince Richfield | C28: 5839 | D28: =SUM($C$3:$C$5)/64 -> 0.5859375 | E28: =C28+D28 -> 5839.5859 | F28: =IF($C$70=0, 0, E28/$C$70) -> 0.013839242 | G28: =F28*$T$5 -> 550.80184 | H28: 3 | I28: =$T$7*H28 -> 353.43498 | J28: =G28+$T$9+I28 -> 909.75924 | K28: =$T$11/64 -> 4458.1875 | L28: 0 | M28: 0 | N28: 0 | O28: 0 | R28: =(J28+K28+L28+M28+N28+O28)*$B$2 -> 5367.9467
A29: G8 | B29: Ranjithkumar R / Sameer (tenant) / Princy (tenant) | C29: 4608 | D29: =SUM($C$3:$C$5)/64 -> 0.5859375 | E29: =C29+D29 -> 4608.5859 | F29: =IF($C$70=0, 0, E29/$C$70) -> 0.010921894 | G29: =F29*$T$5 -> 434.69137 | H29: 3 | I29: =$T$7*H29 -> 353.43498 | J29: =G29+$T$9+I29 -> 793.64877 | K29: =$T$11/64 -> 4458.1875 | L29: 0 | M29: 0 | N29: 0 | O29: 0 | R29: =(J29+K29+L29+M29+N29+O29)*$B$2 -> 5251.8363
A30: G9 | B30: Chandramouli | C30: 7015.5 | D30: =SUM($C$3:$C$5)/64 -> 0.5859375 | E30: =C30+D30 -> 7016.0859 | F30: =IF($C$70=0, 0, E30/$C$70) -> 0.016627431 | G30: =F30*$T$5 -> 661.77176 | H30: 5 | I30: =$T$7*H30 -> 589.0583 | J30: =G30+$T$9+I30 -> 1256.3525 | K30: =$T$11/64 -> 4458.1875 | L30: 0 | M30: 0 | N30: 0 | O30: 0 | R30: =(J30+K30+L30+M30+N30+O30)*$B$2 -> 5714.54
A31: G10 | B31: Cijo Jacob / Thara Joy | C31: 4336 | D31: =SUM($C$3:$C$5)/64 -> 0.5859375 | E31: =C31+D31 -> 4336.5859 | F31: =IF($C$70=0, 0, E31/$C$70) -> 0.010277281 | G31: =F31*$T$5 -> 409.03577 | H31: 3 | I31: =$T$7*H31 -> 353.43498 | J31: =G31+$T$9+I31 -> 767.99317 | K31: =$T$11/64 -> 4458.1875 | L31: 0 | M31: 0 | N31: 0 | O31: 0 | R31: =(J31+K31+L31+M31+N31+O31)*$B$2 -> 5226.1807
A32: G11 | B32: Ketan Verlekar | C32: 1089 | D32: =SUM($C$3:$C$5)/64 -> 0.5859375 | E32: =C32+D32 -> 1089.5859 | F32: =IF($C$70=0, 0, E32/$C$70) -> 0.0025822111 | G32: =F32*$T$5 -> 102.772 | H32: 3 | I32: =$T$7*H32 -> 353.43498 | J32: =G32+$T$9+I32 -> 461.7294 | K32: =$T$11/64 -> 4458.1875 | L32: 0 | M32: 0 | N32: 0 | O32: 0 | R32: =(J32+K32+L32+M32+N32+O32)*$B$2 -> 4919.9169
... A69: T16 | B69: Madhusoodanan P.R. | C69: 6988.5 | D69: =SUM($C$3:$C$5)/64 -> 0.5859375 | E69: =C69+D69 -> 6989.0859 | F69: =IF($C$70=0, 0, E69/$C$70) -> 0.016563444 | G69: =F69*$T$5 -> 659.22507 | H69: 3 | I69: =$T$7*H69 -> 353.43498 | J69: =G69+$T$9+I69 -> 1018.1825 | K69: =$T$11/64 -> 4458.1875 | L69: 0 | M69: 0 | N69: 0 | O69: 0 | R69: =(J69+K69+L69+M69+N69+O69)*$B$2 -> 5476.37
B70: TOTAL | C70: =SUM(C3:C69) -> 421958.5 | D70: =SUM(D3:D69) -> 37.5 | E70: =SUM(E3:E69) -> 421958.5 | F70: =IF($C$70=0, 0, E70/$C$70) -> 1 | G70: =SUM(G3:G69) -> 39800 | H70: =SUM(H3:H69) -> 223 | I70: =SUM(I3:I69) -> 26272 | J70: =SUM(J3:J69) -> 66072 | K70: =SUM(K3:K69) -> 285324 | L70: =SUM(L3:L69) -> 3000 | M70: =SUM(M3:M69) -> 0 | N70: =SUM(N3:N69) -> 0 | O70: =SUM(O3:O69) -> 0 | R70: =SUM(R3:R69) -> 354396

Sheet Dec2025-COLLECTION
A1: FLAT # | C1: Amount | D1: Date | E1: Amount | F1: Date | G1: Amount | H1: Date | I1: Amount | J1: Date | K1: Total
A2: F1 | B2: Shailesh Srivastava / Azeem Nawaz | C2: 13099 | D2: 46006 | K2: =SUM(C2,E2,G2,I2) -> 13099
A3: F2 | B3: Shanthanu | K3: =SUM(C3,E3,G3,I3) -> 0
A4: F3 | B4: Samrat Kar | C4: 6000 | D4: 45992 | K4: =SUM(C4,E4,G4,I4) -> 6000
A5: F4 | B5: Renu R | C5: 7064 | D5: 46005 | K5: =SUM(C5,E5,G5,I5) -> 7064
A6: F5 | B6: Vamsidhar Bethanabatla / Madhuri Anumula | C6: 7069 | D6: 46018 | K6: =SUM(C6,E6,G6,I6) -> 7069
A7: F6 | B7: Meghana Viral Shah and Vviral Shah (Owner) / Sangeet and Swagat (Tenent) | C7: 6114 | D7: 45992 | K7: =SUM(C7,E7,G7,I7) -> 6114
A8: F7 | B8: Vimal NK | C8: 7303 | D8: 46013 | K8: =SUM(C8,E8,G8,I8) -> 7303
A9: F8 | B9: Sujeet Kumar (Tenant)/Sreejith Menon (Owner) | C9: 7529 | D9: 46007 | K9: =SUM(C9,E9,G9,I9) -> 7529
A10: F9 | B10: Vijay Suswaram (Owner) / Divya Shikha (Tenant) / Harshvardhan | C10: 6883 | D10: 46011 | K10: =SUM(C10,E10,G10,I10) -> 6883
A11: F10 | B11: Aby Thomas | K11: =SUM(C11,E11,G11,I11) -> 0
A12: F11 | B12: N. Geetha | C12: 6604 | D12: 46006 | K12: =SUM(C12,E12,G12,I12) -> 6604
A13: F12 | B13: Anirudh Singh | C13: 7315 | D13: 46007 | K13: =SUM(C13,E13,G13,I13) -> 7315
A14: F13 | B14: Sanchay Saxena | C14: 7153.67 | D14: 46018 | E14: 6231 | F14: 46018 | K14: =SUM(C14,E14,G14,I14) -> 13384.67
A15: F14 | B15: Hemant Patel | K15: =SUM(C15,E15,G15,I15) -> 0
A16: F15 | B16: Senthil.Vijayaragavan / Soumya K | C16: 7638.43 | D16: 46013 | K16: =SUM(C16,E16,G16,I16) -> 7638.43
A17: F16 | B17: Sreeja Sudharma | C17: 7879.33 | D17: 46018 | K17: =SUM(C17,E17,G17,I17) -> 7879.33
A18: G1 | B18: Venkataramanan C | C18: 6114 | D18: 45995 | K18: =SUM(C18,E18,G18,I18) -> 6114
A19: G2 | B19: Kaushik Kasibhatla | C19: 8220 | D19: 46015 | K19: =SUM(C19,E19,G19,I19) -> 8220
A20: G3 | B20: Balakrishnan | C20: 7369 | D20: 46015 | K20: =SUM(C20,E20,G20,I20) -> 7369
A21: G4 | B21: Ashwin Pandith | C21: 6231 | D21: 45992 | E21: 8026 | F21: 46014 | K21: =SUM(C21,E21,G21,I21) -> 14257
A22: G5 | B22: Mayank Phophaliya | K22: =SUM(C22,E22,G22,I22) -> 0
A23: G6 | B23: Mohit Daga | C23: 18215 | D23: 46018 | K23: =SUM(C23,E23,G23,I23) -> 18215
A24: G7 | B24: Prince Richfield | K24: =SUM(C24,E24,G24,I24) -> 0
A25: G8 | B25: Ranjithkumar R / Sameer (tenant) / Princy (tenant) | C25: 6114 | D25: 46012 | K25: =SUM(C25,E25,G25,I25) -> 6114
A26: G9 | B26: Chandramouli | K26: =SUM(C26,E26,G26,I26) -> 0
A27: G10 | B27: Richa Singh | C27: 7920.16 | D27: 46009 | K27: =SUM(C27,E27,G27,I27) -> 7920.16
A28: G11 | B28: Ketan Verlekar | K28: =SUM(C28,E28,G28,I28) -> 0
A29: G12 | B29: Shyam Nair | C29: 7936 | D29: 46015 | K29: =SUM(C29,E29,G29,I29) -> 7936
A30: G13 | B30: Ajai.B | K30: =SUM(C30,E30,G30,I30) -> 0
A31: G14 | B31: Surajit Borah | C31: 7366.24 | D31: 46005 | K31: =SUM(C31,E31,G31,I31) -> 7366.24
A32: G15 | B32: Suresh Nallusamy / Antriksh (tenant) | K32: =SUM(C32,E32,G32,I32) -> 0
A33: G16 | B33: Praveen Ganesan | K33: =SUM(C33,E33,G33,I33) -> 0
A34: S1 | B34: S.N.Behera | C34: 7245.47 | D34: 46012 | K34: =SUM(C34,E34,G34,I34) -> 7245.47
A35: S2 | B35: Sonal Singh | K35: =SUM(C35,E35,G35,I35) -> 0
A36: S3 | B36: Manikandan Natarajan / Mahesh K | C36: 6845 | D36: 46012 | K36: =SUM(C36,E36,G36,I36) -> 6845
A37: S4 | B37: Swaminathan | K37: =SUM(C37,E37,G37,I37) -> 0
A38: S5 | B38: Abhishek Gopalakrishnan | C38: 6114 | D38: 46018 | K38: =SUM(C38,E38,G38,I38) -> 6114
A39: S6 | B39: Vivek Dhingra / Pratyush Das | K39: =SUM(C39,E39,G39,I39) -> 0
A40: S7 | B40: Harish B | C40: 6546 | D40: 46015 | K40: =SUM(C40,E40,G40,I40) -> 6546
A41: S8 | B41: Irudayaraj Alwin | C41: 7947.89 | D41: 46018 | K41: =SUM(C41,E41,G41,I41) -> 7947.89
A42: S9 | B42: Pawan GS | C42: 7602 | D42: 46013 | K42: =SUM(C42,E42,G42,I42) -> 7602
A43: S10 | B43: Lakshmikanth | K43: =SUM(C43,E43,G43,I43) -> 0
A44: S11 | B44: Gowrish Patnaik / Somananth GM / Keerthivasan | C44: 7274 | D44: 46018 | K44: =SUM(C44,E44,G44,I44) -> 7274
A45: S12 | B45: Saovik Mondal | C45: 6798.85 | D45: 46019 | K45: =SUM(C45,E45,G45,I45) -> 6798.85
A46: S13 | B46: Ramadevi S. | C46: 6935.98 | D46: 46018 | E46: 6231 | F46: 46018 | K46: =SUM(C46,E46,G46,I46) -> 13166.98
A47: S14 | B47: Nishant Upadhyay(Owner)/ Fabian (Tenant) | K47: =SUM(C47,E47,G47,I47) -> 0
A48: S15 | B48: Manas Dasgupta | C48: 6231 | D48: 46008 | K48: =SUM(C48,E48,G48,I48) -> 6231
A49: S16 | B49: Devendra Singh Rawat / Nancy | C49: 7026 | D49: 46008 | K49: =SUM(C49,E49,G49,I49) -> 7026
A50: T1 | B50: Prashant Sikdar | C50: 7786 | D50: 46008 | K50: =SUM(C50,E50,G50,I50) -> 7786
A51: T2 | B51: Kunal Mehta | C51: 6231 | D51: 46018 | K51: =SUM(C51,E51,G51,I51) -> 6231
A52: T3 | B52: Kapil Garg | C52: 6851 | D52: 46008 | K52: =SUM(C52,E52,G52,I52) -> 6851
A53: T4 | B53: Vijet Alva (Owner) - Masood (Tenant) | C53: 6231 | D53: 46018 | K53: =SUM(C53,E53,G53,I53) -> 6231
A54: T5 | B54: Ganesh Iyer and Latha Iyer( owner) Richa (Tenant) | C54: 6928 | D54: 46019 | K54: =SUM(C54,E54,G54,I54) -> 6928
A55: T6 | B55: Mythili Ramesh | C55: 6114 | D55: 45998 | E55: 7714.61 | F55: 46012 | K55: =SUM(C55,E55,G55,I55) -> 13828.61
A56: T7 | B56: Vinyas Ramachandra / Shwetha Marnamikatta / Katari Siva Rama Raju | C56: 6643.62 | D56: 46019 | K56: =SUM(C56,E56,G56,I56) -> 6643.62
A57: T8 | B57: Lalit Kumar Sharma | K57: =SUM(C57,E57,G57,I57) -> 0
A58: T9 | B58: Nishith Sahu and Priyanka Rani (Owner)/ Anmol Verma (Tenant) | C58: 7087.29 | D58: 46014 | K58: =SUM(C58,E58,G58,I58) -> 7087.29
A59: T10 | B59: Vamsidhar Bethanabatla / Madhuri Anumula | C59: 7323 | D59: 46018 | K59: =SUM(C59,E59,G59,I59) -> 7323
A60: T11 | B60: Chaitanya / Vaishnavi Suthapalli | C60: 6114 | D60: 45999 | E60: 7060.12 | F60: 46012 | K60: =SUM(C60,E60,G60,I60) -> 13174.12
A61: T12 | B61: Prasenjit | C61: 6980.33 | D61: 46006 | K61: =SUM(C61,E61,G61,I61) -> 6980.33
A62: T13 | B62: Rahul Kumar | K62: =SUM(C62,E62,G62,I62) -> 0
A63: T14 | B63: Jeya / Kanda / Satya (tenant)/Vinuta (tenant) | C63: 7045 | D63: 46013 | K63: =SUM(C63,E63,G63,I63) -> 7045
A64: T15 | B64: Trevor | C64: 6231 | D64: 46003 | K64: =SUM(C64,E64,G64,I64) -> 6231
A65: T16 | B65: Madhusoodanan P.R. | C65: 6114 | D65: 46008 | K65: =SUM(C65,E65,G65,I65) -> 6114
A66: TOTAL | K66: =SUM(K2:K65) -> 378644.99

Sheet Jan2026-EXPENSE
B1: JANUARY 2026 EXPENSES
A2: FLAT # | B2: 1 | C2: WATER USED IN LTRS | D2: COMMON AREA EQUALLY DEVIDED | E2: TOTAL FRESH WATER CONSUMED | F2: %OF TOTAL USED | G2: WATER EXPENSE SHARING BY % | H2: #METERS | I2: METER RENT | J2: COMMON AREA METER RENT + WATER EXPENSE+ FLAT METER RENT | K2: FIXED EXPENSE SHARE | L2: PARKING FEE | M2: CLUB BOOKING FEE | N2: SHIFTING FEE | O2: GYM USAGE FEE | R2: TOTAL EXPENSE TO BE PAID
A3: CH | B3: MPFOWA | C3: 0 | D3: 0 | H3: 1 | I3: =T7 -> 117.81166
A4: GYM | B4: MPFOWA | C4: 16 | D4: 0 | H4: 1 | I4: =T7 -> 117.81166 | S4: TOTAL FIXED EXPENSE | T4: ='ANNUAL-EXPENSE-DETAILS'!BF12 -> 280032
A5: BSMT | B5: MPFOWA | C5: 0 | D5: 0 | H5: 1 | I5: =T7 -> 117.81166 | S5: TOTAL WATER EXPENSE | T5: ='ANNUAL-EXPENSE-DETAILS'!BE12 -> 41000
A6: F1 | B6: Shailesh Srivastava / Azeem Nawaz | C6: 4807.5 | D6: =SUM($C$3:$C$5)/64 -> 0.25 | E6: =C6+D6 -> 4807.75 | F6: =IF($C$70=0, 0, E6/$C$70) -> 0.0087044489 | G6: =F6*$T$5 -> 356.8824 | H6: 3 | I6: =$T$7*H6 -> 353.43498 | J6: =G6+$T$9+I6 -> 715.8398 | K6: =$T$11/64 -> 4375.5 | L6: 0 | M6: 0 | N6: 0 | O6: 0 | R6: =(J6+K6+L6+M6+N6+O6)*$B$2 -> 5091.3398
A7: F2 | B7: Shanthanu | C7: 11111.5 | D7: =SUM($C$3:$C$5)/64 -> 0.25 | E7: =C7+D7 -> 11111.75 | F7: =IF($C$70=0, 0, E7/$C$70) -> 0.020117864 | G7: =F7*$T$5 -> 824.83242 | H7: 4 | I7: =$T$7*H7 -> 471.24664 | J7: =G7+$T$9+I7 -> 1301.6015 | K7: =$T$11/64 -> 4375.5 | L7: 0 | M7: 0 | N7: 0 | O7: 0 | R7: =(J7+K7+L7+M7+N7+O7)*$B$2 -> 5677.1015 | S7: RENT PER METER | T7: 117.81166
A8: F3 | B8: Samrat Kar | C8: 13363.5 | D8: =SUM($C$3:$C$5)/64 -> 0.25 | E8: =C8+D8 -> 13363.75 | F8: =IF($C$70=0, 0, E8/$C$70) -> 0.024195118 | G8: =F8*$T$5 -> 991.99984 | H8: 4 | I8: =$T$7*H8 -> 471.24664 | J8: =G8+$T$9+I8 -> 1468.7689 | K8: =$T$11/64 -> 4375.5 | L8: 750 | M8: 0 | N8: 0 | O8: 0 | R8: =(J8+K8+L8+M8+N8+O8)*$B$2 -> 6594.2689 | S8: COMMON AREA METER RENT | T8: =$T$7*3 -> 353.43498
A9: F4 | B9: Renu R | C9: 4363 | D9: =SUM($C$3:$C$5)/64 -> 0.25 | E9: =C9+D9 -> 4363.25 | F9: =IF($C$70=0, 0, E9/$C$70) -> 0.00789968 | G9: =F9*$T$5 -> 323.88688 | H9: 4 | I9: =$T$7*H9 -> 471.24664 | J9: =G9+$T$9+I9 -> 800.65594 | K9: =$T$11/64 -> 4375.5 | L9: 0 | M9: 0 | N9: 0 | O9: 0 | R9: =(J9+K9+L9+M9+N9+O9)*$B$2 -> 5176.1559 | S9: COMMON AREA METER RENT/FLAT | T9: =T8/64 -> 5.5224215
A10: F5 | B10: Vamsidhar Bethanabatla / Madhuri Anumula | C10: 5514.5 | D10: =SUM($C$3:$C$5)/64 -> 0.25 | E10: =C10+D10 -> 5514.75 | F10: =IF($C$70=0, 0, E10/$C$70) -> 0.0099844749 | G10: =F10*$T$5 -> 409.36347 | H10: 3 | I10: =$T$7*H10 -> 353.43498 | J10: =G10+$T$9+I10 -> 768.32087 | K10: =$T$11/64 -> 4375.5 | L10: 0 | M10: 0 | N10: 0 | O10: 0 | R10: =(J10+K10+L10+M10+N10+O10)*$B$2 -> 5143.8209
A11: F6 | B11: Meghana Viral Shah and Vviral Shah (Owner) / Sangeet and Swagat (Tenent) | C11: 4703 | D11: =SUM($C$3:$C$5)/64 -> 0.25 | E11: =C11+D11 -> 4703.25 | F11: =IF($C$70=0, 0, E11/$C$70) -> 0.0085152512 | G11: =F11*$T$5 -> 349.1253 | H11: 3 | I11: =$T$7*H11 -> 353.43498 | J11: =G11+$T$9+I11 -> 708.0827 | K11: =$T$11/64 -> 4375.5 | L11: 0 | M11: 0 | N11: 0 | O11: 0 | R11: =(J11+K11+L11+M11+N11+O11)*$B$2 -> 5083.5827 | S11: TOTAL FIXED EXPENSE | T11: ='ANNUAL-EXPENSE-DETAILS'!BF12 -> 280032
A12: F7 | B12: Vimal NK | C12: 30.5 | D12: =SUM($C$3:$C$5)/64 -> 0.25 | E12: =C12+D12 -> 30.75 | F12: =IF($C$70=0, 0, E12/$C$70) -> 5.5672987e-05 | G12: =F12*$T$5 -> 2.2825925 | H12: 3 | I12: =$T$7*H12 -> 353.43498 | J12: =G12+$T$9+I12 -> 361.23999 | K12: =$T$11/64 -> 4375.5 | L12: 750 | M12: 0 | N12: 0 | O12: 0 | R12: =(J12+K12+L12+M12+N12+O12)*$B$2 -> 5486.74
A13: F8 | B13: Sujeet Kumar (Tenant)/Sreejith Menon (Owner) | C13: 18885.5 | D13: =SUM($C$3:$C$5)/64 -> 0.25 | E13: =C13+D13 -> 18885.75 | F13: =IF($C$70=0, 0, E13/$C$70) -> 0.034192719 | G13: =F13*$T$5 -> 1401.9015 | H13: 3 | I13: =$T$7*H13 -> 353.43498 | J13: =G13+$T$9+I13 -> 1760.8589 | K13: =$T$11/64 -> 4375.5 | L13: 0 | M13: 0 | N13: 0 | O13: 0 | R13: =(J13+K13+L13+M13+N13+O13)*$B$2 -> 6136.3589 | S13: TOTAL WATER METER RENT | T13: =I70 -> 26272
A14: F9 | B14: Vijay Suswaram (Owner) / Divya Shikha (Tenant) | C14: 2242.5 | D14: =SUM($C$3:$C$5)/64 -> 0.25 | E14: =C14+D14 -> 2242.75 | F14: =IF($C$70=0, 0, E14/$C$70) -> 0.004060507 | G14: =F14*$T$5 -> 166.48079 | H14: 4 | I14: =$T$7*H14 -> 471.24664 | J14: =G14+$T$9+I14 -> 643.24985 | K14: =$T$11/64 -> 4375.5 | L14: 0 | M14: 0 | N14: 0 | O14: 0 | R14: =(J14+K14+L14+M14+N14+O14)*$B$2 -> 5018.7498
A15: F10 | B15: Aby Thomas | C15: 11612 | D15: =SUM($C$3:$C$5)/64 -> 0.25 | E15: =C15+D15 -> 11612.25 | F15: =IF($C$70=0, 0, E15/$C$70) -> 0.021024021 | G15: =F15*$T$5 -> 861.98486 | H15: 3 | I15: =$T$7*H15 -> 353.43498 | J15: =G15+$T$9+I15 -> 1220.9423 | K15: =$T$11/64 -> 4375.5 | L15: 0 | M15: 0 | N15: 0 | O15: 0 | R15: =(J15+K15+L15+M15+N15+O15)*$B$2 -> 5596.4423 | S15: BALANCE IN ACCOUNT ON 31-Jan-2023
A16: F11 | B16: Niwin Anto | C16: 581.5 | D16: =SUM($C$3:$C$5)/64 -> 0.25 | E16: =C16+D16 -> 581.75 | F16: =IF($C$70=0, 0, E16/$C$70) -> 0.0010532605 | G16: =F16*$T$5 -> 43.18368 | H16: 3 | I16: =$T$7*H16 -> 353.43498 | J16: =G16+$T$9+I16 -> 402.14108 | K16: =$T$11/64 -> 4375.5 | L16: 0 | M16: 0 | N16: 0 | O16: 0 | R16: =(J16+K16+L16+M16+N16+O16)*$B$2 -> 4777.6411 | S16: TOTAL NON MAINTENANCE CORPUS COLLECTION
A17: F12 | B17: Anirudh Singh | C17: 10 | D17: =SUM($C$3:$C$5)/64 -> 0.25 | E17: =C17+D17 -> 10.25 | F17: =IF($C$70=0, 0, E17/$C$70) -> 1.8557662e-05 | G17: =F17*$T$5 -> 0.76086415 | H17: 3 | I17: =$T$7*H17 -> 353.43498 | J17: =G17+$T$9+I17 -> 359.71826 | K17: =$T$11/64 -> 4375.5 | L17: 0 | M17: 0 | N17: 0 | O17: 0 | R17: =(J17+K17+L17+M17+N17+O17)*$B$2 -> 4735.2183 | S17: TOTAL FD DONE
A18: F13 | B18: Sanchay Saxena | C18: 1559 | D18: =SUM($C$3:$C$5)/64 -> 0.25 | E18: =C18+D18 -> 1559.25 | F18: =IF($C$70=0, 0, E18/$C$70) -> 0.0028230278 | G18: =F18*$T$5 -> 115.74414 | H18: 4 | I18: =$T$7*H18 -> 471.24664 | J18: =G18+$T$9+I18 -> 592.5132 | K18: =$T$11/64 -> 4375.5 | L18: 0 | M18: 0 | N18: 0 | O18: 0 | R18: =(J18+K18+L18+M18+N18+O18)*$B$2 -> 4968.0132 | S18: AMOUNT AVAILABLE FOR NON MAINTENANCE CORPUS IN CURRENT AC | T18: =T16-T17 -> 0
A19: F14 | B19: Hemant Patel | C19: 8123 | D19: =SUM($C$3:$C$5)/64 -> 0.25 | E19: =C19+D19 -> 8123.25 | F19: =IF($C$70=0, 0, E19/$C$70) -> 0.014707174 | G19: =F19*$T$5 -> 602.99412 | H19: 4 | I19: =$T$7*H19 -> 471.24664 | J19: =G19+$T$9+I19 -> 1079.7632 | K19: =$T$11/64 -> 4375.5 | L19: 0 | M19: 0 | N19: 0 | O19: 0 | R19: =(J19+K19+L19+M19+N19+O19)*$B$2 -> 5455.2632 | S19: AMOUNT AVAILABLE FOR MAINTENANCE | T19: =T15-T18 -> 0
A20: F15 | B20: Senthil.Vijayaragavan | C20: 3861.5 | D20: =SUM($C$3:$C$5)/64 -> 0.25 | E20: =C20+D20 -> 3861.75 | F20: =IF($C$70=0, 0, E20/$C$70) -> 0.0069917124 | G20: =F20*$T$5 -> 286.66021 | H20: 4 | I20: =$T$7*H20 -> 471.24664 | J20: =G20+$T$9+I20 -> 763.42927 | K20: =$T$11/64 -> 4375.5 | L20: 750 | M20: 0 | N20: 0 | O20: 0 | R20: =(J20+K20+L20+M20+N20+O20)*$B$2 -> 5888.9293 | S20: TOTAL EXPENSE FOR THE MONTH | T20: ='ANNUAL-EXPENSE-DETAILS'!BH12 -> 347304
A21: F16 | B21: Sreeja Sudharma | C21: 17584 | D21: =SUM($C$3:$C$5)/64 -> 0.25 | E21: =C21+D21 -> 17584.25 | F21: =IF($C$70=0, 0, E21/$C$70) -> 0.031836349 | G21: =F21*$T$5 -> 1305.2903 | H21: 3 | I21: =$T$7*H21 -> 353.43498 | J21: =G21+$T$9+I21 -> 1664.2477 | K21: =$T$11/64 -> 4375.5 | L21: 0 | M21: 0 | N21: 0 | O21: 0 | R21: =(J21+K21+L21+M21+N21+O21)*$B$2 -> 6039.7477
A22: G1 | B22: Venkataramanan C | C22: 9608.5 | D22: =SUM($C$3:$C$5)/64 -> 0.25 | E22: =C22+D22 -> 9608.75 | F22: =IF($C$70=0, 0, E22/$C$70) -> 0.017396677 | G22: =F22*$T$5 -> 713.26375 | H22: 3 | I22: =$T$7*H22 -> 353.43498 | J22: =G22+$T$9+I22 -> 1072.2211 | K22: =$T$11/64 -> 4375.5 | L22: 0 | M22: 0 | N22: 0 | O22: 0 | R22: =(J22+K22+L22+M22+N22+O22)*$B$2 -> 5447.7211
A23: G2 | B23: Kaushik Kasibhatla | C23: 12687.5 | D23: =SUM($C$3:$C$5)/64 -> 0.25 | E23: =C23+D23 -> 12687.75 | F23: =IF($C$70=0, 0, E23/$C$70) -> 0.022971218 | G23: =F23*$T$5 -> 941.81992 | H23: 4 | I23: =$T$7*H23 -> 471.24664 | J23: =G23+$T$9+I23 -> 1418.589 | K23: =$T$11/64 -> 4375.5 | L23: 0 | M23: 0 | N23: 0 | O23: 0 | R23: =(J23+K23+L23+M23+N23+O23)*$B$2 -> 5794.089
A24: G3 | B24: Balakrishnan | C24: 12286.5 | D24: =SUM($C$3:$C$5)/64 -> 0.25 | E24: =C24+D24 -> 12286.75 | F24: =IF($C$70=0, 0, E24/$C$70) -> 0.022245206 | G24: =F24*$T$5 -> 912.05343 | H24: 4 | I24: =$T$7*H24 -> 471.24664 | J24: =G24+$T$9+I24 -> 1388.8225 | K24: =$T$11/64 -> 4375.5 | L24: 0 | M24: 0 | N24: 0 | O24: 0 | R24: =(J24+K24+L24+M24+N24+O24)*$B$2 -> 5764.3225
