Workbook

Sheet Apr2026-EXPENSE
B1: APR 2026 EXPENSES
A2: FLAT # | B2: 1 | C2: WATER USED IN LTRS | D2: COMMON AREA WATER EQUALLY DIVIDED (L) | E2: TOTAL FRESH WATER CONSUMED(L) | F2: %OF TOTAL WATER USED | G2: WATER EXPENSE SHARING BY % | H2: #METERS | I2: METER RENT (Rs) | J2: TOTAL VARIABLE = (COMMON AREA METER RENT + WATER EXPENSE+ FLAT METER RENT (Rs)) | K2: FIXED EXPENSE SHARE(Rs) | L2: PARKING FEE(Rs) | M2: CLUB HOUSE FEE (Rs) | N2: SHIFTING FEE (Rs) | O2: GYM USAGE FEE(Rs) | P2: COVID+ GARBAGE FEE (Rs) | Q2: ANNUAL MEMBERSHIP FEE - 2022-2023 (Rs) | R2: TOTAL EXPENSE TO BE PAID (Rs)
A3: CH | B3: MPFOWA | C3: 0 | D3: 0 | H3: 1 | I3: =T7
A4: GYM | B4: MPFOWA | C4: 0 | D4: 0 | H4: 1 | I4: =T7 | S4: TOTAL FIXED EXPENSE | T4: ='ANNUAL-EXPENSE-DETAILS'!BF3
A5: BSMT | B5: MPFOWA | C5: 0 | D5: 0 | H5: 1 | I5: =T7 | S5: TOTAL WATER EXPENSE | T5: ='ANNUAL-EXPENSE-DETAILS'!BE3
A6: F1 | B6: Shailesh Srivastava / Azeem Nawaz | C6: 0 | D6: =SUM($C$3:$C$5)/64 | E6: =C6+D6 | F6: =IF($C$70=0, 0, E6/$C$70) | G6: =F6*$T$5 | H6: 3 | I6: =$T$7*H6 | J6: =G6+$T$9+I6 | K6: =$T$4/64 | L6: 0 | M6: 0 | N6: 0 | O6: 0 | P6: 0 | Q6: 0 | R6: =(J6+K6+L6+M6+Q6+N6+O6+P6)*$B$2
A7: F2 | B7: Shanthanu | C7: 0 | D7: =SUM($C$3:$C$5)/64 | E7: =C7+D7 | F7: =IF($C$70=0, 0, E7/$C$70) | G7: =F7*$T$5 | H7: 4 | I7: =$T$7*H7 | J7: =G7+$T$9+I7 | K7: =$T$4/64 | L7: 0 | M7: 0 | N7: 0 | O7: 0 | P7: 0 | Q7: 0 | R7: =(J7+K7+L7+M7+Q7+N7+O7+P7)*$B$2 | S7: RENT PER METER (Rs) | T7: 112.21
A8: F3 | B8: Samrat Kar | C8: 0 | D8: =SUM($C$3:$C$5)/64 | E8: =C8+D8 | F8: =IF($C$70=0, 0, E8/$C$70) | G8: =F8*$T$5 | H8: 4 | I8: =$T$7*H8 | J8: =G8+$T$9+I8 | K8: =$T$4/64 | L8: 0 | M8: 0 | N8: 0 | O8: 0 | P8: 0 | Q8: 0 | R8: =(J8+K8+L8+M8+Q8+N8+O8+P8)*$B$2 | S8: COMMON AREA METER RENT(Rs) | T8: =$T$7*3
A9: F4 | B9: Renu R | C9: 0 | D9: =SUM($C$3:$C$5)/64 | E9: =C9+D9 | F9: =IF($C$70=0, 0, E9/$C$70) | G9: =F9*$T$5 | H9: 4 | I9: =$T$7*H9 | J9: =G9+$T$9+I9 | K9: =$T$4/64 | L9: 0 | M9: 0 | N9: 0 | O9: 0 | P9: 0 | Q9: 0 | R9: =(J9+K9+L9+M9+Q9+N9+O9+P9)*$B$2 | S9: COMMON AREA METER RENT/FLAT (Rs) | T9: =T8/64
A10: F5 | B10: Vamsidhar Bethanabatla / Madhuri Anumula | C10: 0 | D10: =SUM($C$3:$C$5)/64 | E10: =C10+D10 | F10: =IF($C$70=0, 0, E10/$C$70) | G10: =F10*$T$5 | H10: 3 | I10: =$T$7*H10 | J10: =G10+$T$9+I10 | K10: =$T$4/64 | L10: 0 | M10: 0 | N10: 0 | O10: 0 | P10: 0 | Q10: 0 | R10: =(J10+K10+L10+M10+Q10+N10+O10+P10)*$B$2
A11: F6 | B11: Meghana Viral Shah and Vviral Shah (Owner) / Sangeet and Swagat (Tenent) | C11: 0 | D11: =SUM($C$3:$C$5)/64 | E11: =C11+D11 | F11: =IF($C$70=0, 0, E11/$C$70) | G11: =F11*$T$5 | H11: 3 | I11: =$T$7*H11 | J11: =G11+$T$9+I11 | K11: =$T$4/64 | L11: 0 | M11: 0 | N11: 0 | O11: 0 | P11: 0 | Q11: 0 | R11: =(J11+K11+L11+M11+Q11+N11+O11+P11)*$B$2 | S11: BALANCE IN ACCOUNT ON 30-Apr-2023
A12: F7 | B12: Vimal NK | C12: 0 | D12: =SUM($C$3:$C$5)/64 | E12: =C12+D12 | F12: =IF($C$70=0, 0, E12/$C$70) | G12: =F12*$T$5 | H12: 3 | I12: =$T$7*H12 | J12: =G12+$T$9+I12 | K12: =$T$4/64 | L12: 0 | M12: 0 | N12: 0 | O12: 0 | P12: 0 | Q12: 0 | R12: =(J12+K12+L12+M12+Q12+N12+O12+P12)*$B$2 | S12: TOTAL NON MAINTENANCE CORPUS COLLECTION
A13: F8 | B13: Sujeet Kumar (Tenant)/Sreejith Menon (Owner) | C13: 0 | D13: =SUM($C$3:$C$5)/64 | E13: =C13+D13 | F13: =IF($C$70=0, 0, E13/$C$70) | G13: =F13*$T$5 | H13: 3 | I13: =$T$7*H13 | J13: =G13+$T$9+I13 | K13: =$T$4/64 | L13: 0 | M13: 0 | N13: 0 | O13: 0 | P13: 0 | Q13: 0 | R13: =(J13+K13+L13+M13+Q13+N13+O13+P13)*$B$2 | S13: TOTAL FD DONE
A14: F9 | B14: Vijay Suswaram (Owner) / Divya Shikha (Tenant) | C14: 0 | D14: =SUM($C$3:$C$5)/64 | E14: =C14+D14 | F14: =IF($C$70=0, 0, E14/$C$70) | G14: =F14*$T$5 | H14: 4 | I14: =$T$7*H14 | J14: =G14+$T$9+I14 | K14: =$T$4/64 | L14: 0 | M14: 0 | N14: 0 | O14: 0 | P14: 0 | Q14: 0 | R14: =(J14+K14+L14+M14+Q14+N14+O14+P14)*$B$2 | S14: AMOUNT AVAILABLE FOR NON MAINTENANCE CORPUS IN CURRENT AC | T14: =T12-T13
A15: F10 | B15: Aby Thomas | C15: 0 | D15: =SUM($C$3:$C$5)/64 | E15: =C15+D15 | F15: =IF($C$70=0, 0, E15/$C$70) | G15: =F15*$T$5 | H15: 3 | I15: =$T$7*H15 | J15: =G15+$T$9+I15 | K15: =$T$4/64 | L15: 0 | M15: 0 | N15: 0 | O15: 0 | P15: 0 | Q15: 0 | R15: =(J15+K15+L15+M15+Q15+N15+O15+P15)*$B$2 | S15: Pending vendor payments
A16: F11 | B16: Niwin Anto | C16: 0 | D16: =SUM($C$3:$C$5)/64 | E16: =C16+D16 | F16: =IF($C$70=0, 0, E16/$C$70) | G16: =F16*$T$5 | H16: 3 | I16: =$T$7*H16 | J16: =G16+$T$9+I16 | K16: =$T$4/64 | L16: 0 | M16: 0 | N16: 0 | O16: 0 | P16: 0 | Q16: 0 | R16: =(J16+K16+L16+M16+Q16+N16+O16+P16)*$B$2 | S16: AMOUNT AVAILABLE FOR MAINTENANCE | T16: =T11-T14-T15
A17: F12 | B17: Anirudh Singh | C17: 0 | D17: =SUM($C$3:$C$5)/64 | E17: =C17+D17 | F17: =IF($C$70=0, 0, E17/$C$70) | G17: =F17*$T$5 | H17: 3 | I17: =$T$7*H17 | J17: =G17+$T$9+I17 | K17: =$T$4/64 | L17: 0 | M17: 0 | N17: 0 | O17: 0 | P17: 0 | Q17: 0 | R17: =(J17+K17+L17+M17+Q17+N17+O17+P17)*$B$2 | S17: TOTAL EXPENSE FOR THE MONTH | T17: ='ANNUAL-EXPENSE-DETAILS'!BI9
A18: F13 | B18: Sanchay Saxena | C18: 0 | D18: =SUM($C$3:$C$5)/64 | E18: =C18+D18 | F18: =IF($C$70=0, 0, E18/$C$70) | G18: =F18*$T$5 | H18: 4 | I18: =$T$7*H18 | J18: =G18+$T$9+I18 | K18: =$T$4/64 | L18: 0 | M18: 0 | N18: 0 | O18: 0 | P18: 0 | Q18: 0 | R18: =(J18+K18+L18+M18+Q18+N18+O18+P18)*$B$2 | S18: Maintenance deficit | T18: =T16-T17
A19: F14 | B19: Hemant Patel | C19: 0 | D19: =SUM($C$3:$C$5)/64 | E19: =C19+D19 | F19: =IF($C$70=0, 0, E19/$C$70) | G19: =F19*$T$5 | H19: 4 | I19: =$T$7*H19 | J19: =G19+$T$9+I19 | K19: =$T$4/64 | L19: 0 | M19: 0 | N19: 0 | O19: 0 | P19: 0 | Q19: 0 | R19: =(J19+K19+L19+M19+Q19+N19+O19+P19)*$B$2
A20: F15 | B20: Senthil.Vijayaragavan | C20: 0 | D20: =SUM($C$3:$C$5)/64 | E20: =C20+D20 | F20: =IF($C$70=0, 0, E20/$C$70) | G20: =F20*$T$5 | H20: 4 | I20: =$T$7*H20 | J20: =G20+$T$9+I20 | K20: =$T$4/64 | L20: 0 | M20: 0 | N20: 0 | O20: 0 | P20: 0 | Q20: 0 | R20: =(J20+K20+L20+M20+Q20+N20+O20+P20)*$B$2
A21: F16 | B21: Sreeja Sudharma | C21: 0 | D21: =SUM($C$3:$C$5)/64 | E21: =C21+D21 | F21: =IF($C$70=0, 0, E21/$C$70) | G21: =F21*$T$5 | H21: 3 | I21: =$T$7*H21 | J21: =G21+$T$9+I21 | K21: =$T$4/64 | L21: 0 | M21: 0 | N21: 0 | O21: 0 | P21: 0 | Q21: 0 | R21: =(J21+K21+L21+M21+Q21+N21+O21+P21)*$B$2
A22: G1 | B22: Venkataramanan C | C22: 0 | D22: =SUM($C$3:$C$5)/64 | E22: =C22+D22 | F22: =IF($C$70=0, 0, E22/$C$70) | G22: =F22*$T$5 | H22: 3 | I22: =$T$7*H22 | J22: =G22+$T$9+I22 | K22: =$T$4/64 | L22: 0 | M22: 0 | N22: 0 | O22: 0 | P22: 0 | Q22: 0 | R22: =(J22+K22+L22+M22+Q22+N22+O22+P22)*$B$2
A23: G2 | B23: Kaushik Kasibhatla | C23: 0 | D23: =SUM($C$3:$C$5)/64 | E23: =C23+D23 | F23: =IF($C$70=0, 0, E23/$C$70) | G23: =F23*$T$5 | H23: 4 | I23: =$T$7*H23 | J23: =G23+$T$9+I23 | K23: =$T$4/64 | L23: 0 | M23: 0 | N23: 0 | O23: 0 | P23: 0 | Q23: 0 | R23: =(J23+K23+L23+M23+Q23+N23+O23+P23)*$B$2
A24: G3 | B24: Balakrishnan | C24: 0 | D24: =SUM($C$3:$C$5)/64 | E24: =C24+D24 | F24: =IF($C$70=0, 0, E24/$C$70) | G24: =F24*$T$5 | H24: 4 | I24: =$T$7*H24 | J24: =G24+$T$9+I24 | K24: =$T$4/64 | L24: 0 | M24: 0 | N24: 0 | O24: 0 | P24: 0 | Q24: 0 | R24: =(J24+K24+L24+M24+Q24+N24+O24+P24)*$B$2
A25: G4 | B25: Ashwin Pandith | C25: 0 | D25: =SUM($C$3:$C$5)/64 | E25: =C25+D25 | F25: =IF($C$70=0, 0, E25/$C$70) | G25: =F25*$T$5 | H25: 4 | I25: =$T$7*H25 | J25: =G25+$T$9+I25 | K25: =$T$4/64 | L25: 0 | M25: 0 | N25: 0 | O25: 0 | P25: 0 | Q25: 0 | R25: =(J25+K25+L25+M25+Q25+N25+O25+P25)*$B$2
A26: G5 | B26: Mayank Phophaliya | C26: 0 | D26: =SUM($C$3:$C$5)/64 | E26: =C26+D26 | F26: =IF($C$70=0, 0, E26/$C$70) | G26: =F26*$T$5 | H26: 3 | I26: =$T$7*H26 | J26: =G26+$T$9+I26 | K26: =$T$4/64 | L26: 0 | M26: 0 | N26: 0 | O26: 0 | P26: 0 | Q26: 0 | R26: =(J26+K26+L26+M26+Q26+N26+O26+P26)*$B$2
A27: G6 | B27: Mohit Daga | C27: 0 | D27: =SUM($C$3:$C$5)/64 | E27: =C27+D27 | F27: =IF($C$70=0, 0, E27/$C$70) | G27: =F27*$T$5 | H27: 3 | I27: =$T$7*H27 | J27: =G27+$T$9+I27 | K27: =$T$4/64 | L27: 0 | M27: 0 | N27: 0 | O27: 0 | P27: 0 | Q27: 0 | R27: =(J27+K27+L27+M27+Q27+N27+O27+P27)*$B$2
A28: G7 | B28: Prince Richfield | C28: 0 | D28: =SUM($C$3:$C$5)/64 | E28: =C28+D28 | F28: =IF($C$70=0, 0, E28/$C$70) | G28: =F28*$T$5 | H28: 3 | I28: =$T$7*H28 | J28: =G28+$T$9+I28 | K28: =$T$4/64 | L28: 0 | M28: 0 | N28: 0 | O28: 0 | P28: 0 | Q28: 0 | R28: =(J28+K28+L28+M28+Q28+N28+O28+P28)*$B$2
A29: G8 | B29: Ranjithkumar R / Sameer (tenant) / Princy (tenant) | C29: 0 | D29: =SUM($C$3:$C$5)/64 | E29: =C29+D29 | F29: =IF($C$70=0, 0, E29/$C$70) | G29: =F29*$T$5 | H29: 3 | I29: =$T$7*H29 | J29: =G29+$T$9+I29 | K29: =$T$4/64 | L29: 0 | M29: 0 | N29: 0 | O29: 0 | P29: 0 | Q29: 0 | R29: =(J29+K29+L29+M29+Q29+N29+O29+P29)*$B$2
A30: G9 | B30: Chandramouli | C30: 0 | D30: =SUM($C$3:$C$5)/64 | E30: =C30+D30 | F30: =IF($C$70=0, 0, E30/$C$70) | G30: =F30*$T$5 | H30: 5 | I30: =$T$7*H30 | J30: =G30+$T$9+I30 | K30: =$T$4/64 | L30: 0 | M30: 0 | N30: 0 | O30: 0 | P30: 0 | Q30: 0 | R30: =(J30+K30+L30+M30+Q30+N30+O30+P30)*$B$2
... A69: T16 | B69: Madhusoodanan P.R. | C69: 0 | D69: =SUM($C$3:$C$5)/64 | E69: =C69+D69 | F69: =IF($C$70=0, 0, E69/$C$70) | G69: =F69*$T$5 | H69: 3 | I69: =$T$7*H69 | J69: =G69+$T$9+I69 | K69: =$T$4/64 | L69: 0 | M69: 0 | N69: 0 | O69: 0 | P69: 0 | Q69: 0 | R69: =(J69+K69+L69+M69+Q69+N69+O69+P69)*$B$2
A70: TOTAL | B70: TOTAL | C70: =SUM(C3:C69) | D70: =SUM(D3:D69) | E70: =SUM(E5:E69) | F70: =SUM(F6:F69) | G70: =SUM(G6:G69) | H70: =SUM(H3:H69) | I70: =SUM(I3:I69) | J70: =SUM(J6:J69) | K70: =SUM(K6:K69) | L70: =SUM(L6:L69) | M70: =SUM(M6:M69) | N70: =SUM(N6:N69) | O70: =SUM(O6:O69) | P70: =SUM(P6:P69) | Q70: =SUM(Q6:Q69) | R70: =SUM(R6:R69)

Sheet Apr2026-COLLECTION
A1: FLAT # | C1: Amount | D1: Date | E1: Amount | F1: Date | G1: Amount | H1: Date | I1: Amount | J1: Date | K1: Total
A2: F1 | B2: Shailesh Srivastava / Azeem Nawaz | K2: =SUM(C2,E2,G2,I2)
A3: F2 | B3: Shanthanu | K3: =SUM(C3,E3,G3,I3)
A4: F3 | B4: Samrat Kar | K4: =SUM(C4,E4,G4,I4)
A5: F4 | B5: Renu R | K5: =SUM(C5,E5,G5,I5)
A6: F5 | B6: Vamsidhar Bethanabatla / Madhuri Anumula | K6: =SUM(C6,E6,G6,I6)
A7: F6 | B7: Meghana Viral Shah and Vviral Shah (Owner) / Sangeet and Swagat (Tenent) | K7: =SUM(C7,E7,G7,I7)
A8: F7 | B8: Vimal NK | K8: =SUM(C8,E8,G8,I8)
A9: F8 | B9: Sujeet Kumar (Tenant)/Sreejith Menon (Owner) | K9: =SUM(C9,E9,G9,I9)
A10: F9 | B10: Vijay Suswaram (Owner) / Divya Shikha (Tenant) | K10: =SUM(C10,E10,G10,I10)
A11: F10 | B11: Aby Thomas | K11: =SUM(C11,E11,G11,I11)
A12: F11 | B12: N. Geetha | K12: =SUM(C12,E12,G12,I12)
A13: F12 | B13: Anirudh Singh | K13: =SUM(C13,E13,G13,I13)
... A65: T16 | B65: Madhusoodanan P.R. | K65: =SUM(C65,E65,G65,I65)
A66: TOTAL | K66: =SUM(K2:K65)

Sheet May2026-EXPENSE
A1: 1 | B1: MAY 2026 EXPENSES
A2: FLAT # | B2: 1 | C2: WATER USED IN LTRS | D2: COMMON AREA EQUALLY DEVIDED | E2: TOTAL FRESH WATER CONSUMED | F2: %OF TOTAL USED | G2: WATER EXPENSE SHARING BY % | H2: #METERS | I2: METER RENT | J2: VARIABLE EXPENSE = COMMON AREA METER RENT + WATER EXPENSE+ FLAT METER RENT | K2: FIXED EXPENSE SHARE | L2: PARKING FEE | M2: CLUB HOUSE BOOKING | N2: SHIFTING FEE | O2: GYM USAGE FEE | P2: POLYCARBONATE SHEET REPAIR | R2: TOTAL EXPENSE TO BE PAID
A3: CH | B3: MPFOWA | C3: 0 | D3: 0 | H3: 1 | I3: =T7
A4: GYM | B4: MPFOWA | C4: 0 | D4: 0 | H4: 1 | I4: =T7 | S4: TOTAL FIXED EXPENSE | T4: ='ANNUAL-EXPENSE-DETAILS'!BF4
A5: BSMT | B5: MPFOWA | C5: 0 | D5: 0 | H5: 1 | I5: =T7 | S5: TOTAL WATER EXPENSE | T5: ='ANNUAL-EXPENSE-DETAILS'!BE4
A6: F1 | B6: Shailesh Srivastava / Azeem Nawaz | C6: 0 | D6: =SUM($C$3:$C$5)/64 | E6: =C6+D6 | F6: =IF($C$70=0, 0, E6/$C$70) | G6: =F6*$T$5 | H6: 3 | I6: =$T$7*H6 | J6: =G6+$T$9+I6 | K6: =$T$4/64 | L6: 0 | M6: 0 | N6: 0 | O6: 0 | R6: =(SUM(J6:P6)*$B$2)
A7: F2 | B7: Shanthanu | C7: 0 | D7: =SUM($C$3:$C$5)/64 | E7: =C7+D7 | F7: =IF($C$70=0, 0, E7/$C$70) | G7: =F7*$T$5 | H7: 4 | I7: =$T$7*H7 | J7: =G7+$T$9+I7 | K7: =$T$4/64 | L7: 0 | M7: 0 | N7: 0 | O7: 0 | R7: =(SUM(J7:P7)*$B$2) | S7: RENT PER METER | T7: 117.81166
A8: F3 | B8: Samrat Kar | C8: 0 | D8: =SUM($C$3:$C$5)/64 | E8: =C8+D8 | F8: =IF($C$70=0, 0, E8/$C$70) | G8: =F8*$T$5 | H8: 4 | I8: =$T$7*H8 | J8: =G8+$T$9+I8 | K8: =$T$4/64 | L8: 0 | M8: 0 | N8: 0 | O8: 0 | R8: =(SUM(J8:P8)*$B$2) | S8: COMMON AREA METER RENT | T8: =$T$7*3
A9: F4 | B9: Renu R | C9: 0 | D9: =SUM($C$3:$C$5)/64 | E9: =C9+D9 | F9: =IF($C$70=0, 0, E9/$C$70) | G9: =F9*$T$5 | H9: 4 | I9: =$T$7*H9 | J9: =G9+$T$9+I9 | K9: =$T$4/64 | L9: 0 | M9: 0 | N9: 0 | O9: 0 | R9: =(SUM(J9:P9)*$B$2) | S9: COMMON AREA METER RENT/FLAT | T9: =T8/64
A10: F5 | B10: Vamsidhar Bethanabatla / Madhuri Anumula | C10: 0 | D10: =SUM($C$3:$C$5)/64 | E10: =C10+D10 | F10: =IF($C$70=0, 0, E10/$C$70) | G10: =F10*$T$5 | H10: 3 | I10: =$T$7*H10 | J10: =G10+$T$9+I10 | K10: =$T$4/64 | L10: 0 | M10: 0 | N10: 0 | O10: 0 | R10: =(SUM(J10:P10)*$B$2)
A11: F6 | B11: Meghana Viral Shah and Vviral Shah (Owner) / Sangeet and Swagat (Tenent) | C11: 0 | D11: =SUM($C$3:$C$5)/64 | E11: =C11+D11 | F11: =IF($C$70=0, 0, E11/$C$70) | G11: =F11*$T$5 | H11: 3 | I11: =$T$7*H11 | J11: =G11+$T$9+I11 | K11: =$T$4/64 | L11: 0 | M11: 0 | N11: 0 | O11: 0 | R11: =(SUM(J11:P11)*$B$2)
A12: F7 | B12: Vimal NK | C12: 0 | D12: =SUM($C$3:$C$5)/64 | E12: =C12+D12 | F12: =IF($C$70=0, 0, E12/$C$70) | G12: =F12*$T$5 | H12: 3 | I12: =$T$7*H12 | J12: =G12+$T$9+I12 | K12: =$T$4/64 | L12: 0 | M12: 0 | N12: 0 | O12: 0 | R12: =(SUM(J12:P12)*$B$2) | S12: BALANCE IN ACCOUNT TILL 31MAY2023
A13: F8 | B13: Sujeet Kumar (Tenant)/Sreejith Menon (Owner) | C13: 0 | D13: =SUM($C$3:$C$5)/64 | E13: =C13+D13 | F13: =IF($C$70=0, 0, E13/$C$70) | G13: =F13*$T$5 | H13: 3 | I13: =$T$7*H13 | J13: =G13+$T$9+I13 | K13: =$T$4/64 | L13: 0 | M13: 0 | N13: 0 | O13: 0 | R13: =(SUM(J13:P13)*$B$2) | S13: TOTAL NON MAINTENANCE CORPUS COLLECTION
A14: F9 | B14: Vijay Suswaram (Owner) / Divya Shikha (Tenant) | C14: 0 | D14: =SUM($C$3:$C$5)/64 | E14: =C14+D14 | F14: =IF($C$70=0, 0, E14/$C$70) | G14: =F14*$T$5 | H14: 4 | I14: =$T$7*H14 | J14: =G14+$T$9+I14 | K14: =$T$4/64 | L14: 0 | M14: 0 | N14: 0 | O14: 0 | R14: =(SUM(J14:P14)*$B$2) | S14: TOTAL FD DONE
A15: F10 | B15: Aby Thomas | C15: 0 | D15: =SUM($C$3:$C$5)/64 | E15: =C15+D15 | F15: =IF($C$70=0, 0, E15/$C$70) | G15: =F15*$T$5 | H15: 3 | I15: =$T$7*H15 | J15: =G15+$T$9+I15 | K15: =$T$4/64 | L15: 0 | M15: 0 | N15: 0 | O15: 0 | R15: =(SUM(J15:P15)*$B$2) | S15: Pending vendor payments
A16: F11 | B16: Niwin Anto | C16: 0 | D16: =SUM($C$3:$C$5)/64 | E16: =C16+D16 | F16: =IF($C$70=0, 0, E16/$C$70) | G16: =F16*$T$5 | H16: 3 | I16: =$T$7*H16 | J16: =G16+$T$9+I16 | K16: =$T$4/64 | L16: 0 | M16: 0 | N16: 0 | O16: 0 | R16: =(SUM(J16:P16)*$B$2) | S16: AMOUNT AVAILABLE FOR NON MAINTENANCE CORPUS | T16: =T13-T14
A17: F12 | B17: Anirudh Singh | C17: 0 | D17: =SUM($C$3:$C$5)/64 | E17: =C17+D17 | F17: =IF($C$70=0, 0, E17/$C$70) | G17: =F17*$T$5 | H17: 3 | I17: =$T$7*H17 | J17: =G17+$T$9+I17 | K17: =$T$4/64 | L17: 0 | M17: 0 | N17: 0 | O17: 0 | R17: =(SUM(J17:P17)*$B$2) | S17: AMOUNT AVAILABLE FOR MAINTENANCE | T17: =T12-T15-T16
A18: F13 | B18: Sanchay Saxena | C18: 0 | D18: =SUM($C$3:$C$5)/64 | E18: =C18+D18 | F18: =IF($C$70=0, 0, E18/$C$70) | G18: =F18*$T$5 | H18: 4 | I18: =$T$7*H18 | J18: =G18+$T$9+I18 | K18: =$T$4/64 | L18: 0 | M18: 0 | N18: 0 | O18: 0 | R18: =(SUM(J18:P18)*$B$2) | S18: Maintenance Deficit | T18: =T17-(T4+T5+23830)
A19: F14 | B19: Hemant Patel | C19: 0 | D19: =SUM($C$3:$C$5)/64 | E19: =C19+D19 | F19: =IF($C$70=0, 0, E19/$C$70) | G19: =F19*$T$5 | H19: 4 | I19: =$T$7*H19 | J19: =G19+$T$9+I19 | K19: =$T$4/64 | L19: 0 | M19: 0 | N19: 0 | O19: 0 | R19: =(SUM(J19:P19)*$B$2)
A20: F15 | B20: Senthil.Vijayaragavan | C20: 0 | D20: =SUM($C$3:$C$5)/64 | E20: =C20+D20 | F20: =IF($C$70=0, 0, E20/$C$70) | G20: =F20*$T$5 | H20: 4 | I20: =$T$7*H20 | J20: =G20+$T$9+I20 | K20: =$T$4/64 | L20: 0 | M20: 0 | N20: 0 | O20: 0 | R20: =(SUM(J20:P20)*$B$2)
A21: F16 | B21: Sreeja Sudharma | C21: 0 | D21: =SUM($C$3:$C$5)/64 | E21: =C21+D21 | F21: =IF($C$70=0, 0, E21/$C$70) | G21: =F21*$T$5 | H21: 3 | I21: =$T$7*H21 | J21: =G21+$T$9+I21 | K21: =$T$4/64 | L21: 0 | M21: 0 | N21: 0 | O21: 0 | R21: =(SUM(J21:P21)*$B$2)
A22: G1 | B22: Venkataramanan C | C22: 0 | D22: =SUM($C$3:$C$5)/64 | E22: =C22+D22 | F22: =IF($C$70=0, 0, E22/$C$70) | G22: =F22*$T$5 | H22: 3 | I22: =$T$7*H22 | J22: =G22+$T$9+I22 | K22: =$T$4/64 | L22: 0 | M22: 0 | N22: 0 | O22: 0 | R22: =(SUM(J22:P22)*$B$2)
A23: G2 | B23: Kaushik Kasibhatla | C23: 0 | D23: =SUM($C$3:$C$5)/64 | E23: =C23+D23 | F23: =IF($C$70=0, 0, E23/$C$70) | G23: =F23*$T$5 | H23: 4 | I23: =$T$7*H23 | J23: =G23+$T$9+I23 | K23: =$T$4/64 | L23: 0 | M23: 0 | N23: 0 | O23: 0 | R23: =(SUM(J23:P23)*$B$2)
A24: G3 | B24: Balakrishnan | C24: 0 | D24: =SUM($C$3:$C$5)/64 | E24: =C24+D24 | F24: =IF($C$70=0, 0, E24/$C$70) | G24: =F24*$T$5 | H24: 4 | I24: =$T$7*H24 | J24: =G24+$T$9+I24 | K24: =$T$4/64 | L24: 0 | M24: 0 | N24: 0 | O24: 0 | R24: =(SUM(J24:P24)*$B$2)
A25: G4 | B25: Ashwin Pandith | C25: 0 | D25: =SUM($C$3:$C$5)/64 | E25: =C25+D25 | F25: =IF($C$70=0, 0, E25/$C$70) | G25: =F25*$T$5 | H25: 4 | I25: =$T$7*H25 | J25: =G25+$T$9+I25 | K25: =$T$4/64 | L25: 0 | M25: 0 | N25: 0 | O25: 0 | R25: =(SUM(J25:P25)*$B$2)
A26: G5 | B26: Mayank Phophaliya | C26: 0 | D26: =SUM($C$3:$C$5)/64 | E26: =C26+D26 | F26: =IF($C$70=0, 0, E26/$C$70) | G26: =F26*$T$5 | H26: 3 | I26: =$T$7*H26 | J26: =G26+$T$9+I26 | K26: =$T$4/64 | L26: 0 | M26: 0 | N26: 0 | O26: 0 | R26: =(SUM(J26:P26)*$B$2)
A27: G6 | B27: Mohit Daga | C27: 0 | D27: =SUM($C$3:$C$5)/64 | E27: =C27+D27 | F27: =IF($C$70=0, 0, E27/$C$70) | G27: =F27*$T$5 | H27: 3 | I27: =$T$7*H27 | J27: =G27+$T$9+I27 | K27: =$T$4/64 | L27: 0 | M27: 0 | N27: 0 | O27: 0 | R27: =(SUM(J27:P27)*$B$2)
A28: G7 | B28: Prince Richfield | C28: 0 | D28: =SUM($C$3:$C$5)/64 | E28: =C28+D28 | F28: =IF($C$70=0, 0, E28/$C$70) | G28: =F28*$T$5 | H28: 3 | I28: =$T$7*H28 | J28: =G28+$T$9+I28 | K28: =$T$4/64 | L28: 0 | M28: 0 | N28: 0 | O28: 0 | R28: =(SUM(J28:P28)*$B$2)
A29: G8 | B29: Ranjithkumar R / Sameer (tenant) / Princy (tenant) | C29: 0 | D29: =SUM($C$3:$C$5)/64 | E29: =C29+D29 | F29: =IF($C$70=0, 0, E29/$C$70) | G29: =F29*$T$5 | H29: 3 | I29: =$T$7*H29 | J29: =G29+$T$9+I29 | K29: =$T$4/64 | L29: 0 | M29: 0 | N29: 0 | O29: 0 | R29: =(SUM(J29:P29)*$B$2)
A30: G9 | B30: Chandramouli | C30: 0 | D30: =SUM($C$3:$C$5)/64 | E30: =C30+D30 | F30: =IF($C$70=0, 0, E30/$C$70) | G30: =F30*$T$5 | H30: 5 | I30: =$T$7*H30 | J30: =G30+$T$9+I30 | K30: =$T$4/64 | L30: 0 | M30: 0 | N30: 0 | O30: 0 | R30: =(SUM(J30:P30)*$B$2)
... A69: T16 | B69: Madhusoodanan P.R. | C69: 0 | D69: =SUM($C$3:$C$5)/64 | E69: =C69+D69 | F69: =IF($C$70=0, 0, E69/$C$70) | G69: =F69*$T$5 | H69: 3 | I69: =$T$7*H69 | J69: =G69+$T$9+I69 | K69: =$T$4/64 | L69: 0 | M69: 0 | N69: 0 | O69: 0 | R69: =(SUM(J69:P69)*$B$2)
A70: TOTAL | B70: TOTAL | C70: =SUM(C3:C69) | D70: =SUM(D3:D69) | E70: =SUM(E5:E69) | F70: =SUM(F6:F69) | G70: =SUM(G6:G69) | H70: =SUM(H3:H69) | I70: =SUM(I3:I69) | J70: =SUM(J6:J69) | K70: =SUM(K6:K69) | L70: =SUM(L3:L69) | M70: =SUM(M3:M69) | N70: =SUM(N3:N69) | O70: =SUM(O3:O69) | P70: =SUM(P3:P69) | R70: =SUM(R3:R69)

Sheet May2026-COLLECTION
A1: FLAT # | C1: Amount | D1: Date | E1: Amount | F1: Date | G1: Amount | H1: Date | I1: Amount | J1: Date | K1: Total
A2: F1 | B2: Shailesh Srivastava / Azeem Nawaz | K2: =SUM(C2,E2,G2,I2)
A3: F2 | B3: Shanthanu | K3: =SUM(C3,E3,G3,I3)
A4: F3 | B4: Samrat Kar | K4: =SUM(C4,E4,G4,I4)
A5: F4 | B5: Renu R | K5: =SUM(C5,E5,G5,I5)
A6: F5 | B6: Vamsidhar Bethanabatla / Madhuri Anumula | K6: =SUM(C6,E6,G6,I6)
A7: F6 | B7: Meghana Viral Shah and Vviral Shah (Owner) / Sangeet and Swagat (Tenent) | K7: =SUM(C7,E7,G7,I7)
A8: F7 | B8: Vimal NK | K8: =SUM(C8,E8,G8,I8)
A9: F8 | B9: Sujeet Kumar (Tenant)/Sreejith Menon (Owner) | K9: =SUM(C9,E9,G9,I9)
A10: F9 | B10: Vijay Suswaram (Owner) / Divya Shikha (Tenant) | K10: =SUM(C10,E10,G10,I10)
A11: F10 | B11: Aby Thomas | K11: =SUM(C11,E11,G11,I11)
A12: F11 | B12: Niwin Anto | K12: =SUM(C12,E12,G12,I12)
A13: F12 | B13: Anirudh Singh | K13: =SUM(C13,E13,G13,I13)
... A65: T16 | B65: Madhusoodanan P.R. | K65: =SUM(C65,E65,G65,I65)
A66: TOTAL | K66: =SUM(K2:K65)

Sheet June2026-EXPENSE
B1: JUN 2026 EXPENSES
A2: FLAT # | B2: 1 | C2: WATER USED IN LTRS (L) | D2: COMMON AREA EQUALLY DEVIDED | E2: TOTAL FRESH WATER CONSUMED | F2: %OF TOTAL USED | G2: WATER EXPENSE SHARING BY % | H2: #METERS | I2: METER RENT | J2: VARIABLE EXPENSE = COMMON AREA METER RENT + WATER EXPENSE+ FLAT METER RENT | K2: FIXED EXPENSE SHARE | L2: PARKING FEE | M2: CLUB BOOKING FEE | N2: POLYCARBONATE PROJECT CANCELLATION CREDIT AMOUNT | O2: SHIFTING FEE | P2: GYM USAGE FEE | R2: TOTAL EXPENSE TO BE PAID
A3: CH | B3: MPFOWA | C3: 0 | D3: 0 | H3: 1 | I3: =H3*$T$7
A4: GYM | B4: MPFOWA | C4: 0 | D4: 0 | H4: 1 | I4: =H4*$T$7 | S4: TOTAL FIXED EXPENSE | T4: ='ANNUAL-EXPENSE-DETAILS'!BF5
A5: BSMT | B5: MPFOWA | C5: 0 | D5: 0 | H5: 1 | I5: =H5*$T$7 | S5: TOTAL WATER EXPENSE | T5: ='ANNUAL-EXPENSE-DETAILS'!BE5
A6: F1 | B6: Shailesh Srivastava / Azeem Nawaz | C6: 0 | D6: =SUM($C$3:$C$5)/64 | E6: =C6+D6 | F6: =IF($C$70=0, 0, E6/$C$70) | G6: =F6*$T$5 | H6: 3 | I6: =$T$7*H6 | J6: =G6+$T$9+I6 | K6: =$T$11/64 | L6: 0 | M6: 0 | O6: 0 | P6: 0 | R6: =(SUM(J6:P6))*$B$2
A7: F2 | B7: Shanthanu | C7: 0 | D7: =SUM($C$3:$C$5)/64 | E7: =C7+D7 | F7: =IF($C$70=0, 0, E7/$C$70) | G7: =F7*$T$5 | H7: 4 | I7: =$T$7*H7 | J7: =G7+$T$9+I7 | K7: =$T$11/64 | L7: 0 | M7: 0 | O7: 0 | P7: 0 | R7: =(SUM(J7:P7))*$B$2 | S7: RENT PER METER | T7: 117.81166
A8: F3 | B8: Samrat Kar | C8: 0 | D8: =SUM($C$3:$C$5)/64 | E8: =C8+D8 | F8: =IF($C$70=0, 0, E8/$C$70) | G8: =F8*$T$5 | H8: 4 | I8: =$T$7*H8 | J8: =G8+$T$9+I8 | K8: =$T$11/64 | L8: 0 | M8: 0 | O8: 0 | P8: 0 | R8: =(SUM(J8:P8))*$B$2 | S8: COMMON AREA METER RENT | T8: =$T$7*3
A9: F4 | B9: Renu R | C9: 0 | D9: =SUM($C$3:$C$5)/64 | E9: =C9+D9 | F9: =IF($C$70=0, 0, E9/$C$70) | G9: =F9*$T$5 | H9: 4 | I9: =$T$7*H9 | J9: =G9+$T$9+I9 | K9: =$T$11/64 | L9: 0 | M9: 0 | O9: 0 | P9: 0 | R9: =(SUM(J9:P9))*$B$2 | S9: COMMON AREA METER RENT/FLAT | T9: =T8/64
A10: F5 | B10: Vamsidhar Bethanabatla / Madhuri Anumula | C10: 0 | D10: =SUM($C$3:$C$5)/64 | E10: =C10+D10 | F10: =IF($C$70=0, 0, E10/$C$70) | G10: =F10*$T$5 | H10: 3 | I10: =$T$7*H10 | J10: =G10+$T$9+I10 | K10: =$T$11/64 | L10: 0 | M10: 0 | O10: 0 | P10: 0 | R10: =(SUM(J10:P10))*$B$2
A11: F6 | B11: Meghana Viral Shah and Vviral Shah (Owner) / Sangeet and Swagat (Tenent) | C11: 0 | D11: =SUM($C$3:$C$5)/64 | E11: =C11+D11 | F11: =IF($C$70=0, 0, E11/$C$70) | G11: =F11*$T$5 | H11: 3 | I11: =$T$7*H11 | J11: =G11+$T$9+I11 | K11: =$T$11/64 | L11: 0 | M11: 0 | O11: 0 | P11: 0 | R11: =(SUM(J11:P11))*$B$2 | S11: TOTAL FIXED EXPENSE | T11: ='ANNUAL-EXPENSE-DETAILS'!BF5
A12: F7 | B12: Vimal NK | C12: 0 | D12: =SUM($C$3:$C$5)/64 | E12: =C12+D12 | F12: =IF($C$70=0, 0, E12/$C$70) | G12: =F12*$T$5 | H12: 3 | I12: =$T$7*H12 | J12: =G12+$T$9+I12 | K12: =$T$11/64 | L12: 0 | M12: 0 | O12: 0 | P12: 0 | R12: =(SUM(J12:P12))*$B$2
A13: F8 | B13: Sujeet Kumar (Tenant)/Sreejith Menon (Owner) | C13: 0 | D13: =SUM($C$3:$C$5)/64 | E13: =C13+D13 | F13: =IF($C$70=0, 0, E13/$C$70) | G13: =F13*$T$5 | H13: 3 | I13: =$T$7*H13 | J13: =G13+$T$9+I13 | K13: =$T$11/64 | L13: 0 | M13: 0 | O13: 0 | P13: 0 | R13: =(SUM(J13:P13))*$B$2
A14: F9 | B14: Vijay Suswaram (Owner) / Divya Shikha (Tenant) | C14: 0 | D14: =SUM($C$3:$C$5)/64 | E14: =C14+D14 | F14: =IF($C$70=0, 0, E14/$C$70) | G14: =F14*$T$5 | H14: 4 | I14: =$T$7*H14 | J14: =G14+$T$9+I14 | K14: =$T$11/64 | L14: 0 | M14: 0 | O14: 0 | P14: 0 | R14: =(SUM(J14:P14))*$B$2 | S14: BALANCE IN ACCOUNT ON 30-JUN-2023
A15: F10 | B15: Aby Thomas | C15: 0 | D15: =SUM($C$3:$C$5)/64 | E15: =C15+D15 | F15: =IF($C$70=0, 0, E15/$C$70) | G15: =F15*$T$5 | H15: 3 | I15: =$T$7*H15 | J15: =G15+$T$9+I15 | K15: =$T$11/64 | L15: 0 | M15: 0 | O15: 0 | P15: 0 | R15: =(SUM(J15:P15))*$B$2 | S15: TOTAL NON MAINTENANCE CORPUS COLLECTION
A16: F11 | B16: Niwin Anto | C16: 0 | D16: =SUM($C$3:$C$5)/64 | E16: =C16+D16 | F16: =IF($C$70=0, 0, E16/$C$70) | G16: =F16*$T$5 | H16: 3 | I16: =$T$7*H16 | J16: =G16+$T$9+I16 | K16: =$T$11/64 | L16: 0 | M16: 0 | O16: 0 | P16: 0 | R16: =(SUM(J16:P16))*$B$2 | S16: TOTAL FD DONE
A17: F12 | B17: Anirudh Singh | C17: 0 | D17: =SUM($C$3:$C$5)/64 | E17: =C17+D17 | F17: =IF($C$70=0, 0, E17/$C$70) | G17: =F17*$T$5 | H17: 3 | I17: =$T$7*H17 | J17: =G17+$T$9+I17 | K17: =$T$11/64 | L17: 0 | M17: 0 | O17: 0 | P17: 0 | R17: =(SUM(J17:P17))*$B$2 | S17: AMOUNT AVAILABLE FOR NON MAINTENANCE CORPUS | T17: =T15-T16
A18: F13 | B18: Sanchay Saxena | C18: 0 | D18: =SUM($C$3:$C$5)/64 | E18: =C18+D18 | F18: =IF($C$70=0, 0, E18/$C$70) | G18: =F18*$T$5 | H18: 4 | I18: =$T$7*H18 | J18: =G18+$T$9+I18 | K18: =$T$11/64 | L18: 0 | M18: 0 | O18: 0 | P18: 0 | R18: =(SUM(J18:P18))*$B$2 | S18: AMOUNT AVAILABLE FOR MAINTENANCE | T18: =T14-T17
A19: F14 | B19: Hemant Patel | C19: 0 | D19: =SUM($C$3:$C$5)/64 | E19: =C19+D19 | F19: =IF($C$70=0, 0, E19/$C$70) | G19: =F19*$T$5 | H19: 4 | I19: =$T$7*H19 | J19: =G19+$T$9+I19 | K19: =$T$11/64 | L19: 0 | M19: 0 | O19: 0 | P19: 0 | R19: =(SUM(J19:P19))*$B$2
A20: F15 | B20: Senthil.Vijayaragavan | C20: 0 | D20: =SUM($C$3:$C$5)/64 | E20: =C20+D20 | F20: =IF($C$70=0, 0, E20/$C$70) | G20: =F20*$T$5 | H20: 4 | I20: =$T$7*H20 | J20: =G20+$T$9+I20 | K20: =$T$11/64 | L20: 0 | M20: 0 | O20: 0 | P20: 0 | R20: =(SUM(J20:P20))*$B$2
A21: F16 | B21: Sreeja Sudharma | C21: 0 | D21: =SUM($C$3:$C$5)/64 | E21: =C21+D21 | F21: =IF($C$70=0, 0, E21/$C$70) | G21: =F21*$T$5 | H21: 3 | I21: =$T$7*H21 | J21: =G21+$T$9+I21 | K21: =$T$11/64 | L21: 0 | M21: 0 | O21: 0 | P21: 0 | R21: =(SUM(J21:P21))*$B$2
A22: G1 | B22: Venkataramanan C | C22: 0 | D22: =SUM($C$3:$C$5)/64 | E22: =C22+D22 | F22: =IF($C$70=0, 0, E22/$C$70) | G22: =F22*$T$5 | H22: 3 | I22: =$T$7*H22 | J22: =G22+$T$9+I22 | K22: =$T$11/64 | L22: 0 | M22: 0 | O22: 0 | P22: 0 | R22: =(SUM(J22:P22))*$B$2
A23: G2 | B23: Kaushik Kasibhatla | C23: 0 | D23: =SUM($C$3:$C$5)/64 | E23: =C23+D23 | F23: =IF($C$70=0, 0, E23/$C$70) | G23: =F23*$T$5 | H23: 4 | I23: =$T$7*H23 | J23: =G23+$T$9+I23 | K23: =$T$11/64 | L23: 0 | M23: 0 | O23: 0 | P23: 0 | R23: =(SUM(J23:P23))*$B$2
A24: G3 | B24: Balakrishnan | C24: 0 | D24: =SUM($C$3:$C$5)/64 | E24: =C24+D24 | F24: =IF($C$70=0, 0, E24/$C$70) | G24: =F24*$T$5 | H24: 4 | I24: =$T$7*H24 | J24: =G24+$T$9+I24 | K24: =$T$11/64 | L24: 0 | M24: 0 | O24: 0 | P24: 0 | R24: =(SUM(J24:P24))*$B$2
A25: G4 | B25: Ashwin Pandith | C25: 0 | D25: =SUM($C$3:$C$5)/64 | E25: =C25+D25 | F25: =IF($C$70=0, 0, E25/$C$70) | G25: =F25*$T$5 | H25: 4 | I25: =$T$7*H25 | J25: =G25+$T$9+I25 | K25: =$T$11/64 | L25: 0 | M25: 0 | O25: 0 | P25: 0 | R25: =(SUM(J25:P25))*$B$2
A26: G5 | B26: Mayank Phophaliya | C26: 0 | D26: =SUM($C$3:$C$5)/64 | E26: =C26+D26 | F26: =IF($C$70=0, 0, E26/$C$70) | G26: =F26*$T$5 | H26: 3 | I26: =$T$7*H26 | J26: =G26+$T$9+I26 | K26: =$T$11/64 | L26: 0 | M26: 0 | O26: 0 | P26: 0 | R26: =(SUM(J26:P26))*$B$2
A27: G6 | B27: Mohit Daga | C27: 0 | D27: =SUM($C$3:$C$5)/64 | E27: =C27+D27 | F27: =IF($C$70=0, 0, E27/$C$70) | G27: =F27*$T$5 | H27: 3 | I27: =$T$7*H27 | J27: =G27+$T$9+I27 | K27: =$T$11/64 | L27: 0 | M27: 0 | O27: 0 | P27: 0 | R27: =(SUM(J27:P27))*$B$2
A28: G7 | B28: Prince Richfield | C28: 0 | D28: =SUM($C$3:$C$5)/64 | E28: =C28+D28 | F28: =IF($C$70=0, 0, E28/$C$70) | G28: =F28*$T$5 | H28: 3 | I28: =$T$7*H28 | J28: =G28+$T$9+I28 | K28: =$T$11/64 | L28: 0 | M28: 0 | O28: 0 | P28: 0 | R28: =(SUM(J28:P28))*$B$2
A29: G8 | B29: Ranjithkumar R / Sameer (tenant) / Princy (tenant) | C29: 0 | D29: =SUM($C$3:$C$5)/64 | E29: =C29+D29 | F29: =IF($C$70=0, 0, E29/$C$70) | G29: =F29*$T$5 | H29: 3 | I29: =$T$7*H29 | J29: =G29+$T$9+I29 | K29: =$T$11/64 | L29: 0 | M29: 0 | O29: 0 | P29: 0 | R29: =(SUM(J29:P29))*$B$2
A30: G9 | B30: Chandramouli | C30: 0 | D30: =SUM($C$3:$C$5)/64 | E30: =C30+D30 | F30: =IF($C$70=0, 0, E30/$C$70) | G30: =F30*$T$5 | H30: 5 | I30: =$T$7*H30 | J30: =G30+$T$9+I30 | K30: =$T$11/64 | L30: 0 | M30: 0 | O30: 0 | P30: 0 | R30: =(SUM(J30:P30))*$B$2
... A69: T16 | B69: Madhusoodanan P.R. | C69: 0 | D69: =SUM($C$3:$C$5)/64 | E69: =C69+D69 | F69: =IF($C$70=0, 0, E69/$C$70) | G69: =F69*$T$5 | H69: 3 | I69: =$T$7*H69 | J69: =G69+$T$9+I69 | K69: =$T$11/64 | L69: 0 | M69: 0 | O69: 0 | P69: 0 | R69: =(SUM(J69:P69))*$B$2
B70: TOTAL | C70: =SUM(C3:C69) | D70: =SUM(D3:D69) | E70: =SUM(E3:E69) | F70: =IF($C$70=0, 0, E70/$C$70) | G70: =SUM(G3:G69) | H70: =SUM(H3:H69) | I70: =SUM(I3:I69) | J70: =SUM(J3:J69) | K70: =SUM(K3:K69) | L70: =SUM(L3:L69) | M70: =SUM(M3:M69) | N70: =SUM(N3:N69) | ... P70: =SUM(P3:P69) | R70: =SUM(R3:R69)

Sheet June2026-COLLECTION
A1: FLAT # | C1: Amount | D1: Date | E1: Amount | F1: Date | G1: Amount | H1: Date | I1: Amount | J1: Date | K1: Total
A2: F1 | B2: Shailesh Srivastava / Azeem Nawaz | K2: =SUM(C2,E2,G2,I2)
A3: F2 | B3: Shanthanu | K3: =SUM(C3,E3,G3,I3)
A4: F3 | B4: Samrat Kar | K4: =SUM(C4,E4,G4,I4)
A5: F4 | B5: Renu R | K5: =SUM(C5,E5,G5,I5)
A6: F5 | B6: Vamsidhar Bethanabatla / Madhuri Anumula | K6: =SUM(C6,E6,G6,I6)
A7: F6 | B7: Meghana Viral Shah and Vviral Shah (Owner) / Sangeet and Swagat (Tenent) | K7: =SUM(C7,E7,G7,I7)
A8: F7 | B8: Vimal NK | K8: =SUM(C8,E8,G8,I8)
A9: F8 | B9: Sujeet Kumar (Tenant)/Sreejith Menon (Owner) | K9: =SUM(C9,E9,G9,I9)
A10: F9 | B10: Vijay Suswaram (Owner) / Divya Shikha (Tenant) | K10: =SUM(C10,E10,G10,I10)
A11: F10 | B11: Aby Thomas | K11: =SUM(C11,E11,G11,I11)
A12: F11 | B12: Niwin Anto | K12: =SUM(C12,E12,G12,I12)
A13: F12 | B13: Anirudh Singh | K13: =SUM(C13,E13,G13,I13)
... A65: T16 | B65: Madhusoodanan P.R. | K65: =SUM(C65,E65,G65,I65)
A66: TOTAL | K66: =SUM(K2:K65)

Sheet July2026-EXPENSE
B1: JUL 2026 EXPENSES
A2: FLAT # | B2: 1 | C2: WATER USED IN LTRS | D2: COMMON AREA EQUALLY DEVIDED | E2: TOTAL FRESH WATER CONSUMED | F2: %OF TOTAL USED | G2: WATER EXPENSE SHARING BY % | H2: #METERS | I2: METER RENT | J2: VARIABLE EXPENSE = COMMON AREA METER RENT + WATER EXPENSE+ FLAT METER RENT | K2: FIXED EXPENSE SHARE | L2: PARKING FEE | M2: CLUB BOOKING FEE | N2: SHIFTING FEE | O2: GYM USAGE FEE | R2: TOTAL EXPENSE TO BE PAID
A3: CH | B3: MPFOWA | C3: 0 | D3: 0 | H3: 1 | I3: =T7
A4: GYM | B4: MPFOWA | C4: 0 | D4: 0 | H4: 1 | I4: =T7 | S4: TOTAL FIXED EXPENSE | T4: ='ANNUAL-EXPENSE-DETAILS'!BF6
A5: BSMT | B5: MPFOWA | C5: 0 | D5: 0 | H5: 1 | I5: =T7 | S5: TOTAL WATER EXPENSE | T5: ='ANNUAL-EXPENSE-DETAILS'!BE6
A6: F1 | B6: Shailesh Srivastava / Azeem Nawaz | C6: 0 | D6: =SUM($C$3:$C$5)/64 | E6: =C6+D6 | F6: =IF($C$70=0, 0, E6/$C$70) | G6: =F6*$T$5 | H6: 3 | I6: =$T$7*H6 | J6: =G6+$T$9+I6 | K6: =$T$11/64 | L6: 0 | M6: 0 | N6: 0 | O6: 0 | R6: =(J6+K6+L6+M6+N6+O6)*$B$2
A7: F2 | B7: Shanthanu | C7: 0 | D7: =SUM($C$3:$C$5)/64 | E7: =C7+D7 | F7: =IF($C$70=0, 0, E7/$C$70) | G7: =F7*$T$5 | H7: 4 | I7: =$T$7*H7 | J7: =G7+$T$9+I7 | K7: =$T$11/64 | L7: 0 | M7: 0 | N7: 0 | O7: 0 | R7: =(J7+K7+L7+M7+N7+O7)*$B$2 | S7: RENT PER METER | T7: 117.81166
A8: F3 | B8: Samrat Kar | C8: 0 | D8: =SUM($C$3:$C$5)/64 | E8: =C8+D8 | F8: =IF($C$70=0, 0, E8/$C$70) | G8: =F8*$T$5 | H8: 4 | I8: =$T$7*H8 | J8: =G8+$T$9+I8 | K8: =$T$11/64 | L8: 0 | M8: 0 | N8: 0 | O8: 0 | R8: =(J8+K8+L8+M8+N8+O8)*$B$2 | S8: COMMON AREA METER RENT | T8: =$T$7*3
A9: F4 | B9: Renu R | C9: 0 | D9: =SUM($C$3:$C$5)/64 | E9: =C9+D9 | F9: =IF($C$70=0, 0, E9/$C$70) | G9: =F9*$T$5 | H9: 4 | I9: =$T$7*H9 | J9: =G9+$T$9+I9 | K9: =$T$11/64 | L9: 0 | M9: 0 | N9: 0 | O9: 0 | R9: =(J9+K9+L9+M9+N9+O9)*$B$2 | S9: COMMON AREA METER RENT/FLAT | T9: =T8/64
A10: F5 | B10: Vamsidhar Bethanabatla / Madhuri Anumula | C10: 0 | D10: =SUM($C$3:$C$5)/64 | E10: =C10+D10 | F10: =IF($C$70=0, 0, E10/$C$70) | G10: =F10*$T$5 | H10: 3 | I10: =$T$7*H10 | J10: =G10+$T$9+I10 | K10: =$T$11/64 | L10: 0 | M10: 0 | N10: 0 | O10: 0 | R10: =(J10+K10+L10+M10+N10+O10)*$B$2
A11: F6 | B11: Meghana Viral Shah and Vviral Shah (Owner) / Sangeet and Swagat (Tenent) | C11: 0 | D11: =SUM($C$3:$C$5)/64 | E11: =C11+D11 | F11: =IF($C$70=0, 0, E11/$C$70) | G11: =F11*$T$5 | H11: 3 | I11: =$T$7*H11 | J11: =G11+$T$9+I11 | K11: =$T$11/64 | L11: 0 | M11: 0 | N11: 0 | O11: 0 | R11: =(J11+K11+L11+M11+N11+O11)*$B$2 | S11: TOTAL FIXED EXPENSE | T11: ='ANNUAL-EXPENSE-DETAILS'!BF6
A12: F7 | B12: Vimal NK | C12: 0 | D12: =SUM($C$3:$C$5)/64 | E12: =C12+D12 | F12: =IF($C$70=0, 0, E12/$C$70) | G12: =F12*$T$5 | H12: 3 | I12: =$T$7*H12 | J12: =G12+$T$9+I12 | K12: =$T$11/64 | L12: 0 | M12: 0 | N12: 0 | O12: 0 | R12: =(J12+K12+L12+M12+N12+O12)*$B$2
A13: F8 | B13: Sujeet Kumar (Tenant)/Sreejith Menon (Owner) | C13: 0 | D13: =SUM($C$3:$C$5)/64 | E13: =C13+D13 | F13: =IF($C$70=0, 0, E13/$C$70) | G13: =F13*$T$5 | H13: 3 | I13: =$T$7*H13 | J13: =G13+$T$9+I13 | K13: =$T$11/64 | L13: 0 | M13: 0 | N13: 0 | O13: 0 | R13: =(J13+K13+L13+M13+N13+O13)*$B$2
A14: F9 | B14: Vijay Suswaram (Owner) / Divya Shikha (Tenant) | C14: 0 | D14: =SUM($C$3:$C$5)/64 | E14: =C14+D14 | F14: =IF($C$70=0, 0, E14/$C$70) | G14: =F14*$T$5 | H14: 4 | I14: =$T$7*H14 | J14: =G14+$T$9+I14 | K14: =$T$11/64 | L14: 0 | M14: 0 | N14: 0 | O14: 0 | R14: =(J14+K14+L14+M14+N14+O14)*$B$2 | S14: BALANCE IN ACCOUNT ON 31-JULY-2023
A15: F10 | B15: Aby Thomas | C15: 0 | D15: =SUM($C$3:$C$5)/64 | E15: =C15+D15 | F15: =IF($C$70=0, 0, E15/$C$70) | G15: =F15*$T$5 | H15: 3 | I15: =$T$7*H15 | J15: =G15+$T$9+I15 | K15: =$T$11/64 | L15: 0 | M15: 0 | N15: 0 | O15: 0 | R15: =(J15+K15+L15+M15+N15+O15)*$B$2 | S15: TOTAL NON MAINTENANCE CORPUS COLLECTION
A16: F11 | B16: Niwin Anto | C16: 0 | D16: =SUM($C$3:$C$5)/64 | E16: =C16+D16 | F16: =IF($C$70=0, 0, E16/$C$70) | G16: =F16*$T$5 | H16: 3 | I16: =$T$7*H16 | J16: =G16+$T$9+I16 | K16: =$T$11/64 | L16: 0 | M16: 0 | N16: 0 | O16: 0 | R16: =(J16+K16+L16+M16+N16+O16)*$B$2 | S16: TOTAL FD DONE
A17: F12 | B17: Anirudh Singh | C17: 0 | D17: =SUM($C$3:$C$5)/64 | E17: =C17+D17 | F17: =IF($C$70=0, 0, E17/$C$70) | G17: =F17*$T$5 | H17: 3 | I17: =$T$7*H17 | J17: =G17+$T$9+I17 | K17: =$T$11/64 | L17: 0 | M17: 0 | N17: 0 | O17: 0 | R17: =(J17+K17+L17+M17+N17+O17)*$B$2 | S17: AMOUNT AVAILABLE FOR NON MAINTENANCE CORPUS | T17: =T15-T16
A18: F13 | B18: Sanchay Saxena | C18: 0 | D18: =SUM($C$3:$C$5)/64 | E18: =C18+D18 | F18: =IF($C$70=0, 0, E18/$C$70) | G18: =F18*$T$5 | H18: 4 | I18: =$T$7*H18 | J18: =G18+$T$9+I18 | K18: =$T$11/64 | L18: 0 | M18: 0 | N18: 0 | O18: 0 | R18: =(J18+K18+L18+M18+N18+O18)*$B$2 | S18: AMOUNT AVAILABLE FOR MAINTENANCE | T18: =T14-T17
A19: F14 | B19: Hemant Patel | C19: 0 | D19: =SUM($C$3:$C$5)/64 | E19: =C19+D19 | F19: =IF($C$70=0, 0, E19/$C$70) | G19: =F19*$T$5 | H19: 4 | I19: =$T$7*H19 | J19: =G19+$T$9+I19 | K19: =$T$11/64 | L19: 0 | M19: 0 | N19: 0 | O19: 0 | R19: =(J19+K19+L19+M19+N19+O19)*$B$2
A20: F15 | B20: Senthil.Vijayaragavan | C20: 0 | D20: =SUM($C$3:$C$5)/64 | E20: =C20+D20 | F20: =IF($C$70=0, 0, E20/$C$70) | G20: =F20*$T$5 | H20: 4 | I20: =$T$7*H20 | J20: =G20+$T$9+I20 | K20: =$T$11/64 | L20: 0 | M20: 0 | N20: 0 | O20: 0 | R20: =(J20+K20+L20+M20+N20+O20)*$B$2
A21: F16 | B21: Sreeja Sudharma | C21: 0 | D21: =SUM($C$3:$C$5)/64 | E21: =C21+D21 | F21: =IF($C$70=0, 0, E21/$C$70) | G21: =F21*$T$5 | H21: 3 | I21: =$T$7*H21 | J21: =G21+$T$9+I21 | K21: =$T$11/64 | L21: 0 | M21: 0 | N21: 0 | O21: 0 | R21: =(J21+K21+L21+M21+N21+O21)*$B$2
A22: G1 | B22: Venkataramanan C | C22: 0 | D22: =SUM($C$3:$C$5)/64 | E22: =C22+D22 | F22: =IF($C$70=0, 0, E22/$C$70) | G22: =F22*$T$5 | H22: 3 | I22: =$T$7*H22 | J22: =G22+$T$9+I22 | K22: =$T$11/64 | L22: 0 | M22: 0 | N22: 0 | O22: 0 | R22: =(J22+K22+L22+M22+N22+O22)*$B$2
A23: G2 | B23: Kaushik Kasibhatla | C23: 0 | D23: =SUM($C$3:$C$5)/64 | E23: =C23+D23 | F23: =IF($C$70=0, 0, E23/$C$70) | G23: =F23*$T$5 | H23: 4 | I23: =$T$7*H23 | J23: =G23+$T$9+I23 | K23: =$T$11/64 | L23: 0 | M23: 0 | N23: 0 | O23: 0 | R23: =(J23+K23+L23+M23+N23+O23)*$B$2
A24: G3 | B24: Balakrishnan | C24: 0 | D24: =SUM($C$3:$C$5)/64 | E24: =C24+D24 | F24: =IF($C$70=0, 0, E24/$C$70) | G24: =F24*$T$5 | H24: 4 | I24: =$T$7*H24 | J24: =G24+$T$9+I24 | K24: =$T$11/64 | L24: 0 | M24: 0 | N24: 0 | O24: 0 | R24: =(J24+K24+L24+M24+N24+O24)*$B$2
A25: G4 | B25: Ashwin Pandith | C25: 0 | D25: =SUM($C$3:$C$5)/64 | E25: =C25+D25 | F25: =IF($C$70=0, 0, E25/$C$70) | G25: =F25*$T$5 | H25: 4 | I25: =$T$7*H25 | J25: =G25+$T$9+I25 | K25: =$T$11/64 | L25: 0 | M25: 0 | N25: 0 | O25: 0 | R25: =(J25+K25+L25+M25+N25+O25)*$B$2
A26: G5 | B26: Mayank Phophaliya | C26: 0 | D26: =SUM($C$3:$C$5)/64 | E26: =C26+D26 | F26: =IF($C$70=0, 0, E26/$C$70) | G26: =F26*$T$5 | H26: 3 | I26: =$T$7*H26 | J26: =G26+$T$9+I26 | K26: =$T$11/64 | L26: 0 | M26: 0 | N26: 0 | O26: 0 | R26: =(J26+K26+L26+M26+N26+O26)*$B$2
A27: G6 | B27: Mohit Daga | C27: 0 | D27: =SUM($C$3:$C$5)/64 | E27: =C27+D27 | F27: =IF($C$70=0, 0, E27/$C$70) | G27: =F27*$T$5 | H27: 3 | I27: =$T$7*H27 | J27: =G27+$T$9+I27 | K27: =$T$11/64 | L27: 0 | M27: 0 | N27: 0 | O27: 0 | R27: =(J27+K27+L27+M27+N27+O27)*$B$2
A28: G7 | B28: Prince Richfield | C28: 0 | D28: =SUM($C$3:$C$5)/64 | E28: =C28+D28 | F28: =IF($C$70=0, 0, E28/$C$70) | G28: =F28*$T$5 | H28: 3 | I28: =$T$7*H28 | J28: =G28+$T$9+I28 | K28: =$T$11/64 | L28: 0 | M28: 0 | N28: 0 | O28: 0 | R28: =(J28+K28+L28+M28+N28+O28)*$B$2
A29: G8 | B29: Ranjithkumar R / Sameer (tenant) / Princy (tenant) | C29: 0 | D29: =SUM($C$3:$C$5)/64 | E29: =C29+D29 | F29: =IF($C$70=0, 0, E29/$C$70) | G29: =F29*$T$5 | H29: 3 | I29: =$T$7*H29 | J29: =G29+$T$9+I29 | K29: =$T$11/64 | L29: 0 | M29: 0 | N29: 0 | O29: 0 | R29: =(J29+K29+L29+M29+N29+O29)*$B$2
A30: G9 | B30: Chandramouli | C30: 0 | D30: =SUM($C$3:$C$5)/64 | E30: =C30+D30 | F30: =IF($C$70=0, 0, E30/$C$70) | G30: =F30*$T$5 | H30: 5 | I30: =$T$7*H30 | J30: =G30+$T$9+I30 | K30: =$T$11/64 | L30: 0 | M30: 0 | N30: 0 | O30: 0 | R30: =(J30+K30+L30+M30+N30+O30)*$B$2
... A69: T16 | B69: Madhusoodanan P.R. | C69: 0 | D69: =SUM($C$3:$C$5)/64 | E69: =C69+D69 | F69: =IF($C$70=0, 0, E69/$C$70) | G69: =F69*$T$5 | H69: 3 | I69: =$T$7*H69 | J69: =G69+$T$9+I69 | K69: =$T$11/64 | L69: 0 | M69: 0 | N69: 0 | O69: 0 | R69: =(J69+K69+L69+M69+N69+O69)*$B$2
B70: TOTAL | C70: =SUM(C3:C69) | D70: =SUM(D3:D69) | E70: =SUM(E3:E69) | F70: =SUM(F3:F69) | G70: =SUM(G3:G69) | H70: =SUM(H3:H69) | I70: =SUM(I3:I69) | J70: =SUM(J3:J69) | ... O70: =SUM(O3:O69) | R70: =SUM(R3:R69)

Sheet July2026-EXPENSE-Flatwise
A1: Expense Head | C1: {=TRANSPOSE('INCOME-EXPENSE-CYCLES'!A3:A66)} | D1: F2 | E1: F3 | F1: F4 | G1: F5 | H1: F6 | I1: F7 | J1: F8 | K1: F9 | L1: F10 | M1: F11 | N1: F12 | O1: F13 | P1: F14 | Q1: F15 | R1: F16 | S1: G1 | T1: G2 | U1: G3 | V1: G4 | W1: G5 | X1: G6 | Y1: G7 | Z1: G8 | AA1: G9 | AB1: G10 | AC1: G11 | AD1: G12 | AE1: G13 | AF1: G14 | AG1: G15 | AH1: G16 | AI1: S1 | AJ1: S2 | AK1: S3 | AL1: S4 | AM1: S5 | AN1: S6 | AO1: S7 | AP1: S8 | AQ1: S9 | AR1: S10 | AS1: S11 | AT1: S12 | AU1: S13 | AV1: S14 | AW1: S15 | AX1: S16 | AY1: T1 | AZ1: T2 | BA1: T3 | BB1: T4 | BC1: T5 | BD1: T6 | BE1: T7 | BF1: T8 | BG1: T9 | BH1: T10 | BI1: T11 | BJ1: T12 | BK1: T13 | BL1: T14 | BM1: T15 | BN1: T16
A2: Water consumption (Litres) | C2: {=TRANSPOSE('July2026-EXPENSE'!E6:E69)} | D2: 0 | E2: 0 | F2: 0 | G2: 0 | H2: 0 | I2: 0 | J2: 0 | K2: 0 | L2: 0 | M2: 0 | N2: 0 | O2: 0 | P2: 0 | Q2: 0 | R2: 0 | S2: 0 | T2: 0 | U2: 0 | V2: 0 | W2: 0 | X2: 0 | Y2: 0 | Z2: 0 | AA2: 0 | AB2: 0 | AC2: 0 | AD2: 0 | AE2: 0 | AF2: 0 | AG2: 0 | AH2: 0 | AI2: 0 | AJ2: 0 | AK2: 0 | AL2: 0 | AM2: 0 | AN2: 0 | AO2: 0 | AP2: 0 | AQ2: 0 | AR2: 0 | AS2: 0 | AT2: 0 | AU2: 0 | AV2: 0 | AW2: 0 | AX2: 0 | AY2: 0 | AZ2: 0 | BA2: 0 | BB2: 0 | BC2: 0 | BD2: 0 | BE2: 0 | BF2: 0 | BG2: 0 | BH2: 0 | BI2: 0 | BJ2: 0 | BK2: 0 | BL2: 0 | BM2: 0 | BN2: 0
A3: Water consumption (%age of total) | C3: {=TRANSPOSE('July2026-EXPENSE'!F6:F69)} | D3: 0 | E3: 0 | F3: 0 | G3: 0 | H3: 0 | I3: 0 | J3: 0 | K3: 0 | L3: 0 | M3: 0 | N3: 0 | O3: 0 | P3: 0 | Q3: 0 | R3: 0 | S3: 0 | T3: 0 | U3: 0 | V3: 0 | W3: 0 | X3: 0 | Y3: 0 | Z3: 0 | AA3: 0 | AB3: 0 | AC3: 0 | AD3: 0 | AE3: 0 | AF3: 0 | AG3: 0 | AH3: 0 | AI3: 0 | AJ3: 0 | AK3: 0 | AL3: 0 | AM3: 0 | AN3: 0 | AO3: 0 | AP3: 0 | AQ3: 0 | AR3: 0 | AS3: 0 | AT3: 0 | AU3: 0 | AV3: 0 | AW3: 0 | AX3: 0 | AY3: 0 | AZ3: 0 | BA3: 0 | BB3: 0 | BC3: 0 | BD3: 0 | BE3: 0 | BF3: 0 | BG3: 0 | BH3: 0 | BI3: 0 | BJ3: 0 | BK3: 0 | BL3: 0 | BM3: 0 | BN3: 0
A4: Water meter rent | C4: {=TRANSPOSE('July2026-EXPENSE'!I6:I69)} | D4: 0 | E4: 0 | F4: 0 | G4: 0 | H4: 0 | I4: 0 | J4: 0 | K4: 0 | L4: 0 | M4: 0 | N4: 0 | O4: 0 | P4: 0 | Q4: 0 | R4: 0 | S4: 0 | T4: 0 | U4: 0 | V4: 0 | W4: 0 | X4: 0 | Y4: 0 | Z4: 0 | AA4: 0 | AB4: 0 | AC4: 0 | AD4: 0 | AE4: 0 | AF4: 0 | AG4: 0 | AH4: 0 | AI4: 0 | AJ4: 0 | AK4: 0 | AL4: 0 | AM4: 0 | AN4: 0 | AO4: 0 | AP4: 0 | AQ4: 0 | AR4: 0 | AS4: 0 | AT4: 0 | AU4: 0 | AV4: 0 | AW4: 0 | AX4: 0 | AY4: 0 | AZ4: 0 | BA4: 0 | BB4: 0 | BC4: 0 | BD4: 0 | BE4: 0 | BF4: 0 | BG4: 0 | BH4: 0 | BI4: 0 | BJ4: 0 | BK4: 0 | BL4: 0 | BM4: 0 | BN4: 0
A5: Common meter rent (eq. distributed) | C5: ='July2026-EXPENSE'!$T$9 | D5: ='July2026-EXPENSE'!$T$9 | E5: ='July2026-EXPENSE'!$T$9 | F5: ='July2026-EXPENSE'!$T$9 | G5: ='July2026-EXPENSE'!$T$9 | H5: ='July2026-EXPENSE'!$T$9 | I5: ='July2026-EXPENSE'!$T$9 | J5: ='July2026-EXPENSE'!$T$9 | ... BN5: ='July2026-EXPENSE'!$T$9
A6: Total water related expense | C6: {=TRANSPOSE('July2026-EXPENSE'!J6:J69)} | D6: 0 | E6: 0 | F6: 0 | G6: 0 | H6: 0 | I6: 0 | J6: 0 | K6: 0 | L6: 0 | M6: 0 | N6: 0 | O6: 0 | P6: 0 | Q6: 0 | R6: 0 | S6: 0 | T6: 0 | U6: 0 | V6: 0 | W6: 0 | X6: 0 | Y6: 0 | Z6: 0 | AA6: 0 | AB6: 0 | AC6: 0 | AD6: 0 | AE6: 0 | AF6: 0 | AG6: 0 | AH6: 0 | AI6: 0 | AJ6: 0 | AK6: 0 | AL6: 0 | AM6: 0 | AN6: 0 | AO6: 0 | AP6: 0 | AQ6: 0 | AR6: 0 | AS6: 0 | AT6: 0 | AU6: 0 | AV6: 0 | AW6: 0 | AX6: 0 | AY6: 0 | AZ6: 0 | BA6: 0 | BB6: 0 | BC6: 0 | BD6: 0 | BE6: 0 | BF6: 0 | BG6: 0 | BH6: 0 | BI6: 0 | BJ6: 0 | BK6: 0 | BL6: 0 | BM6: 0 | BN6: 0
A7: Society Parking Rent | C7: {=TRANSPOSE('July2026-EXPENSE'!L6:L69)} | D7: 0 | E7: 0 | F7: 0 | G7: 0 | H7: 0 | I7: 0 | J7: 0 | K7: 0 | L7: 0 | M7: 0 | N7: 0 | O7: 0 | P7: 0 | Q7: 0 | R7: 0 | S7: 0 | T7: 0 | U7: 0 | V7: 0 | W7: 0 | X7: 0 | Y7: 0 | Z7: 0 | AA7: 0 | AB7: 0 | AC7: 0 | AD7: 0 | AE7: 0 | AF7: 0 | AG7: 0 | AH7: 0 | AI7: 0 | AJ7: 0 | AK7: 0 | AL7: 0 | AM7: 0 | AN7: 0 | AO7: 0 | AP7: 0 | AQ7: 0 | AR7: 0 | AS7: 0 | AT7: 0 | AU7: 0 | AV7: 0 | AW7: 0 | AX7: 0 | AY7: 0 | AZ7: 0 | BA7: 0 | BB7: 0 | BC7: 0 | BD7: 0 | BE7: 0 | BF7: 0 | BG7: 0 | BH7: 0 | BI7: 0 | BJ7: 0 | BK7: 0 | BL7: 0 | BM7: 0 | BN7: 0
A8: Clubhouse booking fee | C8: {=TRANSPOSE('July2026-EXPENSE'!M6:M69)} | D8: 0 | E8: 0 | F8: 0 | G8: 0 | H8: 0 | I8: 0 | J8: 0 | K8: 0 | L8: 0 | M8: 0 | N8: 0 | O8: 0 | P8: 0 | Q8: 0 | R8: 0 | S8: 0 | T8: 0 | U8: 0 | V8: 0 | W8: 0 | X8: 0 | Y8: 0 | Z8: 0 | AA8: 0 | AB8: 0 | AC8: 0 | AD8: 0 | AE8: 0 | AF8: 0 | AG8: 0 | AH8: 0 | AI8: 0 | AJ8: 0 | AK8: 0 | AL8: 0 | AM8: 0 | AN8: 0 | AO8: 0 | AP8: 0 | AQ8: 0 | AR8: 0 | AS8: 0 | AT8: 0 | AU8: 0 | AV8: 0 | AW8: 0 | AX8: 0 | AY8: 0 | AZ8: 0 | BA8: 0 | BB8: 0 | BC8: 0 | BD8: 0 | BE8: 0 | BF8: 0 | BG8: 0 | BH8: 0 | BI8: 0 | BJ8: 0 | BK8: 0 | BL8: 0 | BM8: 0 | BN8: 0
A9: Moving in/out charges | C9: {=TRANSPOSE('July2026-EXPENSE'!N6:N69)} | D9: 0 | E9: 0 | F9: 0 | G9: 0 | H9: 0 | I9: 0 | J9: 0 | K9: 0 | L9: 0 | M9: 0 | N9: 0 | O9: 0 | P9: 0 | Q9: 0 | R9: 0 | S9: 0 | T9: 0 | U9: 0 | V9: 0 | W9: 0 | X9: 0 | Y9: 0 | Z9: 0 | AA9: 0 | AB9: 0 | AC9: 0 | AD9: 0 | AE9: 0 | AF9: 0 | AG9: 0 | AH9: 0 | AI9: 0 | AJ9: 0 | AK9: 0 | AL9: 0 | AM9: 0 | AN9: 0 | AO9: 0 | AP9: 0 | AQ9: 0 | AR9: 0 | AS9: 0 | AT9: 0 | AU9: 0 | AV9: 0 | AW9: 0 | AX9: 0 | AY9: 0 | AZ9: 0 | BA9: 0 | BB9: 0 | BC9: 0 | BD9: 0 | BE9: 0 | BF9: 0 | BG9: 0 | BH9: 0 | BI9: 0 | BJ9: 0 | BK9: 0 | BL9: 0 | BM9: 0 | BN9: 0
A10: Gym usage fee | C10: {=TRANSPOSE('July2026-EXPENSE'!O6:O69)} | D10: 0 | E10: 0 | F10: 0 | G10: 0 | H10: 0 | I10: 0 | J10: 0 | K10: 0 | L10: 0 | M10: 0 | N10: 0 | O10: 0 | P10: 0 | Q10: 0 | R10: 0 | S10: 0 | T10: 0 | U10: 0 | V10: 0 | W10: 0 | X10: 0 | Y10: 0 | Z10: 0 | AA10: 0 | AB10: 0 | AC10: 0 | AD10: 0 | AE10: 0 | AF10: 0 | AG10: 0 | AH10: 0 | AI10: 0 | AJ10: 0 | AK10: 0 | AL10: 0 | AM10: 0 | AN10: 0 | AO10: 0 | AP10: 0 | AQ10: 0 | AR10: 0 | AS10: 0 | AT10: 0 | AU10: 0 | AV10: 0 | AW10: 0 | AX10: 0 | AY10: 0 | AZ10: 0 | BA10: 0 | BB10: 0 | BC10: 0 | BD10: 0 | BE10: 0 | BF10: 0 | BG10: 0 | BH10: 0 | BI10: 0 | BJ10: 0 | BK10: 0 | BL10: 0 | BM10: 0 | BN10: 0
A11: {=TRANSPOSE('ANNUAL-EXPENSE-DETAILS'!B2:BC2)} | B11: {=TRANSPOSE('ANNUAL-EXPENSE-DETAILS'!B6:BC6)}
A12: STP SLUDGE CLEANING BALAJI | B12: 0
A13: STP MAINTENANCE | B13: 0 | C13: =$B13/64 | D13: =$B13/64 | E13: =$B13/64 | F13: =$B13/64 | G13: =$B13/64 | H13: =$B13/64 | I13: =$B13/64 | J13: =$B13/64 | ... BN13: =$B13/64
A14: STP MATERIALS | B14: 0 | C14: =$B14/64 | D14: =$B14/64 | E14: =$B14/64 | F14: =$B14/64 | G14: =$B14/64 | H14: =$B14/64 | I14: =$B14/64 | J14: =$B14/64 | ... BN14: =$B14/64
A15: STP REPAIR | B15: 0 | C15: =$B15/64 | D15: =$B15/64 | E15: =$B15/64 | F15: =$B15/64 | G15: =$B15/64 | H15: =$B15/64 | I15: =$B15/64 | J15: =$B15/64 | ... BN15: =$B15/64
A16: COMMON ELECTRICITY BILL | B16: 0 | C16: =$B16/64 | D16: =$B16/64 | E16: =$B16/64 | F16: =$B16/64 | G16: =$B16/64 | H16: =$B16/64 | I16: =$B16/64 | J16: =$B16/64 | ... BN16: =$B16/64
A17: BECOM Service tax | B17: 0 | C17: =$B17/64 | D17: =$B17/64 | E17: =$B17/64 | F17: =$B17/64 | G17: =$B17/64 | H17: =$B17/64 | I17: =$B17/64 | J17: =$B17/64 | ... BN17: =$B17/64
A18: SECURITY SERVICES | B18: 0 | C18: =$B18/64 | D18: =$B18/64 | E18: =$B18/64 | F18: =$B18/64 | G18: =$B18/64 | H18: =$B18/64 | I18: =$B18/64 | J18: =$B18/64 | ... BN18: =$B18/64
A19: GARBAGE REMOVAL | B19: 0 | C19: =$B19/64 | D19: =$B19/64 | E19: =$B19/64 | F19: =$B19/64 | G19: =$B19/64 | H19: =$B19/64 | I19: =$B19/64 | J19: =$B19/64 | ... BN19: =$B19/64
A20: PETTY CASH | B20: 0 | C20: =$B20/64 | D20: =$B20/64 | E20: =$B20/64 | F20: =$B20/64 | G20: =$B20/64 | H20: =$B20/64 | I20: =$B20/64 | J20: =$B20/64 | ... BN20: =$B20/64
A21: ELEVATOR MAINTENANCE | B21: 0 | C21: =$B21/64 | D21: =$B21/64 | E21: =$B21/64 | F21: =$B21/64 | G21: =$B21/64 | H21: =$B21/64 | I21: =$B21/64 | J21: =$B21/64 | ... BN21: =$B21/64
A22: MOTOR REPAIR | B22: 0 | C22: =$B22/64 | D22: =$B22/64 | E22: =$B22/64 | F22: =$B22/64 | G22: =$B22/64 | H22: =$B22/64 | I22: =$B22/64 | J22: =$B22/64 | ... BN22: =$B22/64
A23: PLUMBING MATERIAL | B23: 0 | C23: =$B23/64 | D23: =$B23/64 | E23: =$B23/64 | F23: =$B23/64 | G23: =$B23/64 | H23: =$B23/64 | I23: =$B23/64 | J23: =$B23/64 | ... BN23: =$B23/64
A24: ELECTRICITY MATERIAL | B24: 0 | C24: =$B24/64 | D24: =$B24/64 | E24: =$B24/64 | F24: =$B24/64 | G24: =$B24/64 | H24: =$B24/64 | I24: =$B24/64 | J24: =$B24/64 | ... BN24: =$B24/64
... A60: Speed Breaker near the gate | B60: 0 | C60: =$B60/64 | D60: =$B60/64 | E60: =$B60/64 | F60: =$B60/64 | G60: =$B60/64 | H60: =$B60/64 | I60: =$B60/64 | J60: =$B60/64 | ... BN60: =$B60/64
A61: Gym Equipment Repairs | B61: 0 | C61: =SUM(C6,C13:C60) | D61: =SUM(D6,D13:D60) | E61: =SUM(E6,E13:E60) | F61: =SUM(F6,F13:F60) | G61: =SUM(G6,G13:G60) | H61: =SUM(H6,H13:H60) | I61: =SUM(I6,I13:I60) | J61: =SUM(J6,J13:J60) | ... BN61: =SUM(BN6,BN13:BN60)
A62: Additional Waste Disposal | B62: 0
A63: Swimming Pool Cleaning | B63: 0
A64: HOUSE KEEPING MATERIALS | B64: 0

Sheet July2026-EXPENSE-Flatwise-Trans
A1: {=TRANSPOSE('July2026-EXPENSE-Flatwise'!A1:BN61)} | B1: Water consumption (Litres) | C1: Water consumption (%age of total) | D1: Water meter rent | E1: Common meter rent (eq. distributed) | F1: Total water related expense | G1: Society Parking Rent | H1: Clubhouse booking fee | I1: Moving in/out charges | J1: Gym usage fee | K1: DRINKING WATER SLN WATER SUP | L1: STP SLUDGE CLEANING BALAJI | M1: STP MAINTENANCE | N1: STP MATERIALS | O1: STP REPAIR | P1: COMMON ELECTRICITY BILL | Q1: BECOM Service tax | R1: SECURITY SERVICES | S1: GARBAGE REMOVAL | T1: PETTY CASH | U1: ELEVATOR MAINTENANCE | V1: MOTOR REPAIR | W1: PLUMBING MATERIAL | X1: ELECTRICITY MATERIAL | Y1: ELECTRICITY MATERIAL | Z1: TRANSFORMER REPAIR | AA1: GENERATOR MAINTENANCE EPITOME | AB1: GARDENING | AC1: PLUMBER WAGE | AD1: ELECTRICIAN WAGE | AE1: MANAGER WAGE | AF1: TANK AND SUMP CLEANING | AG1: SECURITY WATER EXPENSES GREENMART | AH1: SWIMMING POOL MOTOR REPAIR | AI1: CCTV REPAIR | AJ1: CCTV monitor | AK1: WATER PIPE | AL1: RAILING FOR STAIRCASE | AM1: Play area sand | AN1: BARBED WIRE REPAIR | AO1: DRIED LEAVES REMOVAL | AP1: DRAIN CLEANING | AQ1: Security room & Play area painting | AR1: Play area sand removal & cracks filling | AS1: Front garden cleaning and red soil filling | AT1: Landscaping work for STP water disposal | AU1: ACCOUNTING | AV1: Lift Painting | AW1: Lift wiring sepration | AX1: Earthing repair | AY1: Pest Control | AZ1: Freshwater pipe repair | BA1: NBH device replacement | BB1: NBH VMS | BC1: REPAIRS | BD1: Cricket Net | BE1: LOOK AHEAD EXPENSE | BF1: Rear bondary cleaning | BG1: 9,7,8,11 series terrace pipe repairs | BH1: Speed Breaker near the gate | BI1: Gym Equipment Repairs
A2: 0 | B2: 0 | C2: 0 | D2: 0 | E2: 0 | F2: 0 | G2: 0 | H2: 0 | I2: 0 | J2: 0 | K2: 0 | L2: 0 | M2: 0 | N2: 0 | O2: 0 | P2: 0 | Q2: 0 | R2: 0 | S2: 0 | T2: 0 | U2: 0 | V2: 0 | W2: 0 | X2: 0 | Y2: 0 | Z2: 0 | AA2: 0 | AB2: 0 | AC2: 0 | AD2: 0 | AE2: 0 | AF2: 0 | AG2: 0 | AH2: 0 | AI2: 0 | AJ2: 0 | AK2: 0 | AL2: 0 | AM2: 0 | AN2: 0 | AO2: 0 | AP2: 0 | AQ2: 0 | AR2: 0 | AS2: 0 | AT2: 0 | AU2: 0 | AV2: 0 | AW2: 0 | AX2: 0 | AY2: 0 | AZ2: 0 | BA2: 0 | BB2: 0 | BC2: 0 | BD2: 0 | BE2: 0 | BF2: 0 | BG2: 0 | BH2: 0 | BI2: 0
A3: F1 | B3: 0 | C3: 0 | D3: 0 | E3: 0 | F3: 0 | G3: 0 | H3: 0 | I3: 0 | J3: 0 | K3: 0 | L3: 0 | M3: 0 | N3: 0 | O3: 0 | P3: 0 | Q3: 0 | R3: 0 | S3: 0 | T3: 0 | U3: 0 | V3: 0 | W3: 0 | X3: 0 | Y3: 0 | Z3: 0 | AA3: 0 | AB3: 0 | AC3: 0 | AD3: 0 | AE3: 0 | AF3: 0 | AG3: 0 | AH3: 0 | AI3: 0 | AJ3: 0 | AK3: 0 | AL3: 0 | AM3: 0 | AN3: 0 | AO3: 0 | AP3: 0 | AQ3: 0 | AR3: 0 | AS3: 0 | AT3: 0 | AU3: 0 | AV3: 0 | AW3: 0 | AX3: 0 | AY3: 0 | AZ3: 0 | BA3: 0 | BB3: 0 | BC3: 0 | BD3: 0 | BE3: 0 | BF3: 0 | BG3: 0 | BH3: 0 | BI3: 0
A4: F2 | B4: 0 | C4: 0 | D4: 0 | E4: 0 | F4: 0 | G4: 0 | H4: 0 | I4: 0 | J4: 0 | K4: 0 | L4: 0 | M4: 0 | N4: 0 | O4: 0 | P4: 0 | Q4: 0 | R4: 0 | S4: 0 | T4: 0 | U4: 0 | V4: 0 | W4: 0 | X4: 0 | Y4: 0 | Z4: 0 | AA4: 0 | AB4: 0 | AC4: 0 | AD4: 0 | AE4: 0 | AF4: 0 | AG4: 0 | AH4: 0 | AI4: 0 | AJ4: 0 | AK4: 0 | AL4: 0 | AM4: 0 | AN4: 0 | AO4: 0 | AP4: 0 | AQ4: 0 | AR4: 0 | AS4: 0 | AT4: 0 | AU4: 0 | AV4: 0 | AW4: 0 | AX4: 0 | AY4: 0 | AZ4: 0 | BA4: 0 | BB4: 0 | BC4: 0 | BD4: 0 | BE4: 0 | BF4: 0 | BG4: 0 | BH4: 0 | BI4: 0
A5: F3 | B5: 0 | C5: 0 | D5: 0 | E5: 0 | F5: 0 | G5: 0 | H5: 0 | I5: 0 | J5: 0 | K5: 0 | L5: 0 | M5: 0 | N5: 0 | O5: 0 | P5: 0 | Q5: 0 | R5: 0 | S5: 0 | T5: 0 | U5: 0 | V5: 0 | W5: 0 | X5: 0 | Y5: 0 | Z5: 0 | AA5: 0 | AB5: 0 | AC5: 0 | AD5: 0 | AE5: 0 | AF5: 0 | AG5: 0 | AH5: 0 | AI5: 0 | AJ5: 0 | AK5: 0 | AL5: 0 | AM5: 0 | AN5: 0 | AO5: 0 | AP5: 0 | AQ5: 0 | AR5: 0 | AS5: 0 | AT5: 0 | AU5: 0 | AV5: 0 | AW5: 0 | AX5: 0 | AY5: 0 | AZ5: 0 | BA5: 0 | BB5: 0 | BC5: 0 | BD5: 0 | BE5: 0 | BF5: 0 | BG5: 0 | BH5: 0 | BI5: 0
A6: F4 | B6: 0 | C6: 0 | D6: 0 | E6: 0 | F6: 0 | G6: 0 | H6: 0 | I6: 0 | J6: 0 | K6: 0 | L6: 0 | M6: 0 | N6: 0 | O6: 0 | P6: 0 | Q6: 0 | R6: 0 | S6: 0 | T6: 0 | U6: 0 | V6: 0 | W6: 0 | X6: 0 | Y6: 0 | Z6: 0 | AA6: 0 | AB6: 0 | AC6: 0 | AD6: 0 | AE6: 0 | AF6: 0 | AG6: 0 | AH6: 0 | AI6: 0 | AJ6: 0 | AK6: 0 | AL6: 0 | AM6: 0 | AN6: 0 | AO6: 0 | AP6: 0 | AQ6: 0 | AR6: 0 | AS6: 0 | AT6: 0 | AU6: 0 | AV6: 0 | AW6: 0 | AX6: 0 | AY6: 0 | AZ6: 0 | BA6: 0 | BB6: 0 | BC6: 0 | BD6: 0 | BE6: 0 | BF6: 0 | BG6: 0 | BH6: 0 | BI6: 0
A7: F5 | B7: 0 | C7: 0 | D7: 0 | E7: 0 | F7: 0 | G7: 0 | H7: 0 | I7: 0 | J7: 0 | K7: 0 | L7: 0 | M7: 0 | N7: 0 | O7: 0 | P7: 0 | Q7: 0 | R7: 0 | S7: 0 | T7: 0 | U7: 0 | V7: 0 | W7: 0 | X7: 0 | Y7: 0 | Z7: 0 | AA7: 0 | AB7: 0 | AC7: 0 | AD7: 0 | AE7: 0 | AF7: 0 | AG7: 0 | AH7: 0 | AI7: 0 | AJ7: 0 | AK7: 0 | AL7: 0 | AM7: 0 | AN7: 0 | AO7: 0 | AP7: 0 | AQ7: 0 | AR7: 0 | AS7: 0 | AT7: 0 | AU7: 0 | AV7: 0 | AW7: 0 | AX7: 0 | AY7: 0 | AZ7: 0 | BA7: 0 | BB7: 0 | BC7: 0 | BD7: 0 | BE7: 0 | BF7: 0 | BG7: 0 | BH7: 0 | BI7: 0
A8: F6 | B8: 0 | C8: 0 | D8: 0 | E8: 0 | F8: 0 | G8: 0 | H8: 0 | I8: 0 | J8: 0 | K8: 0 | L8: 0 | M8: 0 | N8: 0 | O8: 0 | P8: 0 | Q8: 0 | R8: 0 | S8: 0 | T8: 0 | U8: 0 | V8: 0 | W8: 0 | X8: 0 | Y8: 0 | Z8: 0 | AA8: 0 | AB8: 0 | AC8: 0 | AD8: 0 | AE8: 0 | AF8: 0 | AG8: 0 | AH8: 0 | AI8: 0 | AJ8: 0 | AK8: 0 | AL8: 0 | AM8: 0 | AN8: 0 | AO8: 0 | AP8: 0 | AQ8: 0 | AR8: 0 | AS8: 0 | AT8: 0 | AU8: 0 | AV8: 0 | AW8: 0 | AX8: 0 | AY8: 0 | AZ8: 0 | BA8: 0 | BB8: 0 | BC8: 0 | BD8: 0 | BE8: 0 | BF8: 0 | BG8: 0 | BH8: 0 | BI8: 0
A9: F7 | B9: 0 | C9: 0 | D9: 0 | E9: 0 | F9: 0 | G9: 0 | H9: 0 | I9: 0 | J9: 0 | K9: 0 | L9: 0 | M9: 0 | N9: 0 | O9: 0 | P9: 0 | Q9: 0 | R9: 0 | S9: 0 | T9: 0 | U9: 0 | V9: 0 | W9: 0 | X9: 0 | Y9: 0 | Z9: 0 | AA9: 0 | AB9: 0 | AC9: 0 | AD9: 0 | AE9: 0 | AF9: 0 | AG9: 0 | AH9: 0 | AI9: 0 | AJ9: 0 | AK9: 0 | AL9: 0 | AM9: 0 | AN9: 0 | AO9: 0 | AP9: 0 | AQ9: 0 | AR9: 0 | AS9: 0 | AT9: 0 | AU9: 0 | AV9: 0 | AW9: 0 | AX9: 0 | AY9: 0 | AZ9: 0 | BA9: 0 | BB9: 0 | BC9: 0 | BD9: 0 | BE9: 0 | BF9: 0 | BG9: 0 | BH9: 0 | BI9: 0
A10: F8 | B10: 0 | C10: 0 | D10: 0 | E10: 0 | F10: 0 | G10: 0 | H10: 0 | I10: 0 | J10: 0 | K10: 0 | L10: 0 | M10: 0 | N10: 0 | O10: 0 | P10: 0 | Q10: 0 | R10: 0 | S10: 0 | T10: 0 | U10: 0 | V10: 0 | W10: 0 | X10: 0 | Y10: 0 | Z10: 0 | AA10: 0 | AB10: 0 | AC10: 0 | AD10: 0 | AE10: 0 | AF10: 0 | AG10: 0 | AH10: 0 | AI10: 0 | AJ10: 0 | AK10: 0 | AL10: 0 | AM10: 0 | AN10: 0 | AO10: 0 | AP10: 0 | AQ10: 0 | AR10: 0 | AS10: 0 | AT10: 0 | AU10: 0 | AV10: 0 | AW10: 0 | AX10: 0 | AY10: 0 | AZ10: 0 | BA10: 0 | BB10: 0 | BC10: 0 | BD10: 0 | BE10: 0 | BF10: 0 | BG10: 0 | BH10: 0 | BI10: 0
A11: F9 | B11: 0 | C11: 0 | D11: 0 | E11: 0 | F11: 0 | G11: 0 | H11: 0 | I11: 0 | J11: 0 | K11: 0 | L11: 0 | M11: 0 | N11: 0 | O11: 0 | P11: 0 | Q11: 0 | R11: 0 | S11: 0 | T11: 0 | U11: 0 | V11: 0 | W11: 0 | X11: 0 | Y11: 0 | Z11: 0 | AA11: 0 | AB11: 0 | AC11: 0 | AD11: 0 | AE11: 0 | AF11: 0 | AG11: 0 | AH11: 0 | AI11: 0 | AJ11: 0 | AK11: 0 | AL11: 0 | AM11: 0 | AN11: 0 | AO11: 0 | AP11: 0 | AQ11: 0 | AR11: 0 | AS11: 0 | AT11: 0 | AU11: 0 | AV11: 0 | AW11: 0 | AX11: 0 | AY11: 0 | AZ11: 0 | BA11: 0 | BB11: 0 | BC11: 0 | BD11: 0 | BE11: 0 | BF11: 0 | BG11: 0 | BH11: 0 | BI11: 0
A12: F10 | B12: 0 | C12: 0 | D12: 0 | E12: 0 | F12: 0 | G12: 0 | H12: 0 | I12: 0 | J12: 0 | K12: 0 | L12: 0 | M12: 0 | N12: 0 | O12: 0 | P12: 0 | Q12: 0 | R12: 0 | S12: 0 | T12: 0 | U12: 0 | V12: 0 | W12: 0 | X12: 0 | Y12: 0 | Z12: 0 | AA12: 0 | AB12: 0 | AC12: 0 | AD12: 0 | AE12: 0 | AF12: 0 | AG12: 0 | AH12: 0 | AI12: 0 | AJ12: 0 | AK12: 0 | AL12: 0 | AM12: 0 | AN12: 0 | AO12: 0 | AP12: 0 | AQ12: 0 | AR12: 0 | AS12: 0 | AT12: 0 | AU12: 0 | AV12: 0 | AW12: 0 | AX12: 0 | AY12: 0 | AZ12: 0 | BA12: 0 | BB12: 0 | BC12: 0 | BD12: 0 | BE12: 0 | BF12: 0 | BG12: 0 | BH12: 0 | BI12: 0
A13: F11 | B13: 0 | C13: 0 | D13: 0 | E13: 0 | F13: 0 | G13: 0 | H13: 0 | I13: 0 | J13: 0 | K13: 0 | L13: 0 | M13: 0 | N13: 0 | O13: 0 | P13: 0 | Q13: 0 | R13: 0 | S13: 0 | T13: 0 | U13: 0 | V13: 0 | W13: 0 | X13: 0 | Y13: 0 | Z13: 0 | AA13: 0 | AB13: 0 | AC13: 0 | AD13: 0 | AE13: 0 | AF13: 0 | AG13: 0 | AH13: 0 | AI13: 0 | AJ13: 0 | AK13: 0 | AL13: 0 | AM13: 0 | AN13: 0 | AO13: 0 | AP13: 0 | AQ13: 0 | AR13: 0 | AS13: 0 | AT13: 0 | AU13: 0 | AV13: 0 | AW13: 0 | AX13: 0 | AY13: 0 | AZ13: 0 | BA13: 0 | BB13: 0 | BC13: 0 | BD13: 0 | BE13: 0 | BF13: 0 | BG13: 0 | BH13: 0 | BI13: 0
A14: F12 | B14: 0 | C14: 0 | D14: 0 | E14: 0 | F14: 0 | G14: 0 | H14: 0 | I14: 0 | J14: 0 | K14: 0 | L14: 0 | M14: 0 | N14: 0 | O14: 0 | P14: 0 | Q14: 0 | R14: 0 | S14: 0 | T14: 0 | U14: 0 | V14: 0 | W14: 0 | X14: 0 | Y14: 0 | Z14: 0 | AA14: 0 | AB14: 0 | AC14: 0 | AD14: 0 | AE14: 0 | AF14: 0 | AG14: 0 | AH14: 0 | AI14: 0 | AJ14: 0 | AK14: 0 | AL14: 0 | AM14: 0 | AN14: 0 | AO14: 0 | AP14: 0 | AQ14: 0 | AR14: 0 | AS14: 0 | AT14: 0 | AU14: 0 | AV14: 0 | AW14: 0 | AX14: 0 | AY14: 0 | AZ14: 0 | BA14: 0 | BB14: 0 | BC14: 0 | BD14: 0 | BE14: 0 | BF14: 0 | BG14: 0 | BH14: 0 | BI14: 0
... A66: T16 | B66: 0 | C66: 0 | D66: 0 | E66: 0 | F66: 0 | G66: 0 | H66: 0 | I66: 0 | J66: 0 | K66: 0 | L66: 0 | M66: 0 | N66: 0 | O66: 0 | P66: 0 | Q66: 0 | R66: 0 | S66: 0 | T66: 0 | U66: 0 | V66: 0 | W66: 0 | X66: 0 | Y66: 0 | Z66: 0 | AA66: 0 | AB66: 0 | AC66: 0 | AD66: 0 | AE66: 0 | AF66: 0 | AG66: 0 | AH66: 0 | AI66: 0 | AJ66: 0 | AK66: 0 | AL66: 0 | AM66: 0 | AN66: 0 | AO66: 0 | AP66: 0 | AQ66: 0 | AR66: 0 | AS66: 0 | AT66: 0 | AU66: 0 | AV66: 0 | AW66: 0 | AX66: 0 | AY66: 0 | AZ66: 0 | BA66: 0 | BB66: 0 | BC66: 0 | BD66: 0 | BE66: 0 | BF66: 0 | BG66: 0 | BH66: 0 | BI66: 0

Sheet July2026-COLLECTION
A1: FLAT # | C1: Amount | D1: Date | E1: Amount | F1: Date | G1: Amount | H1: Date | I1: Amount | J1: Date | K1: Total
A2: F1 | B2: Shailesh Srivastava / Azeem Nawaz | K2: =SUM(C2,E2,G2,I2)
A3: F2 | B3: Shanthanu | K3: =SUM(C3,E3,G3,I3)
A4: F3 | B4: Samrat Kar | K4: =SUM(C4,E4,G4,I4)
A5: F4 | B5: Renu R | K5: =SUM(C5,E5,G5,I5)
A6: F5 | B6: Vamsidhar Bethanabatla / Madhuri Anumula | K6: =SUM(C6,E6,G6,I6)
A7: F6 | B7: Meghana Viral Shah and Vviral Shah (Owner) / Sangeet and Swagat (Tenent) | K7: =SUM(C7,E7,G7,I7)
A8: F7 | B8: Vimal NK | K8: =SUM(C8,E8,G8,I8)
A9: F8 | B9: Sujeet Kumar (Tenant)/Sreejith Menon (Owner) | K9: =SUM(C9,E9,G9,I9)
A10: F9 | B10: Vijay Suswaram (Owner) / Divya Shikha (Tenant) | K10: =SUM(C10,E10,G10,I10)
A11: F10 | B11: Aby Thomas | K11: =SUM(C11,E11,G11,I11)
A12: F11 | B12: N. Geetha | K12: =SUM(C12,E12,G12,I12)
A13: F12 | B13: Anirudh Singh | K13: =SUM(C13,E13,G13,I13)
... A65: T16 | B65: Madhusoodanan P.R. | K65: =SUM(C65,E65,G65,I65)
A66: TOTAL | K66: =SUM(K2:K65)

Sheet Aug2026-EXPENSE
B1: AUG 2026 EXPENSES
A2: FLAT # | B2: 1 | C2: WATER USED IN LTRS | D2: COMMON AREA EQUALLY DEVIDED | E2: TOTAL FRESH WATER CONSUMED | F2: %OF TOTAL USED | G2: WATER EXPENSE SHARING BY % | H2: #METERS | I2: METER RENT | J2: COMMON AREA METER RENT + WATER EXPENSE+ FLAT METER RENT | K2: FIXED EXPENSE SHARE | L2: PARKING FEE | M2: CLUB HOUSE BOOKING | N2: SHIFTING FEE | O2: GYM USAGE FEE | R2: TOTAL EXPENSE TO BE PAID
A3: CH | B3: MPFOWA | D3: 0 | H3: 1 | I3: =T7
A4: GYM | B4: MPFOWA | D4: 0 | H4: 1 | I4: =T7 | S4: TOTAL FIXED EXPENSE | T4: ='ANNUAL-EXPENSE-DETAILS'!BF7
A5: BSMT | B5: MPFOWA | D5: 0 | H5: 1 | I5: =T7 | S5: TOTAL WATER EXPENSE | T5: ='ANNUAL-EXPENSE-DETAILS'!BE7
A6: F1 | B6: Shailesh Srivastava / Azeem Nawaz | C6: 0 | D6: =SUM($C$3:$C$5)/64 | E6: =C6+D6 | F6: =IF($C$70=0, 0, E6/$C$70) | G6: =F6*$T$5 | H6: 3 | I6: =$T$7*H6 | J6: =G6+$T$9+I6 | K6: =$T$11/64 | L6: 0 | M6: 0 | N6: 0 | O6: 0 | R6: =(J6+K6+L6+M6+N6+O6)*$B$2
A7: F2 | B7: Shanthanu | C7: 0 | D7: =SUM($C$3:$C$5)/64 | E7: =C7+D7 | F7: =IF($C$70=0, 0, E7/$C$70) | G7: =F7*$T$5 | H7: 4 | I7: =$T$7*H7 | J7: =G7+$T$9+I7 | K7: =$T$11/64 | L7: 0 | M7: 0 | N7: 0 | O7: 0 | R7: =(J7+K7+L7+M7+N7+O7)*$B$2 | S7: RENT PER METER | T7: 117.81166
A8: F3 | B8: Samrat Kar | C8: 0 | D8: =SUM($C$3:$C$5)/64 | E8: =C8+D8 | F8: =IF($C$70=0, 0, E8/$C$70) | G8: =F8*$T$5 | H8: 4 | I8: =$T$7*H8 | J8: =G8+$T$9+I8 | K8: =$T$11/64 | L8: 0 | M8: 0 | N8: 0 | O8: 0 | R8: =(J8+K8+L8+M8+N8+O8)*$B$2 | S8: COMMON AREA METER RENT | T8: =$T$7*3
A9: F4 | B9: Renu R | C9: 0 | D9: =SUM($C$3:$C$5)/64 | E9: =C9+D9 | F9: =IF($C$70=0, 0, E9/$C$70) | G9: =F9*$T$5 | H9: 4 | I9: =$T$7*H9 | J9: =G9+$T$9+I9 | K9: =$T$11/64 | L9: 0 | M9: 0 | N9: 0 | O9: 0 | R9: =(J9+K9+L9+M9+N9+O9)*$B$2 | S9: COMMON AREA METER RENT/FLAT | T9: =T8/64
A10: F5 | B10: Vamsidhar Bethanabatla / Madhuri Anumula | C10: 0 | D10: =SUM($C$3:$C$5)/64 | E10: =C10+D10 | F10: =IF($C$70=0, 0, E10/$C$70) | G10: =F10*$T$5 | H10: 3 | I10: =$T$7*H10 | J10: =G10+$T$9+I10 | K10: =$T$11/64 | L10: 0 | M10: 0 | N10: 0 | O10: 0 | R10: =(J10+K10+L10+M10+N10+O10)*$B$2
A11: F6 | B11: Meghana Viral Shah and Vviral Shah (Owner) / Sangeet and Swagat (Tenent) | C11: 0 | D11: =SUM($C$3:$C$5)/64 | E11: =C11+D11 | F11: =IF($C$70=0, 0, E11/$C$70) | G11: =F11*$T$5 | H11: 3 | I11: =$T$7*H11 | J11: =G11+$T$9+I11 | K11: =$T$11/64 | L11: 0 | M11: 0 | N11: 0 | O11: 0 | R11: =(J11+K11+L11+M11+N11+O11)*$B$2 | S11: TOTAL FIXED EXPENSE | T11: ='ANNUAL-EXPENSE-DETAILS'!BF7
A12: F7 | B12: Vimal NK | C12: 0 | D12: =SUM($C$3:$C$5)/64 | E12: =C12+D12 | F12: =IF($C$70=0, 0, E12/$C$70) | G12: =F12*$T$5 | H12: 3 | I12: =$T$7*H12 | J12: =G12+$T$9+I12 | K12: =$T$11/64 | L12: 0 | M12: 0 | N12: 0 | O12: 0 | R12: =(J12+K12+L12+M12+N12+O12)*$B$2
A13: F8 | B13: Sujeet Kumar (Tenant)/Sreejith Menon (Owner) | C13: 0 | D13: =SUM($C$3:$C$5)/64 | E13: =C13+D13 | F13: =IF($C$70=0, 0, E13/$C$70) | G13: =F13*$T$5 | H13: 3 | I13: =$T$7*H13 | J13: =G13+$T$9+I13 | K13: =$T$11/64 | L13: 0 | M13: 0 | N13: 0 | O13: 0 | R13: =(J13+K13+L13+M13+N13+O13)*$B$2 | S13: BALANCE IN ACCOUNT ON 31-AUG-2022
A14: F9 | B14: Vijay Suswaram (Owner) / Divya Shikha (Tenant) | C14: 0 | D14: =SUM($C$3:$C$5)/64 | E14: =C14+D14 | F14: =IF($C$70=0, 0, E14/$C$70) | G14: =F14*$T$5 | H14: 4 | I14: =$T$7*H14 | J14: =G14+$T$9+I14 | K14: =$T$11/64 | L14: 0 | M14: 0 | N14: 0 | O14: 0 | R14: =(J14+K14+L14+M14+N14+O14)*$B$2 | S14: TOTAL NON MAINTENANCE CORPUS COLLECTION
A15: F10 | B15: Aby Thomas | C15: 0 | D15: =SUM($C$3:$C$5)/64 | E15: =C15+D15 | F15: =IF($C$70=0, 0, E15/$C$70) | G15: =F15*$T$5 | H15: 3 | I15: =$T$7*H15 | J15: =G15+$T$9+I15 | K15: =$T$11/64 | L15: 0 | M15: 0 | N15: 0 | O15: 0 | R15: =(J15+K15+L15+M15+N15+O15)*$B$2 | S15: TOTAL FD DONE
A16: F11 | B16: Niwin Anto | C16: 0 | D16: =SUM($C$3:$C$5)/64 | E16: =C16+D16 | F16: =IF($C$70=0, 0, E16/$C$70) | G16: =F16*$T$5 | H16: 3 | I16: =$T$7*H16 | J16: =G16+$T$9+I16 | K16: =$T$11/64 | L16: 0 | M16: 0 | N16: 0 | O16: 0 | R16: =(J16+K16+L16+M16+N16+O16)*$B$2 | S16: AMOUNT AVAILABLE FOR NON MAINTENANCE CORPUS IN CURRENT AC | T16: =T14-T15
A17: F12 | B17: Anirudh Singh | C17: 0 | D17: =SUM($C$3:$C$5)/64 | E17: =C17+D17 | F17: =IF($C$70=0, 0, E17/$C$70) | G17: =F17*$T$5 | H17: 3 | I17: =$T$7*H17 | J17: =G17+$T$9+I17 | K17: =$T$11/64 | L17: 0 | M17: 0 | N17: 0 | O17: 0 | R17: =(J17+K17+L17+M17+N17+O17)*$B$2 | S17: AMOUNT AVAILABLE FOR MAINTENANCE | T17: =T13-T16
A18: F13 | B18: Sanchay Saxena | C18: 0 | D18: =SUM($C$3:$C$5)/64 | E18: =C18+D18 | F18: =IF($C$70=0, 0, E18/$C$70) | G18: =F18*$T$5 | H18: 4 | I18: =$T$7*H18 | J18: =G18+$T$9+I18 | K18: =$T$11/64 | L18: 0 | M18: 0 | N18: 0 | O18: 0 | R18: =(J18+K18+L18+M18+N18+O18)*$B$2
A19: F14 | B19: Hemant Patel | C19: 0 | D19: =SUM($C$3:$C$5)/64 | E19: =C19+D19 | F19: =IF($C$70=0, 0, E19/$C$70) | G19: =F19*$T$5 | H19: 4 | I19: =$T$7*H19 | J19: =G19+$T$9+I19 | K19: =$T$11/64 | L19: 0 | M19: 0 | N19: 0 | O19: 0 | R19: =(J19+K19+L19+M19+N19+O19)*$B$2
A20: F15 | B20: Senthil.Vijayaragavan | C20: 0 | D20: =SUM($C$3:$C$5)/64 | E20: =C20+D20 | F20: =IF($C$70=0, 0, E20/$C$70) | G20: =F20*$T$5 | H20: 4 | I20: =$T$7*H20 | J20: =G20+$T$9+I20 | K20: =$T$11/64 | L20: 0 | M20: 0 | N20: 0 | O20: 0 | R20: =(J20+K20+L20+M20+N20+O20)*$B$2 | S20: TOTAL WATER METER RENT (INR) | T20: =I70
A21: F16 | B21: Sreeja Sudharma | C21: 0 | D21: =SUM($C$3:$C$5)/64 | E21: =C21+D21 | F21: =IF($C$70=0, 0, E21/$C$70) | G21: =F21*$T$5 | H21: 3 | I21: =$T$7*H21 | J21: =G21+$T$9+I21 | K21: =$T$11/64 | L21: 0 | M21: 0 | N21: 0 | O21: 0 | R21: =(J21+K21+L21+M21+N21+O21)*$B$2
A22: G1 | B22: Venkataramanan C | C22: 0 | D22: =SUM($C$3:$C$5)/64 | E22: =C22+D22 | F22: =IF($C$70=0, 0, E22/$C$70) | G22: =F22*$T$5 | H22: 3 | I22: =$T$7*H22 | J22: =G22+$T$9+I22 | K22: =$T$11/64 | L22: 0 | M22: 0 | N22: 0 | O22: 0 | R22: =(J22+K22+L22+M22+N22+O22)*$B$2
A23: G2 | B23: Kaushik Kasibhatla | C23: 0 | D23: =SUM($C$3:$C$5)/64 | E23: =C23+D23 | F23: =IF($C$70=0, 0, E23/$C$70) | G23: =F23*$T$5 | H23: 4 | I23: =$T$7*H23 | J23: =G23+$T$9+I23 | K23: =$T$11/64 | L23: 0 | M23: 0 | N23: 0 | O23: 0 | R23: =(J23+K23+L23+M23+N23+O23)*$B$2
A24: G3 | B24: Balakrishnan | C24: 0 | D24: =SUM($C$3:$C$5)/64 | E24: =C24+D24 | F24: =IF($C$70=0, 0, E24/$C$70) | G24: =F24*$T$5 | H24: 4 | I24: =$T$7*H24 | J24: =G24+$T$9+I24 | K24: =$T$11/64 | L24: 0 | M24: 0 | N24: 0 | O24: 0 | R24: =(J24+K24+L24+M24+N24+O24)*$B$2
A25: G4 | B25: Ashwin Pandith | C25: 0 | D25: =SUM($C$3:$C$5)/64 | E25: =C25+D25 | F25: =IF($C$70=0, 0, E25/$C$70) | G25: =F25*$T$5 | H25: 4 | I25: =$T$7*H25 | J25: =G25+$T$9+I25 | K25: =$T$11/64 | L25: 0 | M25: 0 | N25: 0 | O25: 0 | R25: =(J25+K25+L25+M25+N25+O25)*$B$2
A26: G5 | B26: Mayank Phophaliya | C26: 0 | D26: =SUM($C$3:$C$5)/64 | E26: =C26+D26 | F26: =IF($C$70=0, 0, E26/$C$70) | G26: =F26*$T$5 | H26: 3 | I26: =$T$7*H26 | J26: =G26+$T$9+I26 | K26: =$T$11/64 | L26: 0 | M26: 0 | N26: 0 | O26: 0 | R26: =(J26+K26+L26+M26+N26+O26)*$B$2
A27: G6 | B27: Mohit Daga | C27: 0 | D27: =SUM($C$3:$C$5)/64 | E27: =C27+D27 | F27: =IF($C$70=0, 0, E27/$C$70) | G27: =F27*$T$5 | H27: 3 | I27: =$T$7*H27 | J27: =G27+$T$9+I27 | K27: =$T$11/64 | L27: 0 | M27: 0 | N27: 0 | O27: 0 | R27: =(J27+K27+L27+M27+N27+O27)*$B$2
A28: G7 | B28: Prince Richfield | C28: 0 | D28: =SUM($C$3:$C$5)/64 | E28: =C28+D28 | F28: =IF($C$70=0, 0, E28/$C$70) | G28: =F28*$T$5 | H28: 3 | I28: =$T$7*H28 | J28: =G28+$T$9+I28 | K28: =$T$11/64 | L28: 0 | M28: 0 | N28: 0 | O28: 0 | R28: =(J28+K28+L28+M28+N28+O28)*$B$2
A29: G8 | B29: Ranjithkumar R / Sameer (tenant) / Princy (tenant) | C29: 0 | D29: =SUM($C$3:$C$5)/64 | E29: =C29+D29 | F29: =IF($C$70=0, 0, E29/$C$70) | G29: =F29*$T$5 | H29: 3 | I29: =$T$7*H29 | J29: =G29+$T$9+I29 | K29: =$T$11/64 | L29: 0 | M29: 0 | N29: 0 | O29: 0 | R29: =(J29+K29+L29+M29+N29+O29)*$B$2
A30: G9 | B30: Chandramouli | C30: 0 | D30: =SUM($C$3:$C$5)/64 | E30: =C30+D30 | F30: =IF($C$70=0, 0, E30/$C$70) | G30: =F30*$T$5 | H30: 5 | I30: =$T$7*H30 | J30: =G30+$T$9+I30 | K30: =$T$11/64 | L30: 0 | M30: 0 | N30: 0 | O30: 0 | R30: =(J30+K30+L30+M30+N30+O30)*$B$2
A31: G10 | B31: Cijo Jacob / Thara Joy | C31: 0 | D31: =SUM($C$3:$C$5)/64 | E31: =C31+D31 | F31: =IF($C$70=0, 0, E31/$C$70) | G31: =F31*$T$5 | H31: 3 | I31: =$T$7*H31 | J31: =G31+$T$9+I31 | K31: =$T$11/64 | L31: 0 | M31: 0 | N31: 0 | O31: 0 | R31: =(J31+K31+L31+M31+N31+O31)*$B$2
A32: G11 | B32: Ketan Verlekar | C32: 0 | D32: =SUM($C$3:$C$5)/64 | E32: =C32+D32 | F32: =IF($C$70=0, 0, E32/$C$70) | G32: =F32*$T$5 | H32: 3 | I32: =$T$7*H32 | J32: =G32+$T$9+I32 | K32: =$T$11/64 | L32: 0 | M32: 0 | N32: 0 | O32: 0 | R32: =(J32+K32+L32+M32+N32+O32)*$B$2
... A69: T16 | B69: Madhusoodanan P.R. | C69: 0 | D69: =SUM($C$3:$C$5)/64 | E69: =C69+D69 | F69: =IF($C$70=0, 0, E69/$C$70) | G69: =F69*$T$5 | H69: 3 | I69: =$T$7*H69 | J69: =G69+$T$9+I69 | K69: =$T$11/64 | L69: 0 | M69: 0 | N69: 0 | O69: 0 | R69: =(J69+K69+L69+M69+N69+O69)*$B$2
B70: TOTAL | C70: =SUM(C3:C69) | D70: =SUM(D3:D69) | E70: =SUM(E3:E69) | F70: =IF($C$70=0, 0, E70/$C$70) | G70: =SUM(G3:G69) | H70: =SUM(H3:H69) | I70: =SUM(I3:I69) | J70: =SUM(J3:J69) | K70: =SUM(K3:K69) | L70: =SUM(L3:L69) | M70: =SUM(M3:M69) | N70: =SUM(N3:N69) | O70: =SUM(O3:O69) | R70: =SUM(R3:R69)

Sheet Aug2026-COLLECTION
A1: FLAT # | C1: Amount | D1: Date | E1: Amount | F1: Date | G1: Amount | H1: Date | I1: Amount | J1: Date | K1: Total
A2: F1 | B2: Shailesh Srivastava / Azeem Nawaz | K2: =SUM(C2,E2,G2,I2)
A3: F2 | B3: Shanthanu | K3: =SUM(C3,E3,G3,I3)
A4: F3 | B4: Samrat Kar | K4: =SUM(C4,E4,G4,I4)
A5: F4 | B5: Renu R | K5: =SUM(C5,E5,G5,I5)
A6: F5 | B6: Vamsidhar Bethanabatla / Madhuri Anumula | K6: =SUM(C6,E6,G6,I6)
A7: F6 | B7: Meghana Viral Shah and Vviral Shah (Owner) / Sangeet and Swagat (Tenent) | K7: =SUM(C7,E7,G7,I7)
A8: F7 | B8: Vimal NK | K8: =SUM(C8,E8,G8,I8)
A9: F8 | B9: Sujeet Kumar (Tenant)/Sreejith Menon (Owner) | K9: =SUM(C9,E9,G9,I9)
A10: F9 | B10: Vijay Suswaram (Owner) / Divya Shikha (Tenant) | K10: =SUM(C10,E10,G10,I10)
A11: F10 | B11: Aby Thomas | K11: =SUM(C11,E11,G11,I11)
A12: F11 | B12: N. Geetha | K12: =SUM(C12,E12,G12,I12)
A13: F12 | B13: Debashis Ghoshal / Manisha Ghoshal | K13: =SUM(C13,E13,G13,I13)
... A65: T16 | B65: Madhusoodanan P.R. | K65: =SUM(C65,E65,G65,I65)
A66: TOTAL | K66: =SUM(K2:K65)

Sheet Sep2026-EXPENSE
B1: SEPTEMBER 2026 EXPENSES
A2: FLAT # | B2: 1 | C2: WATER USED IN LTRS | D2: COMMON AREA EQUALLY DEVIDED | E2: TOTAL FRESH WATER CONSUMED | F2: %OF TOTAL USED | G2: WATER EXPENSE SHARING BY % | H2: #METERS | I2: METER RENT (INR) | J2: COMMON AREA METER RENT + WATER EXPENSE+ FLAT METER RENT | K2: FIXED EXPENSE SHARE | L2: PARKING FEE | M2: CLUB HOUSE BOOKING | N2: SHIFTING FEE | O2: GYM USAGE FEE | R2: TOTAL EXPENSE TO BE PAID
A3: CH | B3: MPFOWA | C3: 0 | D3: 0 | H3: 1 | I3: =T7
A4: GYM | B4: MPFOWA | C4: 0 | D4: 0 | H4: 1 | I4: =T7 | S4: TOTAL FIXED EXPENSE | T4: ='ANNUAL-EXPENSE-DETAILS'!BF8
A5: BSMT | B5: MPFOWA | C5: 0 | D5: 0 | H5: 1 | I5: =T7 | S5: TOTAL WATER EXPENSE | T5: ='ANNUAL-EXPENSE-DETAILS'!BE8
A6: F1 | B6: Shailesh Srivastava / Azeem Nawaz | C6: 0 | D6: =SUM($C$3:$C$5)/64 | E6: =C6+D6 | F6: =IF($C$70=0, 0, E6/$C$70) | G6: =F6*$T$5 | H6: 3 | I6: =$T$7*H6 | J6: =G6+$T$9+I6 | K6: =$T$11/64 | L6: 0 | M6: 0 | N6: 0 | O6: 0 | R6: =(J6+K6+L6+M6+N6+O6)*$B$2
A7: F2 | B7: Shanthanu | C7: 0 | D7: =SUM($C$3:$C$5)/64 | E7: =C7+D7 | F7: =IF($C$70=0, 0, E7/$C$70) | G7: =F7*$T$5 | H7: 4 | I7: =$T$7*H7 | J7: =G7+$T$9+I7 | K7: =$T$11/64 | L7: 0 | M7: 0 | N7: 0 | O7: 0 | R7: =(J7+K7+L7+M7+N7+O7)*$B$2 | S7: RENT PER METER | T7: 117.81166
A8: F3 | B8: Samrat Kar | C8: 0 | D8: =SUM($C$3:$C$5)/64 | E8: =C8+D8 | F8: =IF($C$70=0, 0, E8/$C$70) | G8: =F8*$T$5 | H8: 4 | I8: =$T$7*H8 | J8: =G8+$T$9+I8 | K8: =$T$11/64 | L8: 0 | M8: 0 | N8: 0 | O8: 0 | R8: =(J8+K8+L8+M8+N8+O8)*$B$2 | S8: COMMON AREA METER RENT (INR) | T8: =$T$7*3
A9: F4 | B9: Renu R | C9: 0 | D9: =SUM($C$3:$C$5)/64 | E9: =C9+D9 | F9: =IF($C$70=0, 0, E9/$C$70) | G9: =F9*$T$5 | H9: 4 | I9: =$T$7*H9 | J9: =G9+$T$9+I9 | K9: =$T$11/64 | L9: 0 | M9: 0 | N9: 0 | O9: 0 | R9: =(J9+K9+L9+M9+N9+O9)*$B$2 | S9: COMMON AREA METER RENT/FLAT | T9: =T8/64
A10: F5 | B10: Vamsidhar Bethanabatla / Madhuri Anumula | C10: 0 | D10: =SUM($C$3:$C$5)/64 | E10: =C10+D10 | F10: =IF($C$70=0, 0, E10/$C$70) | G10: =F10*$T$5 | H10: 3 | I10: =$T$7*H10 | J10: =G10+$T$9+I10 | K10: =$T$11/64 | L10: 0 | M10: 0 | N10: 0 | O10: 0 | R10: =(J10+K10+L10+M10+N10+O10)*$B$2
A11: F6 | B11: Meghana Viral Shah and Vviral Shah (Owner) / Sangeet and Swagat (Tenent) | C11: 0 | D11: =SUM($C$3:$C$5)/64 | E11: =C11+D11 | F11: =IF($C$70=0, 0, E11/$C$70) | G11: =F11*$T$5 | H11: 3 | I11: =$T$7*H11 | J11: =G11+$T$9+I11 | K11: =$T$11/64 | L11: 0 | M11: 0 | N11: 0 | O11: 0 | R11: =(J11+K11+L11+M11+N11+O11)*$B$2 | S11: TOTAL FIXED EXPENSE | T11: ='ANNUAL-EXPENSE-DETAILS'!BF8
A12: F7 | B12: Vimal NK | C12: 0 | D12: =SUM($C$3:$C$5)/64 | E12: =C12+D12 | F12: =IF($C$70=0, 0, E12/$C$70) | G12: =F12*$T$5 | H12: 3 | I12: =$T$7*H12 | J12: =G12+$T$9+I12 | K12: =$T$11/64 | L12: 0 | M12: 0 | N12: 0 | O12: 0 | R12: =(J12+K12+L12+M12+N12+O12)*$B$2
A13: F8 | B13: Sujeet Kumar (Tenant)/Sreejith Menon (Owner) | C13: 0 | D13: =SUM($C$3:$C$5)/64 | E13: =C13+D13 | F13: =IF($C$70=0, 0, E13/$C$70) | G13: =F13*$T$5 | H13: 3 | I13: =$T$7*H13 | J13: =G13+$T$9+I13 | K13: =$T$11/64 | L13: 0 | M13: 0 | N13: 0 | O13: 0 | R13: =(J13+K13+L13+M13+N13+O13)*$B$2
A14: F9 | B14: Vijay Suswaram (Owner) / Divya Shikha (Tenant) | C14: 0 | D14: =SUM($C$3:$C$5)/64 | E14: =C14+D14 | F14: =IF($C$70=0, 0, E14/$C$70) | G14: =F14*$T$5 | H14: 4 | I14: =$T$7*H14 | J14: =G14+$T$9+I14 | K14: =$T$11/64 | L14: 0 | M14: 0 | N14: 0 | O14: 0 | R14: =(J14+K14+L14+M14+N14+O14)*$B$2
A15: F10 | B15: Aby Thomas | C15: 0 | D15: =SUM($C$3:$C$5)/64 | E15: =C15+D15 | F15: =IF($C$70=0, 0, E15/$C$70) | G15: =F15*$T$5 | H15: 3 | I15: =$T$7*H15 | J15: =G15+$T$9+I15 | K15: =$T$11/64 | L15: 0 | M15: 0 | N15: 0 | O15: 0 | R15: =(J15+K15+L15+M15+N15+O15)*$B$2 | S15: BALANCE IN ACCOUNT ON 30-SEP-2022
A16: F11 | B16: Niwin Anto | C16: 0 | D16: =SUM($C$3:$C$5)/64 | E16: =C16+D16 | F16: =IF($C$70=0, 0, E16/$C$70) | G16: =F16*$T$5 | H16: 3 | I16: =$T$7*H16 | J16: =G16+$T$9+I16 | K16: =$T$11/64 | L16: 0 | M16: 0 | N16: 0 | O16: 0 | R16: =(J16+K16+L16+M16+N16+O16)*$B$2 | S16: TOTAL NON MAINTENANCE CORPUS COLLECTION
A17: F12 | B17: Anirudh Singh | C17: 0 | D17: =SUM($C$3:$C$5)/64 | E17: =C17+D17 | F17: =IF($C$70=0, 0, E17/$C$70) | G17: =F17*$T$5 | H17: 3 | I17: =$T$7*H17 | J17: =G17+$T$9+I17 | K17: =$T$11/64 | L17: 0 | M17: 0 | N17: 0 | O17: 0 | R17: =(J17+K17+L17+M17+N17+O17)*$B$2 | S17: TOTAL FD DONE
A18: F13 | B18: Sanchay Saxena | C18: 0 | D18: =SUM($C$3:$C$5)/64 | E18: =C18+D18 | F18: =IF($C$70=0, 0, E18/$C$70) | G18: =F18*$T$5 | H18: 4 | I18: =$T$7*H18 | J18: =G18+$T$9+I18 | K18: =$T$11/64 | L18: 0 | M18: 0 | N18: 0 | O18: 0 | R18: =(J18+K18+L18+M18+N18+O18)*$B$2 | S18: AMOUNT AVAILABLE FOR NON MAINTENANCE CORPUS IN CURRENT AC | T18: =T16-T17
A19: F14 | B19: Hemant Patel | C19: 0 | D19: =SUM($C$3:$C$5)/64 | E19: =C19+D19 | F19: =IF($C$70=0, 0, E19/$C$70) | G19: =F19*$T$5 | H19: 4 | I19: =$T$7*H19 | J19: =G19+$T$9+I19 | K19: =$T$11/64 | L19: 0 | M19: 0 | N19: 0 | O19: 0 | R19: =(J19+K19+L19+M19+N19+O19)*$B$2 | S19: AMOUNT AVAILABLE FOR MAINTENANCE | T19: =T15-T18
A20: F15 | B20: Senthil.Vijayaragavan | C20: 0 | D20: =SUM($C$3:$C$5)/64 | E20: =C20+D20 | F20: =IF($C$70=0, 0, E20/$C$70) | G20: =F20*$T$5 | H20: 4 | I20: =$T$7*H20 | J20: =G20+$T$9+I20 | K20: =$T$11/64 | L20: 0 | M20: 0 | N20: 0 | O20: 0 | R20: =(J20+K20+L20+M20+N20+O20)*$B$2 | S20: TOTAL EXPENSE FOR THE MONTH | T20: ='ANNUAL-EXPENSE-DETAILS'!BH8
A21: F16 | B21: Sreeja Sudharma | C21: 0 | D21: =SUM($C$3:$C$5)/64 | E21: =C21+D21 | F21: =IF($C$70=0, 0, E21/$C$70) | G21: =F21*$T$5 | H21: 3 | I21: =$T$7*H21 | J21: =G21+$T$9+I21 | K21: =$T$11/64 | L21: 0 | M21: 0 | N21: 0 | O21: 0 | R21: =(J21+K21+L21+M21+N21+O21)*$B$2
A22: G1 | B22: Venkataramanan C | C22: 0 | D22: =SUM($C$3:$C$5)/64 | E22: =C22+D22 | F22: =IF($C$70=0, 0, E22/$C$70) | G22: =F22*$T$5 | H22: 3 | I22: =$T$7*H22 | J22: =G22+$T$9+I22 | K22: =$T$11/64 | L22: 0 | M22: 0 | N22: 0 | O22: 0 | R22: =(J22+K22+L22+M22+N22+O22)*$B$2
A23: G2 | B23: Kaushik Kasibhatla | C23: 0 | D23: =SUM($C$3:$C$5)/64 | E23: =C23+D23 | F23: =IF($C$70=0, 0, E23/$C$70) | G23: =F23*$T$5 | H23: 4 | I23: =$T$7*H23 | J23: =G23+$T$9+I23 | K23: =$T$11/64 | L23: 0 | M23: 0 | N23: 0 | O23: 0 | R23: =(J23+K23+L23+M23+N23+O23)*$B$2
A24: G3 | B24: Balakrishnan | C24: 0 | D24: =SUM($C$3:$C$5)/64 | E24: =C24+D24 | F24: =IF($C$70=0, 0, E24/$C$70) | G24: =F24*$T$5 | H24: 4 | I24: =$T$7*H24 | J24: =G24+$T$9+I24 | K24: =$T$11/64 | L24: 0 | M24: 0 | N24: 0 | O24: 0 | R24: =(J24+K24+L24+M24+N24+O24)*$B$2
A25: G4 | B25: Ashwin Pandith | C25: 0 | D25: =SUM($C$3:$C$5)/64 | E25: =C25+D25 | F25: =IF($C$70=0, 0, E25/$C$70) | G25: =F25*$T$5 | H25: 4 | I25: =$T$7*H25 | J25: =G25+$T$9+I25 | K25: =$T$11/64 | L25: 0 | M25: 0 | N25: 0 | O25: 0 | R25: =(J25+K25+L25+M25+N25+O25)*$B$2
A26: G5 | B26: Mayank Phophaliya | C26: 0 | D26: =SUM($C$3:$C$5)/64 | E26: =C26+D26 | F26: =IF($C$70=0, 0, E26/$C$70) | G26: =F26*$T$5 | H26: 3 | I26: =$T$7*H26 | J26: =G26+$T$9+I26 | K26: =$T$11/64 | L26: 0 | M26: 0 | N26: 0 | O26: 0 | R26: =(J26+K26+L26+M26+N26+O26)*$B$2
A27: G6 | B27: Mohit Daga | C27: 0 | D27: =SUM($C$3:$C$5)/64 | E27: =C27+D27 | F27: =IF($C$70=0, 0, E27/$C$70) | G27: =F27*$T$5 | H27: 3 | I27: =$T$7*H27 | J27: =G27+$T$9+I27 | K27: =$T$11/64 | L27: 0 | M27: 0 | N27: 0 | O27: 0 | R27: =(J27+K27+L27+M27+N27+O27)*$B$2
A28: G7 | B28: Prince Richfield | C28: 0 | D28: =SUM($C$3:$C$5)/64 | E28: =C28+D28 | F28: =IF($C$70=0, 0, E28/$C$70) | G28: =F28*$T$5 | H28: 3 | I28: =$T$7*H28 | J28: =G28+$T$9+I28 | K28: =$T$11/64 | L28: 0 | M28: 0 | N28: 0 | O28: 0 | R28: =(J28+K28+L28+M28+N28+O28)*$B$2
A29: G8 | B29: Ranjithkumar R / Sameer (tenant) / Princy (tenant) | C29: 0 | D29: =SUM($C$3:$C$5)/64 | E29: =C29+D29 | F29: =IF($C$70=0, 0, E29/$C$70) | G29: =F29*$T$5 | H29: 3 | I29: =$T$7*H29 | J29: =G29+$T$9+I29 | K29: =$T$11/64 | L29: 0 | M29: 0 | N29: 0 | O29: 0 | R29: =(J29+K29+L29+M29+N29+O29)*$B$2
A30: G9 | B30: Chandramouli | C30: 0 | D30: =SUM($C$3:$C$5)/64 | E30: =C30+D30 | F30: =IF($C$70=0, 0, E30/$C$70) | G30: =F30*$T$5 | H30: 5 | I30: =$T$7*H30 | J30: =G30+$T$9+I30 | K30: =$T$11/64 | L30: 0 | M30: 0 | N30: 0 | O30: 0 | R30: =(J30+K30+L30+M30+N30+O30)*$B$2
A31: G10 | B31: Cijo Jacob / Thara Joy | C31: 0 | D31: =SUM($C$3:$C$5)/64 | E31: =C31+D31 | F31: =IF($C$70=0, 0, E31/$C$70) | G31: =F31*$T$5 | H31: 3 | I31: =$T$7*H31 | J31: =G31+$T$9+I31 | K31: =$T$11/64 | L31: 0 | M31: 0 | N31: 0 | O31: 0 | R31: =(J31+K31+L31+M31+N31+O31)*$B$2
A32: G11 | B32: Ketan Verlekar | C32: 0 | D32: =SUM($C$3:$C$5)/64 | E32: =C32+D32 | F32: =IF($C$70=0, 0, E32/$C$70) | G32: =F32*$T$5 | H32: 3 | I32: =$T$7*H32 | J32: =G32+$T$9+I32 | K32: =$T$11/64 | L32: 0 | M32: 0 | N32: 0 | O32: 0 | R32: =(J32+K32+L32+M32+N32+O32)*$B$2
... A69: T16 | B69: Madhusoodanan P.R. | C69: 0 | D69: =SUM($C$3:$C$5)/64 | E69: =C69+D69 | F69: =IF($C$70=0, 0, E69/$C$70) | G69: =F69*$T$5 | H69: 3 | I69: =$T$7*H69 | J69: =G69+$T$9+I69 | K69: =$T$11/64 | L69: 0 | M69: 0 | N69: 0 | O69: 0 | R69: =(J69+K69+L69+M69+N69+O69)*$B$2
B70: TOTAL | C70: =SUM(C3:C69) | D70: =SUM(D3:D69) | E70: =SUM(E3:E69) | F70: =IF($C$70=0, 0, E70/$C$70) | G70: =SUM(G3:G69) | H70: =SUM(H3:H69) | I70: =SUM(I3:I69) | J70: =SUM(J3:J69) | K70: =SUM(K3:K69) | L70: =SUM(L3:L69) | M70: =SUM(M3:M69) | N70: =SUM(N3:N69) | O70: =SUM(O3:O69) | R70: =SUM(R3:R69)

Sheet Sep2026-COLLECTION
A1: FLAT # | C1: Amount | D1: Date | E1: Amount | F1: Date | G1: Amount | H1: Date | I1: Amount | J1: Date | K1: Total
A2: F1 | B2: Shailesh Srivastava / Azeem Nawaz | K2: =SUM(C2,E2,G2,I2)
A3: F2 | B3: Shanthanu | K3: =SUM(C3,E3,G3,I3)
A4: F3 | B4: Samrat Kar | K4: =SUM(C4,E4,G4,I4)
A5: F4 | B5: Renu R | K5: =SUM(C5,E5,G5,I5)
A6: F5 | B6: Vamsidhar Bethanabatla / Madhuri Anumula | K6: =SUM(C6,E6,G6,I6)
A7: F6 | B7: Meghana Viral Shah and Vviral Shah (Owner) / Sangeet and Swagat (Tenent) | K7: =SUM(C7,E7,G7,I7)
A8: F7 | B8: Vimal NK | K8: =SUM(C8,E8,G8,I8)
A9: F8 | B9: Sujeet Kumar (Tenant)/Sreejith Menon (Owner) | K9: =SUM(C9,E9,G9,I9)
A10: F9 | B10: Vijay Suswaram (Owner) / Divya Shikha (Tenant) | K10: =SUM(C10,E10,G10,I10)
A11: F10 | B11: Aby Thomas | K11: =SUM(C11,E11,G11,I11)
A12: F11 | B12: N. Geetha | K12: =SUM(C12,E12,G12,I12)
A13: F12 | B13: Anirudh Singh | K13: =SUM(C13,E13,G13,I13)
... A27: G10 | B27: Cijo Jacob / Thara Joy | K27: =SUM(C27,E27,G27,I27)
A28: G11 | B28: Ketan Verlekar | D28: 9-Sep-0205 | K28: =SUM(C28,E28,G28,I28)
A29: G12 | B29: Shyam Nair | K29: =SUM(C29,E29,G29,I29)
A30: G13 | B30: Ajai.B | K30: =SUM(C30,E30,G30,I30)
A31: G14 | B31: Surajit Borah | K31: =SUM(C31,E31,G31,I31)
A32: G15 | B32: Suresh Nallusamy / Antriksh (tenant) | K32: =SUM(C32,E32,G32,I32)
A33: G16 | B33: Praveen Ganesan | K33: =SUM(C33,E33,G33,I33)
A34: S1 | B34: S.N.Behera | K34: =SUM(C34,E34,G34,I34)
A35: S2 | B35: Sonal Singh | K35: =SUM(C35,E35,G35,I35)
A36: S3 | B36: Koteswararao | K36: =SUM(C36,E36,G36,I36)
A37: S4 | B37: Swaminathan | K37: =SUM(C37,E37,G37,I37)
A38: S5 | B38: Abhishek Gopalakrishnan | K38: =SUM(C38,E38,G38,I38)
A39: S6 | B39: Vivek Dhingra / Pratyush Das | K39: =SUM(C39,E39,G39,I39)
A40: S7 | B40: Harish B | K40: =SUM(C40,E40,G40,I40)
... A65: T16 | B65: Madhusoodanan P.R. | K65: =SUM(C65,E65,G65,I65)
A66: TOTAL | K66: =SUM(K2:K65)

Sheet Oct2026-EXPENSE
B1: OCTOBER 2026 EXPENSES
A2: FLAT # | B2: 1 | C2: WATER USED IN LTRS | D2: COMMON AREA EQUALLY DEVIDED | E2: TOTAL FRESH WATER CONSUMED | F2: %OF TOTAL USED | G2: WATER EXPENSE SHARING BY % | H2: #METERS | I2: METER RENT | J2: COMMON AREA METER RENT + WATER EXPENSE+ FLAT METER RENT | K2: FIXED EXPENSE SHARE | L2: PARKING FEE | M2: CLUB HOUSE BOOKING FEE | N2: SHIFTING FEE | O2: GYM USAGE FEE | R2: TOTAL EXPENSE TO BE PAID
A3: CH | B3: MPFOWA | C3: 0 | D3: 0 | H3: 1 | I3: =T7 | J3: =I3
A4: GYM | B4: MPFOWA | C4: 0 | D4: 0 | H4: 1 | I4: =T7 | J4: =I4 | S4: TOTAL FIXED EXPENSE | T4: ='ANNUAL-EXPENSE-DETAILS'!BF9
A5: BSMT | B5: MPFOWA | C5: 0 | D5: 0 | H5: 1 | I5: =T7 | J5: =I5 | S5: TOTAL WATER EXPENSE | T5: ='ANNUAL-EXPENSE-DETAILS'!BE9
A6: F1 | B6: Shailesh Srivastava / Azeem Nawaz | C6: 0 | D6: =SUM($C$3:$C$4)/64 | E6: =C6+D6 | F6: =IF($C$70=0, 0, E6/$C$70) | G6: =F6*$T$5 | H6: 3 | I6: =$T$7*H6 | J6: =G6+$T$9+I6 | K6: =$T$11/64 | L6: 0 | M6: 0 | N6: 0 | O6: 0 | R6: =(J6+K6+L6+M6+N6+O6)*$B$2
A7: F2 | B7: Shanthanu | C7: 0 | D7: =SUM($C$3:$C$4)/64 | E7: =C7+D7 | F7: =IF($C$70=0, 0, E7/$C$70) | G7: =F7*$T$5 | H7: 4 | I7: =$T$7*H7 | J7: =G7+$T$9+I7 | K7: =$T$11/64 | L7: 0 | M7: 0 | N7: 0 | O7: 0 | R7: =(J7+K7+L7+M7+N7+O7)*$B$2 | S7: RENT PER METER | T7: 117.81166
A8: F3 | B8: Samrat Kar | C8: 0 | D8: =SUM($C$3:$C$4)/64 | E8: =C8+D8 | F8: =IF($C$70=0, 0, E8/$C$70) | G8: =F8*$T$5 | H8: 4 | I8: =$T$7*H8 | J8: =G8+$T$9+I8 | K8: =$T$11/64 | L8: 0 | M8: 0 | N8: 0 | O8: 0 | R8: =(J8+K8+L8+M8+N8+O8)*$B$2 | S8: COMMON AREA METER RENT | T8: =$T$7*3
A9: F4 | B9: Renu R | C9: 0 | D9: =SUM($C$3:$C$4)/64 | E9: =C9+D9 | F9: =IF($C$70=0, 0, E9/$C$70) | G9: =F9*$T$5 | H9: 4 | I9: =$T$7*H9 | J9: =G9+$T$9+I9 | K9: =$T$11/64 | L9: 0 | M9: 0 | N9: 0 | O9: 0 | R9: =(J9+K9+L9+M9+N9+O9)*$B$2 | S9: COMMON AREA METER RENT/FLAT | T9: =T8/64
A10: F5 | B10: Vamsidhar Bethanabatla / Madhuri Anumula | C10: 0 | D10: =SUM($C$3:$C$4)/64 | E10: =C10+D10 | F10: =IF($C$70=0, 0, E10/$C$70) | G10: =F10*$T$5 | H10: 3 | I10: =$T$7*H10 | J10: =G10+$T$9+I10 | K10: =$T$11/64 | L10: 0 | M10: 0 | N10: 0 | O10: 0 | R10: =(J10+K10+L10+M10+N10+O10)*$B$2
A11: F6 | B11: Meghana Viral Shah and Vviral Shah (Owner) / Sangeet and Swagat (Tenent) | C11: 0 | D11: =SUM($C$3:$C$4)/64 | E11: =C11+D11 | F11: =IF($C$70=0, 0, E11/$C$70) | G11: =F11*$T$5 | H11: 3 | I11: =$T$7*H11 | J11: =G11+$T$9+I11 | K11: =$T$11/64 | L11: 0 | M11: 0 | N11: 0 | O11: 0 | R11: =(J11+K11+L11+M11+N11+O11)*$B$2 | S11: TOTAL FIXED EXPENSE | T11: ='ANNUAL-EXPENSE-DETAILS'!BF9
A12: F7 | B12: Vimal NK | C12: 0 | D12: =SUM($C$3:$C$4)/64 | E12: =C12+D12 | F12: =IF($C$70=0, 0, E12/$C$70) | G12: =F12*$T$5 | H12: 3 | I12: =$T$7*H12 | J12: =G12+$T$9+I12 | K12: =$T$11/64 | L12: 0 | M12: 0 | N12: 0 | O12: 0 | R12: =(J12+K12+L12+M12+N12+O12)*$B$2
A13: F8 | B13: Sujeet Kumar (Tenant)/Sreejith Menon (Owner) | C13: 0 | D13: =SUM($C$3:$C$4)/64 | E13: =C13+D13 | F13: =IF($C$70=0, 0, E13/$C$70) | G13: =F13*$T$5 | H13: 3 | I13: =$T$7*H13 | J13: =G13+$T$9+I13 | K13: =$T$11/64 | L13: 0 | M13: 0 | N13: 0 | O13: 0 | R13: =(J13+K13+L13+M13+N13+O13)*$B$2 | S13: BALANCE IN ACCOUNT ON 31-OCT-2023
A14: F9 | B14: Vijay Suswaram (Owner) / Divya Shikha (Tenant) | C14: 0 | D14: =SUM($C$3:$C$4)/64 | E14: =C14+D14 | F14: =IF($C$70=0, 0, E14/$C$70) | G14: =F14*$T$5 | H14: 4 | I14: =$T$7*H14 | J14: =G14+$T$9+I14 | K14: =$T$11/64 | L14: 0 | M14: 0 | N14: 0 | O14: 0 | R14: =(J14+K14+L14+M14+N14+O14)*$B$2 | S14: TOTAL NON MAINTENANCE CORPUS COLLECTION
A15: F10 | B15: Aby Thomas | C15: 0 | D15: =SUM($C$3:$C$4)/64 | E15: =C15+D15 | F15: =IF($C$70=0, 0, E15/$C$70) | G15: =F15*$T$5 | H15: 3 | I15: =$T$7*H15 | J15: =G15+$T$9+I15 | K15: =$T$11/64 | L15: 0 | M15: 0 | N15: 0 | O15: 0 | R15: =(J15+K15+L15+M15+N15+O15)*$B$2 | S15: TOTAL FD DONE
A16: F11 | B16: Niwin Anto | C16: 0 | D16: =SUM($C$3:$C$4)/64 | E16: =C16+D16 | F16: =IF($C$70=0, 0, E16/$C$70) | G16: =F16*$T$5 | H16: 3 | I16: =$T$7*H16 | J16: =G16+$T$9+I16 | K16: =$T$11/64 | L16: 0 | M16: 0 | N16: 0 | O16: 0 | R16: =(J16+K16+L16+M16+N16+O16)*$B$2 | S16: AMOUNT AVAILABLE FOR NON MAINTENANCE CORPUS IN CURRENT AC | T16: =T14-T15
A17: F12 | B17: Anirudh Singh | C17: 0 | D17: =SUM($C$3:$C$4)/64 | E17: =C17+D17 | F17: =IF($C$70=0, 0, E17/$C$70) | G17: =F17*$T$5 | H17: 3 | I17: =$T$7*H17 | J17: =G17+$T$9+I17 | K17: =$T$11/64 | L17: 0 | M17: 0 | N17: 0 | O17: 0 | R17: =(J17+K17+L17+M17+N17+O17)*$B$2 | S17: AMOUNT AVAILABLE FOR MAINTENANCE | T17: =T13-T16
A18: F13 | B18: Sanchay Saxena | C18: 0 | D18: =SUM($C$3:$C$4)/64 | E18: =C18+D18 | F18: =IF($C$70=0, 0, E18/$C$70) | G18: =F18*$T$5 | H18: 4 | I18: =$T$7*H18 | J18: =G18+$T$9+I18 | K18: =$T$11/64 | L18: 0 | M18: 0 | N18: 0 | O18: 0 | R18: =(J18+K18+L18+M18+N18+O18)*$B$2 | S18: TOTAL EXPENSE FOR THE MONTH | T18: ='ANNUAL-EXPENSE-DETAILS'!BH9
A19: F14 | B19: Hemant Patel | C19: 0 | D19: =SUM($C$3:$C$4)/64 | E19: =C19+D19 | F19: =IF($C$70=0, 0, E19/$C$70) | G19: =F19*$T$5 | H19: 4 | I19: =$T$7*H19 | J19: =G19+$T$9+I19 | K19: =$T$11/64 | L19: 0 | M19: 0 | N19: 0 | O19: 0 | R19: =(J19+K19+L19+M19+N19+O19)*$B$2
A20: F15 | B20: Senthil.Vijayaragavan | C20: 0 | D20: =SUM($C$3:$C$4)/64 | E20: =C20+D20 | F20: =IF($C$70=0, 0, E20/$C$70) | G20: =F20*$T$5 | H20: 4 | I20: =$T$7*H20 | J20: =G20+$T$9+I20 | K20: =$T$11/64 | L20: 0 | M20: 0 | N20: 0 | O20: 0 | R20: =(J20+K20+L20+M20+N20+O20)*$B$2
A21: F16 | B21: Sreeja Sudharma | C21: 0 | D21: =SUM($C$3:$C$4)/64 | E21: =C21+D21 | F21: =IF($C$70=0, 0, E21/$C$70) | G21: =F21*$T$5 | H21: 3 | I21: =$T$7*H21 | J21: =G21+$T$9+I21 | K21: =$T$11/64 | L21: 0 | M21: 0 | N21: 0 | O21: 0 | R21: =(J21+K21+L21+M21+N21+O21)*$B$2
A22: G1 | B22: Venkataramanan C | C22: 0 | D22: =SUM($C$3:$C$4)/64 | E22: =C22+D22 | F22: =IF($C$70=0, 0, E22/$C$70) | G22: =F22*$T$5 | H22: 3 | I22: =$T$7*H22 | J22: =G22+$T$9+I22 | K22: =$T$11/64 | L22: 0 | M22: 0 | N22: 0 | O22: 0 | R22: =(J22+K22+L22+M22+N22+O22)*$B$2
A23: G2 | B23: Kaushik Kasibhatla | C23: 0 | D23: =SUM($C$3:$C$4)/64 | E23: =C23+D23 | F23: =IF($C$70=0, 0, E23/$C$70) | G23: =F23*$T$5 | H23: 4 | I23: =$T$7*H23 | J23: =G23+$T$9+I23 | K23: =$T$11/64 | L23: 0 | M23: 0 | N23: 0 | O23: 0 | R23: =(J23+K23+L23+M23+N23+O23)*$B$2
A24: G3 | B24: Balakrishnan | C24: 0 | D24: =SUM($C$3:$C$4)/64 | E24: =C24+D24 | F24: =IF($C$70=0, 0, E24/$C$70) | G24: =F24*$T$5 | H24: 4 | I24: =$T$7*H24 | J24: =G24+$T$9+I24 | K24: =$T$11/64 | L24: 0 | M24: 0 | N24: 0 | O24: 0 | R24: =(J24+K24+L24+M24+N24+O24)*$B$2
A25: G4 | B25: Ashwin Pandith | C25: 0 | D25: =SUM($C$3:$C$4)/64 | E25: =C25+D25 | F25: =IF($C$70=0, 0, E25/$C$70) | G25: =F25*$T$5 | H25: 4 | I25: =$T$7*H25 | J25: =G25+$T$9+I25 | K25: =$T$11/64 | L25: 0 | M25: 0 | N25: 0 | O25: 0 | R25: =(J25+K25+L25+M25+N25+O25)*$B$2
A26: G5 | B26: Mayank Phophaliya | C26: 0 | D26: =SUM($C$3:$C$4)/64 | E26: =C26+D26 | F26: =IF($C$70=0, 0, E26/$C$70) | G26: =F26*$T$5 | H26: 3 | I26: =$T$7*H26 | J26: =G26+$T$9+I26 | K26: =$T$11/64 | L26: 0 | M26: 0 | N26: 0 | O26: 0 | R26: =(J26+K26+L26+M26+N26+O26)*$B$2
A27: G6 | B27: Mohit Daga | C27: 0 | D27: =SUM($C$3:$C$4)/64 | E27: =C27+D27 | F27: =IF($C$70=0, 0, E27/$C$70) | G27: =F27*$T$5 | H27: 3 | I27: =$T$7*H27 | J27: =G27+$T$9+I27 | K27: =$T$11/64 | L27: 0 | M27: 0 | N27: 0 | O27: 0 | R27: =(J27+K27+L27+M27+N27+O27)*$B$2
A28: G7 | B28: Prince Richfield | C28: 0 | D28: =SUM($C$3:$C$4)/64 | E28: =C28+D28 | F28: =IF($C$70=0, 0, E28/$C$70) | G28: =F28*$T$5 | H28: 3 | I28: =$T$7*H28 | J28: =G28+$T$9+I28 | K28: =$T$11/64 | L28: 0 | M28: 0 | N28: 0 | O28: 0 | R28: =(J28+K28+L28+M28+N28+O28)*$B$2
A29: G8 | B29: Ranjithkumar R / Sameer (tenant) / Princy (tenant) | C29: 0 | D29: =SUM($C$3:$C$4)/64 | E29: =C29+D29 | F29: =IF($C$70=0, 0, E29/$C$70) | G29: =F29*$T$5 | H29: 3 | I29: =$T$7*H29 | J29: =G29+$T$9+I29 | K29: =$T$11/64 | L29: 0 | M29: 0 | N29: 0 | O29: 0 | R29: =(J29+K29+L29+M29+N29+O29)*$B$2
A30: G9 | B30: Chandramouli | C30: 0 | D30: =SUM($C$3:$C$4)/64 | E30: =C30+D30 | F30: =IF($C$70=0, 0, E30/$C$70) | G30: =F30*$T$5 | H30: 5 | I30: =$T$7*H30 | J30: =G30+$T$9+I30 | K30: =$T$11/64 | L30: 0 | M30: 0 | N30: 0 | O30: 0 | R30: =(J30+K30+L30+M30+N30+O30)*$B$2
... A69: T16 | B69: Madhusoodanan P.R. | C69: 0 | D69: =SUM($C$3:$C$4)/64 | E69: =C69+D69 | F69: =IF($C$70=0, 0, E69/$C$70) | G69: =F69*$T$5 | H69: 3 | I69: =$T$7*H69 | J69: =G69+$T$9+I69 | K69: =$T$11/64 | L69: 0 | M69: 0 | N69: 0 | O69: 0 | R69: =(J69+K69+L69+M69+N69+O69)*$B$2
B70: TOTAL | C70: =SUM(C3:C69) | D70: =SUM(D3:D69) | E70: =SUM(E3:E69) | F70: =IF($C$70=0, 0, E70/$C$70) | G70: =SUM(G3:G69) | H70: =SUM(H3:H69) | I70: =SUM(I3:I69) | J70: =SUM(J3:J69) | K70: =SUM(K3:K69) | L70: =SUM(L3:L69) | M70: =SUM(M3:M69) | N70: =SUM(N3:N69) | O70: =SUM(O3:O69) | R70: =SUM(R3:R69)

Sheet Oct2026-COLLECTION
A1: FLAT # | C1: Amount | D1: Date | E1: Amount | F1: Date | G1: Amount | H1: Date | I1: Amount | J1: Date | K1: Total
A2: F1 | B2: Shailesh Srivastava / Azeem Nawaz | K2: =SUM(C2,E2,G2,I2)
A3: F2 | B3: Shanthanu | K3: =SUM(C3,E3,G3,I3)
A4: F3 | B4: Samrat Kar | K4: =SUM(C4,E4,G4,I4)
A5: F4 | B5: Renu R | K5: =SUM(C5,E5,G5,I5)
A6: F5 | B6: Vamsidhar Bethanabatla / Madhuri Anumula / Pulkit Gupta | K6: =SUM(C6,E6,G6,I6)
A7: F6 | B7: Meghana Viral Shah and Vviral Shah (Owner) / Sangeet and Swagat (Tenent) | K7: =SUM(C7,E7,G7,I7)
A8: F7 | B8: Vimal NK | K8: =SUM(C8,E8,G8,I8)
A9: F8 | B9: Sujeet Kumar (Tenant)/Sreejith Menon (Owner) | K9: =SUM(C9,E9,G9,I9)
A10: F9 | B10: Vijay Suswaram (Owner) / Divya Shikha (Tenant) | K10: =SUM(C10,E10,G10,I10)
A11: F10 | B11: Aby Thomas | K11: =SUM(C11,E11,G11,I11)
A12: F11 | B12: N. Geetha | K12: =SUM(C12,E12,G12,I12)
A13: F12 | B13: Anirudh Singh | K13: =SUM(C13,E13,G13,I13)
... A65: T16 | B65: Madhusoodanan P.R. | K65: =SUM(C65,E65,G65,I65)
A66: TOTAL | K66: =SUM(K2:K65)

Sheet Nov2026-EXPENSE
B1: NOVEMBER 2026 EXPENSES
A2: FLAT # | B2: 1 | C2: WATER USED IN LTRS | D2: COMMON AREA EQUALLY DEVIDED | E2: TOTAL FRESH WATER CONSUMED | F2: %OF TOTAL USED | G2: WATER EXPENSE SHARING BY % | H2: #METERS | I2: METER RENT | J2: COMMON AREA METER RENT + WATER EXPENSE+ FLAT METER RENT | K2: FIXED EXPENSE SHARE | L2: PARKING FEE | M2: CLUB BOOKING FEE | N2: SHIFTING FEE | O2: GYM USAGE FEE | P2: OWNERSHIP TRANSFER FEE | R2: TOTAL EXPENSE TO BE PAID
A3: CH | B3: MPFOWA | C3: 0 | D3: 0 | H3: 1 | I3: =T7
A4: GYM | B4: MPFOWA | C4: 0 | D4: 0 | H4: 1 | I4: =T7 | S4: TOTAL FIXED EXPENSE | T4: ='ANNUAL-EXPENSE-DETAILS'!BF10
A5: BSMT | B5: MPFOWA | D5: 0 | H5: 1 | I5: =T7 | S5: TOTAL WATER EXPENSE | T5: ='ANNUAL-EXPENSE-DETAILS'!BE10
A6: F1 | B6: Shailesh Srivastava / Azeem Nawaz | C6: 0 | D6: =SUM($C$3:$C$5)/64 | E6: =C6+D6 | F6: =IF($C$70=0, 0, E6/$C$70) | G6: =F6*$T$5 | H6: 3 | I6: =$T$7*H6 | J6: =G6+$T$9+I6 | K6: =$T$11/64 | L6: 0 | M6: 0 | N6: 0 | O6: 0 | R6: =(J6+K6+L6+M6+N6+O6)*$B$2
A7: F2 | B7: Shanthanu | C7: 0 | D7: =SUM($C$3:$C$5)/64 | E7: =C7+D7 | F7: =IF($C$70=0, 0, E7/$C$70) | G7: =F7*$T$5 | H7: 4 | I7: =$T$7*H7 | J7: =G7+$T$9+I7 | K7: =$T$11/64 | L7: 0 | M7: 0 | N7: 0 | O7: 0 | R7: =(J7+K7+L7+M7+N7+O7)*$B$2 | S7: RENT PER METER | T7: 117.81166
A8: F3 | B8: Samrat Kar | C8: 0 | D8: =SUM($C$3:$C$5)/64 | E8: =C8+D8 | F8: =IF($C$70=0, 0, E8/$C$70) | G8: =F8*$T$5 | H8: 4 | I8: =$T$7*H8 | J8: =G8+$T$9+I8 | K8: =$T$11/64 | L8: 0 | M8: 0 | N8: 0 | O8: 0 | R8: =(J8+K8+L8+M8+N8+O8)*$B$2 | S8: COMMON AREA METER RENT | T8: =$T$7*3
A9: F4 | B9: Renu R | C9: 0 | D9: =SUM($C$3:$C$5)/64 | E9: =C9+D9 | F9: =IF($C$70=0, 0, E9/$C$70) | G9: =F9*$T$5 | H9: 4 | I9: =$T$7*H9 | J9: =G9+$T$9+I9 | K9: =$T$11/64 | L9: 0 | M9: 0 | N9: 0 | O9: 0 | R9: =(J9+K9+L9+M9+N9+O9)*$B$2 | S9: COMMON AREA METER RENT/FLAT | T9: =T8/64
A10: F5 | B10: Vamsidhar Bethanabatla / Madhuri Anumula | C10: 0 | D10: =SUM($C$3:$C$5)/64 | E10: =C10+D10 | F10: =IF($C$70=0, 0, E10/$C$70) | G10: =F10*$T$5 | H10: 3 | I10: =$T$7*H10 | J10: =G10+$T$9+I10 | K10: =$T$11/64 | L10: 0 | M10: 0 | N10: 0 | O10: 0 | R10: =(J10+K10+L10+M10+N10+O10)*$B$2
A11: F6 | B11: Meghana Viral Shah and Vviral Shah (Owner) / Sangeet and Swagat (Tenent) | C11: 0 | D11: =SUM($C$3:$C$5)/64 | E11: =C11+D11 | F11: =IF($C$70=0, 0, E11/$C$70) | G11: =F11*$T$5 | H11: 3 | I11: =$T$7*H11 | J11: =G11+$T$9+I11 | K11: =$T$11/64 | L11: 0 | M11: 0 | N11: 0 | O11: 0 | R11: =(J11+K11+L11+M11+N11+O11)*$B$2 | S11: TOTAL FIXED EXPENSE | T11: ='ANNUAL-EXPENSE-DETAILS'!BF10
A12: F7 | B12: Vimal NK | C12: 0 | D12: =SUM($C$3:$C$5)/64 | E12: =C12+D12 | F12: =IF($C$70=0, 0, E12/$C$70) | G12: =F12*$T$5 | H12: 3 | I12: =$T$7*H12 | J12: =G12+$T$9+I12 | K12: =$T$11/64 | L12: 0 | M12: 0 | N12: 0 | O12: 0 | R12: =(J12+K12+L12+M12+N12+O12)*$B$2
A13: F8 | B13: Sujeet Kumar (Tenant)/Sreejith Menon (Owner) | C13: 0 | D13: =SUM($C$3:$C$5)/64 | E13: =C13+D13 | F13: =IF($C$70=0, 0, E13/$C$70) | G13: =F13*$T$5 | H13: 3 | I13: =$T$7*H13 | J13: =G13+$T$9+I13 | K13: =$T$11/64 | L13: 0 | M13: 0 | N13: 0 | O13: 0 | R13: =(J13+K13+L13+M13+N13+O13)*$B$2
A14: F9 | B14: Vijay Suswaram (Owner) / Divya Shikha (Tenant) | C14: 0 | D14: =SUM($C$3:$C$5)/64 | E14: =C14+D14 | F14: =IF($C$70=0, 0, E14/$C$70) | G14: =F14*$T$5 | H14: 4 | I14: =$T$7*H14 | J14: =G14+$T$9+I14 | K14: =$T$11/64 | L14: 0 | M14: 0 | N14: 0 | O14: 0 | R14: =(J14+K14+L14+M14+N14+O14)*$B$2 | S14: TOTAL WATER METER RENT | T14: =CEILING( I70,1)
A15: F10 | B15: Aby Thomas | C15: 0 | D15: =SUM($C$3:$C$5)/64 | E15: =C15+D15 | F15: =IF($C$70=0, 0, E15/$C$70) | G15: =F15*$T$5 | H15: 3 | I15: =$T$7*H15 | J15: =G15+$T$9+I15 | K15: =$T$11/64 | L15: 0 | M15: 0 | N15: 0 | O15: 0 | R15: =(J15+K15+L15+M15+N15+O15)*$B$2
A16: F11 | B16: Niwin Anto | C16: 0 | D16: =SUM($C$3:$C$5)/64 | E16: =C16+D16 | F16: =IF($C$70=0, 0, E16/$C$70) | G16: =F16*$T$5 | H16: 3 | I16: =$T$7*H16 | J16: =G16+$T$9+I16 | K16: =$T$11/64 | L16: 0 | M16: 0 | N16: 0 | O16: 0 | R16: =(J16+K16+L16+M16+N16+O16)*$B$2 | S16: BALANCE IN ACCOUNT ON 30-NOV-2023
A17: F12 | B17: Anirudh Singh | C17: 0 | D17: =SUM($C$3:$C$5)/64 | E17: =C17+D17 | F17: =IF($C$70=0, 0, E17/$C$70) | G17: =F17*$T$5 | H17: 3 | I17: =$T$7*H17 | J17: =G17+$T$9+I17 | K17: =$T$11/64 | L17: 0 | M17: 0 | N17: 0 | O17: 0 | R17: =(J17+K17+L17+M17+N17+O17)*$B$2 | S17: TOTAL NON MAINTENANCE CORPUS COLLECTION
A18: F13 | B18: Sanchay Saxena | C18: 0 | D18: =SUM($C$3:$C$5)/64 | E18: =C18+D18 | F18: =IF($C$70=0, 0, E18/$C$70) | G18: =F18*$T$5 | H18: 4 | I18: =$T$7*H18 | J18: =G18+$T$9+I18 | K18: =$T$11/64 | L18: 0 | M18: 0 | N18: 0 | O18: 0 | R18: =(J18+K18+L18+M18+N18+O18)*$B$2 | S18: TOTAL FD DONE
A19: F14 | B19: Hemant Patel | C19: 0 | D19: =SUM($C$3:$C$5)/64 | E19: =C19+D19 | F19: =IF($C$70=0, 0, E19/$C$70) | G19: =F19*$T$5 | H19: 4 | I19: =$T$7*H19 | J19: =G19+$T$9+I19 | K19: =$T$11/64 | L19: 0 | M19: 0 | N19: 0 | O19: 0 | R19: =(J19+K19+L19+M19+N19+O19)*$B$2 | S19: AMOUNT AVAILABLE FOR NON MAINTENANCE CORPUS IN CURRENT AC | T19: =T17-T18
A20: F15 | B20: Senthil.Vijayaragavan | C20: 0 | D20: =SUM($C$3:$C$5)/64 | E20: =C20+D20 | F20: =IF($C$70=0, 0, E20/$C$70) | G20: =F20*$T$5 | H20: 4 | I20: =$T$7*H20 | J20: =G20+$T$9+I20 | K20: =$T$11/64 | L20: 0 | M20: 0 | N20: 0 | O20: 0 | R20: =(J20+K20+L20+M20+N20+O20)*$B$2 | S20: AMOUNT AVAILABLE FOR MAINTENANCE | T20: =T16-T19
A21: F16 | B21: Sreeja Sudharma | C21: 0 | D21: =SUM($C$3:$C$5)/64 | E21: =C21+D21 | F21: =IF($C$70=0, 0, E21/$C$70) | G21: =F21*$T$5 | H21: 3 | I21: =$T$7*H21 | J21: =G21+$T$9+I21 | K21: =$T$11/64 | L21: 0 | M21: 0 | N21: 0 | O21: 0 | R21: =(J21+K21+L21+M21+N21+O21)*$B$2 | S21: TOTAL EXPENSE FOR THE MONTH | T21: ='ANNUAL-EXPENSE-DETAILS'!BH10
A22: G1 | B22: Venkataramanan C | C22: 0 | D22: =SUM($C$3:$C$5)/64 | E22: =C22+D22 | F22: =IF($C$70=0, 0, E22/$C$70) | G22: =F22*$T$5 | H22: 3 | I22: =$T$7*H22 | J22: =G22+$T$9+I22 | K22: =$T$11/64 | L22: 0 | M22: 0 | N22: 0 | O22: 0 | R22: =(J22+K22+L22+M22+N22+O22)*$B$2
A23: G2 | B23: Kaushik Kasibhatla | C23: 0 | D23: =SUM($C$3:$C$5)/64 | E23: =C23+D23 | F23: =IF($C$70=0, 0, E23/$C$70) | G23: =F23*$T$5 | H23: 4 | I23: =$T$7*H23 | J23: =G23+$T$9+I23 | K23: =$T$11/64 | L23: 0 | M23: 0 | N23: 0 | O23: 0 | R23: =(J23+K23+L23+M23+N23+O23)*$B$2
A24: G3 | B24: Balakrishnan | C24: 0 | D24: =SUM($C$3:$C$5)/64 | E24: =C24+D24 | F24: =IF($C$70=0, 0, E24/$C$70) | G24: =F24*$T$5 | H24: 4 | I24: =$T$7*H24 | J24: =G24+$T$9+I24 | K24: =$T$11/64 | L24: 0 | M24: 0 | N24: 0 | O24: 0 | R24: =(J24+K24+L24+M24+N24+O24)*$B$2
A25: G4 | B25: Ashwin Pandith | C25: 0 | D25: =SUM($C$3:$C$5)/64 | E25: =C25+D25 | F25: =IF($C$70=0, 0, E25/$C$70) | G25: =F25*$T$5 | H25: 4 | I25: =$T$7*H25 | J25: =G25+$T$9+I25 | K25: =$T$11/64 | L25: 0 | M25: 0 | N25: 0 | O25: 0 | R25: =(J25+K25+L25+M25+N25+O25)*$B$2
A26: G5 | B26: Mayank Phophaliya | C26: 0 | D26: =SUM($C$3:$C$5)/64 | E26: =C26+D26 | F26: =IF($C$70=0, 0, E26/$C$70) | G26: =F26*$T$5 | H26: 3 | I26: =$T$7*H26 | J26: =G26+$T$9+I26 | K26: =$T$11/64 | L26: 0 | M26: 0 | N26: 0 | O26: 0 | R26: =(J26+K26+L26+M26+N26+O26)*$B$2
A27: G6 | B27: Mohit Daga | C27: 0 | D27: =SUM($C$3:$C$5)/64 | E27: =C27+D27 | F27: =IF($C$70=0, 0, E27/$C$70) | G27: =F27*$T$5 | H27: 3 | I27: =$T$7*H27 | J27: =G27+$T$9+I27 | K27: =$T$11/64 | L27: 0 | M27: 0 | N27: 0 | O27: 0 | R27: =(J27+K27+L27+M27+N27+O27)*$B$2
A28: G7 | B28: Prince Richfield | C28: 0 | D28: =SUM($C$3:$C$5)/64 | E28: =C28+D28 | F28: =IF($C$70=0, 0, E28/$C$70) | G28: =F28*$T$5 | H28: 3 | I28: =$T$7*H28 | J28: =G28+$T$9+I28 | K28: =$T$11/64 | L28: 0 | M28: 0 | N28: 0 | O28: 0 | R28: =(J28+K28+L28+M28+N28+O28)*$B$2
A29: G8 | B29: Ranjithkumar R / Sameer (tenant) / Princy (tenant) | C29: 0 | D29: =SUM($C$3:$C$5)/64 | E29: =C29+D29 | F29: =IF($C$70=0, 0, E29/$C$70) | G29: =F29*$T$5 | H29: 3 | I29: =$T$7*H29 | J29: =G29+$T$9+I29 | K29: =$T$11/64 | L29: 0 | M29: 0 | N29: 0 | O29: 0 | R29: =(J29+K29+L29+M29+N29+O29)*$B$2
A30: G9 | B30: Chandramouli | C30: 0 | D30: =SUM($C$3:$C$5)/64 | E30: =C30+D30 | F30: =IF($C$70=0, 0, E30/$C$70) | G30: =F30*$T$5 | H30: 5 | I30: =$T$7*H30 | J30: =G30+$T$9+I30 | K30: =$T$11/64 | L30: 0 | M30: 0 | N30: 0 | O30: 0 | R30: =(J30+K30+L30+M30+N30+O30)*$B$2
A31: G10 | B31: Richa Singh | C31: 0 | D31: =SUM($C$3:$C$5)/64 | E31: =C31+D31 | F31: =IF($C$70=0, 0, E31/$C$70) | G31: =F31*$T$5 | H31: 3 | I31: =$T$7*H31 | J31: =G31+$T$9+I31 | K31: =$T$11/64 | L31: 0 | M31: 0 | N31: 0 | O31: 0 | P31: 0 | R31: =(J31+K31+L31+M31+N31+O31+P31)*$B$2
A32: G11 | B32: Ketan Verlekar | C32: 0 | D32: =SUM($C$3:$C$5)/64 | E32: =C32+D32 | F32: =IF($C$70=0, 0, E32/$C$70) | G32: =F32*$T$5 | H32: 3 | I32: =$T$7*H32 | J32: =G32+$T$9+I32 | K32: =$T$11/64 | L32: 0 | M32: 0 | N32: 0 | O32: 0 | R32: =(J32+K32+L32+M32+N32+O32)*$B$2
A33: G12 | B33: Shyam Nair | C33: 0 | D33: =SUM($C$3:$C$5)/64 | E33: =C33+D33 | F33: =IF($C$70=0, 0, E33/$C$70) | G33: =F33*$T$5 | H33: 3 | I33: =$T$7*H33 | J33: =G33+$T$9+I33 | K33: =$T$11/64 | L33: 0 | M33: 0 | N33: 0 | O33: 0 | R33: =(J33+K33+L33+M33+N33+O33)*$B$2
A34: G13 | B34: Ajai.B | C34: 0 | D34: =SUM($C$3:$C$5)/64 | E34: =C34+D34 | F34: =IF($C$70=0, 0, E34/$C$70) | G34: =F34*$T$5 | H34: 4 | I34: =$T$7*H34 | J34: =G34+$T$9+I34 | K34: =$T$11/64 | L34: 0 | M34: 0 | N34: 0 | O34: 0 | R34: =(J34+K34+L34+M34+N34+O34)*$B$2
A35: G14 | B35: Surajit Borah | C35: 0 | D35: =SUM($C$3:$C$5)/64 | E35: =C35+D35 | F35: =IF($C$70=0, 0, E35/$C$70) | G35: =F35*$T$5 | H35: 4 | I35: =$T$7*H35 | J35: =G35+$T$9+I35 | K35: =$T$11/64 | L35: 0 | M35: 0 | N35: 0 | O35: 0 | R35: =(J35+K35+L35+M35+N35+O35)*$B$2
A36: G15 | B36: Suresh Nallusamy / Antriksh (tenant) | C36: 0 | D36: =SUM($C$3:$C$5)/64 | E36: =C36+D36 | F36: =IF($C$70=0, 0, E36/$C$70) | G36: =F36*$T$5 | H36: 4 | I36: =$T$7*H36 | J36: =G36+$T$9+I36 | K36: =$T$11/64 | L36: 0 | M36: 0 | N36: 0 | O36: 0 | R36: =(J36+K36+L36+M36+N36+O36)*$B$2
A37: G16 | B37: Praveen Ganesan | C37: 0 | D37: =SUM($C$3:$C$5)/64 | E37: =C37+D37 | F37: =IF($C$70=0, 0, E37/$C$70) | G37: =F37*$T$5 | H37: 3 | I37: =$T$7*H37 | J37: =G37+$T$9+I37 | K37: =$T$11/64 | L37: 0 | M37: 0 | N37: 0 | O37: 0 | R37: =(J37+K37+L37+M37+N37+O37)*$B$2
A38: S1 | B38: S.N.Behera | C38: 0 | D38: =SUM($C$3:$C$5)/64 | E38: =C38+D38 | F38: =IF($C$70=0, 0, E38/$C$70) | G38: =F38*$T$5 | H38: 3 | I38: =$T$7*H38 | J38: =G38+$T$9+I38 | K38: =$T$11/64 | L38: 0 | M38: 0 | N38: 0 | O38: 0 | R38: =(J38+K38+L38+M38+N38+O38)*$B$2
A39: S2 | B39: Sonal Singh | C39: 0 | D39: =SUM($C$3:$C$5)/64 | E39: =C39+D39 | F39: =IF($C$70=0, 0, E39/$C$70) | G39: =F39*$T$5 | H39: 4 | I39: =$T$7*H39 | J39: =G39+$T$9+I39 | K39: =$T$11/64 | L39: 0 | M39: 0 | N39: 0 | O39: 0 | R39: =(J39+K39+L39+M39+N39+O39)*$B$2
A40: S3 | B40: Koteswararao | C40: 0 | D40: =SUM($C$3:$C$5)/64 | E40: =C40+D40 | F40: =IF($C$70=0, 0, E40/$C$70) | G40: =F40*$T$5 | H40: 4 | I40: =$T$7*H40 | J40: =G40+$T$9+I40 | K40: =$T$11/64 | L40: 0 | M40: 0 | N40: 0 | O40: 0 | R40: =(J40+K40+L40+M40+N40+O40)*$B$2
A41: S4 | B41: Swaminathan | C41: 0 | D41: =SUM($C$3:$C$5)/64 | E41: =C41+D41 | F41: =IF($C$70=0, 0, E41/$C$70) | G41: =F41*$T$5 | H41: 3 | I41: =$T$7*H41 | J41: =G41+$T$9+I41 | K41: =$T$11/64 | L41: 0 | M41: 0 | N41: 0 | O41: 0 | R41: =(J41+K41+L41+M41+N41+O41)*$B$2
A42: S5 | B42: Abhishek Gopalakrishnan | C42: 0 | D42: =SUM($C$3:$C$5)/64 | E42: =C42+D42 | F42: =IF($C$70=0, 0, E42/$C$70) | G42: =F42*$T$5 | H42: 3 | I42: =$T$7*H42 | J42: =G42+$T$9+I42 | K42: =$T$11/64 | L42: 0 | M42: 0 | N42: 0 | O42: 0 | R42: =(J42+K42+L42+M42+N42+O42)*$B$2
A43: S6 | B43: Vivek Dhingra / Pratyush Das | C43: 0 | D43: =SUM($C$3:$C$5)/64 | E43: =C43+D43 | F43: =IF($C$70=0, 0, E43/$C$70) | G43: =F43*$T$5 | H43: 3 | I43: =$T$7*H43 | J43: =G43+$T$9+I43 | K43: =$T$11/64 | L43: 0 | M43: 0 | N43: 0 | O43: 0 | R43: =(J43+K43+L43+M43+N43+O43)*$B$2
... A69: T16 | B69: Madhusoodanan P.R. | C69: 0 | D69: =SUM($C$3:$C$5)/64 | E69: =C69+D69 | F69: =IF($C$70=0, 0, E69/$C$70) | G69: =F69*$T$5 | H69: 3 | I69: =$T$7*H69 | J69: =G69+$T$9+I69 | K69: =$T$11/64 | L69: 0 | M69: 0 | N69: 0 | O69: 0 | R69: =(J69+K69+L69+M69+N69+O69)*$B$2
B70: TOTAL | C70: =SUM(C3:C69) | D70: =SUM(D3:D69) | E70: =SUM(E3:E69) | F70: =IF($C$70=0, 0, E70/$C$70) | G70: =SUM(G3:G69) | H70: =SUM(H3:H69) | I70: =SUM(I3:I69) | J70: =SUM(J3:J69) | K70: =SUM(K3:K69) | L70: =SUM(L3:L69) | M70: =SUM(M3:M69) | N70: =SUM(N3:N69) | O70: =SUM(O3:O69) | R70: =SUM(R3:R69)

Sheet Nov2026-COLLECTION
A1: FLAT # | C1: Amount | D1: Date | E1: Amount | F1: Date | G1: Amount | H1: Date | I1: Amount | J1: Date | K1: Total
A2: F1 | B2: Shailesh Srivastava / Azeem Nawaz | K2: =SUM(C2,E2,G2,I2)
A3: F2 | B3: Shanthanu | K3: =SUM(C3,E3,G3,I3)
A4: F3 | B4: Samrat Kar | K4: =SUM(C4,E4,G4,I4)
A5: F4 | B5: Renu R | K5: =SUM(C5,E5,G5,I5)
A6: F5 | B6: Vamsidhar Bethanabatla / Madhuri Anumula / Pulkit Gupta | K6: =SUM(C6,E6,G6,I6)
A7: F6 | B7: Meghana Viral Shah and Vviral Shah (Owner) / Sangeet and Swagat (Tenent) | K7: =SUM(C7,E7,G7,I7)
A8: F7 | B8: Vimal NK | K8: =SUM(C8,E8,G8,I8)
A9: F8 | B9: Sreejith Menon (Owner) | K9: =SUM(C9,E9,G9,I9)
A10: F9 | B10: Vijay Suswaram (Owner) / Divya Shikha (Tenant) | K10: =SUM(C10,E10,G10,I10)
A11: F10 | B11: Aby Thomas | K11: =SUM(C11,E11,G11,I11)
A12: F11 | B12: Geetha. N | K12: =SUM(C12,E12,G12,I12)
A13: F12 | B13: Anirudh Singh | K13: =SUM(C13,E13,G13,I13)
... A65: T16 | B65: Madhusoodanan P.R. | K65: =SUM(C65,E65,G65,I65)
A66: TOTAL | K66: =SUM(K2:K65)

Sheet Dec2026-EXPENSE
B1: DECEMBER 2026 EXPENSES
A2: FLAT # | B2: 1 | C2: WATER USED IN LTRS | D2: COMMON AREA EQUALLY DEVIDED | E2: TOTAL FRESH WATER CONSUMED | F2: %OF TOTAL USED | G2: WATER EXPENSE SHARING BY % | H2: #METERS | I2: METER RENT | J2: COMMON AREA METER RENT + WATER EXPENSE+ FLAT METER RENT | K2: FIXED EXPENSE SHARE | L2: PARKING FEE | M2: CLUB BOOKING FEE | N2: SHIFTING FEE | O2: GYM USAGE FEE | R2: TOTAL EXPENSE TO BE PAID
A3: CH | B3: MPFOWA | C3: 0 | D3: 0 | H3: 1 | I3: =T7
A4: GYM | B4: MPFOWA | C4: 0 | D4: 0 | H4: 1 | I4: =T7 | S4: TOTAL FIXED EXPENSE | T4: ='ANNUAL-EXPENSE-DETAILS'!BF11
A5: BSMT | B5: MPFOWA | C5: 0 | D5: 0 | H5: 1 | I5: =T7 | S5: TOTAL WATER EXPENSE | T5: ='ANNUAL-EXPENSE-DETAILS'!BE11
A6: F1 | B6: Shailesh Srivastava / Azeem Nawaz | C6: 0 | D6: =SUM($C$3:$C$5)/64 | E6: =C6+D6 | F6: =IF($C$70=0, 0, E6/$C$70) | G6: =F6*$T$5 | H6: 3 | I6: =$T$7*H6 | J6: =G6+$T$9+I6 | K6: =$T$11/64 | L6: 0 | M6: 0 | N6: 0 | O6: 0 | R6: =(J6+K6+L6+M6+N6+O6)*$B$2
A7: F2 | B7: Shanthanu | C7: 0 | D7: =SUM($C$3:$C$5)/64 | E7: =C7+D7 | F7: =IF($C$70=0, 0, E7/$C$70) | G7: =F7*$T$5 | H7: 4 | I7: =$T$7*H7 | J7: =G7+$T$9+I7 | K7: =$T$11/64 | L7: 0 | M7: 0 | N7: 0 | O7: 0 | R7: =(J7+K7+L7+M7+N7+O7)*$B$2 | S7: RENT PER METER | T7: 117.81166
A8: F3 | B8: Samrat Kar | C8: 0 | D8: =SUM($C$3:$C$5)/64 | E8: =C8+D8 | F8: =IF($C$70=0, 0, E8/$C$70) | G8: =F8*$T$5 | H8: 4 | I8: =$T$7*H8 | J8: =G8+$T$9+I8 | K8: =$T$11/64 | L8: 0 | M8: 0 | N8: 0 | O8: 0 | R8: =(J8+K8+L8+M8+N8+O8)*$B$2 | S8: COMMON AREA METER RENT | T8: =$T$7*3
A9: F4 | B9: Renu R | C9: 0 | D9: =SUM($C$3:$C$5)/64 | E9: =C9+D9 | F9: =IF($C$70=0, 0, E9/$C$70) | G9: =F9*$T$5 | H9: 4 | I9: =$T$7*H9 | J9: =G9+$T$9+I9 | K9: =$T$11/64 | L9: 0 | M9: 0 | N9: 0 | O9: 0 | R9: =(J9+K9+L9+M9+N9+O9)*$B$2 | S9: COMMON AREA METER RENT/FLAT | T9: =T8/64
A10: F5 | B10: Vamsidhar Bethanabatla / Madhuri Anumula | C10: 0 | D10: =SUM($C$3:$C$5)/64 | E10: =C10+D10 | F10: =IF($C$70=0, 0, E10/$C$70) | G10: =F10*$T$5 | H10: 3 | I10: =$T$7*H10 | J10: =G10+$T$9+I10 | K10: =$T$11/64 | L10: 0 | M10: 0 | N10: 0 | O10: 0 | R10: =(J10+K10+L10+M10+N10+O10)*$B$2
A11: F6 | B11: Meghana Viral Shah and Vviral Shah (Owner) / Sangeet and Swagat (Tenent) | C11: 0 | D11: =SUM($C$3:$C$5)/64 | E11: =C11+D11 | F11: =IF($C$70=0, 0, E11/$C$70) | G11: =F11*$T$5 | H11: 3 | I11: =$T$7*H11 | J11: =G11+$T$9+I11 | K11: =$T$11/64 | L11: 0 | M11: 0 | N11: 0 | O11: 0 | R11: =(J11+K11+L11+M11+N11+O11)*$B$2 | S11: TOTAL FIXED EXPENSE | T11: ='ANNUAL-EXPENSE-DETAILS'!BF11
A12: F7 | B12: Vimal NK | C12: 0 | D12: =SUM($C$3:$C$5)/64 | E12: =C12+D12 | F12: =IF($C$70=0, 0, E12/$C$70) | G12: =F12*$T$5 | H12: 3 | I12: =$T$7*H12 | J12: =G12+$T$9+I12 | K12: =$T$11/64 | L12: 0 | M12: 0 | N12: 0 | O12: 0 | R12: =(J12+K12+L12+M12+N12+O12)*$B$2
A13: F8 | B13: Sujeet Kumar (Tenant)/Sreejith Menon (Owner) | C13: 0 | D13: =SUM($C$3:$C$5)/64 | E13: =C13+D13 | F13: =IF($C$70=0, 0, E13/$C$70) | G13: =F13*$T$5 | H13: 3 | I13: =$T$7*H13 | J13: =G13+$T$9+I13 | K13: =$T$11/64 | L13: 0 | M13: 0 | N13: 0 | O13: 0 | R13: =(J13+K13+L13+M13+N13+O13)*$B$2 | S13: TOTAL WATER METER RENT | T13: =I70
A14: F9 | B14: Vijay Suswaram (Owner) / Divya Shikha (Tenant) | C14: 0 | D14: =SUM($C$3:$C$5)/64 | E14: =C14+D14 | F14: =IF($C$70=0, 0, E14/$C$70) | G14: =F14*$T$5 | H14: 4 | I14: =$T$7*H14 | J14: =G14+$T$9+I14 | K14: =$T$11/64 | L14: 0 | M14: 0 | N14: 0 | O14: 0 | R14: =(J14+K14+L14+M14+N14+O14)*$B$2
A15: F10 | B15: Aby Thomas | C15: 0 | D15: =SUM($C$3:$C$5)/64 | E15: =C15+D15 | F15: =IF($C$70=0, 0, E15/$C$70) | G15: =F15*$T$5 | H15: 3 | I15: =$T$7*H15 | J15: =G15+$T$9+I15 | K15: =$T$11/64 | L15: 0 | M15: 0 | N15: 0 | O15: 0 | R15: =(J15+K15+L15+M15+N15+O15)*$B$2 | S15: BALANCE IN ACCOUNT ON 31-DEC-2023
A16: F11 | B16: Niwin Anto | C16: 0 | D16: =SUM($C$3:$C$5)/64 | E16: =C16+D16 | F16: =IF($C$70=0, 0, E16/$C$70) | G16: =F16*$T$5 | H16: 3 | I16: =$T$7*H16 | J16: =G16+$T$9+I16 | K16: =$T$11/64 | L16: 0 | M16: 0 | N16: 0 | O16: 0 | R16: =(J16+K16+L16+M16+N16+O16)*$B$2 | S16: TOTAL NON MAINTENANCE CORPUS COLLECTION
A17: F12 | B17: Anirudh Singh | C17: 0 | D17: =SUM($C$3:$C$5)/64 | E17: =C17+D17 | F17: =IF($C$70=0, 0, E17/$C$70) | G17: =F17*$T$5 | H17: 3 | I17: =$T$7*H17 | J17: =G17+$T$9+I17 | K17: =$T$11/64 | L17: 0 | M17: 0 | N17: 0 | O17: 0 | R17: =(J17+K17+L17+M17+N17+O17)*$B$2 | S17: TOTAL FD DONE
A18: F13 | B18: Sanchay Saxena | C18: 0 | D18: =SUM($C$3:$C$5)/64 | E18: =C18+D18 | F18: =IF($C$70=0, 0, E18/$C$70) | G18: =F18*$T$5 | H18: 4 | I18: =$T$7*H18 | J18: =G18+$T$9+I18 | K18: =$T$11/64 | L18: 0 | M18: 0 | N18: 0 | O18: 0 | R18: =(J18+K18+L18+M18+N18+O18)*$B$2 | S18: AMOUNT AVAILABLE FOR NON MAINTENANCE CORPUS IN CURRENT AC | T18: =T16-T17
A19: F14 | B19: Hemant Patel | C19: 0 | D19: =SUM($C$3:$C$5)/64 | E19: =C19+D19 | F19: =IF($C$70=0, 0, E19/$C$70) | G19: =F19*$T$5 | H19: 4 | I19: =$T$7*H19 | J19: =G19+$T$9+I19 | K19: =$T$11/64 | L19: 0 | M19: 0 | N19: 0 | O19: 0 | R19: =(J19+K19+L19+M19+N19+O19)*$B$2 | S19: AMOUNT AVAILABLE FOR MAINTENANCE | T19: =T15-T18
A20: F15 | B20: Senthil.Vijayaragavan | C20: 0 | D20: =SUM($C$3:$C$5)/64 | E20: =C20+D20 | F20: =IF($C$70=0, 0, E20/$C$70) | G20: =F20*$T$5 | H20: 4 | I20: =$T$7*H20 | J20: =G20+$T$9+I20 | K20: =$T$11/64 | L20: 0 | M20: 0 | N20: 0 | O20: 0 | R20: =(J20+K20+L20+M20+N20+O20)*$B$2 | S20: TOTAL EXPENSE FOR THE MONTH | T20: ='ANNUAL-EXPENSE-DETAILS'!BH11
A21: F16 | B21: Sreeja Sudharma | C21: 0 | D21: =SUM($C$3:$C$5)/64 | E21: =C21+D21 | F21: =IF($C$70=0, 0, E21/$C$70) | G21: =F21*$T$5 | H21: 3 | I21: =$T$7*H21 | J21: =G21+$T$9+I21 | K21: =$T$11/64 | L21: 0 | M21: 0 | N21: 0 | O21: 0 | R21: =(J21+K21+L21+M21+N21+O21)*$B$2
A22: G1 | B22: Venkataramanan C | C22: 0 | D22: =SUM($C$3:$C$5)/64 | E22: =C22+D22 | F22: =IF($C$70=0, 0, E22/$C$70) | G22: =F22*$T$5 | H22: 3 | I22: =$T$7*H22 | J22: =G22+$T$9+I22 | K22: =$T$11/64 | L22: 0 | M22: 0 | N22: 0 | O22: 0 | R22: =(J22+K22+L22+M22+N22+O22)*$B$2
A23: G2 | B23: Kaushik Kasibhatla | C23: 0 | D23: =SUM($C$3:$C$5)/64 | E23: =C23+D23 | F23: =IF($C$70=0, 0, E23/$C$70) | G23: =F23*$T$5 | H23: 4 | I23: =$T$7*H23 | J23: =G23+$T$9+I23 | K23: =$T$11/64 | L23: 0 | M23: 0 | N23: 0 | O23: 0 | R23: =(J23+K23+L23+M23+N23+O23)*$B$2
A24: G3 | B24: Balakrishnan | C24: 0 | D24: =SUM($C$3:$C$5)/64 | E24: =C24+D24 | F24: =IF($C$70=0, 0, E24/$C$70) | G24: =F24*$T$5 | H24: 4 | I24: =$T$7*H24 | J24: =G24+$T$9+I24 | K24: =$T$11/64 | L24: 0 | M24: 0 | N24: 0 | O24: 0 | R24: =(J24+K24+L24+M24+N24+O24)*$B$2
A25: G4 | B25: Ashwin Pandith | C25: 0 | D25: =SUM($C$3:$C$5)/64 | E25: =C25+D25 | F25: =IF($C$70=0, 0, E25/$C$70) | G25: =F25*$T$5 | H25: 4 | I25: =$T$7*H25 | J25: =G25+$T$9+I25 | K25: =$T$11/64 | L25: 0 | M25: 0 | N25: 0 | O25: 0 | R25: =(J25+K25+L25+M25+N25+O25)*$B$2
A26: G5 | B26: Mayank Phophaliya | C26: 0 | D26: =SUM($C$3:$C$5)/64 | E26: =C26+D26 | F26: =IF($C$70=0, 0, E26/$C$70) | G26: =F26*$T$5 | H26: 3 | I26: =$T$7*H26 | J26: =G26+$T$9+I26 | K26: =$T$11/64 | L26: 0 | M26: 0 | N26: 0 | O26: 0 | R26: =(J26+K26+L26+M26+N26+O26)*$B$2
A27: G6 | B27: Mohit Daga | C27: 0 | D27: =SUM($C$3:$C$5)/64 | E27: =C27+D27 | F27: =IF($C$70=0, 0, E27/$C$70) | G27: =F27*$T$5 | H27: 3 | I27: =$T$7*H27 | J27: =G27+$T$9+I27 | K27: =$T$11/64 | L27: 0 | M27: 0 | N27: 0 | O27: 0 | R27: =(J27+K27+L27+M27+N27+O27)*$B$2
A28: G7 | B28: Prince Richfield | C28: 0 | D28: =SUM($C$3:$C$5)/64 | E28: =C28+D28 | F28: =IF($C$70=0, 0, E28/$C$70) | G28: =F28*$T$5 | H28: 3 | I28: =$T$7*H28 | J28: =G28+$T$9+I28 | K28: =$T$11/64 | L28: 0 | M28: 0 | N28: 0 | O28: 0 | R28: =(J28+K28+L28+M28+N28+O28)*$B$2
A29: G8 | B29: Ranjithkumar R / Sameer (tenant) / Princy (tenant) | C29: 0 | D29: =SUM($C$3:$C$5)/64 | E29: =C29+D29 | F29: =IF($C$70=0, 0, E29/$C$70) | G29: =F29*$T$5 | H29: 3 | I29: =$T$7*H29 | J29: =G29+$T$9+I29 | K29: =$T$11/64 | L29: 0 | M29: 0 | N29: 0 | O29: 0 | R29: =(J29+K29+L29+M29+N29+O29)*$B$2
A30: G9 | B30: Chandramouli | C30: 0 | D30: =SUM($C$3:$C$5)/64 | E30: =C30+D30 | F30: =IF($C$70=0, 0, E30/$C$70) | G30: =F30*$T$5 | H30: 5 | I30: =$T$7*H30 | J30: =G30+$T$9+I30 | K30: =$T$11/64 | L30: 0 | M30: 0 | N30: 0 | O30: 0 | R30: =(J30+K30+L30+M30+N30+O30)*$B$2
A31: G10 | B31: Cijo Jacob / Thara Joy | C31: 0 | D31: =SUM($C$3:$C$5)/64 | E31: =C31+D31 | F31: =IF($C$70=0, 0, E31/$C$70) | G31: =F31*$T$5 | H31: 3 | I31: =$T$7*H31 | J31: =G31+$T$9+I31 | K31: =$T$11/64 | L31: 0 | M31: 0 | N31: 0 | O31: 0 | R31: =(J31+K31+L31+M31+N31+O31)*$B$2
A32: G11 | B32: Ketan Verlekar | C32: 0 | D32: =SUM($C$3:$C$5)/64 | E32: =C32+D32 | F32: =IF($C$70=0, 0, E32/$C$70) | G32: =F32*$T$5 | H32: 3 | I32: =$T$7*H32 | J32: =G32+$T$9+I32 | K32: =$T$11/64 | L32: 0 | M32: 0 | N32: 0 | O32: 0 | R32: =(J32+K32+L32+M32+N32+O32)*$B$2
... A69: T16 | B69: Madhusoodanan P.R. | C69: 0 | D69: =SUM($C$3:$C$5)/64 | E69: =C69+D69 | F69: =IF($C$70=0, 0, E69/$C$70) | G69: =F69*$T$5 | H69: 3 | I69: =$T$7*H69 | J69: =G69+$T$9+I69 | K69: =$T$11/64 | L69: 0 | M69: 0 | N69: 0 | O69: 0 | R69: =(J69+K69+L69+M69+N69+O69)*$B$2
B70: TOTAL | C70: =SUM(C3:C69) | D70: =SUM(D3:D69) | E70: =SUM(E3:E69) | F70: =IF($C$70=0, 0, E70/$C$70) | G70: =SUM(G3:G69) | H70: =SUM(H3:H69) | I70: =SUM(I3:I69) | J70: =SUM(J3:J69) | K70: =SUM(K3:K69) | L70: =SUM(L3:L69) | M70: =SUM(M3:M69) | N70: =SUM(N3:N69) | O70: =SUM(O3:O69) | R70: =SUM(R3:R69)

Sheet Dec2026-COLLECTION
A1: FLAT # | C1: Amount | D1: Date | E1: Amount | F1: Date | G1: Amount | H1: Date | I1: Amount | J1: Date | K1: Total
A2: F1 | B2: Shailesh Srivastava / Azeem Nawaz | K2: =SUM(C2,E2,G2,I2)
A3: F2 | B3: Shanthanu | K3: =SUM(C3,E3,G3,I3)
A4: F3 | B4: Samrat Kar | K4: =SUM(C4,E4,G4,I4)
A5: F4 | B5: Renu R | K5: =SUM(C5,E5,G5,I5)
A6: F5 | B6: Vamsidhar Bethanabatla / Madhuri Anumula | K6: =SUM(C6,E6,G6,I6)
A7: F6 | B7: Meghana Viral Shah and Vviral Shah (Owner) / Sangeet and Swagat (Tenent) | K7: =SUM(C7,E7,G7,I7)
A8: F7 | B8: Vimal NK | K8: =SUM(C8,E8,G8,I8)
A9: F8 | B9: Sujeet Kumar (Tenant)/Sreejith Menon (Owner) | K9: =SUM(C9,E9,G9,I9)
A10: F9 | B10: Vijay Suswaram (Owner) / Divya Shikha (Tenant) / Harshvardhan | K10: =SUM(C10,E10,G10,I10)
A11: F10 | B11: Aby Thomas | K11: =SUM(C11,E11,G11,I11)
A12: F11 | B12: N. Geetha | K12: =SUM(C12,E12,G12,I12)
A13: F12 | B13: Anirudh Singh | K13: =SUM(C13,E13,G13,I13)
... A65: T16 | B65: Madhusoodanan P.R. | K65: =SUM(C65,E65,G65,I65)
A66: TOTAL | K66: =SUM(K2:K65)

Sheet Jan2027-EXPENSE
B1: JANUARY 2027 EXPENSES
A2: FLAT # | B2: 1 | C2: WATER USED IN LTRS | D2: COMMON AREA EQUALLY DEVIDED | E2: TOTAL FRESH WATER CONSUMED | F2: %OF TOTAL USED | G2: WATER EXPENSE SHARING BY % | H2: #METERS | I2: METER RENT | J2: COMMON AREA METER RENT + WATER EXPENSE+ FLAT METER RENT | K2: FIXED EXPENSE SHARE | L2: PARKING FEE | M2: CLUB BOOKING FEE | N2: SHIFTING FEE | O2: GYM USAGE FEE | R2: TOTAL EXPENSE TO BE PAID
A3: CH | B3: MPFOWA | C3: 0 | D3: 0 | H3: 1 | I3: =T7
A4: GYM | B4: MPFOWA | C4: 0 | D4: 0 | H4: 1 | I4: =T7 | S4: TOTAL FIXED EXPENSE | T4: ='ANNUAL-EXPENSE-DETAILS'!BF12
A5: BSMT | B5: MPFOWA | C5: 0 | D5: 0 | H5: 1 | I5: =T7 | S5: TOTAL WATER EXPENSE | T5: ='ANNUAL-EXPENSE-DETAILS'!BE12
A6: F1 | B6: Shailesh Srivastava / Azeem Nawaz | C6: 0 | D6: =SUM($C$3:$C$5)/64 | E6: =C6+D6 | F6: =IF($C$70=0, 0, E6/$C$70) | G6: =F6*$T$5 | H6: 3 | I6: =$T$7*H6 | J6: =G6+$T$9+I6 | K6: =$T$11/64 | L6: 0 | M6: 0 | N6: 0 | O6: 0 | R6: =(J6+K6+L6+M6+N6+O6)*$B$2
A7: F2 | B7: Shanthanu | C7: 0 | D7: =SUM($C$3:$C$5)/64 | E7: =C7+D7 | F7: =IF($C$70=0, 0, E7/$C$70) | G7: =F7*$T$5 | H7: 4 | I7: =$T$7*H7 | J7: =G7+$T$9+I7 | K7: =$T$11/64 | L7: 0 | M7: 0 | N7: 0 | O7: 0 | R7: =(J7+K7+L7+M7+N7+O7)*$B$2 | S7: RENT PER METER | T7: 117.81166
A8: F3 | B8: Samrat Kar | C8: 0 | D8: =SUM($C$3:$C$5)/64 | E8: =C8+D8 | F8: =IF($C$70=0, 0, E8/$C$70) | G8: =F8*$T$5 | H8: 4 | I8: =$T$7*H8 | J8: =G8+$T$9+I8 | K8: =$T$11/64 | L8: 0 | M8: 0 | N8: 0 | O8: 0 | R8: =(J8+K8+L8+M8+N8+O8)*$B$2 | S8: COMMON AREA METER RENT | T8: =$T$7*3
A9: F4 | B9: Renu R | C9: 0 | D9: =SUM($C$3:$C$5)/64 | E9: =C9+D9 | F9: =IF($C$70=0, 0, E9/$C$70) | G9: =F9*$T$5 | H9: 4 | I9: =$T$7*H9 | J9: =G9+$T$9+I9 | K9: =$T$11/64 | L9: 0 | M9: 0 | N9: 0 | O9: 0 | R9: =(J9+K9+L9+M9+N9+O9)*$B$2 | S9: COMMON AREA METER RENT/FLAT | T9: =T8/64
A10: F5 | B10: Vamsidhar Bethanabatla / Madhuri Anumula | C10: 0 | D10: =SUM($C$3:$C$5)/64 | E10: =C10+D10 | F10: =IF($C$70=0, 0, E10/$C$70) | G10: =F10*$T$5 | H10: 3 | I10: =$T$7*H10 | J10: =G10+$T$9+I10 | K10: =$T$11/64 | L10: 0 | M10: 0 | N10: 0 | O10: 0 | R10: =(J10+K10+L10+M10+N10+O10)*$B$2
A11: F6 | B11: Meghana Viral Shah and Vviral Shah (Owner) / Sangeet and Swagat (Tenent) | C11: 0 | D11: =SUM($C$3:$C$5)/64 | E11: =C11+D11 | F11: =IF($C$70=0, 0, E11/$C$70) | G11: =F11*$T$5 | H11: 3 | I11: =$T$7*H11 | J11: =G11+$T$9+I11 | K11: =$T$11/64 | L11: 0 | M11: 0 | N11: 0 | O11: 0 | R11: =(J11+K11+L11+M11+N11+O11)*$B$2 | S11: TOTAL FIXED EXPENSE | T11: ='ANNUAL-EXPENSE-DETAILS'!BF12
A12: F7 | B12: Vimal NK | C12: 0 | D12: =SUM($C$3:$C$5)/64 | E12: =C12+D12 | F12: =IF($C$70=0, 0, E12/$C$70) | G12: =F12*$T$5 | H12: 3 | I12: =$T$7*H12 | J12: =G12+$T$9+I12 | K12: =$T$11/64 | L12: 0 | M12: 0 | N12: 0 | O12: 0 | R12: =(J12+K12+L12+M12+N12+O12)*$B$2
A13: F8 | B13: Sujeet Kumar (Tenant)/Sreejith Menon (Owner) | C13: 0 | D13: =SUM($C$3:$C$5)/64 | E13: =C13+D13 | F13: =IF($C$70=0, 0, E13/$C$70) | G13: =F13*$T$5 | H13: 3 | I13: =$T$7*H13 | J13: =G13+$T$9+I13 | K13: =$T$11/64 | L13: 0 | M13: 0 | N13: 0 | O13: 0 | R13: =(J13+K13+L13+M13+N13+O13)*$B$2 | S13: TOTAL WATER METER RENT | T13: =I70
A14: F9 | B14: Vijay Suswaram (Owner) / Divya Shikha (Tenant) | C14: 0 | D14: =SUM($C$3:$C$5)/64 | E14: =C14+D14 | F14: =IF($C$70=0, 0, E14/$C$70) | G14: =F14*$T$5 | H14: 4 | I14: =$T$7*H14 | J14: =G14+$T$9+I14 | K14: =$T$11/64 | L14: 0 | M14: 0 | N14: 0 | O14: 0 | R14: =(J14+K14+L14+M14+N14+O14)*$B$2
A15: F10 | B15: Aby Thomas | C15: 0 | D15: =SUM($C$3:$C$5)/64 | E15: =C15+D15 | F15: =IF($C$70=0, 0, E15/$C$70) | G15: =F15*$T$5 | H15: 3 | I15: =$T$7*H15 | J15: =G15+$T$9+I15 | K15: =$T$11/64 | L15: 0 | M15: 0 | N15: 0 | O15: 0 | R15: =(J15+K15+L15+M15+N15+O15)*$B$2 | S15: BALANCE IN ACCOUNT ON 31-Jan-2023
A16: F11 | B16: Niwin Anto | C16: 0 | D16: =SUM($C$3:$C$5)/64 | E16: =C16+D16 | F16: =IF($C$70=0, 0, E16/$C$70) | G16: =F16*$T$5 | H16: 3 | I16: =$T$7*H16 | J16: =G16+$T$9+I16 | K16: =$T$11/64 | L16: 0 | M16: 0 | N16: 0 | O16: 0 | R16: =(J16+K16+L16+M16+N16+O16)*$B$2 | S16: TOTAL NON MAINTENANCE CORPUS COLLECTION
A17: F12 | B17: Anirudh Singh | C17: 0 | D17: =SUM($C$3:$C$5)/64 | E17: =C17+D17 | F17: =IF($C$70=0, 0, E17/$C$70) | G17: =F17*$T$5 | H17: 3 | I17: =$T$7*H17 | J17: =G17+$T$9+I17 | K17: =$T$11/64 | L17: 0 | M17: 0 | N17: 0 | O17: 0 | R17: =(J17+K17+L17+M17+N17+O17)*$B$2 | S17: TOTAL FD DONE
A18: F13 | B18: Sanchay Saxena | C18: 0 | D18: =SUM($C$3:$C$5)/64 | E18: =C18+D18 | F18: =IF($C$70=0, 0, E18/$C$70) | G18: =F18*$T$5 | H18: 4 | I18: =$T$7*H18 | J18: =G18+$T$9+I18 | K18: =$T$11/64 | L18: 0 | M18: 0 | N18: 0 | O18: 0 | R18: =(J18+K18+L18+M18+N18+O18)*$B$2 | S18: AMOUNT AVAILABLE FOR NON MAINTENANCE CORPUS IN CURRENT AC | T18: =T16-T17
A19: F14 | B19: Hemant Patel | C19: 0 | D19: =SUM($C$3:$C$5)/64 | E19: =C19+D19 | F19: =IF($C$70=0, 0, E19/$C$70) | G19: =F19*$T$5 | H19: 4 | I19: =$T$7*H19 | J19: =G19+$T$9+I19 | K19: =$T$11/64 | L19: 0 | M19: 0 | N19: 0 | O19: 0 | R19: =(J19+K19+L19+M19+N19+O19)*$B$2 | S19: AMOUNT AVAILABLE FOR MAINTENANCE | T19: =T15-T18
A20: F15 | B20: Senthil.Vijayaragavan | C20: 0 | D20: =SUM($C$3:$C$5)/64 | E20: =C20+D20 | F20: =IF($C$70=0, 0, E20/$C$70) | G20: =F20*$T$5 | H20: 4 | I20: =$T$7*H20 | J20: =G20+$T$9+I20 | K20: =$T$11/64 | L20: 0 | M20: 0 | N20: 0 | O20: 0 | R20: =(J20+K20+L20+M20+N20+O20)*$B$2 | S20: TOTAL EXPENSE FOR THE MONTH | T20: ='ANNUAL-EXPENSE-DETAILS'!BH12
A21: F16 | B21: Sreeja Sudharma | C21: 0 | D21: =SUM($C$3:$C$5)/64 | E21: =C21+D21 | F21: =IF($C$70=0, 0, E21/$C$70) | G21: =F21*$T$5 | H21: 3 | I21: =$T$7*H21 | J21: =G21+$T$9+I21 | K21: =$T$11/64 | L21: 0 | M21: 0 | N21: 0 | O21: 0 | R21: =(J21+K21+L21+M21+N21+O21)*$B$2
A22: G1 | B22: Venkataramanan C | C22: 0 | D22: =SUM($C$3:$C$5)/64 | E22: =C22+D22 | F22: =IF($C$70=0, 0, E22/$C$70) | G22: =F22*$T$5 | H22: 3 | I22: =$T$7*H22 | J22: =G22+$T$9+I22 | K22: =$T$11/64 | L22: 0 | M22: 0 | N22: 0 | O22: 0 | R22: =(J22+K22+L22+M22+N22+O22)*$B$2
A23: G2 | B23: Kaushik Kasibhatla | C23: 0 | D23: =SUM($C$3:$C$5)/64 | E23: =C23+D23 | F23: =IF($C$70=0, 0, E23/$C$70) | G23: =F23*$T$5 | H23: 4 | I23: =$T$7*H23 | J23: =G23+$T$9+I23 | K23: =$T$11/64 | L23: 0 | M23: 0 | N23: 0 | O23: 0 | R23: =(J23+K23+L23+M23+N23+O23)*$B$2
A24: G3 | B24: Balakrishnan | C24: 0 | D24: =SUM($C$3:$C$5)/64 | E24: =C24+D24 | F24: =IF($C$70=0, 0, E24/$C$70) | G24: =F24*$T$5 | H24: 4 | I24: =$T$7*H24 | J24: =G24+$T$9+I24 | K24: =$T$11/64 | L24: 0 | M24: 0 | N24: 0 | O24: 0 | R24: =(J24+K24+L24+M24+N24+O24)*$B$2
A25: G4 | B25: Ashwin Pandith | C25: 0 | D25: =SUM($C$3:$C$5)/64 | E25: =C25+D25 | F25: =IF($C$70=0, 0, E25/$C$70) | G25: =F25*$T$5 | H25: 4 | I25: =$T$7*H25 | J25: =G25+$T$9+I25 | K25: =$T$11/64 | L25: 0 | M25: 0 | N25: 0 | O25: 0 | R25: =(J25+K25+L25+M25+N25+O25)*$B$2
A26: G5 | B26: Mayank Phophaliya | C26: 0 | D26: =SUM($C$3:$C$5)/64 | E26: =C26+D26 | F26: =IF($C$70=0, 0, E26/$C$70) | G26: =F26*$T$5 | H26: 3 | I26: =$T$7*H26 | J26: =G26+$T$9+I26 | K26: =$T$11/64 | L26: 0 | M26: 0 | N26: 0 | O26: 0 | R26: =(J26+K26+L26+M26+N26+O26)*$B$2
A27: G6 | B27: Mohit Daga | C27: 0 | D27: =SUM($C$3:$C$5)/64 | E27: =C27+D27 | F27: =IF($C$70=0, 0, E27/$C$70) | G27: =F27*$T$5 | H27: 3 | I27: =$T$7*H27 | J27: =G27+$T$9+I27 | K27: =$T$11/64 | L27: 0 | M27: 0 | N27: 0 | O27: 0 | R27: =(J27+K27+L27+M27+N27+O27)*$B$2
A28: G7 | B28: Prince Richfield | C28: 0 | D28: =SUM($C$3:$C$5)/64 | E28: =C28+D28 | F28: =IF($C$70=0, 0, E28/$C$70) | G28: =F28*$T$5 | H28: 3 | I28: =$T$7*H28 | J28: =G28+$T$9+I28 | K28: =$T$11/64 | L28: 0 | M28: 0 | N28: 0 | O28: 0 | R28: =(J28+K28+L28+M28+N28+O28)*$B$2
A29: G8 | B29: Ranjithkumar R / Sameer (tenant) / Princy (tenant) | C29: 0 | D29: =SUM($C$3:$C$5)/64 | E29: =C29+D29 | F29: =IF($C$70=0, 0, E29/$C$70) | G29: =F29*$T$5 | H29: 3 | I29: =$T$7*H29 | J29: =G29+$T$9+I29 | K29: =$T$11/64 | L29: 0 | M29: 0 | N29: 0 | O29: 0 | R29: =(J29+K29+L29+M29+N29+O29)*$B$2
A30: G9 | B30: Chandramouli | C30: 0 | D30: =SUM($C$3:$C$5)/64 | E30: =C30+D30 | F30: =IF($C$70=0, 0, E30/$C$70) | G30: =F30*$T$5 | H30: 5 | I30: =$T$7*H30 | J30: =G30+$T$9+I30 | K30: =$T$11/64 | L30: 0 | M30: 0 | N30: 0 | O30: 0 | R30: =(J30+K30+L30+M30+N30+O30)*$B$2
A31: G10 | B31: Cijo Jacob / Thara Joy | C31: 0 | D31: =SUM($C$3:$C$5)/64 | E31: =C31+D31 | F31: =IF($C$70=0, 0, E31/$C$70) | G31: =F31*$T$5 | H31: 3 | I31: =$T$7*H31 | J31: =G31+$T$9+I31 | K31: =$T$11/64 | L31: 0 | M31: 0 | N31: 0 | O31: 0 | R31: =(J31+K31+L31+M31+N31+O31)*$B$2
A32: G11 | B32: Ketan Verlekar | C32: 0 | D32: =SUM($C$3:$C$5)/64 | E32: =C32+D32 | F32: =IF($C$70=0, 0, E32/$C$70) | G32: =F32*$T$5 | H32: 3 | I32: =$T$7*H32 | J32: =G32+$T$9+I32 | K32: =$T$11/64 | L32: 0 | M32: 0 | N32: 0 | O32: 0 | R32: =(J32+K32+L32+M32+N32+O32)*$B$2
... A69: T16 | B69: Madhusoodanan P.R. | C69: 0 | D69: =SUM($C$3:$C$5)/64 | E69: =C69+D69 | F69: =IF($C$70=0, 0, E69/$C$70) | G69: =F69*$T$5 | H69: 3 | I69: =$T$7*H69 | J69: =G69+$T$9+I69 | K69: =$T$11/64 | L69: 0 | M69: 0 | N69: 0 | O69: 0 | R69: =(J69+K69+L69+M69+N69+O69)*$B$2
B70: TOTAL | C70: =SUM(C3:C69) | D70: =SUM(D3:D69) | E70: =SUM(E3:E69) | F70: =IF($C$70=0, 0, E70/$C$70) | G70: =SUM(G3:G69) | H70: =SUM(H3:H69) | I70: =SUM(I3:I69) | J70: =SUM(J3:J69) | K70: =SUM(K3:K69) | L70: =SUM(L3:L69) | M70: =SUM(M3:M69) | N70: =SUM(N3:N69) | O70: =SUM(O3:O69) | R70: =SUM(R3:R69)

Sheet Jan2027-COLLECTION
A1: FLAT # | C1: Amount | D1: Date | E1: Amount | F1: Date | G1: Amount | H1: Date | I1: Amount | J1: Date | K1: Total
A2: F1 | B2: Shailesh Srivastava / Azeem Nawaz | K2: =SUM(C2,E2,G2,I2)
A3: F2 | B3: Shanthanu | K3: =SUM(C3,E3,G3,I3)
A4: F3 | B4: Samrat Kar | K4: =SUM(C4,E4,G4,I4)
A5: F4 | B5: Renu R | K5: =SUM(C5,E5,G5,I5)
A6: F5 | B6: Vamsidhar Bethanabatla / Madhuri Anumula | K6: =SUM(C6,E6,G6,I6)
A7: F6 | B7: Meghana Viral Shah and Vviral Shah (Owner) / Sangeet and Swagat (Tenent) | K7: =SUM(C7,E7,G7,I7)
A8: F7 | B8: Vimal NK | K8: =SUM(C8,E8,G8,I8)
A9: F8 | B9: Sujeet Kumar (Tenant)/Sreejith Menon (Owner) | K9: =SUM(C9,E9,G9,I9)
A10: F9 | B10: Vijay Suswaram (Owner) / Divya Shikha (Tenant) | K10: =SUM(C10,E10,G10,I10)
A11: F10 | B11: Aby Thomas | K11: =SUM(C11,E11,G11,I11)
A12: F11 | B12: Niwin Anto | K12: =SUM(C12,E12,G12,I12)
A13: F12 | B13: Anirudh Singh | K13: =SUM(C13,E13,G13,I13)
... A65: T16 | B65: Madhusoodanan P.R. | K65: =SUM(C65,E65,G65,I65)
A66: TOTAL | K66: =SUM(K2:K65)

Sheet Feb2027-COLLECTION
A1: FLAT # | C1: Amount | D1: Date | E1: Amount | F1: Date | G1: Amount | H1: Date | I1: Amount | J1: Date | K1: Total
A2: F1 | B2: Shailesh Srivastava / Azeem Nawaz | K2: =SUM(C2,E2,G2,I2)
A3: F2 | B3: Shanthanu | K3: =SUM(C3,E3,G3,I3)
A4: F3 | B4: Samrat Kar | K4: =SUM(C4,E4,G4,I4)
A5: F4 | B5: Renu R | K5: =SUM(C5,E5,G5,I5)
A6: F5 | B6: Vamsidhar Bethanabatla / Madhuri Anumula | K6: =SUM(C6,E6,G6,I6)
A7: F6 | B7: Meghana Viral Shah and Vviral Shah (Owner) / Sangeet and Swagat (Tenent) | K7: =SUM(C7,E7,G7,I7)
A8: F7 | B8: Vimal NK | K8: =SUM(C8,E8,G8,I8)
A9: F8 | B9: Sujeet Kumar (Tenant)/Sreejith Menon (Owner) | K9: =SUM(C9,E9,G9,I9)
A10: F9 | B10: Vijay Suswaram (Owner) / Divya Shikha (Tenant) | K10: =SUM(C10,E10,G10,I10)
A11: F10 | B11: Aby Thomas | K11: =SUM(C11,E11,G11,I11)
A12: F11 | B12: N. Geetha | K12: =SUM(C12,E12,G12,I12)
A13: F12 | B13: Anirudh Singh | K13: =SUM(C13,E13,G13,I13)
... A65: T16 | B65: Madhusoodanan P.R. | K65: =SUM(C65,E65,G65,I65)
A66: TOTAL | K66: =SUM(K2:K65)

Sheet Feb2027-EXPENSE
B1: FEBRUARY 2027 EXPENSES
A2: FLAT # | B2: 1 | C2: WATER USED IN LTRS | D2: COMMON AREA EQUALLY DEVIDED | E2: TOTAL FRESH WATER CONSUMED | F2: %OF TOTAL USED | G2: WATER EXPENSE SHARING BY % | H2: #METERS | I2: METER RENT | J2: COMMON AREA METER RENT + WATER EXPENSE+ FLAT METER RENT | K2: FIXED EXPENSE SHARE | L2: PARKING FEE | M2: CLUB BOOKING FEE | N2: SHIFTING FEE | O2: GYM USAGE FEE | R2: TOTAL EXPENSE TO BE PAID
A3: CH | B3: MPFOWA | C3: 0 | D3: 0 | H3: 1 | I3: =T7
A4: GYM | B4: MPFOWA | C4: 0 | D4: 0 | H4: 1 | I4: =T7 | S4: TOTAL FIXED EXPENSE | T4: ='ANNUAL-EXPENSE-DETAILS'!BF13
A5: BSMT | B5: MPFOWA | C5: 0 | D5: 0 | H5: 1 | I5: =T7 | S5: TOTAL WATER EXPENSE | T5: ='ANNUAL-EXPENSE-DETAILS'!BE13
A6: F1 | B6: Shailesh Srivastava / Azeem Nawaz | C6: 0 | D6: =SUM($C$3:$C$5)/64 | E6: =C6+D6 | F6: =IF($C$70=0, 0, E6/$C$70) | G6: =F6*$T$5 | H6: 3 | I6: =$T$7*H6 | J6: =G6+$T$9+I6 | K6: =$T$11/64 | L6: 0 | M6: 0 | N6: 0 | O6: 0 | R6: =(J6+K6+L6+M6+N6+O6)*$B$2
A7: F2 | B7: Shanthanu | C7: 0 | D7: =SUM($C$3:$C$5)/64 | E7: =C7+D7 | F7: =IF($C$70=0, 0, E7/$C$70) | G7: =F7*$T$5 | H7: 4 | I7: =$T$7*H7 | J7: =G7+$T$9+I7 | K7: =$T$11/64 | L7: 0 | M7: 0 | N7: 0 | O7: 0 | R7: =(J7+K7+L7+M7+N7+O7)*$B$2 | S7: RENT PER METER | T7: 117.81
A8: F3 | B8: Samrat Kar | C8: 0 | D8: =SUM($C$3:$C$5)/64 | E8: =C8+D8 | F8: =IF($C$70=0, 0, E8/$C$70) | G8: =F8*$T$5 | H8: 4 | I8: =$T$7*H8 | J8: =G8+$T$9+I8 | K8: =$T$11/64 | L8: 0 | M8: 0 | N8: 0 | O8: 0 | R8: =(J8+K8+L8+M8+N8+O8)*$B$2 | S8: COMMON AREA METER RENT | T8: =$T$7*3
A9: F4 | B9: Renu R | C9: 0 | D9: =SUM($C$3:$C$5)/64 | E9: =C9+D9 | F9: =IF($C$70=0, 0, E9/$C$70) | G9: =F9*$T$5 | H9: 4 | I9: =$T$7*H9 | J9: =G9+$T$9+I9 | K9: =$T$11/64 | L9: 0 | M9: 0 | N9: 0 | O9: 0 | R9: =(J9+K9+L9+M9+N9+O9)*$B$2 | S9: COMMON AREA METER RENT/FLAT | T9: =T8/64
A10: F5 | B10: Vamsidhar Bethanabatla / Madhuri Anumula | C10: 0 | D10: =SUM($C$3:$C$5)/64 | E10: =C10+D10 | F10: =IF($C$70=0, 0, E10/$C$70) | G10: =F10*$T$5 | H10: 3 | I10: =$T$7*H10 | J10: =G10+$T$9+I10 | K10: =$T$11/64 | L10: 0 | M10: 0 | N10: 0 | O10: 0 | R10: =(J10+K10+L10+M10+N10+O10)*$B$2
A11: F6 | B11: Meghana Viral Shah and Vviral Shah (Owner) / Sangeet and Swagat (Tenent) | C11: 0 | D11: =SUM($C$3:$C$5)/64 | E11: =C11+D11 | F11: =IF($C$70=0, 0, E11/$C$70) | G11: =F11*$T$5 | H11: 3 | I11: =$T$7*H11 | J11: =G11+$T$9+I11 | K11: =$T$11/64 | L11: 0 | M11: 0 | N11: 0 | O11: 0 | R11: =(J11+K11+L11+M11+N11+O11)*$B$2 | S11: TOTAL FIXED EXPENSE | T11: ='ANNUAL-EXPENSE-DETAILS'!BF13
A12: F7 | B12: Vimal NK | C12: 0 | D12: =SUM($C$3:$C$5)/64 | E12: =C12+D12 | F12: =IF($C$70=0, 0, E12/$C$70) | G12: =F12*$T$5 | H12: 3 | I12: =$T$7*H12 | J12: =G12+$T$9+I12 | K12: =$T$11/64 | L12: 0 | M12: 0 | N12: 0 | O12: 0 | R12: =(J12+K12+L12+M12+N12+O12)*$B$2
A13: F8 | B13: Sujeet Kumar (Tenant)/Sreejith Menon (Owner) | C13: 0 | D13: =SUM($C$3:$C$5)/64 | E13: =C13+D13 | F13: =IF($C$70=0, 0, E13/$C$70) | G13: =F13*$T$5 | H13: 3 | I13: =$T$7*H13 | J13: =G13+$T$9+I13 | K13: =$T$11/64 | L13: 0 | M13: 0 | N13: 0 | O13: 0 | R13: =(J13+K13+L13+M13+N13+O13)*$B$2 | S13: TOTAL WATER METER RENT | T13: =T8+I70
A14: F9 | B14: Vijay Suswaram (Owner) / Divya Shikha (Tenant) | C14: 0 | D14: =SUM($C$3:$C$5)/64 | E14: =C14+D14 | F14: =IF($C$70=0, 0, E14/$C$70) | G14: =F14*$T$5 | H14: 4 | I14: =$T$7*H14 | J14: =G14+$T$9+I14 | K14: =$T$11/64 | L14: 0 | M14: 0 | N14: 0 | O14: 0 | R14: =(J14+K14+L14+M14+N14+O14)*$B$2
A15: F10 | B15: Aby Thomas | C15: 0 | D15: =SUM($C$3:$C$5)/64 | E15: =C15+D15 | F15: =IF($C$70=0, 0, E15/$C$70) | G15: =F15*$T$5 | H15: 3 | I15: =$T$7*H15 | J15: =G15+$T$9+I15 | K15: =$T$11/64 | L15: 0 | M15: 0 | N15: 0 | O15: 0 | R15: =(J15+K15+L15+M15+N15+O15)*$B$2 | S15: BALANCE IN ACCOUNT ON 28-Feb-2023
A16: F11 | B16: Niwin Anto | C16: 0 | D16: =SUM($C$3:$C$5)/64 | E16: =C16+D16 | F16: =IF($C$70=0, 0, E16/$C$70) | G16: =F16*$T$5 | H16: 3 | I16: =$T$7*H16 | J16: =G16+$T$9+I16 | K16: =$T$11/64 | L16: 0 | M16: 0 | N16: 0 | O16: 0 | R16: =(J16+K16+L16+M16+N16+O16)*$B$2 | S16: TOTAL NON MAINTENANCE CORPUS COLLECTION
A17: F12 | B17: Anirudh Singh | C17: 0 | D17: =SUM($C$3:$C$5)/64 | E17: =C17+D17 | F17: =IF($C$70=0, 0, E17/$C$70) | G17: =F17*$T$5 | H17: 3 | I17: =$T$7*H17 | J17: =G17+$T$9+I17 | K17: =$T$11/64 | L17: 0 | M17: 0 | N17: 0 | O17: 0 | R17: =(J17+K17+L17+M17+N17+O17)*$B$2 | S17: TOTAL FD DONE
A18: F13 | B18: Sanchay Saxena | C18: 0 | D18: =SUM($C$3:$C$5)/64 | E18: =C18+D18 | F18: =IF($C$70=0, 0, E18/$C$70) | G18: =F18*$T$5 | H18: 4 | I18: =$T$7*H18 | J18: =G18+$T$9+I18 | K18: =$T$11/64 | L18: 0 | M18: 0 | N18: 0 | O18: 0 | R18: =(J18+K18+L18+M18+N18+O18)*$B$2 | S18: AMOUNT AVAILABLE FOR NON MAINTENANCE CORPUS IN CURRENT AC | T18: =T16-T17
A19: F14 | B19: Hemant Patel | C19: 0 | D19: =SUM($C$3:$C$5)/64 | E19: =C19+D19 | F19: =IF($C$70=0, 0, E19/$C$70) | G19: =F19*$T$5 | H19: 4 | I19: =$T$7*H19 | J19: =G19+$T$9+I19 | K19: =$T$11/64 | L19: 0 | M19: 0 | N19: 0 | O19: 0 | R19: =(J19+K19+L19+M19+N19+O19)*$B$2 | S19: AMOUNT AVAILABLE FOR MAINTENANCE | T19: =T15-T18
A20: F15 | B20: Senthil.Vijayaragavan | C20: 0 | D20: =SUM($C$3:$C$5)/64 | E20: =C20+D20 | F20: =IF($C$70=0, 0, E20/$C$70) | G20: =F20*$T$5 | H20: 4 | I20: =$T$7*H20 | J20: =G20+$T$9+I20 | K20: =$T$11/64 | L20: 0 | M20: 0 | N20: 0 | O20: 0 | R20: =(J20+K20+L20+M20+N20+O20)*$B$2 | S20: TOTAL EXPENSE FOR THE MONTH | T20: ='ANNUAL-EXPENSE-DETAILS'!BH13
A21: F16 | B21: Sreeja Sudharma | C21: 0 | D21: =SUM($C$3:$C$5)/64 | E21: =C21+D21 | F21: =IF($C$70=0, 0, E21/$C$70) | G21: =F21*$T$5 | H21: 3 | I21: =$T$7*H21 | J21: =G21+$T$9+I21 | K21: =$T$11/64 | L21: 0 | M21: 0 | N21: 0 | O21: 0 | R21: =(J21+K21+L21+M21+N21+O21)*$B$2 | S21: Maintenance deficit | T21: =T19-T20
A22: G1 | B22: Venkataramanan C | C22: 0 | D22: =SUM($C$3:$C$5)/64 | E22: =C22+D22 | F22: =IF($C$70=0, 0, E22/$C$70) | G22: =F22*$T$5 | H22: 3 | I22: =$T$7*H22 | J22: =G22+$T$9+I22 | K22: =$T$11/64 | L22: 0 | M22: 0 | N22: 0 | O22: 0 | R22: =(J22+K22+L22+M22+N22+O22)*$B$2
A23: G2 | B23: Kaushik Kasibhatla | C23: 0 | D23: =SUM($C$3:$C$5)/64 | E23: =C23+D23 | F23: =IF($C$70=0, 0, E23/$C$70) | G23: =F23*$T$5 | H23: 4 | I23: =$T$7*H23 | J23: =G23+$T$9+I23 | K23: =$T$11/64 | L23: 0 | M23: 0 | N23: 0 | O23: 0 | R23: =(J23+K23+L23+M23+N23+O23)*$B$2
A24: G3 | B24: Balakrishnan | C24: 0 | D24: =SUM($C$3:$C$5)/64 | E24: =C24+D24 | F24: =IF($C$70=0, 0, E24/$C$70) | G24: =F24*$T$5 | H24: 4 | I24: =$T$7*H24 | J24: =G24+$T$9+I24 | K24: =$T$11/64 | L24: 0 | M24: 0 | N24: 0 | O24: 0 | R24: =(J24+K24+L24+M24+N24+O24)*$B$2
A25: G4 | B25: Ashwin Pandith | C25: 0 | D25: =SUM($C$3:$C$5)/64 | E25: =C25+D25 | F25: =IF($C$70=0, 0, E25/$C$70) | G25: =F25*$T$5 | H25: 4 | I25: =$T$7*H25 | J25: =G25+$T$9+I25 | K25: =$T$11/64 | L25: 0 | M25: 0 | N25: 0 | O25: 0 | R25: =(J25+K25+L25+M25+N25+O25)*$B$2
A26: G5 | B26: Mayank Phophaliya | C26: 0 | D26: =SUM($C$3:$C$5)/64 | E26: =C26+D26 | F26: =IF($C$70=0, 0, E26/$C$70) | G26: =F26*$T$5 | H26: 3 | I26: =$T$7*H26 | J26: =G26+$T$9+I26 | K26: =$T$11/64 | L26: 0 | M26: 0 | N26: 0 | O26: 0 | R26: =(J26+K26+L26+M26+N26+O26)*$B$2
A27: G6 | B27: Mohit Daga | C27: 0 | D27: =SUM($C$3:$C$5)/64 | E27: =C27+D27 | F27: =IF($C$70=0, 0, E27/$C$70) | G27: =F27*$T$5 | H27: 3 | I27: =$T$7*H27 | J27: =G27+$T$9+I27 | K27: =$T$11/64 | L27: 0 | M27: 0 | N27: 0 | O27: 0 | R27: =(J27+K27+L27+M27+N27+O27)*$B$2
A28: G7 | B28: Prince Richfield | C28: 0 | D28: =SUM($C$3:$C$5)/64 | E28: =C28+D28 | F28: =IF($C$70=0, 0, E28/$C$70) | G28: =F28*$T$5 | H28: 3 | I28: =$T$7*H28 | J28: =G28+$T$9+I28 | K28: =$T$11/64 | L28: 0 | M28: 0 | N28: 0 | O28: 0 | R28: =(J28+K28+L28+M28+N28+O28)*$B$2
A29: G8 | B29: Ranjithkumar R / Sameer (tenant) / Princy (tenant) | C29: 0 | D29: =SUM($C$3:$C$5)/64 | E29: =C29+D29 | F29: =IF($C$70=0, 0, E29/$C$70) | G29: =F29*$T$5 | H29: 3 | I29: =$T$7*H29 | J29: =G29+$T$9+I29 | K29: =$T$11/64 | L29: 0 | M29: 0 | N29: 0 | O29: 0 | R29: =(J29+K29+L29+M29+N29+O29)*$B$2
A30: G9 | B30: Chandramouli | C30: 0 | D30: =SUM($C$3:$C$5)/64 | E30: =C30+D30 | F30: =IF($C$70=0, 0, E30/$C$70) | G30: =F30*$T$5 | H30: 5 | I30: =$T$7*H30 | J30: =G30+$T$9+I30 | K30: =$T$11/64 | L30: 0 | M30: 0 | N30: 0 | O30: 0 | R30: =(J30+K30+L30+M30+N30+O30)*$B$2
A31: G10 | B31: Cijo Jacob / Thara Joy | C31: 0 | D31: =SUM($C$3:$C$5)/64 | E31: =C31+D31 | F31: =IF($C$70=0, 0, E31/$C$70) | G31: =F31*$T$5 | H31: 3 | I31: =$T$7*H31 | J31: =G31+$T$9+I31 | K31: =$T$11/64 | L31: 0 | M31: 0 | N31: 0 | O31: 0 | R31: =(J31+K31+L31+M31+N31+O31)*$B$2
A32: G11 | B32: Ketan Verlekar | C32: 0 | D32: =SUM($C$3:$C$5)/64 | E32: =C32+D32 | F32: =IF($C$70=0, 0, E32/$C$70) | G32: =F32*$T$5 | H32: 3 | I32: =$T$7*H32 | J32: =G32+$T$9+I32 | K32: =$T$11/64 | L32: 0 | M32: 0 | N32: 0 | O32: 0 | R32: =(J32+K32+L32+M32+N32+O32)*$B$2
A33: G12 | B33: Shyam Nair | C33: 0 | D33: =SUM($C$3:$C$5)/64 | E33: =C33+D33 | F33: =IF($C$70=0, 0, E33/$C$70) | G33: =F33*$T$5 | H33: 3 | I33: =$T$7*H33 | J33: =G33+$T$9+I33 | K33: =$T$11/64 | L33: 0 | M33: 0 | N33: 0 | O33: 0 | R33: =(J33+K33+L33+M33+N33+O33)*$B$2
... A69: T16 | B69: Madhusoodanan P.R. | C69: 0 | D69: =SUM($C$3:$C$5)/64 | E69: =C69+D69 | F69: =IF($C$70=0, 0, E69/$C$70) | G69: =F69*$T$5 | H69: 3 | I69: =$T$7*H69 | J69: =G69+$T$9+I69 | K69: =$T$11/64 | L69: 0 | M69: 0 | N69: 0 | O69: 0 | R69: =(J69+K69+L69+M69+N69+O69)*$B$2
B70: TOTAL | C70: =SUM(C3:C69) | D70: =SUM(D3:D69) | E70: =SUM(E3:E69) | F70: =IF($C$70=0, 0, E70/$C$70) | G70: =SUM(G3:G69) | H70: =SUM(H3:H69) | I70: =SUM(I3:I69) | J70: =SUM(J3:J69) | K70: =SUM(K3:K69) | L70: =SUM(L3:L69) | M70: =SUM(M3:M69) | N70: =SUM(N3:N69) | O70: =SUM(O3:O69) | R70: =SUM(R3:R69)

Sheet Mar2027-EXPENSE
B1: MARCH 2027 EXPENSES
A2: FLAT # | B2: 1 | C2: WATER USED IN LTRS | D2: COMMON AREA EQUALLY DEVIDED | E2: TOTAL FRESH WATER CONSUMED | F2: %OF TOTAL USED | G2: WATER EXPENSE SHARING BY % | H2: #METERS | I2: METER RENT | J2: COMMON AREA METER RENT + WATER EXPENSE+ FLAT METER RENT | K2: FIXED EXPENSE SHARE | L2: PARKING FEE | M2: CLUB BOOKING FEE | N2: SHIFTING FEE | O2: GYM USAGE FEE | P2: OWNERSHIP TRANSFER FEE | R2: TOTAL EXPENSE TO BE PAID
A3: CH | B3: MPFOWA | C3: 0 | D3: 0 | H3: 1 | I3: =T7
A4: GYM | B4: MPFOWA | C4: 0 | D4: 0 | H4: 1 | I4: =T7 | S4: TOTAL FIXED EXPENSE | T4: ='ANNUAL-EXPENSE-DETAILS'!BF14
A5: BSMT | B5: MPFOWA | C5: 0 | D5: 0 | H5: 1 | I5: =T7 | S5: TOTAL WATER EXPENSE | T5: ='ANNUAL-EXPENSE-DETAILS'!BE14
A6: F1 | B6: Shailesh Srivastava / Azeem Nawaz | C6: 0 | D6: =SUM($C$3:$C$5)/64 | E6: =C6+D6 | F6: =IF($C$70=0, 0, E6/$C$70) | G6: =F6*$T$5 | H6: 3 | I6: =$T$7*H6 | J6: =G6+$T$9+I6 | K6: =$T$11/64 | L6: 0 | M6: 0 | N6: 0 | O6: 0 | R6: =(J6+K6+L6+M6+N6+O6+P6)*$B$2
A7: F2 | B7: Shanthanu | C7: 0 | D7: =SUM($C$3:$C$5)/64 | E7: =C7+D7 | F7: =IF($C$70=0, 0, E7/$C$70) | G7: =F7*$T$5 | H7: 4 | I7: =$T$7*H7 | J7: =G7+$T$9+I7 | K7: =$T$11/64 | L7: 0 | M7: 0 | N7: 0 | O7: 0 | R7: =(J7+K7+L7+M7+N7+O7+P7)*$B$2 | S7: RENT PER METER | T7: 117.81
A8: F3 | B8: Samrat Kar | C8: 0 | D8: =SUM($C$3:$C$5)/64 | E8: =C8+D8 | F8: =IF($C$70=0, 0, E8/$C$70) | G8: =F8*$T$5 | H8: 4 | I8: =$T$7*H8 | J8: =G8+$T$9+I8 | K8: =$T$11/64 | L8: 0 | M8: 0 | N8: 0 | O8: 0 | R8: =(J8+K8+L8+M8+N8+O8+P8)*$B$2 | S8: COMMON AREA METER RENT | T8: =$T$7*3
A9: F4 | B9: Renu R | C9: 0 | D9: =SUM($C$3:$C$5)/64 | E9: =C9+D9 | F9: =IF($C$70=0, 0, E9/$C$70) | G9: =F9*$T$5 | H9: 4 | I9: =$T$7*H9 | J9: =G9+$T$9+I9 | K9: =$T$11/64 | L9: 0 | M9: 0 | N9: 0 | O9: 0 | R9: =(J9+K9+L9+M9+N9+O9+P9)*$B$2 | S9: COMMON AREA METER RENT/FLAT | T9: =T8/64
A10: F5 | B10: Vamsidhar Bethanabatla / Madhuri Anumula | C10: 0 | D10: =SUM($C$3:$C$5)/64 | E10: =C10+D10 | F10: =IF($C$70=0, 0, E10/$C$70) | G10: =F10*$T$5 | H10: 3 | I10: =$T$7*H10 | J10: =G10+$T$9+I10 | K10: =$T$11/64 | L10: 0 | M10: 0 | N10: 0 | O10: 0 | P10: 0 | R10: =(J10+K10+L10+M10+N10+O10+P10)*$B$2
A11: F6 | B11: Meghana Viral Shah and Vviral Shah (Owner) / Sangeet and Swagat (Tenent) | C11: 0 | D11: =SUM($C$3:$C$5)/64 | E11: =C11+D11 | F11: =IF($C$70=0, 0, E11/$C$70) | G11: =F11*$T$5 | H11: 3 | I11: =$T$7*H11 | J11: =G11+$T$9+I11 | K11: =$T$11/64 | L11: 0 | M11: 0 | N11: 0 | O11: 0 | R11: =(J11+K11+L11+M11+N11+O11+P11)*$B$2 | S11: TOTAL FIXED EXPENSE | T11: ='ANNUAL-EXPENSE-DETAILS'!BF14
A12: F7 | B12: Vimal NK | C12: 0 | D12: =SUM($C$3:$C$5)/64 | E12: =C12+D12 | F12: =IF($C$70=0, 0, E12/$C$70) | G12: =F12*$T$5 | H12: 3 | I12: =$T$7*H12 | J12: =G12+$T$9+I12 | K12: =$T$11/64 | L12: 0 | M12: 0 | N12: 0 | O12: 0 | R12: =(J12+K12+L12+M12+N12+O12+P12)*$B$2
A13: F8 | B13: Sujeet Kumar (Tenant)/Sreejith Menon (Owner) | C13: 0 | D13: =SUM($C$3:$C$5)/64 | E13: =C13+D13 | F13: =IF($C$70=0, 0, E13/$C$70) | G13: =F13*$T$5 | H13: 3 | I13: =$T$7*H13 | J13: =G13+$T$9+I13 | K13: =$T$11/64 | L13: 0 | M13: 0 | N13: 0 | O13: 0 | R13: =(J13+K13+L13+M13+N13+O13+P13)*$B$2 | S13: TOTAL WATER METER RENT | T13: =T8+I70
A14: F9 | B14: Vijay Suswaram (Owner) / Divya Shikha (Tenant) | C14: 0 | D14: =SUM($C$3:$C$5)/64 | E14: =C14+D14 | F14: =IF($C$70=0, 0, E14/$C$70) | G14: =F14*$T$5 | H14: 4 | I14: =$T$7*H14 | J14: =G14+$T$9+I14 | K14: =$T$11/64 | L14: 0 | M14: 0 | N14: 0 | O14: 0 | R14: =(J14+K14+L14+M14+N14+O14+P14)*$B$2
A15: F10 | B15: Aby Thomas | C15: 0 | D15: =SUM($C$3:$C$5)/64 | E15: =C15+D15 | F15: =IF($C$70=0, 0, E15/$C$70) | G15: =F15*$T$5 | H15: 3 | I15: =$T$7*H15 | J15: =G15+$T$9+I15 | K15: =$T$11/64 | L15: 0 | M15: 0 | N15: 0 | O15: 0 | R15: =(J15+K15+L15+M15+N15+O15+P15)*$B$2
A16: F11 | B16: Niwin Anto | C16: 0 | D16: =SUM($C$3:$C$5)/64 | E16: =C16+D16 | F16: =IF($C$70=0, 0, E16/$C$70) | G16: =F16*$T$5 | H16: 3 | I16: =$T$7*H16 | J16: =G16+$T$9+I16 | K16: =$T$11/64 | L16: 0 | M16: 0 | N16: 0 | O16: 0 | R16: =(J16+K16+L16+M16+N16+O16+P16)*$B$2
A17: F12 | B17: Anirudh Singh | C17: 0 | D17: =SUM($C$3:$C$5)/64 | E17: =C17+D17 | F17: =IF($C$70=0, 0, E17/$C$70) | G17: =F17*$T$5 | H17: 3 | I17: =$T$7*H17 | J17: =G17+$T$9+I17 | K17: =$T$11/64 | L17: 0 | M17: 0 | N17: 0 | O17: 0 | P17: 0 | R17: =(J17+K17+L17+M17+N17+O17+P17)*$B$2
A18: F13 | B18: Sanchay Saxena | C18: 0 | D18: =SUM($C$3:$C$5)/64 | E18: =C18+D18 | F18: =IF($C$70=0, 0, E18/$C$70) | G18: =F18*$T$5 | H18: 4 | I18: =$T$7*H18 | J18: =G18+$T$9+I18 | K18: =$T$11/64 | L18: 0 | M18: 0 | N18: 0 | O18: 0 | R18: =(J18+K18+L18+M18+N18+O18+P18)*$B$2
A19: F14 | B19: Hemant Patel | C19: 0 | D19: =SUM($C$3:$C$5)/64 | E19: =C19+D19 | F19: =IF($C$70=0, 0, E19/$C$70) | G19: =F19*$T$5 | H19: 4 | I19: =$T$7*H19 | J19: =G19+$T$9+I19 | K19: =$T$11/64 | L19: 0 | M19: 0 | N19: 0 | O19: 0 | R19: =(J19+K19+L19+M19+N19+O19+P19)*$B$2
A20: F15 | B20: Senthil.Vijayaragavan | C20: 0 | D20: =SUM($C$3:$C$5)/64 | E20: =C20+D20 | F20: =IF($C$70=0, 0, E20/$C$70) | G20: =F20*$T$5 | H20: 4 | I20: =$T$7*H20 | J20: =G20+$T$9+I20 | K20: =$T$11/64 | L20: 0 | M20: 0 | N20: 0 | O20: 0 | R20: =(J20+K20+L20+M20+N20+O20+P20)*$B$2
A21: F16 | B21: Sreeja Sudharma | C21: 0 | D21: =SUM($C$3:$C$5)/64 | E21: =C21+D21 | F21: =IF($C$70=0, 0, E21/$C$70) | G21: =F21*$T$5 | H21: 3 | I21: =$T$7*H21 | J21: =G21+$T$9+I21 | K21: =$T$11/64 | L21: 0 | M21: 0 | N21: 0 | O21: 0 | R21: =(J21+K21+L21+M21+N21+O21+P21)*$B$2
A22: G1 | B22: Venkataramanan C | C22: 0 | D22: =SUM($C$3:$C$5)/64 | E22: =C22+D22 | F22: =IF($C$70=0, 0, E22/$C$70) | G22: =F22*$T$5 | H22: 3 | I22: =$T$7*H22 | J22: =G22+$T$9+I22 | K22: =$T$11/64 | L22: 0 | M22: 0 | N22: 0 | O22: 0 | P22: 0 | R22: =(J22+K22+L22+M22+N22+O22+P22)*$B$2
A23: G2 | B23: Kaushik Kasibhatla | C23: 0 | D23: =SUM($C$3:$C$5)/64 | E23: =C23+D23 | F23: =IF($C$70=0, 0, E23/$C$70) | G23: =F23*$T$5 | H23: 4 | I23: =$T$7*H23 | J23: =G23+$T$9+I23 | K23: =$T$11/64 | L23: 0 | M23: 0 | N23: 0 | O23: 0 | R23: =(J23+K23+L23+M23+N23+O23+P23)*$B$2
A24: G3 | B24: Balakrishnan | C24: 0 | D24: =SUM($C$3:$C$5)/64 | E24: =C24+D24 | F24: =IF($C$70=0, 0, E24/$C$70) | G24: =F24*$T$5 | H24: 4 | I24: =$T$7*H24 | J24: =G24+$T$9+I24 | K24: =$T$11/64 | L24: 0 | M24: 0 | N24: 0 | O24: 0 | R24: =(J24+K24+L24+M24+N24+O24+P24)*$B$2
A25: G4 | B25: Ashwin Pandith | C25: 0 | D25: =SUM($C$3:$C$5)/64 | E25: =C25+D25 | F25: =IF($C$70=0, 0, E25/$C$70) | G25: =F25*$T$5 | H25: 4 | I25: =$T$7*H25 | J25: =G25+$T$9+I25 | K25: =$T$11/64 | L25: 0 | M25: 0 | N25: 0 | O25: 0 | R25: =(J25+K25+L25+M25+N25+O25+P25)*$B$2
A26: G5 | B26: Mayank Phophaliya | C26: 0 | D26: =SUM($C$3:$C$5)/64 | E26: =C26+D26 | F26: =IF($C$70=0, 0, E26/$C$70) | G26: =F26*$T$5 | H26: 3 | I26: =$T$7*H26 | J26: =G26+$T$9+I26 | K26: =$T$11/64 | L26: 0 | M26: 0 | N26: 0 | O26: 0 | R26: =(J26+K26+L26+M26+N26+O26+P26)*$B$2
A27: G6 | B27: Mohit Daga | C27: 0 | D27: =SUM($C$3:$C$5)/64 | E27: =C27+D27 | F27: =IF($C$70=0, 0, E27/$C$70) | G27: =F27*$T$5 | H27: 3 | I27: =$T$7*H27 | J27: =G27+$T$9+I27 | K27: =$T$11/64 | L27: 0 | M27: 0 | N27: 0 | O27: 0 | R27: =(J27+K27+L27+M27+N27+O27+P27)*$B$2
A28: G7 | B28: Prince Richfield | C28: 0 | D28: =SUM($C$3:$C$5)/64 | E28: =C28+D28 | F28: =IF($C$70=0, 0, E28/$C$70) | G28: =F28*$T$5 | H28: 3 | I28: =$T$7*H28 | J28: =G28+$T$9+I28 | K28: =$T$11/64 | L28: 0 | M28: 0 | N28: 0 | O28: 0 | R28: =(J28+K28+L28+M28+N28+O28+P28)*$B$2
A29: G8 | B29: Ranjithkumar R / Sameer (tenant) / Princy (tenant) | C29: 0 | D29: =SUM($C$3:$C$5)/64 | E29: =C29+D29 | F29: =IF($C$70=0, 0, E29/$C$70) | G29: =F29*$T$5 | H29: 3 | I29: =$T$7*H29 | J29: =G29+$T$9+I29 | K29: =$T$11/64 | L29: 0 | M29: 0 | N29: 0 | O29: 0 | R29: =(J29+K29+L29+M29+N29+O29+P29)*$B$2
A30: G9 | B30: Chandramouli | C30: 0 | D30: =SUM($C$3:$C$5)/64 | E30: =C30+D30 | F30: =IF($C$70=0, 0, E30/$C$70) | G30: =F30*$T$5 | H30: 5 | I30: =$T$7*H30 | J30: =G30+$T$9+I30 | K30: =$T$11/64 | L30: 0 | M30: 0 | N30: 0 | O30: 0 | R30: =(J30+K30+L30+M30+N30+O30+P30)*$B$2
A31: G10 | B31: Cijo Jacob / Thara Joy | C31: 0 | D31: =SUM($C$3:$C$5)/64 | E31: =C31+D31 | F31: =IF($C$70=0, 0, E31/$C$70) | G31: =F31*$T$5 | H31: 3 | I31: =$T$7*H31 | J31: =G31+$T$9+I31 | K31: =$T$11/64 | L31: 0 | M31: 0 | N31: 0 | O31: 0 | R31: =(J31+K31+L31+M31+N31+O31+P31)*$B$2
A32: G11 | B32: Ketan Verlekar | C32: 0 | D32: =SUM($C$3:$C$5)/64 | E32: =C32+D32 | F32: =IF($C$70=0, 0, E32/$C$70) | G32: =F32*$T$5 | H32: 3 | I32: =$T$7*H32 | J32: =G32+$T$9+I32 | K32: =$T$11/64 | L32: 0 | M32: 0 | N32: 0 | O32: 0 | R32: =(J32+K32+L32+M32+N32+O32+P32)*$B$2
A33: G12 | B33: Shyam Nair | C33: 0 | D33: =SUM($C$3:$C$5)/64 | E33: =C33+D33 | F33: =IF($C$70=0, 0, E33/$C$70) | G33: =F33*$T$5 | H33: 3 | I33: =$T$7*H33 | J33: =G33+$T$9+I33 | K33: =$T$11/64 | L33: 0 | M33: 0 | N33: 0 | O33: 0 | R33: =(J33+K33+L33+M33+N33+O33+P33)*$B$2
A34: G13 | B34: Ajai.B | C34: 0 | D34: =SUM($C$3:$C$5)/64 | E34: =C34+D34 | F34: =IF($C$70=0, 0, E34/$C$70) | G34: =F34*$T$5 | H34: 4 | I34: =$T$7*H34 | J34: =G34+$T$9+I34 | K34: =$T$11/64 | L34: 0 | M34: 0 | N34: 0 | O34: 0 | R34: =(J34+K34+L34+M34+N34+O34+P34)*$B$2
... A69: T16 | B69: Madhusoodanan P.R. | C69: 0 | D69: =SUM($C$3:$C$5)/64 | E69: =C69+D69 | F69: =IF($C$70=0, 0, E69/$C$70) | G69: =F69*$T$5 | H69: 3 | I69: =$T$7*H69 | J69: =G69+$T$9+I69 | K69: =$T$11/64 | L69: 0 | M69: 0 | N69: 0 | O69: 0 | R69: =(J69+K69+L69+M69+N69+O69+P69)*$B$2
B70: TOTAL | C70: =SUM(C3:C69) | D70: =SUM(D3:D69) | E70: =SUM(E3:E69) | F70: =IF($C$70=0, 0, E70/$C$70) | G70: =SUM(G3:G69) | H70: =SUM(H3:H69) | I70: =SUM(I3:I69) | J70: =SUM(J3:J69) | K70: =SUM(K3:K69) | L70: =SUM(L3:L69) | M70: =SUM(M3:M69) | N70: =SUM(N3:N69) | O70: =SUM(O3:O69) | R70: =SUM(R3:R69)

Sheet Mar2027-COLLECTION
A1: FLAT # | C1: Amount | D1: Date | E1: Amount | F1: Date | G1: Amount | H1: Date | I1: Amount | J1: Date | K1: Total
A2: F1 | B2: Shailesh Srivastava / Azeem Nawaz | K2: =SUM(C2,E2,G2,I2)
A3: F2 | B3: Shanthanu | K3: =SUM(C3,E3,G3,I3)
A4: F3 | B4: Samrat Kar | K4: =SUM(C4,E4,G4,I4)
A5: F4 | B5: Renu R | K5: =SUM(C5,E5,G5,I5)
A6: F5 | B6: Vamsidhar Bethanabatla / Madhuri Anumula | K6: =SUM(C6,E6,G6,I6)
A7: F6 | B7: Meghana Viral Shah and Vviral Shah (Owner) / Sangeet and Swagat (Tenent) | K7: =SUM(C7,E7,G7,I7)
A8: F7 | B8: Vimal NK | K8: =SUM(C8,E8,G8,I8)
A9: F8 | B9: Sujeet Kumar (Tenant)/Sreejith Menon (Owner) | K9: =SUM(C9,E9,G9,I9)
A10: F9 | B10: Vijay Suswaram (Owner) / Divya Shikha (Tenant) | K10: =SUM(C10,E10,G10,I10)
A11: F10 | B11: Aby Thomas | K11: =SUM(C11,E11,G11,I11)
A12: F11 | B12: N. Geetha | K12: =SUM(C12,E12,G12,I12)
A13: F12 | B13: Anirudh Singh | K13: =SUM(C13,E13,G13,I13)
... A65: T16 | B65: Madhusoodanan P.R. | K65: =SUM(C65,E65,G65,I65)
A66: TOTAL | K66: =SUM(K2:K65)

Sheet ANNUAL-EXPENSE-DETAILS
A1: MONTHS | B1: VARIABLE EXPENSE | D1: FIXED EXPENSE | BD1: GROSS EXPENSE | BE1: GROSS VARIABLE EXPENSE | BF1: GROSS FIXED EXPENSE | BG1: WATER METER RENT | BH1: TOTAL EXPENSE
B2: DRINKING WATER SLN WATER SUP | C2: STP SLUDGE CLEANING BALAJI | D2: STP MAINTENANCE | E2: STP MATERIALS | F2: STP REPAIR | G2: COMMON ELECTRICITY BILL | H2: BECOM Service tax | I2: SECURITY SERVICES | J2: GARBAGE REMOVAL | K2: PETTY CASH | L2: ELEVATOR MAINTENANCE | M2: MOTOR REPAIR | N2: PLUMBING MATERIAL | O2: ELECTRICITY MATERIAL | P2: ELECTRICITY MATERIAL | Q2: TRANSFORMER REPAIR | R2: GENERATOR MAINTENANCE EPITOME | S2: GARDENING | T2: PLUMBER WAGE | U2: ELECTRICIAN WAGE | V2: MANAGER WAGE | W2: TANK AND SUMP CLEANING | X2: SECURITY WATER EXPENSES GREENMART | Y2: SWIMMING POOL MOTOR REPAIR | Z2: CCTV REPAIR | AA2: CCTV monitor | AB2: WATER PIPE | AC2: RAILING FOR STAIRCASE | AD2: Play area sand | AE2: BARBED WIRE REPAIR | AF2: DRIED LEAVES REMOVAL | AG2: DRAIN CLEANING | AH2: Security room & Play area painting | AI2: Play area sand removal & cracks filling | AJ2: Front garden cleaning and red soil filling | AK2: Landscaping work for STP water disposal | AL2: ACCOUNTING | AM2: Lift Painting | AN2: Lift wiring sepration | AO2: Earthing repair | AP2: Pest Control | AQ2: Freshwater pipe repair | AR2: NBH device replacement | AS2: NBH VMS | AT2: REPAIRS | AU2: Cricket Net | AV2: LOOK AHEAD EXPENSE | AW2: Rear bondary cleaning | AX2: 9,7,8,11 series terrace pipe repairs | AY2: Speed Breaker near the gate | AZ2: Gym Equipment Repairs | BA2: Additional Waste Disposal | BB2: Swimming Pool Cleaning | BC2: HOUSE KEEPING MATERIALS
A3: APRIL 2026 | B3: 0 | C3: 0 | D3: 0 | E3: 0 | G3: 0 | I3: 0 | J3: 0 | K3: 0 | M3: 0 | N3: 0 | O3: =3290+4300 | S3: 0 | T3: 0 | U3: 0 | V3: 0 | AL3: 0 | AP3: 0 | AS3: 0 | BD3: =SUM(B3:BC3) | BE3: =SUM(B3:C3) | BF3: =BD3-BE3 | BG3: 0 | BH3: =BD3+BG3
A4: MAY 2026 | B4: 0 | C4: 0 | D4: 0 | E4: 0 | G4: 0 | I4: 0 | J4: 0 | K4: 0 | N4: 0 | S4: 0 | T4: 0 | U4: 0 | V4: 0 | AL4: 0 | AP4: 0 | BD4: =SUM(B4:BC4) | BE4: =SUM(B4:C4) | BF4: =BD4-BE4 | BG4: 0 | BH4: =BD4+BG4
A5: JUN 2026 | B5: 0 | C5: 0 | D5: 0 | E5: 0 | G5: 0 | I5: 0 | J5: 0 | K5: 0 | S5: 0 | T5: 0 | U5: 0 | V5: 0 | AF5: 0 | AL5: 0 | AP5: 0 | BC5: 0 | BD5: =SUM(B5:BC5) | BE5: =SUM(B5:C5) | BF5: =BD5-BE5 | BG5: 0 | BH5: =BD5+BG5
A6: JUL 2026 | B6: 0 | C6: 0 | D6: 0 | E6: 0 | G6: 0 | I6: 0 | J6: 0 | K6: 0 | L6: 0 | S6: 0 | T6: 0 | U6: 0 | V6: 0 | AF6: 0 | AL6: 0 | AP6: 0 | AY6: 0 | BD6: =SUM(B6:BC6) | BE6: =SUM(B6:C6) | BF6: =BD6-BE6 | BG6: 0 | BH6: =BD6+BG6
A7: AUG 2026 | B7: 0 | C7: 0 | D7: 0 | E7: 0 | G7: 0 | I7: 0 | J7: 0 | K7: 0 | O7: =25000 | P7: 0 | S7: 0 | T7: 0 | U7: 0 | V7: 0 | AF7: 0 | AL7: 0 | AP7: 0 | AR7: 0 | AZ7: 0 | BD7: =SUM(B7:BC7) | BE7: =SUM(B7:C7) | BF7: =BD7-BE7 | BG7: 0 | BH7: =BD7+BG7
A8: SEP 2026 | B8: 0 | C8: 0 | D8: 0 | E8: 0 | G8: 0 | I8: 0 | J8: 0 | K8: 0 | O8: 0 | P8: 0 | S8: 0 | T8: 0 | U8: 0 | V8: 0 | AF8: 0 | AS8: 0 | BD8: =SUM(B8:BC8) | BE8: =SUM(B8:C8) | BF8: =BD8-BE8 | BG8: 0 | BH8: =BD8+BG8
A9: OCT 2026 | B9: 0 | C9: 0 | D9: 0 | E9: 0 | G9: 0 | I9: 0 | J9: 0 | K9: 0 | L9: 0 | M9: 0 | S9: 0 | T9: 0 | U9: 0 | V9: 0 | AF9: 0 | AL9: 0 | AT9: 0 | BC9: =4309+1367+3127 | BD9: =SUM(B9:BC9) | BE9: =SUM(B9:C9) | BF9: =BD9-BE9 | BG9: 0 | BH9: =BD9+BG9
A10: NOV 2026 | B10: 0 | C10: 0 | D10: 0 | E10: 0 | G10: 0 | I10: 0 | J10: 0 | K10: 0 | L10: 0 | R10: 0 | S10: 0 | T10: 0 | U10: 0 | V10: 0 | W10: 0 | AF10: 0 | BA10: 0 | BB10: 0 | BD10: =SUM(B10:BC10) | BE10: =SUM(B10:C10) | BF10: =BD10-BE10 | BG10: 0 | BH10: =BD10+BG10
A11: DEC 2026 | B11: 0 | C11: 0 | D11: 0 | E11: 0 | G11: 0 | I11: 0 | J11: 0 | K11: 0 | R11: 0 | S11: 0 | T11: 0 | U11: 0 | V11: 0 | AF11: 0 | AL11: 0 | BD11: =SUM(B11:BC11) | BE11: =SUM(B11:C11) | BF11: =BD11-BE11 | BG11: 0 | BH11: =BD11+BG11
A12: JAN 2027 | B12: 0 | C12: 0 | D12: 0 | E12: 0 | G12: 0 | I12: 0 | J12: 0 | K12: 0 | S12: 0 | T12: 0 | U12: 0 | V12: 0 | AF12: =3300+8500 | AL12: 0 | BC12: =3198+3127 | BD12: =SUM(B12:BC12) | BE12: =SUM(B12:C12) | BF12: =BD12-BE12 | BG12: 0 | BH12: =BD12+BG12
A13: FEB 2027 | B13: 0 | C13: 0 | D13: 0 | E13: 0 | G13: 0 | I13: 0 | J13: 0 | K13: 0 | S13: 0 | T13: 0 | U13: 0 | V13: 0 | AF13: 0 | AL13: 0 | BD13: =SUM(B13:BC13) | BE13: =SUM(B13:C13) | BF13: =BD13-BE13 | BG13: 0 | BH13: =BD13+BG13
A14: MAR 2027 | B14: 0 | C14: 0 | D14: 0 | E14: 0 | G14: 0 | I14: 0 | J14: 0 | K14: 0 | S14: 0 | T14: 0 | U14: 0 | V14: 0 | AF14: 0 | AL14: 0 | BC14: =4575+3198 | BD14: =SUM(B14:BC14) | BE14: =SUM(B14:C14) | BF14: =BD14-BE14 | BG14: 0 | BH14: =BD14+BG14
A15: TOTAL | B15: =SUM(B3:B14) | C15: =SUM(C3:C14) | D15: =SUM(D3:D14) | E15: =SUM(E3:E14) | G15: =SUM(G3:G14) | I15: =SUM(I3:I14) | J15: =SUM(J3:J14) | K15: =SUM(K3:K14) | L15: =SUM(L3:L14) | N15: =SUM(N3:N14) | O15: =SUM(O3:O14) | Q15: =SUM(Q3:Q14) | R15: =SUM(R3:R14) | S15: =SUM(S3:S14) | T15: =SUM(T3:T14) | U15: =SUM(U3:U14) | V15: =SUM(V3:V14) | W15: =SUM(W3:W14) | X15: =SUM(X3:X14) | ... Z15: =SUM(Z3:Z14) | AD15: =SUM(AD3:AD14) | AF15: =SUM(AF3:AF14) | BC15: =SUM(BC3:BC14) | BD15: =SUM(B15:BC15) | BE15: =SUM(BE3:BE14) | BF15: =SUM(BF3:BF14) | BG15: =SUM(BG3:BG14) | BH15: =SUM(BH3:BH14)

Sheet INCOME-EXPENSE-CYCLES
D1: Balance from last FY year | E1: 46113 | I1: 46143 | M1: 46174 | Q1: 46204 | U1: 46235 | Y1: 46266 | AC1: 46296 | AG1: 46327 | AK1: 46357 | AO1: 46388 | AS1: 46419 | AW1: 46447 | BA1: TOTAL COLLECTION (Apr2026 to Mar2027) | BB1: TOTAL EXPENSE (Apr2026 to Mar2027) | BC1: TOTAL LATE FEE (Apr2026 to Mar2027) | BD1: TOTAL COLLECTION - EXPENSE (Apr2026 to Mar2027) | BE1: Total Dues (Since FY 26-27)
A2: FLAT# | B2: email id | C2: OCCUPANT | E2: COLLECTION | F2: EXPENSE | G2: LATE PAYMENT FEE | H2: COLLECTION - EXPENSE | I2: COLLECTION | J2: EXPENSE | K2: LATE PAYMENT FEE | L2: COLLECTION - EXPENSE | M2: COLLECTION | N2: EXPENSE | O2: LATE PAYMENT FEE | P2: COLLECTION - EXPENSE | Q2: COLLECTION | R2: EXPENSE | S2: LATE PAYMENT FEE | T2: COLLECTION - EXPENSE | U2: COLLECTION | V2: EXPENSE | W2: LATE PAYMENT FEE | X2: COLLECTION - EXPENSE | Y2: COLLECTION | Z2: EXPENSE | AA2: LATE PAYMENT FEE | AB2: COLLECTION - EXPENSE | AC2: COLLECTION | AD2: EXPENSE | AE2: LATE PAYMENT FEE | AF2: COLLECTION - EXPENSE | AG2: COLLECTION | AH2: EXPENSE | AI2: LATE PAYMENT FEE | AJ2: COLLECTION - EXPENSE | AK2: COLLECTION | AL2: EXPENSE | AM2: LATE PAYMENT FEE | AN2: COLLECTION - EXPENSE | AO2: COLLECTION | AP2: EXPENSE | AQ2: LATE PAYMENT FEE | AR2: COLLECTION - EXPENSE | AS2: COLLECTION | AT2: EXPENSE | AU2: LATE PAYMENT FEE | AV2: COLLECTION - EXPENSE | AW2: COLLECTION | AX2: EXPENSE | AY2: LATE PAYMENT FEE | AZ2: COLLECTION - EXPENSE
A3: F1 | C3: Shailesh Srivastava / Azeem Nawaz | D3: 0 | H3: =E3-(F3+G3) | L3: =I3-(J3+K3) | P3: =M3-(N3+O3) | T3: =Q3-(R3+S3) | X3: =U3-(V3+W3) | AB3: =Y3-(Z3+AA3) | AF3: =AC3-(AD3+AE3) | AJ3: =AG3-(AH3+AI3) | AN3: =AK3-(AL3+AM3) | AR3: =AO3-(AP3+AQ3) | AV3: =AS3-(AT3+AU3) | AZ3: =AW3-(AX3+AY3) | BA3: =SUM(E3,I3,M3,Q3,U3,Y3,AC3,AG3,AK3,AO3,AS3,AW3) | BB3: =SUM(F3,J3,N3,R3,V3,Z3,AD3,AH3,AL3,AP3,AT3,AX3) | BC3: =SUM(G3,K3,O3,S3,W3,AA3,AE3,AI3,AM3,AQ3,AU3,AY3) | BD3: =BA3-(BB3+BC3) | BE3: =BD3+D3
A4: F2 | B4: ramazen1@gmail.com | C4: Ramamurthy Pachaiyappan | D4: 0 | H4: =E4-(F4+G4) | L4: =I4-(J4+K4) | P4: =M4-(N4+O4) | T4: =Q4-(R4+S4) | X4: =U4-(V4+W4) | AB4: =Y4-(Z4+AA4) | AF4: =AC4-(AD4+AE4) | AJ4: =AG4-(AH4+AI4) | AN4: =AK4-(AL4+AM4) | AR4: =AO4-(AP4+AQ4) | AV4: =AS4-(AT4+AU4) | AZ4: =AW4-(AX4+AY4) | BA4: =SUM(E4,I4,M4,Q4,U4,Y4,AC4,AG4,AK4,AO4,AS4,AW4) | BB4: =SUM(F4,J4,N4,R4,V4,Z4,AD4,AH4,AL4,AP4,AT4,AX4) | BC4: =SUM(G4,K4,O4,S4,W4,AA4,AE4,AI4,AM4,AQ4,AU4,AY4) | BD4: =BA4-(BB4+BC4) | BE4: =BD4+D4
A5: F3 | C5: Samrat Kar | D5: 0 | H5: =E5-(F5+G5) | L5: =I5-(J5+K5) | P5: =M5-(N5+O5) | T5: =Q5-(R5+S5) | X5: =U5-(V5+W5) | AB5: =Y5-(Z5+AA5) | AF5: =AC5-(AD5+AE5) | AJ5: =AG5-(AH5+AI5) | AN5: =AK5-(AL5+AM5) | AR5: =AO5-(AP5+AQ5) | AV5: =AS5-(AT5+AU5) | AZ5: =AW5-(AX5+AY5) | BA5: =SUM(E5,I5,M5,Q5,U5,Y5,AC5,AG5,AK5,AO5,AS5,AW5) | BB5: =SUM(F5,J5,N5,R5,V5,Z5,AD5,AH5,AL5,AP5,AT5,AX5) | BC5: =SUM(G5,K5,O5,S5,W5,AA5,AE5,AI5,AM5,AQ5,AU5,AY5) | BD5: =BA5-(BB5+BC5) | BE5: =BD5+D5
A6: F4 | C6: Renu R | D6: 0 | H6: =E6-(F6+G6) | L6: =I6-(J6+K6) | P6: =M6-(N6+O6) | T6: =Q6-(R6+S6) | X6: =U6-(V6+W6) | AB6: =Y6-(Z6+AA6) | AF6: =AC6-(AD6+AE6) | AJ6: =AG6-(AH6+AI6) | AN6: =AK6-(AL6+AM6) | AR6: =AO6-(AP6+AQ6) | AV6: =AS6-(AT6+AU6) | AZ6: =AW6-(AX6+AY6) | BA6: =SUM(E6,I6,M6,Q6,U6,Y6,AC6,AG6,AK6,AO6,AS6,AW6) | BB6: =SUM(F6,J6,N6,R6,V6,Z6,AD6,AH6,AL6,AP6,AT6,AX6) | BC6: =SUM(G6,K6,O6,S6,W6,AA6,AE6,AI6,AM6,AQ6,AU6,AY6) | BD6: =BA6-(BB6+BC6) | BE6: =BD6+D6
A7: F5 | C7: Vamsidhar Bethanabatla / Madhuri Anumula | D7: 0 | H7: =E7-(F7+G7) | L7: =I7-(J7+K7) | P7: =M7-(N7+O7) | T7: =Q7-(R7+S7) | X7: =U7-(V7+W7) | AB7: =Y7-(Z7+AA7) | AF7: =AC7-(AD7+AE7) | AJ7: =AG7-(AH7+AI7) | AN7: =AK7-(AL7+AM7) | AR7: =AO7-(AP7+AQ7) | AV7: =AS7-(AT7+AU7) | AZ7: =AW7-(AX7+AY7) | BA7: =SUM(E7,I7,M7,Q7,U7,Y7,AC7,AG7,AK7,AO7,AS7,AW7) | BB7: =SUM(F7,J7,N7,R7,V7,Z7,AD7,AH7,AL7,AP7,AT7,AX7) | BC7: =SUM(G7,K7,O7,S7,W7,AA7,AE7,AI7,AM7,AQ7,AU7,AY7) | BD7: =BA7-(BB7+BC7) | BE7: =BD7+D7
A8: F6 | C8: Meghana Viral Shah and Vviral Shah (Owner) / Sangeet and Swagat (Tenent) | D8: 0 | H8: =E8-(F8+G8) | L8: =I8-(J8+K8) | P8: =M8-(N8+O8) | T8: =Q8-(R8+S8) | X8: =U8-(V8+W8) | AB8: =Y8-(Z8+AA8) | AF8: =AC8-(AD8+AE8) | AJ8: =AG8-(AH8+AI8) | AN8: =AK8-(AL8+AM8) | AR8: =AO8-(AP8+AQ8) | AV8: =AS8-(AT8+AU8) | AZ8: =AW8-(AX8+AY8) | BA8: =SUM(E8,I8,M8,Q8,U8,Y8,AC8,AG8,AK8,AO8,AS8,AW8) | BB8: =SUM(F8,J8,N8,R8,V8,Z8,AD8,AH8,AL8,AP8,AT8,AX8) | BC8: =SUM(G8,K8,O8,S8,W8,AA8,AE8,AI8,AM8,AQ8,AU8,AY8) | BD8: =BA8-(BB8+BC8) | BE8: =BD8+D8
A9: F7 | C9: Vimal NK | D9: 0 | H9: =E9-(F9+G9) | L9: =I9-(J9+K9) | P9: =M9-(N9+O9) | T9: =Q9-(R9+S9) | X9: =U9-(V9+W9) | AB9: =Y9-(Z9+AA9) | AF9: =AC9-(AD9+AE9) | AJ9: =AG9-(AH9+AI9) | AN9: =AK9-(AL9+AM9) | AR9: =AO9-(AP9+AQ9) | AV9: =AS9-(AT9+AU9) | AZ9: =AW9-(AX9+AY9) | BA9: =SUM(E9,I9,M9,Q9,U9,Y9,AC9,AG9,AK9,AO9,AS9,AW9) | BB9: =SUM(F9,J9,N9,R9,V9,Z9,AD9,AH9,AL9,AP9,AT9,AX9) | BC9: =SUM(G9,K9,O9,S9,W9,AA9,AE9,AI9,AM9,AQ9,AU9,AY9) | BD9: =BA9-(BB9+BC9) | BE9: =BD9+D9
A10: F8 | C10: Sujeet Kumar (Tenant)/Sreejith Menon (Owner) | D10: 0 | H10: =E10-(F10+G10) | L10: =I10-(J10+K10) | P10: =M10-(N10+O10) | T10: =Q10-(R10+S10) | X10: =U10-(V10+W10) | AB10: =Y10-(Z10+AA10) | AF10: =AC10-(AD10+AE10) | AJ10: =AG10-(AH10+AI10) | AN10: =AK10-(AL10+AM10) | AR10: =AO10-(AP10+AQ10) | AV10: =AS10-(AT10+AU10) | AZ10: =AW10-(AX10+AY10) | BA10: =SUM(E10,I10,M10,Q10,U10,Y10,AC10,AG10,AK10,AO10,AS10,AW10) | BB10: =SUM(F10,J10,N10,R10,V10,Z10,AD10,AH10,AL10,AP10,AT10,AX10) | BC10: =SUM(G10,K10,O10,S10,W10,AA10,AE10,AI10,AM10,AQ10,AU10,AY10) | BD10: =BA10-(BB10+BC10) | BE10: =BD10+D10
A11: F9 | C11: Vijay Suswaram (Owner) / Divya Shikha (Tenant) | D11: 0 | H11: =E11-(F11+G11) | L11: =I11-(J11+K11) | P11: =M11-(N11+O11) | T11: =Q11-(R11+S11) | X11: =U11-(V11+W11) | AB11: =Y11-(Z11+AA11) | AF11: =AC11-(AD11+AE11) | AJ11: =AG11-(AH11+AI11) | AN11: =AK11-(AL11+AM11) | AR11: =AO11-(AP11+AQ11) | AV11: =AS11-(AT11+AU11) | AZ11: =AW11-(AX11+AY11) | BA11: =SUM(E11,I11,M11,Q11,U11,Y11,AC11,AG11,AK11,AO11,AS11,AW11) | BB11: =SUM(F11,J11,N11,R11,V11,Z11,AD11,AH11,AL11,AP11,AT11,AX11) | BC11: =SUM(G11,K11,O11,S11,W11,AA11,AE11,AI11,AM11,AQ11,AU11,AY11) | BD11: =BA11-(BB11+BC11) | BE11: =BD11+D11
A12: F10 | C12: Aby Thomas | D12: 0 | H12: =E12-(F12+G12) | L12: =I12-(J12+K12) | P12: =M12-(N12+O12) | T12: =Q12-(R12+S12) | X12: =U12-(V12+W12) | AB12: =Y12-(Z12+AA12) | AF12: =AC12-(AD12+AE12) | AJ12: =AG12-(AH12+AI12) | AN12: =AK12-(AL12+AM12) | AR12: =AO12-(AP12+AQ12) | AV12: =AS12-(AT12+AU12) | AZ12: =AW12-(AX12+AY12) | BA12: =SUM(E12,I12,M12,Q12,U12,Y12,AC12,AG12,AK12,AO12,AS12,AW12) | BB12: =SUM(F12,J12,N12,R12,V12,Z12,AD12,AH12,AL12,AP12,AT12,AX12) | BC12: =SUM(G12,K12,O12,S12,W12,AA12,AE12,AI12,AM12,AQ12,AU12,AY12) | BD12: =BA12-(BB12+BC12) | BE12: =BD12+D12
A13: F11 | C13: Niwin Anto | D13: 0 | H13: =E13-(F13+G13) | L13: =I13-(J13+K13) | P13: =M13-(N13+O13) | T13: =Q13-(R13+S13) | X13: =U13-(V13+W13) | AB13: =Y13-(Z13+AA13) | AF13: =AC13-(AD13+AE13) | AJ13: =AG13-(AH13+AI13) | AN13: =AK13-(AL13+AM13) | AR13: =AO13-(AP13+AQ13) | AV13: =AS13-(AT13+AU13) | AZ13: =AW13-(AX13+AY13) | BA13: =SUM(E13,I13,M13,Q13,U13,Y13,AC13,AG13,AK13,AO13,AS13,AW13) | BB13: =SUM(F13,J13,N13,R13,V13,Z13,AD13,AH13,AL13,AP13,AT13,AX13) | BC13: =SUM(G13,K13,O13,S13,W13,AA13,AE13,AI13,AM13,AQ13,AU13,AY13) | BD13: =BA13-(BB13+BC13) | BE13: =BD13+D13
A14: F12 | C14: Anirudh Singh | D14: 0 | H14: =E14-(F14+G14) | L14: =I14-(J14+K14) | P14: =M14-(N14+O14) | T14: =Q14-(R14+S14) | X14: =U14-(V14+W14) | AB14: =Y14-(Z14+AA14) | AF14: =AC14-(AD14+AE14) | AJ14: =AG14-(AH14+AI14) | AN14: =AK14-(AL14+AM14) | AR14: =AO14-(AP14+AQ14) | AV14: =AS14-(AT14+AU14) | AZ14: =AW14-(AX14+AY14) | BA14: =SUM(E14,I14,M14,Q14,U14,Y14,AC14,AG14,AK14,AO14,AS14,AW14) | BB14: =SUM(F14,J14,N14,R14,V14,Z14,AD14,AH14,AL14,AP14,AT14,AX14) | BC14: =SUM(G14,K14,O14,S14,W14,AA14,AE14,AI14,AM14,AQ14,AU14,AY14) | BD14: =BA14-(BB14+BC14) | BE14: =BD14+D14
A15: F13 | C15: Sanchay Saxena | D15: 0 | H15: =E15-(F15+G15) | L15: =I15-(J15+K15) | P15: =M15-(N15+O15) | T15: =Q15-(R15+S15) | X15: =U15-(V15+W15) | AB15: =Y15-(Z15+AA15) | AF15: =AC15-(AD15+AE15) | AJ15: =AG15-(AH15+AI15) | AN15: =AK15-(AL15+AM15) | AR15: =AO15-(AP15+AQ15) | AV15: =AS15-(AT15+AU15) | AZ15: =AW15-(AX15+AY15) | BA15: =SUM(E15,I15,M15,Q15,U15,Y15,AC15,AG15,AK15,AO15,AS15,AW15) | BB15: =SUM(F15,J15,N15,R15,V15,Z15,AD15,AH15,AL15,AP15,AT15,AX15) | BC15: =SUM(G15,K15,O15,S15,W15,AA15,AE15,AI15,AM15,AQ15,AU15,AY15) | BD15: =BA15-(BB15+BC15) | BE15: =BD15+D15
A16: F14 | C16: Hemant Patel | D16: 0 | H16: =E16-(F16+G16) | L16: =I16-(J16+K16) | P16: =M16-(N16+O16) | T16: =Q16-(R16+S16) | X16: =U16-(V16+W16) | AB16: =Y16-(Z16+AA16) | AF16: =AC16-(AD16+AE16) | AJ16: =AG16-(AH16+AI16) | AN16: =AK16-(AL16+AM16) | AR16: =AO16-(AP16+AQ16) | AV16: =AS16-(AT16+AU16) | AZ16: =AW16-(AX16+AY16) | BA16: =SUM(E16,I16,M16,Q16,U16,Y16,AC16,AG16,AK16,AO16,AS16,AW16) | BB16: =SUM(F16,J16,N16,R16,V16,Z16,AD16,AH16,AL16,AP16,AT16,AX16) | BC16: =SUM(G16,K16,O16,S16,W16,AA16,AE16,AI16,AM16,AQ16,AU16,AY16) | BD16: =BA16-(BB16+BC16) | BE16: =BD16+D16
... A18: F16 | C18: Sreeja Sudharma | D18: 0 | H18: =E18-(F18+G18) | L18: =I18-(J18+K18) | P18: =M18-(N18+O18) | T18: =Q18-(R18+S18) | X18: =U18-(V18+W18) | AB18: =Y18-(Z18+AA18) | AF18: =AC18-(AD18+AE18) | AJ18: =AG18-(AH18+AI18) | AN18: =AK18-(AL18+AM18) | AR18: =AO18-(AP18+AQ18) | AV18: =AS18-(AT18+AU18) | AZ18: =AW18-(AX18+AY18) | BA18: =SUM(E18,I18,M18,Q18,U18,Y18,AC18,AG18,AK18,AO18,AS18,AW18) | BB18: =SUM(F18,J18,N18,R18,V18,Z18,AD18,AH18,AL18,AP18,AT18,AX18) | BC18: =SUM(G18,K18,O18,S18,W18,AA18,AE18,AI18,AM18,AQ18,AU18,AY18) | BD18: =BA18-(BB18+BC18) | BE18: =BD18+D18
A19: G1 | B19: jyothij1979@gmail.com | C19: Venkataramanan C | D19: 0 | H19: =E19-(F19+G19) | L19: =I19-(J19+K19) | P19: =M19-(N19+O19) | T19: =Q19-(R19+S19) | X19: =U19-(V19+W19) | AB19: =Y19-(Z19+AA19) | AF19: =AC19-(AD19+AE19) | AJ19: =AG19-(AH19+AI19) | AN19: =AK19-(AL19+AM19) | AR19: =AO19-(AP19+AQ19) | AV19: =AS19-(AT19+AU19) | AZ19: =AW19-(AX19+AY19) | BA19: =SUM(E19,I19,M19,Q19,U19,Y19,AC19,AG19,AK19,AO19,AS19,AW19) | BB19: =SUM(F19,J19,N19,R19,V19,Z19,AD19,AH19,AL19,AP19,AT19,AX19) | BC19: =SUM(G19,K19,O19,S19,W19,AA19,AE19,AI19,AM19,AQ19,AU19,AY19) | BD19: =BA19-(BB19+BC19) | BE19: =BD19+D19
A20: G2 | C20: Kaushik Kasibhatla | D20: 0 | H20: =E20-(F20+G20) | L20: =I20-(J20+K20) | P20: =M20-(N20+O20) | T20: =Q20-(R20+S20) | X20: =U20-(V20+W20) | AB20: =Y20-(Z20+AA20) | AF20: =AC20-(AD20+AE20) | AJ20: =AG20-(AH20+AI20) | AN20: =AK20-(AL20+AM20) | AR20: =AO20-(AP20+AQ20) | AV20: =AS20-(AT20+AU20) | AZ20: =AW20-(AX20+AY20) | BA20: =SUM(E20,I20,M20,Q20,U20,Y20,AC20,AG20,AK20,AO20,AS20,AW20) | BB20: =SUM(F20,J20,N20,R20,V20,Z20,AD20,AH20,AL20,AP20,AT20,AX20) | BC20: =SUM(G20,K20,O20,S20,W20,AA20,AE20,AI20,AM20,AQ20,AU20,AY20) | BD20: =BA20-(BB20+BC20) | BE20: =BD20+D20
A21: G3 | C21: Balakrishnan | D21: 0 | H21: =E21-(F21+G21) | L21: =I21-(J21+K21) | P21: =M21-(N21+O21) | T21: =Q21-(R21+S21) | X21: =U21-(V21+W21) | AB21: =Y21-(Z21+AA21) | AF21: =AC21-(AD21+AE21) | AJ21: =AG21-(AH21+AI21) | AN21: =AK21-(AL21+AM21) | AR21: =AO21-(AP21+AQ21) | AV21: =AS21-(AT21+AU21) | AZ21: =AW21-(AX21+AY21) | BA21: =SUM(E21,I21,M21,Q21,U21,Y21,AC21,AG21,AK21,AO21,AS21,AW21) | BB21: =SUM(F21,J21,N21,R21,V21,Z21,AD21,AH21,AL21,AP21,AT21,AX21) | BC21: =SUM(G21,K21,O21,S21,W21,AA21,AE21,AI21,AM21,AQ21,AU21,AY21) | BD21: =BA21-(BB21+BC21) | BE21: =BD21+D21
A22: G4 | C22: Ashwin Pandith | D22: 0 | H22: =E22-(F22+G22) | L22: =I22-(J22+K22) | P22: =M22-(N22+O22) | T22: =Q22-(R22+S22) | X22: =U22-(V22+W22) | AB22: =Y22-(Z22+AA22) | AF22: =AC22-(AD22+AE22) | AJ22: =AG22-(AH22+AI22) | AN22: =AK22-(AL22+AM22) | AR22: =AO22-(AP22+AQ22) | AV22: =AS22-(AT22+AU22) | AZ22: =AW22-(AX22+AY22) | BA22: =SUM(E22,I22,M22,Q22,U22,Y22,AC22,AG22,AK22,AO22,AS22,AW22) | BB22: =SUM(F22,J22,N22,R22,V22,Z22,AD22,AH22,AL22,AP22,AT22,AX22) | BC22: =SUM(G22,K22,O22,S22,W22,AA22,AE22,AI22,AM22,AQ22,AU22,AY22) | BD22: =BA22-(BB22+BC22) | BE22: =BD22+D22
A23: G5 | C23: Mayank Phophaliya | D23: 0 | H23: =E23-(F23+G23) | L23: =I23-(J23+K23) | P23: =M23-(N23+O23) | T23: =Q23-(R23+S23) | X23: =U23-(V23+W23) | AB23: =Y23-(Z23+AA23) | AF23: =AC23-(AD23+AE23) | AJ23: =AG23-(AH23+AI23) | AN23: =AK23-(AL23+AM23) | AR23: =AO23-(AP23+AQ23) | AV23: =AS23-(AT23+AU23) | AZ23: =AW23-(AX23+AY23) | BA23: =SUM(E23,I23,M23,Q23,U23,Y23,AC23,AG23,AK23,AO23,AS23,AW23) | BB23: =SUM(F23,J23,N23,R23,V23,Z23,AD23,AH23,AL23,AP23,AT23,AX23) | BC23: =SUM(G23,K23,O23,S23,W23,AA23,AE23,AI23,AM23,AQ23,AU23,AY23) | BD23: =BA23-(BB23+BC23) | BE23: =BD23+D23
A24: G6 | C24: Srinath / Tenant - Mohit Daga | D24: 0 | H24: =E24-(F24+G24) | L24: =I24-(J24+K24) | P24: =M24-(N24+O24) | T24: =Q24-(R24+S24) | X24: =U24-(V24+W24) | AB24: =Y24-(Z24+AA24) | AF24: =AC24-(AD24+AE24) | AJ24: =AG24-(AH24+AI24) | AN24: =AK24-(AL24+AM24) | AR24: =AO24-(AP24+AQ24) | AV24: =AS24-(AT24+AU24) | AZ24: =AW24-(AX24+AY24) | BA24: =SUM(E24,I24,M24,Q24,U24,Y24,AC24,AG24,AK24,AO24,AS24,AW24) | BB24: =SUM(F24,J24,N24,R24,V24,Z24,AD24,AH24,AL24,AP24,AT24,AX24) | BC24: =SUM(G24,K24,O24,S24,W24,AA24,AE24,AI24,AM24,AQ24,AU24,AY24) | BD24: =BA24-(BB24+BC24) | BE24: =BD24+D24
A25: G7 | C25: Prince Richfield | D25: 0 | H25: =E25-(F25+G25) | L25: =I25-(J25+K25) | P25: =M25-(N25+O25) | T25: =Q25-(R25+S25) | X25: =U25-(V25+W25) | AB25: =Y25-(Z25+AA25) | AF25: =AC25-(AD25+AE25) | AJ25: =AG25-(AH25+AI25) | AN25: =AK25-(AL25+AM25) | AR25: =AO25-(AP25+AQ25) | AV25: =AS25-(AT25+AU25) | AZ25: =AW25-(AX25+AY25) | BA25: =SUM(E25,I25,M25,Q25,U25,Y25,AC25,AG25,AK25,AO25,AS25,AW25) | BB25: =SUM(F25,J25,N25,R25,V25,Z25,AD25,AH25,AL25,AP25,AT25,AX25) | BC25: =SUM(G25,K25,O25,S25,W25,AA25,AE25,AI25,AM25,AQ25,AU25,AY25) | BD25: =BA25-(BB25+BC25) | BE25: =BD25+D25
A26: G8 | C26: Ranjithkumar R / Sameer (tenant) / Princy (tenant) | D26: 0 | H26: =E26-(F26+G26) | L26: =I26-(J26+K26) | P26: =M26-(N26+O26) | T26: =Q26-(R26+S26) | X26: =U26-(V26+W26) | AB26: =Y26-(Z26+AA26) | AF26: =AC26-(AD26+AE26) | AJ26: =AG26-(AH26+AI26) | AN26: =AK26-(AL26+AM26) | AR26: =AO26-(AP26+AQ26) | AV26: =AS26-(AT26+AU26) | AZ26: =AW26-(AX26+AY26) | BA26: =SUM(E26,I26,M26,Q26,U26,Y26,AC26,AG26,AK26,AO26,AS26,AW26) | BB26: =SUM(F26,J26,N26,R26,V26,Z26,AD26,AH26,AL26,AP26,AT26,AX26) | BC26: =SUM(G26,K26,O26,S26,W26,AA26,AE26,AI26,AM26,AQ26,AU26,AY26) | BD26: =BA26-(BB26+BC26) | BE26: =BD26+D26
A27: G9 | C27: Chandramouli | D27: 0 | H27: =E27-(F27+G27) | L27: =I27-(J27+K27) | P27: =M27-(N27+O27) | T27: =Q27-(R27+S27) | X27: =U27-(V27+W27) | AB27: =Y27-(Z27+AA27) | AF27: =AC27-(AD27+AE27) | AJ27: =AG27-(AH27+AI27) | AN27: =AK27-(AL27+AM27) | AR27: =AO27-(AP27+AQ27) | AV27: =AS27-(AT27+AU27) | AZ27: =AW27-(AX27+AY27) | BA27: =SUM(E27,I27,M27,Q27,U27,Y27,AC27,AG27,AK27,AO27,AS27,AW27) | BB27: =SUM(F27,J27,N27,R27,V27,Z27,AD27,AH27,AL27,AP27,AT27,AX27) | BC27: =SUM(G27,K27,O27,S27,W27,AA27,AE27,AI27,AM27,AQ27,AU27,AY27) | BD27: =BA27-(BB27+BC27) | BE27: =BD27+D27
A28: G10 | C28: Cijo Jacob / Thara Joy | D28: 0 | H28: =E28-(F28+G28) | L28: =I28-(J28+K28) | P28: =M28-(N28+O28) | T28: =Q28-(R28+S28) | X28: =U28-(V28+W28) | AB28: =Y28-(Z28+AA28) | AF28: =AC28-(AD28+AE28) | AJ28: =AG28-(AH28+AI28) | AN28: =AK28-(AL28+AM28) | AR28: =AO28-(AP28+AQ28) | AV28: =AS28-(AT28+AU28) | AZ28: =AW28-(AX28+AY28) | BA28: =SUM(E28,I28,M28,Q28,U28,Y28,AC28,AG28,AK28,AO28,AS28,AW28) | BB28: =SUM(F28,J28,N28,R28,V28,Z28,AD28,AH28,AL28,AP28,AT28,AX28) | BC28: =SUM(G28,K28,O28,S28,W28,AA28,AE28,AI28,AM28,AQ28,AU28,AY28) | BD28: =BA28-(BB28+BC28) | BE28: =BD28+D28
A29: G11 | C29: Ketan Verlekar | D29: 0 | H29: =E29-(F29+G29) | L29: =I29-(J29+K29) | P29: =M29-(N29+O29) | T29: =Q29-(R29+S29) | X29: =U29-(V29+W29) | AB29: =Y29-(Z29+AA29) | AF29: =AC29-(AD29+AE29) | AJ29: =AG29-(AH29+AI29) | AN29: =AK29-(AL29+AM29) | AR29: =AO29-(AP29+AQ29) | AV29: =AS29-(AT29+AU29) | AZ29: =AW29-(AX29+AY29) | BA29: =SUM(E29,I29,M29,Q29,U29,Y29,AC29,AG29,AK29,AO29,AS29,AW29) | BB29: =SUM(F29,J29,N29,R29,V29,Z29,AD29,AH29,AL29,AP29,AT29,AX29) | BC29: =SUM(G29,K29,O29,S29,W29,AA29,AE29,AI29,AM29,AQ29,AU29,AY29) | BD29: =BA29-(BB29+BC29) | BE29: =BD29+D29
A30: G12 | C30: Shyam Nair | D30: 0 | H30: =E30-(F30+G30) | L30: =I30-(J30+K30) | P30: =M30-(N30+O30) | T30: =Q30-(R30+S30) | X30: =U30-(V30+W30) | AB30: =Y30-(Z30+AA30) | AF30: =AC30-(AD30+AE30) | AJ30: =AG30-(AH30+AI30) | AN30: =AK30-(AL30+AM30) | AR30: =AO30-(AP30+AQ30) | AV30: =AS30-(AT30+AU30) | AZ30: =AW30-(AX30+AY30) | BA30: =SUM(E30,I30,M30,Q30,U30,Y30,AC30,AG30,AK30,AO30,AS30,AW30) | BB30: =SUM(F30,J30,N30,R30,V30,Z30,AD30,AH30,AL30,AP30,AT30,AX30) | BC30: =SUM(G30,K30,O30,S30,W30,AA30,AE30,AI30,AM30,AQ30,AU30,AY30) | BD30: =BA30-(BB30+BC30) | BE30: =BD30+D30
A31: G13 | C31: Ajai.B | D31: 0 | H31: =E31-(F31+G31) | L31: =I31-(J31+K31) | P31: =M31-(N31+O31) | T31: =Q31-(R31+S31) | X31: =U31-(V31+W31) | AB31: =Y31-(Z31+AA31) | AF31: =AC31-(AD31+AE31) | AJ31: =AG31-(AH31+AI31) | AN31: =AK31-(AL31+AM31) | AR31: =AO31-(AP31+AQ31) | AV31: =AS31-(AT31+AU31) | AZ31: =AW31-(AX31+AY31) | BA31: =SUM(E31,I31,M31,Q31,U31,Y31,AC31,AG31,AK31,AO31,AS31,AW31) | BB31: =SUM(F31,J31,N31,R31,V31,Z31,AD31,AH31,AL31,AP31,AT31,AX31) | BC31: =SUM(G31,K31,O31,S31,W31,AA31,AE31,AI31,AM31,AQ31,AU31,AY31) | BD31: =BA31-(BB31+BC31) | BE31: =BD31+D31
... A36: S2 | C36: Sonal Singhal | D36: 0 | H36: =E36-(F36+G36) | L36: =I36-(J36+K36) | P36: =M36-(N36+O36) | T36: =Q36-(R36+S36) | X36: =U36-(V36+W36) | AB36: =Y36-(Z36+AA36) | AF36: =AC36-(AD36+AE36) | AJ36: =AG36-(AH36+AI36) | AN36: =AK36-(AL36+AM36) | AR36: =AO36-(AP36+AQ36) | AV36: =AS36-(AT36+AU36) | AZ36: =AW36-(AX36+AY36) | BA36: =SUM(E36,I36,M36,Q36,U36,Y36,AC36,AG36,AK36,AO36,AS36,AW36) | BB36: =SUM(F36,J36,N36,R36,V36,Z36,AD36,AH36,AL36,AP36,AT36,AX36) | BC36: =SUM(G36,K36,O36,S36,W36,AA36,AE36,AI36,AM36,AQ36,AU36,AY36) | BD36: =BA36-(BB36+BC36) | BE36: =BD36+D36
A37: S3 | B37: manikandan.nj@gmail.com | C37: Manikandan NG | D37: 0 | H37: =E37-(F37+G37) | L37: =I37-(J37+K37) | P37: =M37-(N37+O37) | T37: =Q37-(R37+S37) | X37: =U37-(V37+W37) | AB37: =Y37-(Z37+AA37) | AF37: =AC37-(AD37+AE37) | AJ37: =AG37-(AH37+AI37) | AN37: =AK37-(AL37+AM37) | AR37: =AO37-(AP37+AQ37) | AV37: =AS37-(AT37+AU37) | AZ37: =AW37-(AX37+AY37) | BA37: =SUM(E37,I37,M37,Q37,U37,Y37,AC37,AG37,AK37,AO37,AS37,AW37) | BB37: =SUM(F37,J37,N37,R37,V37,Z37,AD37,AH37,AL37,AP37,AT37,AX37) | BC37: =SUM(G37,K37,O37,S37,W37,AA37,AE37,AI37,AM37,AQ37,AU37,AY37) | BD37: =BA37-(BB37+BC37) | BE37: =BD37+D37
A38: S4 | C38: Swaminathan | D38: 0 | H38: =E38-(F38+G38) | L38: =I38-(J38+K38) | P38: =M38-(N38+O38) | T38: =Q38-(R38+S38) | X38: =U38-(V38+W38) | AB38: =Y38-(Z38+AA38) | AF38: =AC38-(AD38+AE38) | AJ38: =AG38-(AH38+AI38) | AN38: =AK38-(AL38+AM38) | AR38: =AO38-(AP38+AQ38) | AV38: =AS38-(AT38+AU38) | AZ38: =AW38-(AX38+AY38) | BA38: =SUM(E38,I38,M38,Q38,U38,Y38,AC38,AG38,AK38,AO38,AS38,AW38) | BB38: =SUM(F38,J38,N38,R38,V38,Z38,AD38,AH38,AL38,AP38,AT38,AX38) | BC38: =SUM(G38,K38,O38,S38,W38,AA38,AE38,AI38,AM38,AQ38,AU38,AY38) | BD38: =BA38-(BB38+BC38) | BE38: =BD38+D38
A39: S5 | C39: Abhishek Gopalakrishnan | D39: 0 | H39: =E39-(F39+G39) | L39: =I39-(J39+K39) | P39: =M39-(N39+O39) | T39: =Q39-(R39+S39) | X39: =U39-(V39+W39) | AB39: =Y39-(Z39+AA39) | AF39: =AC39-(AD39+AE39) | AJ39: =AG39-(AH39+AI39) | AN39: =AK39-(AL39+AM39) | AR39: =AO39-(AP39+AQ39) | AV39: =AS39-(AT39+AU39) | AZ39: =AW39-(AX39+AY39) | BA39: =SUM(E39,I39,M39,Q39,U39,Y39,AC39,AG39,AK39,AO39,AS39,AW39) | BB39: =SUM(F39,J39,N39,R39,V39,Z39,AD39,AH39,AL39,AP39,AT39,AX39) | BC39: =SUM(G39,K39,O39,S39,W39,AA39,AE39,AI39,AM39,AQ39,AU39,AY39) | BD39: =BA39-(BB39+BC39) | BE39: =BD39+D39
A40: S6 | C40: Vivek Dhingra / Pratyush Das | D40: 0 | H40: =E40-(F40+G40) | L40: =I40-(J40+K40) | P40: =M40-(N40+O40) | T40: =Q40-(R40+S40) | X40: =U40-(V40+W40) | AB40: =Y40-(Z40+AA40) | AF40: =AC40-(AD40+AE40) | AJ40: =AG40-(AH40+AI40) | AN40: =AK40-(AL40+AM40) | AR40: =AO40-(AP40+AQ40) | AV40: =AS40-(AT40+AU40) | AZ40: =AW40-(AX40+AY40) | BA40: =SUM(E40,I40,M40,Q40,U40,Y40,AC40,AG40,AK40,AO40,AS40,AW40) | BB40: =SUM(F40,J40,N40,R40,V40,Z40,AD40,AH40,AL40,AP40,AT40,AX40) | BC40: =SUM(G40,K40,O40,S40,W40,AA40,AE40,AI40,AM40,AQ40,AU40,AY40) | BD40: =BA40-(BB40+BC40) | BE40: =BD40+D40
A41: S7 | C41: Harish B | D41: 0 | H41: =E41-(F41+G41) | L41: =I41-(J41+K41) | P41: =M41-(N41+O41) | T41: =Q41-(R41+S41) | X41: =U41-(V41+W41) | AB41: =Y41-(Z41+AA41) | AF41: =AC41-(AD41+AE41) | AJ41: =AG41-(AH41+AI41) | AN41: =AK41-(AL41+AM41) | AR41: =AO41-(AP41+AQ41) | AV41: =AS41-(AT41+AU41) | AZ41: =AW41-(AX41+AY41) | BA41: =SUM(E41,I41,M41,Q41,U41,Y41,AC41,AG41,AK41,AO41,AS41,AW41) | BB41: =SUM(F41,J41,N41,R41,V41,Z41,AD41,AH41,AL41,AP41,AT41,AX41) | BC41: =SUM(G41,K41,O41,S41,W41,AA41,AE41,AI41,AM41,AQ41,AU41,AY41) | BD41: =BA41-(BB41+BC41) | BE41: =BD41+D41
A42: S8 | C42: Irudayaraj Alwin | D42: 0 | H42: =E42-(F42+G42) | L42: =I42-(J42+K42) | P42: =M42-(N42+O42) | T42: =Q42-(R42+S42) | X42: =U42-(V42+W42) | AB42: =Y42-(Z42+AA42) | AF42: =AC42-(AD42+AE42) | AJ42: =AG42-(AH42+AI42) | AN42: =AK42-(AL42+AM42) | AR42: =AO42-(AP42+AQ42) | AV42: =AS42-(AT42+AU42) | AZ42: =AW42-(AX42+AY42) | BA42: =SUM(E42,I42,M42,Q42,U42,Y42,AC42,AG42,AK42,AO42,AS42,AW42) | BB42: =SUM(F42,J42,N42,R42,V42,Z42,AD42,AH42,AL42,AP42,AT42,AX42) | BC42: =SUM(G42,K42,O42,S42,W42,AA42,AE42,AI42,AM42,AQ42,AU42,AY42) | BD42: =BA42-(BB42+BC42) | BE42: =BD42+D42
A43: S9 | C43: Pawan GS | D43: 0 | H43: =E43-(F43+G43) | L43: =I43-(J43+K43) | P43: =M43-(N43+O43) | T43: =Q43-(R43+S43) | X43: =U43-(V43+W43) | AB43: =Y43-(Z43+AA43) | AF43: =AC43-(AD43+AE43) | AJ43: =AG43-(AH43+AI43) | AN43: =AK43-(AL43+AM43) | AR43: =AO43-(AP43+AQ43) | AV43: =AS43-(AT43+AU43) | AZ43: =AW43-(AX43+AY43) | BA43: =SUM(E43,I43,M43,Q43,U43,Y43,AC43,AG43,AK43,AO43,AS43,AW43) | BB43: =SUM(F43,J43,N43,R43,V43,Z43,AD43,AH43,AL43,AP43,AT43,AX43) | BC43: =SUM(G43,K43,O43,S43,W43,AA43,AE43,AI43,AM43,AQ43,AU43,AY43) | BD43: =BA43-(BB43+BC43) | BE43: =BD43+D43
A44: S10 | B44: esky2524@gmail.com | C44: Previous owner - Rohith. New owner name not known | D44: 0 | H44: =E44-(F44+G44) | L44: =I44-(J44+K44) | P44: =M44-(N44+O44) | T44: =Q44-(R44+S44) | X44: =U44-(V44+W44) | AB44: =Y44-(Z44+AA44) | AF44: =AC44-(AD44+AE44) | AJ44: =AG44-(AH44+AI44) | AN44: =AK44-(AL44+AM44) | AR44: =AO44-(AP44+AQ44) | AV44: =AS44-(AT44+AU44) | AZ44: =AW44-(AX44+AY44) | BA44: =SUM(E44,I44,M44,Q44,U44,Y44,AC44,AG44,AK44,AO44,AS44,AW44) | BB44: =SUM(F44,J44,N44,R44,V44,Z44,AD44,AH44,AL44,AP44,AT44,AX44) | BC44: =SUM(G44,K44,O44,S44,W44,AA44,AE44,AI44,AM44,AQ44,AU44,AY44) | BD44: =BA44-(BB44+BC44) | BE44: =BD44+D44
A45: S11 | C45: Gowrish Patnaik / Somananth GM | D45: 0 | H45: =E45-(F45+G45) | L45: =I45-(J45+K45) | P45: =M45-(N45+O45) | T45: =Q45-(R45+S45) | X45: =U45-(V45+W45) | AB45: =Y45-(Z45+AA45) | AF45: =AC45-(AD45+AE45) | AJ45: =AG45-(AH45+AI45) | AN45: =AK45-(AL45+AM45) | AR45: =AO45-(AP45+AQ45) | AV45: =AS45-(AT45+AU45) | AZ45: =AW45-(AX45+AY45) | BA45: =SUM(E45,I45,M45,Q45,U45,Y45,AC45,AG45,AK45,AO45,AS45,AW45) | BB45: =SUM(F45,J45,N45,R45,V45,Z45,AD45,AH45,AL45,AP45,AT45,AX45) | BC45: =SUM(G45,K45,O45,S45,W45,AA45,AE45,AI45,AM45,AQ45,AU45,AY45) | BD45: =BA45-(BB45+BC45) | BE45: =BD45+D45
A46: S12 | C46: Saovik Mondal | D46: 0 | H46: =E46-(F46+G46) | L46: =I46-(J46+K46) | P46: =M46-(N46+O46) | T46: =Q46-(R46+S46) | X46: =U46-(V46+W46) | AB46: =Y46-(Z46+AA46) | AF46: =AC46-(AD46+AE46) | AJ46: =AG46-(AH46+AI46) | AN46: =AK46-(AL46+AM46) | AR46: =AO46-(AP46+AQ46) | AV46: =AS46-(AT46+AU46) | AZ46: =AW46-(AX46+AY46) | BA46: =SUM(E46,I46,M46,Q46,U46,Y46,AC46,AG46,AK46,AO46,AS46,AW46) | BB46: =SUM(F46,J46,N46,R46,V46,Z46,AD46,AH46,AL46,AP46,AT46,AX46) | BC46: =SUM(G46,K46,O46,S46,W46,AA46,AE46,AI46,AM46,AQ46,AU46,AY46) | BD46: =BA46-(BB46+BC46) | BE46: =BD46+D46
A47: S13 | C47: Ramadevi S. | D47: 0 | H47: =E47-(F47+G47) | L47: =I47-(J47+K47) | P47: =M47-(N47+O47) | T47: =Q47-(R47+S47) | X47: =U47-(V47+W47) | AB47: =Y47-(Z47+AA47) | AF47: =AC47-(AD47+AE47) | AJ47: =AG47-(AH47+AI47) | AN47: =AK47-(AL47+AM47) | AR47: =AO47-(AP47+AQ47) | AV47: =AS47-(AT47+AU47) | AZ47: =AW47-(AX47+AY47) | BA47: =SUM(E47,I47,M47,Q47,U47,Y47,AC47,AG47,AK47,AO47,AS47,AW47) | BB47: =SUM(F47,J47,N47,R47,V47,Z47,AD47,AH47,AL47,AP47,AT47,AX47) | BC47: =SUM(G47,K47,O47,S47,W47,AA47,AE47,AI47,AM47,AQ47,AU47,AY47) | BD47: =BA47-(BB47+BC47) | BE47: =BD47+D47
A48: S14 | C48: Nishant Upadhyay(Owner)/ Fabian (Tenant) | D48: 0 | H48: =E48-(F48+G48) | L48: =I48-(J48+K48) | P48: =M48-(N48+O48) | T48: =Q48-(R48+S48) | X48: =U48-(V48+W48) | AB48: =Y48-(Z48+AA48) | AF48: =AC48-(AD48+AE48) | AJ48: =AG48-(AH48+AI48) | AN48: =AK48-(AL48+AM48) | AR48: =AO48-(AP48+AQ48) | AV48: =AS48-(AT48+AU48) | AZ48: =AW48-(AX48+AY48) | BA48: =SUM(E48,I48,M48,Q48,U48,Y48,AC48,AG48,AK48,AO48,AS48,AW48) | BB48: =SUM(F48,J48,N48,R48,V48,Z48,AD48,AH48,AL48,AP48,AT48,AX48) | BC48: =SUM(G48,K48,O48,S48,W48,AA48,AE48,AI48,AM48,AQ48,AU48,AY48) | BD48: =BA48-(BB48+BC48) | BE48: =BD48+D48
A49: S15 | C49: Manas Dasgupta | D49: 0 | H49: =E49-(F49+G49) | L49: =I49-(J49+K49) | P49: =M49-(N49+O49) | T49: =Q49-(R49+S49) | X49: =U49-(V49+W49) | AB49: =Y49-(Z49+AA49) | AF49: =AC49-(AD49+AE49) | AJ49: =AG49-(AH49+AI49) | AN49: =AK49-(AL49+AM49) | AR49: =AO49-(AP49+AQ49) | AV49: =AS49-(AT49+AU49) | AZ49: =AW49-(AX49+AY49) | BA49: =SUM(E49,I49,M49,Q49,U49,Y49,AC49,AG49,AK49,AO49,AS49,AW49) | BB49: =SUM(F49,J49,N49,R49,V49,Z49,AD49,AH49,AL49,AP49,AT49,AX49) | BC49: =SUM(G49,K49,O49,S49,W49,AA49,AE49,AI49,AM49,AQ49,AU49,AY49) | BD49: =BA49-(BB49+BC49) | BE49: =BD49+D49
A50: S16 | C50: Devendra Singh Rawat / Nancy | D50: 0 | H50: =E50-(F50+G50) | L50: =I50-(J50+K50) | P50: =M50-(N50+O50) | T50: =Q50-(R50+S50) | X50: =U50-(V50+W50) | AB50: =Y50-(Z50+AA50) | AF50: =AC50-(AD50+AE50) | AJ50: =AG50-(AH50+AI50) | AN50: =AK50-(AL50+AM50) | AR50: =AO50-(AP50+AQ50) | AV50: =AS50-(AT50+AU50) | AZ50: =AW50-(AX50+AY50) | BA50: =SUM(E50,I50,M50,Q50,U50,Y50,AC50,AG50,AK50,AO50,AS50,AW50) | BB50: =SUM(F50,J50,N50,R50,V50,Z50,AD50,AH50,AL50,AP50,AT50,AX50) | BC50: =SUM(G50,K50,O50,S50,W50,AA50,AE50,AI50,AM50,AQ50,AU50,AY50) | BD50: =BA50-(BB50+BC50) | BE50: =BD50+D50
A51: T1 | C51: Prashant Sikdar | D51: 0 | H51: =E51-(F51+G51) | L51: =I51-(J51+K51) | P51: =M51-(N51+O51) | T51: =Q51-(R51+S51) | X51: =U51-(V51+W51) | AB51: =Y51-(Z51+AA51) | AF51: =AC51-(AD51+AE51) | AJ51: =AG51-(AH51+AI51) | AN51: =AK51-(AL51+AM51) | AR51: =AO51-(AP51+AQ51) | AV51: =AS51-(AT51+AU51) | AZ51: =AW51-(AX51+AY51) | BA51: =SUM(E51,I51,M51,Q51,U51,Y51,AC51,AG51,AK51,AO51,AS51,AW51) | BB51: =SUM(F51,J51,N51,R51,V51,Z51,AD51,AH51,AL51,AP51,AT51,AX51) | BC51: =SUM(G51,K51,O51,S51,W51,AA51,AE51,AI51,AM51,AQ51,AU51,AY51) | BD51: =BA51-(BB51+BC51) | BE51: =BD51+D51
A52: T2 | C52: Kunal Mehta | D52: 0 | H52: =E52-(F52+G52) | L52: =I52-(J52+K52) | P52: =M52-(N52+O52) | T52: =Q52-(R52+S52) | X52: =U52-(V52+W52) | AB52: =Y52-(Z52+AA52) | AF52: =AC52-(AD52+AE52) | AJ52: =AG52-(AH52+AI52) | AN52: =AK52-(AL52+AM52) | AR52: =AO52-(AP52+AQ52) | AV52: =AS52-(AT52+AU52) | AZ52: =AW52-(AX52+AY52) | BA52: =SUM(E52,I52,M52,Q52,U52,Y52,AC52,AG52,AK52,AO52,AS52,AW52) | BB52: =SUM(F52,J52,N52,R52,V52,Z52,AD52,AH52,AL52,AP52,AT52,AX52) | BC52: =SUM(G52,K52,O52,S52,W52,AA52,AE52,AI52,AM52,AQ52,AU52,AY52) | BD52: =BA52-(BB52+BC52) | BE52: =BD52+D52
A53: T3 | C53: Kapil Garg | D53: 0 | H53: =E53-(F53+G53) | L53: =I53-(J53+K53) | P53: =M53-(N53+O53) | T53: =Q53-(R53+S53) | X53: =U53-(V53+W53) | AB53: =Y53-(Z53+AA53) | AF53: =AC53-(AD53+AE53) | AJ53: =AG53-(AH53+AI53) | AN53: =AK53-(AL53+AM53) | AR53: =AO53-(AP53+AQ53) | AV53: =AS53-(AT53+AU53) | AZ53: =AW53-(AX53+AY53) | BA53: =SUM(E53,I53,M53,Q53,U53,Y53,AC53,AG53,AK53,AO53,AS53,AW53) | BB53: =SUM(F53,J53,N53,R53,V53,Z53,AD53,AH53,AL53,AP53,AT53,AX53) | BC53: =SUM(G53,K53,O53,S53,W53,AA53,AE53,AI53,AM53,AQ53,AU53,AY53) | BD53: =BA53-(BB53+BC53) | BE53: =BD53+D53
A54: T4 | C54: Vijet Alva (Owner) - Masood (Tenant) | D54: 0 | H54: =E54-(F54+G54) | L54: =I54-(J54+K54) | P54: =M54-(N54+O54) | T54: =Q54-(R54+S54) | X54: =U54-(V54+W54) | AB54: =Y54-(Z54+AA54) | AF54: =AC54-(AD54+AE54) | AJ54: =AG54-(AH54+AI54) | AN54: =AK54-(AL54+AM54) | AR54: =AO54-(AP54+AQ54) | AV54: =AS54-(AT54+AU54) | AZ54: =AW54-(AX54+AY54) | BA54: =SUM(E54,I54,M54,Q54,U54,Y54,AC54,AG54,AK54,AO54,AS54,AW54) | BB54: =SUM(F54,J54,N54,R54,V54,Z54,AD54,AH54,AL54,AP54,AT54,AX54) | BC54: =SUM(G54,K54,O54,S54,W54,AA54,AE54,AI54,AM54,AQ54,AU54,AY54) | BD54: =BA54-(BB54+BC54) | BE54: =BD54+D54
A55: T5 | C55: Ganesh Iyer and Latha Iyer( owner) Richa (Tenant) | D55: 0 | H55: =E55-(F55+G55) | L55: =I55-(J55+K55) | P55: =M55-(N55+O55) | T55: =Q55-(R55+S55) | X55: =U55-(V55+W55) | AB55: =Y55-(Z55+AA55) | AF55: =AC55-(AD55+AE55) | AJ55: =AG55-(AH55+AI55) | AN55: =AK55-(AL55+AM55) | AR55: =AO55-(AP55+AQ55) | AV55: =AS55-(AT55+AU55) | AZ55: =AW55-(AX55+AY55) | BA55: =SUM(E55,I55,M55,Q55,U55,Y55,AC55,AG55,AK55,AO55,AS55,AW55) | BB55: =SUM(F55,J55,N55,R55,V55,Z55,AD55,AH55,AL55,AP55,AT55,AX55) | BC55: =SUM(G55,K55,O55,S55,W55,AA55,AE55,AI55,AM55,AQ55,AU55,AY55) | BD55: =BA55-(BB55+BC55) | BE55: =BD55+D55
A56: T6 | C56: Mythili Ramesh | D56: 0 | H56: =E56-(F56+G56) | L56: =I56-(J56+K56) | P56: =M56-(N56+O56) | T56: =Q56-(R56+S56) | X56: =U56-(V56+W56) | AB56: =Y56-(Z56+AA56) | AF56: =AC56-(AD56+AE56) | AJ56: =AG56-(AH56+AI56) | AN56: =AK56-(AL56+AM56) | AR56: =AO56-(AP56+AQ56) | AV56: =AS56-(AT56+AU56) | AZ56: =AW56-(AX56+AY56) | BA56: =SUM(E56,I56,M56,Q56,U56,Y56,AC56,AG56,AK56,AO56,AS56,AW56) | BB56: =SUM(F56,J56,N56,R56,V56,Z56,AD56,AH56,AL56,AP56,AT56,AX56) | BC56: =SUM(G56,K56,O56,S56,W56,AA56,AE56,AI56,AM56,AQ56,AU56,AY56) | BD56: =BA56-(BB56+BC56) | BE56: =BD56+D56
... A66: T16 | C66: Madhusoodanan P.R. | D66: 0 | H66: =E66-(F66+G66) | L66: =I66-(J66+K66) | P66: =M66-(N66+O66) | T66: =Q66-(R66+S66) | X66: =U66-(V66+W66) | AB66: =Y66-(Z66+AA66) | AF66: =AC66-(AD66+AE66) | AJ66: =AG66-(AH66+AI66) | AN66: =AK66-(AL66+AM66) | AR66: =AO66-(AP66+AQ66) | AV66: =AS66-(AT66+AU66) | AZ66: =AW66-(AX66+AY66) | BA66: =SUM(E66,I66,M66,Q66,U66,Y66,AC66,AG66,AK66,AO66,AS66,AW66) | BB66: =SUM(F66,J66,N66,R66,V66,Z66,AD66,AH66,AL66,AP66,AT66,AX66) | BC66: =SUM(G66,K66,O66,S66,W66,AA66,AE66,AI66,AM66,AQ66,AU66,AY66) | BD66: =BA66-(BB66+BC66) | BE66: =BD66+D66
C67: TOTAL | D67: =SUM(D3:D66) | E67: =SUM(E3:E66) | F67: =SUM(F3:F66) | G67: =SUM(G3:G66) | H67: =SUM(H3:H66) | I67: =SUM(I3:I66) | J67: =SUM(J3:J66) | K67: =SUM(K3:K66) | ... BD67: =SUM(BD3:BD66) | BE67: =BD67+D67

Sheet INCOME-EXPENSE-CYCLES-2026-27
C1: Tallied till 19 Sep'23 | D1: COLLECTION CARRY OVER (Mar2013-Mar2022) | E1: 2013-25 Pending Maintenance | F1: 46113 | J1: 46143 | N1: 46174 | R1: 46204 | V1: 46235 | Z1: 46266 | AD1: 46296 | AH1: 46327 | AL1: 46357 | AP1: 46388 | AT1: 46419 | AX1: 46447 | BB1: TOTAL COLLECTION (Apr2026 to Mar2027) | BC1: TOTAL EXPENSE (Apr2026 to Mar2027) | BD1: TOTAL LATE FEE (Apr2026 to Mar2027) | BE1: TOTAL COLLECTION - EXPENSE (Apr2026 to Mar2027) | BF1: Balance (2013 till date)
A2: FLAT# | B2: email id | C2: OCCUPANT | F2: COLLECTION | G2: EXPENSE | H2: LATE PAYMENT FEE | I2: COLLECTION - EXPENSE | J2: COLLECTION | K2: EXPENSE | L2: LATE PAYMENT FEE | M2: COLLECTION - EXPENSE | N2: COLLECTION | O2: EXPENSE | P2: LATE PAYMENT FEE | Q2: COLLECTION - EXPENSE | R2: COLLECTION | S2: EXPENSE | T2: LATE PAYMENT FEE | U2: COLLECTION - EXPENSE | V2: COLLECTION | W2: EXPENSE | X2: LATE PAYMENT FEE | Y2: COLLECTION - EXPENSE | Z2: COLLECTION | AA2: EXPENSE | AB2: LATE PAYMENT FEE | AC2: COLLECTION - EXPENSE | AD2: COLLECTION | AE2: EXPENSE | AF2: LATE PAYMENT FEE | AG2: COLLECTION - EXPENSE | AH2: COLLECTION | AI2: EXPENSE | AJ2: LATE PAYMENT FEE | AK2: COLLECTION - EXPENSE | AL2: COLLECTION | AM2: EXPENSE | AN2: LATE PAYMENT FEE | AO2: COLLECTION - EXPENSE | AP2: COLLECTION | AQ2: EXPENSE | AR2: LATE PAYMENT FEE | AS2: COLLECTION - EXPENSE | AT2: COLLECTION | AU2: EXPENSE | AV2: LATE PAYMENT FEE | AW2: COLLECTION - EXPENSE | AX2: COLLECTION | AY2: EXPENSE | AZ2: LATE PAYMENT FEE | BA2: COLLECTION - EXPENSE
A3: F1 | C3: Shailesh Srivastava / Azeem Nawaz | D3: 0 | E3: 0 | F3: ='Apr2026-COLLECTION'!K2 | G3: ='Apr2026-EXPENSE'!R6 | I3: =F3-(G3+H3) | J3: ='May2026-COLLECTION'!K2 | K3: ='May2026-EXPENSE'!R6 | M3: =J3-(K3+L3) | N3: ='June2026-COLLECTION'!K2 | O3: ='June2026-EXPENSE'!R6 | Q3: =N3-(O3+P3) | R3: ='July2026-COLLECTION'!K2 | S3: ='July2026-EXPENSE'!R6 | U3: =R3-(S3+T3) | V3: ='Aug2026-COLLECTION'!K2 | W3: ='Aug2026-EXPENSE'!R6 | Y3: =V3-(W3+X3) | Z3: ='Sep2026-COLLECTION'!K2 | AA3: ='Sep2026-EXPENSE'!R6 | AC3: =Z3-(AA3+AB3) | AD3: ='Oct2026-COLLECTION'!K2 | AE3: ='Oct2026-EXPENSE'!R6 | AG3: =AD3-(AE3+AF3) | AH3: ='Nov2026-COLLECTION'!K2 | AI3: ='Nov2026-EXPENSE'!R6 | AK3: =AH3-(AI3+AJ3) | AL3: ='Dec2026-COLLECTION'!K2 | AM3: ='Dec2026-EXPENSE'!R6 | AO3: =AL3-(AM3+AN3) | AP3: ='Jan2027-COLLECTION'!K2 | AQ3: ='Jan2027-EXPENSE'!R6 | AS3: =AP3-(AQ3+AR3) | AT3: ='Feb2027-COLLECTION'!K2 | AU3: ='Feb2027-EXPENSE'!R6 | AW3: =AT3-(AU3+AV3) | AX3: ='Mar2027-COLLECTION'!K2 | AY3: ='Mar2027-EXPENSE'!R6 | BA3: =AX3-(AY3+AZ3) | BB3: =SUM(F3,J3,N3,R3,V3,Z3,AD3,AH3,AL3,AP3,AT3,AX3) | BC3: =SUM(G3,K3,O3,S3,W3,AA3,AE3,AI3,AM3,AQ3,AU3,AY3) | BD3: =SUM(H3,L3,P3,T3,X3,AB3,AF3,AJ3,AN3,AR3,AV3,AZ3) | BE3: =BB3-(BC3+BD3) | BF3: =E3+BE3 | BG3: 0
A4: F2 | B4: ramazen1@gmail.com | C4: Ramamurthy Pachaiyappan | D4: 0 | E4: =-43932 | F4: ='Apr2026-COLLECTION'!K3 | G4: ='Apr2026-EXPENSE'!R7 | I4: =F4-(G4+H4) | J4: ='May2026-COLLECTION'!K3 | K4: ='May2026-EXPENSE'!R7 | L4: 0 | M4: =J4-(K4+L4) | N4: ='June2026-COLLECTION'!K3 | O4: ='June2026-EXPENSE'!R7 | Q4: =N4-(O4+P4) | R4: ='July2026-COLLECTION'!K3 | S4: ='July2026-EXPENSE'!R7 | T4: 0 | U4: =R4-(S4+T4) | V4: ='Aug2026-COLLECTION'!K3 | W4: ='Aug2026-EXPENSE'!R7 | Y4: =V4-(W4+X4) | Z4: ='Sep2026-COLLECTION'!K3 | AA4: ='Sep2026-EXPENSE'!R7 | AC4: =Z4-(AA4+AB4) | AD4: ='Oct2026-COLLECTION'!K3 | AE4: ='Oct2026-EXPENSE'!R7 | AG4: =AD4-(AE4+AF4) | AH4: ='Nov2026-COLLECTION'!K3 | AI4: ='Nov2026-EXPENSE'!R7 | AK4: =AH4-(AI4+AJ4) | AL4: ='Dec2026-COLLECTION'!K3 | AM4: ='Dec2026-EXPENSE'!R7 | AO4: =AL4-(AM4+AN4) | AP4: ='Jan2027-COLLECTION'!K3 | AQ4: ='Jan2027-EXPENSE'!R7 | AS4: =AP4-(AQ4+AR4) | AT4: ='Feb2027-COLLECTION'!K3 | AU4: ='Feb2027-EXPENSE'!R7 | AW4: =AT4-(AU4+AV4) | AX4: ='Mar2027-COLLECTION'!K3 | AY4: ='Mar2027-EXPENSE'!R7 | BA4: =AX4-(AY4+AZ4) | BB4: =SUM(F4,J4,N4,R4,V4,Z4,AD4,AH4,AL4,AP4,AT4,AX4) | BC4: =SUM(G4,K4,O4,S4,W4,AA4,AE4,AI4,AM4,AQ4,AU4,AY4) | BD4: =SUM(H4,L4,P4,T4,X4,AB4,AF4,AJ4,AN4,AR4,AV4,AZ4) | BE4: =BB4-(BC4+BD4) | BF4: =E4+BE4 | BG4: 0
A5: F3 | C5: Samrat Kar | D5: 0 | E5: 0 | F5: ='Apr2026-COLLECTION'!K4 | G5: ='Apr2026-EXPENSE'!R8 | I5: =F5-(G5+H5) | J5: ='May2026-COLLECTION'!K4 | K5: ='May2026-EXPENSE'!R8 | M5: =J5-(K5+L5) | N5: ='June2026-COLLECTION'!K4 | O5: ='June2026-EXPENSE'!R8 | Q5: =N5-(O5+P5) | R5: ='July2026-COLLECTION'!K4 | S5: ='July2026-EXPENSE'!R8 | U5: =R5-(S5+T5) | V5: ='Aug2026-COLLECTION'!K4 | W5: ='Aug2026-EXPENSE'!R8 | Y5: =V5-(W5+X5) | Z5: ='Sep2026-COLLECTION'!K4 | AA5: ='Sep2026-EXPENSE'!R8 | AC5: =Z5-(AA5+AB5) | AD5: ='Oct2026-COLLECTION'!K4 | AE5: ='Oct2026-EXPENSE'!R8 | AG5: =AD5-(AE5+AF5) | AH5: ='Nov2026-COLLECTION'!K4 | AI5: ='Nov2026-EXPENSE'!R8 | AK5: =AH5-(AI5+AJ5) | AL5: ='Dec2026-COLLECTION'!K4 | AM5: ='Dec2026-EXPENSE'!R8 | AO5: =AL5-(AM5+AN5) | AP5: ='Jan2027-COLLECTION'!K4 | AQ5: ='Jan2027-EXPENSE'!R8 | AS5: =AP5-(AQ5+AR5) | AT5: ='Feb2027-COLLECTION'!K4 | AU5: ='Feb2027-EXPENSE'!R8 | AW5: =AT5-(AU5+AV5) | AX5: ='Mar2027-COLLECTION'!K4 | AY5: ='Mar2027-EXPENSE'!R8 | BA5: =AX5-(AY5+AZ5) | BB5: =SUM(F5,J5,N5,R5,V5,Z5,AD5,AH5,AL5,AP5,AT5,AX5) | BC5: =SUM(G5,K5,O5,S5,W5,AA5,AE5,AI5,AM5,AQ5,AU5,AY5) | BD5: =SUM(H5,L5,P5,T5,X5,AB5,AF5,AJ5,AN5,AR5,AV5,AZ5) | BE5: =BB5-(BC5+BD5) | BF5: =E5+BE5 | BG5: 0
A6: F4 | C6: Renu R | D6: 0 | E6: 0 | F6: ='Apr2026-COLLECTION'!K5 | G6: ='Apr2026-EXPENSE'!R9 | I6: =F6-(G6+H6) | J6: ='May2026-COLLECTION'!K5 | K6: ='May2026-EXPENSE'!R9 | M6: =J6-(K6+L6) | N6: ='June2026-COLLECTION'!K5 | O6: ='June2026-EXPENSE'!R9 | Q6: =N6-(O6+P6) | R6: ='July2026-COLLECTION'!K5 | S6: ='July2026-EXPENSE'!R9 | U6: =R6-(S6+T6) | V6: ='Aug2026-COLLECTION'!K5 | W6: ='Aug2026-EXPENSE'!R9 | Y6: =V6-(W6+X6) | Z6: ='Sep2026-COLLECTION'!K5 | AA6: ='Sep2026-EXPENSE'!R9 | AC6: =Z6-(AA6+AB6) | AD6: ='Oct2026-COLLECTION'!K5 | AE6: ='Oct2026-EXPENSE'!R9 | AG6: =AD6-(AE6+AF6) | AH6: ='Nov2026-COLLECTION'!K5 | AI6: ='Nov2026-EXPENSE'!R9 | AK6: =AH6-(AI6+AJ6) | AL6: ='Dec2026-COLLECTION'!K5 | AM6: ='Dec2026-EXPENSE'!R9 | AO6: =AL6-(AM6+AN6) | AP6: ='Jan2027-COLLECTION'!K5 | AQ6: ='Jan2027-EXPENSE'!R9 | AS6: =AP6-(AQ6+AR6) | AT6: ='Feb2027-COLLECTION'!K5 | AU6: ='Feb2027-EXPENSE'!R9 | AW6: =AT6-(AU6+AV6) | AX6: ='Mar2027-COLLECTION'!K5 | AY6: ='Mar2027-EXPENSE'!R9 | BA6: =AX6-(AY6+AZ6) | BB6: =SUM(F6,J6,N6,R6,V6,Z6,AD6,AH6,AL6,AP6,AT6,AX6) | BC6: =SUM(G6,K6,O6,S6,W6,AA6,AE6,AI6,AM6,AQ6,AU6,AY6) | BD6: =SUM(H6,L6,P6,T6,X6,AB6,AF6,AJ6,AN6,AR6,AV6,AZ6) | BE6: =BB6-(BC6+BD6) | BF6: =E6+BE6 | BG6: 0
A7: F5 | C7: Vamsidhar Bethanabatla / Madhuri Anumula | D7: 0 | E7: =-1876.43+(-7566) | F7: ='Apr2026-COLLECTION'!K6 | G7: ='Apr2026-EXPENSE'!R10 | I7: =F7-(G7+H7) | J7: ='May2026-COLLECTION'!K6 | K7: ='May2026-EXPENSE'!R10 | M7: =J7-(K7+L7) | N7: ='June2026-COLLECTION'!K6 | O7: ='June2026-EXPENSE'!R10 | Q7: =N7-(O7+P7) | R7: ='July2026-COLLECTION'!K6 | S7: ='July2026-EXPENSE'!R10 | U7: =R7-(S7+T7) | V7: ='Aug2026-COLLECTION'!K6 | W7: ='Aug2026-EXPENSE'!R10 | Y7: =V7-(W7+X7) | Z7: ='Sep2026-COLLECTION'!K6 | AA7: ='Sep2026-EXPENSE'!R10 | AC7: =Z7-(AA7+AB7) | AD7: ='Oct2026-COLLECTION'!K6 | AE7: ='Oct2026-EXPENSE'!R10 | AG7: =AD7-(AE7+AF7) | AH7: ='Nov2026-COLLECTION'!K6 | AI7: ='Nov2026-EXPENSE'!R10 | AK7: =AH7-(AI7+AJ7) | AL7: ='Dec2026-COLLECTION'!K6 | AM7: ='Dec2026-EXPENSE'!R10 | AO7: =AL7-(AM7+AN7) | AP7: ='Jan2027-COLLECTION'!K6 | AQ7: ='Jan2027-EXPENSE'!R10 | AS7: =AP7-(AQ7+AR7) | AT7: ='Feb2027-COLLECTION'!K6 | AU7: ='Feb2027-EXPENSE'!R10 | AW7: =AT7-(AU7+AV7) | AX7: ='Mar2027-COLLECTION'!K6 | AY7: ='Mar2027-EXPENSE'!R10 | BA7: =AX7-(AY7+AZ7) | BB7: =SUM(F7,J7,N7,R7,V7,Z7,AD7,AH7,AL7,AP7,AT7,AX7) | BC7: =SUM(G7,K7,O7,S7,W7,AA7,AE7,AI7,AM7,AQ7,AU7,AY7) | BD7: =SUM(H7,L7,P7,T7,X7,AB7,AF7,AJ7,AN7,AR7,AV7,AZ7) | BE7: =BB7-(BC7+BD7) | BF7: =E7+BE7 | BG7: 0
A8: F6 | C8: Meghana Viral Shah and Vviral Shah (Owner) / Sangeet and Swagat (Tenent) | D8: 0 | E8: 0 | F8: ='Apr2026-COLLECTION'!K7 | G8: ='Apr2026-EXPENSE'!R11 | I8: =F8-(G8+H8) | J8: ='May2026-COLLECTION'!K7 | K8: ='May2026-EXPENSE'!R11 | M8: =J8-(K8+L8) | N8: ='June2026-COLLECTION'!K7 | O8: ='June2026-EXPENSE'!R11 | Q8: =N8-(O8+P8) | R8: ='July2026-COLLECTION'!K7 | S8: ='July2026-EXPENSE'!R11 | U8: =R8-(S8+T8) | V8: ='Aug2026-COLLECTION'!K7 | W8: ='Aug2026-EXPENSE'!R11 | Y8: =V8-(W8+X8) | Z8: ='Sep2026-COLLECTION'!K7 | AA8: ='Sep2026-EXPENSE'!R11 | AC8: =Z8-(AA8+AB8) | AD8: ='Oct2026-COLLECTION'!K7 | AE8: ='Oct2026-EXPENSE'!R11 | AG8: =AD8-(AE8+AF8) | AH8: ='Nov2026-COLLECTION'!K7 | AI8: ='Nov2026-EXPENSE'!R11 | AK8: =AH8-(AI8+AJ8) | AL8: ='Dec2026-COLLECTION'!K7 | AM8: ='Dec2026-EXPENSE'!R11 | AO8: =AL8-(AM8+AN8) | AP8: ='Jan2027-COLLECTION'!K7 | AQ8: ='Jan2027-EXPENSE'!R11 | AS8: =AP8-(AQ8+AR8) | AT8: ='Feb2027-COLLECTION'!K7 | AU8: ='Feb2027-EXPENSE'!R11 | AW8: =AT8-(AU8+AV8) | AX8: ='Mar2027-COLLECTION'!K7 | AY8: ='Mar2027-EXPENSE'!R11 | BA8: =AX8-(AY8+AZ8) | BB8: =SUM(F8,J8,N8,R8,V8,Z8,AD8,AH8,AL8,AP8,AT8,AX8) | BC8: =SUM(G8,K8,O8,S8,W8,AA8,AE8,AI8,AM8,AQ8,AU8,AY8) | BD8: =SUM(H8,L8,P8,T8,X8,AB8,AF8,AJ8,AN8,AR8,AV8,AZ8) | BE8: =BB8-(BC8+BD8) | BF8: =E8+BE8 | BG8: 0
A9: F7 | C9: Vimal NK | D9: 0 | E9: 0 | F9: ='Apr2026-COLLECTION'!K8 | G9: ='Apr2026-EXPENSE'!R12 | I9: =F9-(G9+H9) | J9: ='May2026-COLLECTION'!K8 | K9: ='May2026-EXPENSE'!R12 | M9: =J9-(K9+L9) | N9: ='June2026-COLLECTION'!K8 | O9: ='June2026-EXPENSE'!R12 | Q9: =N9-(O9+P9) | R9: ='July2026-COLLECTION'!K8 | S9: ='July2026-EXPENSE'!R12 | U9: =R9-(S9+T9) | V9: ='Aug2026-COLLECTION'!K8 | W9: ='Aug2026-EXPENSE'!R12 | Y9: =V9-(W9+X9) | Z9: ='Sep2026-COLLECTION'!K8 | AA9: ='Sep2026-EXPENSE'!R12 | AC9: =Z9-(AA9+AB9) | AD9: ='Oct2026-COLLECTION'!K8 | AE9: ='Oct2026-EXPENSE'!R12 | AG9: =AD9-(AE9+AF9) | AH9: ='Nov2026-COLLECTION'!K8 | AI9: ='Nov2026-EXPENSE'!R12 | AK9: =AH9-(AI9+AJ9) | AL9: ='Dec2026-COLLECTION'!K8 | AM9: ='Dec2026-EXPENSE'!R12 | AO9: =AL9-(AM9+AN9) | AP9: ='Jan2027-COLLECTION'!K8 | AQ9: ='Jan2027-EXPENSE'!R12 | AS9: =AP9-(AQ9+AR9) | AT9: ='Feb2027-COLLECTION'!K8 | AU9: ='Feb2027-EXPENSE'!R12 | AW9: =AT9-(AU9+AV9) | AX9: ='Mar2027-COLLECTION'!K8 | AY9: ='Mar2027-EXPENSE'!R12 | BA9: =AX9-(AY9+AZ9) | BB9: =SUM(F9,J9,N9,R9,V9,Z9,AD9,AH9,AL9,AP9,AT9,AX9) | BC9: =SUM(G9,K9,O9,S9,W9,AA9,AE9,AI9,AM9,AQ9,AU9,AY9) | BD9: =SUM(H9,L9,P9,T9,X9,AB9,AF9,AJ9,AN9,AR9,AV9,AZ9) | BE9: =BB9-(BC9+BD9) | BF9: =E9+BE9 | BG9: 0
A10: F8 | C10: Sujeet Kumar (Tenant)/Sreejith Menon (Owner) | D10: 0 | E10: 0 | F10: ='Apr2026-COLLECTION'!K9 | G10: ='Apr2026-EXPENSE'!R13 | I10: =F10-(G10+H10) | J10: ='May2026-COLLECTION'!K9 | K10: ='May2026-EXPENSE'!R13 | M10: =J10-(K10+L10) | N10: ='June2026-COLLECTION'!K9 | O10: ='June2026-EXPENSE'!R13 | Q10: =N10-(O10+P10) | R10: ='July2026-COLLECTION'!K9 | S10: ='July2026-EXPENSE'!R13 | U10: =R10-(S10+T10) | V10: ='Aug2026-COLLECTION'!K9 | W10: ='Aug2026-EXPENSE'!R13 | Y10: =V10-(W10+X10) | Z10: ='Sep2026-COLLECTION'!K9 | AA10: ='Sep2026-EXPENSE'!R13 | AC10: =Z10-(AA10+AB10) | AD10: ='Oct2026-COLLECTION'!K9 | AE10: ='Oct2026-EXPENSE'!R13 | AG10: =AD10-(AE10+AF10) | AH10: ='Nov2026-COLLECTION'!K9 | AI10: ='Nov2026-EXPENSE'!R13 | AK10: =AH10-(AI10+AJ10) | AL10: ='Dec2026-COLLECTION'!K9 | AM10: ='Dec2026-EXPENSE'!R13 | AO10: =AL10-(AM10+AN10) | AP10: ='Jan2027-COLLECTION'!K9 | AQ10: ='Jan2027-EXPENSE'!R13 | AS10: =AP10-(AQ10+AR10) | AT10: ='Feb2027-COLLECTION'!K9 | AU10: ='Feb2027-EXPENSE'!R13 | AW10: =AT10-(AU10+AV10) | AX10: ='Mar2027-COLLECTION'!K9 | AY10: ='Mar2027-EXPENSE'!R13 | BA10: =AX10-(AY10+AZ10) | BB10: =SUM(F10,J10,N10,R10,V10,Z10,AD10,AH10,AL10,AP10,AT10,AX10) | BC10: =SUM(G10,K10,O10,S10,W10,AA10,AE10,AI10,AM10,AQ10,AU10,AY10) | BD10: =SUM(H10,L10,P10,T10,X10,AB10,AF10,AJ10,AN10,AR10,AV10,AZ10) | BE10: =BB10-(BC10+BD10) | BF10: =E10+BE10 | BG10: 0
A11: F9 | C11: Vijay Suswaram (Owner) / Divya Shikha (Tenant) | D11: 0 | E11: 0 | F11: ='Apr2026-COLLECTION'!K10 | G11: ='Apr2026-EXPENSE'!R14 | I11: =F11-(G11+H11) | J11: ='May2026-COLLECTION'!K10 | K11: ='May2026-EXPENSE'!R14 | M11: =J11-(K11+L11) | N11: ='June2026-COLLECTION'!K10 | O11: ='June2026-EXPENSE'!R14 | Q11: =N11-(O11+P11) | R11: ='July2026-COLLECTION'!K10 | S11: ='July2026-EXPENSE'!R14 | U11: =R11-(S11+T11) | V11: ='Aug2026-COLLECTION'!K10 | W11: ='Aug2026-EXPENSE'!R14 | Y11: =V11-(W11+X11) | Z11: ='Sep2026-COLLECTION'!K10 | AA11: ='Sep2026-EXPENSE'!R14 | AC11: =Z11-(AA11+AB11) | AD11: ='Oct2026-COLLECTION'!K10 | AE11: ='Oct2026-EXPENSE'!R14 | AG11: =AD11-(AE11+AF11) | AH11: ='Nov2026-COLLECTION'!K10 | AI11: ='Nov2026-EXPENSE'!R14 | AK11: =AH11-(AI11+AJ11) | AL11: ='Dec2026-COLLECTION'!K10 | AM11: ='Dec2026-EXPENSE'!R14 | AO11: =AL11-(AM11+AN11) | AP11: ='Jan2027-COLLECTION'!K10 | AQ11: ='Jan2027-EXPENSE'!R14 | AS11: =AP11-(AQ11+AR11) | AT11: ='Feb2027-COLLECTION'!K10 | AU11: ='Feb2027-EXPENSE'!R14 | AW11: =AT11-(AU11+AV11) | AX11: ='Mar2027-COLLECTION'!K10 | AY11: ='Mar2027-EXPENSE'!R14 | BA11: =AX11-(AY11+AZ11) | BB11: =SUM(F11,J11,N11,R11,V11,Z11,AD11,AH11,AL11,AP11,AT11,AX11) | BC11: =SUM(G11,K11,O11,S11,W11,AA11,AE11,AI11,AM11,AQ11,AU11,AY11) | BD11: =SUM(H11,L11,P11,T11,X11,AB11,AF11,AJ11,AN11,AR11,AV11,AZ11) | BE11: =BB11-(BC11+BD11) | BF11: =E11+BE11 | BG11: 0
A12: F10 | C12: Aby Thomas | D12: 0 | E12: 0 | F12: ='Apr2026-COLLECTION'!K11 | G12: ='Apr2026-EXPENSE'!R15 | I12: =F12-(G12+H12) | J12: ='May2026-COLLECTION'!K11 | K12: ='May2026-EXPENSE'!R15 | M12: =J12-(K12+L12) | N12: ='June2026-COLLECTION'!K11 | O12: ='June2026-EXPENSE'!R15 | Q12: =N12-(O12+P12) | R12: ='July2026-COLLECTION'!K11 | S12: ='July2026-EXPENSE'!R15 | U12: =R12-(S12+T12) | V12: ='Aug2026-COLLECTION'!K11 | W12: ='Aug2026-EXPENSE'!R15 | Y12: =V12-(W12+X12) | Z12: ='Sep2026-COLLECTION'!K11 | AA12: ='Sep2026-EXPENSE'!R15 | AC12: =Z12-(AA12+AB12) | AD12: ='Oct2026-COLLECTION'!K11 | AE12: ='Oct2026-EXPENSE'!R15 | AG12: =AD12-(AE12+AF12) | AH12: ='Nov2026-COLLECTION'!K11 | AI12: ='Nov2026-EXPENSE'!R15 | AK12: =AH12-(AI12+AJ12) | AL12: ='Dec2026-COLLECTION'!K11 | AM12: ='Dec2026-EXPENSE'!R15 | AO12: =AL12-(AM12+AN12) | AP12: ='Jan2027-COLLECTION'!K11 | AQ12: ='Jan2027-EXPENSE'!R15 | AS12: =AP12-(AQ12+AR12) | AT12: ='Feb2027-COLLECTION'!K11 | AU12: ='Feb2027-EXPENSE'!R15 | AW12: =AT12-(AU12+AV12) | AX12: ='Mar2027-COLLECTION'!K11 | AY12: ='Mar2027-EXPENSE'!R15 | BA12: =AX12-(AY12+AZ12) | BB12: =SUM(F12,J12,N12,R12,V12,Z12,AD12,AH12,AL12,AP12,AT12,AX12) | BC12: =SUM(G12,K12,O12,S12,W12,AA12,AE12,AI12,AM12,AQ12,AU12,AY12) | BD12: =SUM(H12,L12,P12,T12,X12,AB12,AF12,AJ12,AN12,AR12,AV12,AZ12) | BE12: =BB12-(BC12+BD12) | BF12: =E12+BE12 | BG12: 0
A13: F11 | C13: Niwin Anto | D13: 0 | E13: 0 | F13: ='Apr2026-COLLECTION'!K12 | G13: ='Apr2026-EXPENSE'!R16 | I13: =F13-(G13+H13) | J13: ='May2026-COLLECTION'!K12 | K13: ='May2026-EXPENSE'!R16 | M13: =J13-(K13+L13) | N13: ='June2026-COLLECTION'!K12 | O13: ='June2026-EXPENSE'!R16 | Q13: =N13-(O13+P13) | R13: ='July2026-COLLECTION'!K12 | S13: ='July2026-EXPENSE'!R16 | U13: =R13-(S13+T13) | V13: ='Aug2026-COLLECTION'!K12 | W13: ='Aug2026-EXPENSE'!R16 | Y13: =V13-(W13+X13) | Z13: ='Sep2026-COLLECTION'!K12 | AA13: ='Sep2026-EXPENSE'!R16 | AC13: =Z13-(AA13+AB13) | AD13: ='Oct2026-COLLECTION'!K12 | AE13: ='Oct2026-EXPENSE'!R16 | AG13: =AD13-(AE13+AF13) | AH13: ='Nov2026-COLLECTION'!K12 | AI13: ='Nov2026-EXPENSE'!R16 | AK13: =AH13-(AI13+AJ13) | AL13: ='Dec2026-COLLECTION'!K12 | AM13: ='Dec2026-EXPENSE'!R16 | AO13: =AL13-(AM13+AN13) | AP13: ='Jan2027-COLLECTION'!K12 | AQ13: ='Jan2027-EXPENSE'!R16 | AS13: =AP13-(AQ13+AR13) | AT13: ='Feb2027-COLLECTION'!K12 | AU13: ='Feb2027-EXPENSE'!R16 | AW13: =AT13-(AU13+AV13) | AX13: ='Mar2027-COLLECTION'!K12 | AY13: ='Mar2027-EXPENSE'!R16 | BA13: =AX13-(AY13+AZ13) | BB13: =SUM(F13,J13,N13,R13,V13,Z13,AD13,AH13,AL13,AP13,AT13,AX13) | BC13: =SUM(G13,K13,O13,S13,W13,AA13,AE13,AI13,AM13,AQ13,AU13,AY13) | BD13: =SUM(H13,L13,P13,T13,X13,AB13,AF13,AJ13,AN13,AR13,AV13,AZ13) | BE13: =BB13-(BC13+BD13) | BF13: =E13+BE13 | BG13: 0
A14: F12 | C14: Anirudh Singh | D14: 0 | E14: 0 | F14: ='Apr2026-COLLECTION'!K13 | G14: ='Apr2026-EXPENSE'!R17 | I14: =F14-(G14+H14) | J14: ='May2026-COLLECTION'!K13 | K14: ='May2026-EXPENSE'!R17 | M14: =J14-(K14+L14) | N14: ='June2026-COLLECTION'!K13 | O14: ='June2026-EXPENSE'!R17 | Q14: =N14-(O14+P14) | R14: ='July2026-COLLECTION'!K13 | S14: ='July2026-EXPENSE'!R17 | U14: =R14-(S14+T14) | V14: ='Aug2026-COLLECTION'!K13 | W14: ='Aug2026-EXPENSE'!R17 | Y14: =V14-(W14+X14) | Z14: ='Sep2026-COLLECTION'!K13 | AA14: ='Sep2026-EXPENSE'!R17 | AC14: =Z14-(AA14+AB14) | AD14: ='Oct2026-COLLECTION'!K13 | AE14: ='Oct2026-EXPENSE'!R17 | AG14: =AD14-(AE14+AF14) | AH14: ='Nov2026-COLLECTION'!K13 | AI14: ='Nov2026-EXPENSE'!R17 | AK14: =AH14-(AI14+AJ14) | AL14: ='Dec2026-COLLECTION'!K13 | AM14: ='Dec2026-EXPENSE'!R17 | AO14: =AL14-(AM14+AN14) | AP14: ='Jan2027-COLLECTION'!K13 | AQ14: ='Jan2027-EXPENSE'!R17 | AS14: =AP14-(AQ14+AR14) | AT14: ='Feb2027-COLLECTION'!K13 | AU14: ='Feb2027-EXPENSE'!R17 | AW14: =AT14-(AU14+AV14) | AX14: ='Mar2027-COLLECTION'!K13 | AY14: ='Mar2027-EXPENSE'!R17 | BA14: =AX14-(AY14+AZ14) | BB14: =SUM(F14,J14,N14,R14,V14,Z14,AD14,AH14,AL14,AP14,AT14,AX14) | BC14: =SUM(G14,K14,O14,S14,W14,AA14,AE14,AI14,AM14,AQ14,AU14,AY14) | BD14: =SUM(H14,L14,P14,T14,X14,AB14,AF14,AJ14,AN14,AR14,AV14,AZ14) | BE14: =BB14-(BC14+BD14) | BF14: =E14+BE14 | BG14: 0
A15: F13 | C15: Sanchay Saxena | D15: 0 | E15: 0 | F15: ='Apr2026-COLLECTION'!K14 | G15: ='Apr2026-EXPENSE'!R18 | I15: =F15-(G15+H15) | J15: ='May2026-COLLECTION'!K14 | K15: ='May2026-EXPENSE'!R18 | L15: 0 | M15: =J15-(K15+L15) | N15: ='June2026-COLLECTION'!K14 | O15: ='June2026-EXPENSE'!R18 | Q15: =N15-(O15+P15) | R15: ='July2026-COLLECTION'!K14 | S15: ='July2026-EXPENSE'!R18 | U15: =R15-(S15+T15) | V15: ='Aug2026-COLLECTION'!K14 | W15: ='Aug2026-EXPENSE'!R18 | Y15: =V15-(W15+X15) | Z15: ='Sep2026-COLLECTION'!K14 | AA15: ='Sep2026-EXPENSE'!R18 | AC15: =Z15-(AA15+AB15) | AD15: ='Oct2026-COLLECTION'!K14 | AE15: ='Oct2026-EXPENSE'!R18 | AG15: =AD15-(AE15+AF15) | AH15: ='Nov2026-COLLECTION'!K14 | AI15: ='Nov2026-EXPENSE'!R18 | AK15: =AH15-(AI15+AJ15) | AL15: ='Dec2026-COLLECTION'!K14 | AM15: ='Dec2026-EXPENSE'!R18 | AO15: =AL15-(AM15+AN15) | AP15: ='Jan2027-COLLECTION'!K14 | AQ15: ='Jan2027-EXPENSE'!R18 | AS15: =AP15-(AQ15+AR15) | AT15: ='Feb2027-COLLECTION'!K14 | AU15: ='Feb2027-EXPENSE'!R18 | AW15: =AT15-(AU15+AV15) | AX15: ='Mar2027-COLLECTION'!K14 | AY15: ='Mar2027-EXPENSE'!R18 | BA15: =AX15-(AY15+AZ15) | BB15: =SUM(F15,J15,N15,R15,V15,Z15,AD15,AH15,AL15,AP15,AT15,AX15) | BC15: =SUM(G15,K15,O15,S15,W15,AA15,AE15,AI15,AM15,AQ15,AU15,AY15) | BD15: =SUM(H15,L15,P15,T15,X15,AB15,AF15,AJ15,AN15,AR15,AV15,AZ15) | BE15: =BB15-(BC15+BD15) | BF15: =E15+BE15 | BG15: 0
A16: F14 | C16: Hemant Patel | D16: 0 | E16: 0 | F16: ='Apr2026-COLLECTION'!K15 | G16: ='Apr2026-EXPENSE'!R19 | I16: =F16-(G16+H16) | J16: ='May2026-COLLECTION'!K15 | K16: ='May2026-EXPENSE'!R19 | M16: =J16-(K16+L16) | N16: ='June2026-COLLECTION'!K15 | O16: ='June2026-EXPENSE'!R19 | Q16: =N16-(O16+P16) | R16: ='July2026-COLLECTION'!K15 | S16: ='July2026-EXPENSE'!R19 | U16: =R16-(S16+T16) | V16: ='Aug2026-COLLECTION'!K15 | W16: ='Aug2026-EXPENSE'!R19 | Y16: =V16-(W16+X16) | Z16: ='Sep2026-COLLECTION'!K15 | AA16: ='Sep2026-EXPENSE'!R19 | AC16: =Z16-(AA16+AB16) | AD16: ='Oct2026-COLLECTION'!K15 | AE16: ='Oct2026-EXPENSE'!R19 | AG16: =AD16-(AE16+AF16) | AH16: ='Nov2026-COLLECTION'!K15 | AI16: ='Nov2026-EXPENSE'!R19 | AK16: =AH16-(AI16+AJ16) | AL16: ='Dec2026-COLLECTION'!K15 | AM16: ='Dec2026-EXPENSE'!R19 | AO16: =AL16-(AM16+AN16) | AP16: ='Jan2027-COLLECTION'!K15 | AQ16: ='Jan2027-EXPENSE'!R19 | AS16: =AP16-(AQ16+AR16) | AT16: ='Feb2027-COLLECTION'!K15 | AU16: ='Feb2027-EXPENSE'!R19 | AW16: =AT16-(AU16+AV16) | AX16: ='Mar2027-COLLECTION'!K15 | AY16: ='Mar2027-EXPENSE'!R19 | BA16: =AX16-(AY16+AZ16) | BB16: =SUM(F16,J16,N16,R16,V16,Z16,AD16,AH16,AL16,AP16,AT16,AX16) | BC16: =SUM(G16,K16,O16,S16,W16,AA16,AE16,AI16,AM16,AQ16,AU16,AY16) | BD16: =SUM(H16,L16,P16,T16,X16,AB16,AF16,AJ16,AN16,AR16,AV16,AZ16) | BE16: =BB16-(BC16+BD16) | BF16: =E16+BE16 | BG16: 0
